package br.com.santander.investimentoV2.features.efetivacao.view;

import ack;
import android.os.Bundle;
import android.support.annotation.Nullable;
import ss;

public class EfetivacaoActivity extends ack {
  private ss a;
  
  protected void onCreate(@Nullable Bundle paramBundle) {
    // Byte code:
    //   0: aconst_null
    //   1: astore_2
    //   2: aload_0
    //   3: aload_1
    //   4: invokespecial onCreate : (Landroid/os/Bundle;)V
    //   7: aload_0
    //   8: getstatic lc.activity_efetivacao : I
    //   11: invokevirtual setContentView : (I)V
    //   14: aload_0
    //   15: invokevirtual getIntent : ()Landroid/content/Intent;
    //   18: invokevirtual getExtras : ()Landroid/os/Bundle;
    //   21: ldc 'cso'
    //   23: invokevirtual containsKey : (Ljava/lang/String;)Z
    //   26: ifeq -> 116
    //   29: aload_0
    //   30: invokevirtual getIntent : ()Landroid/content/Intent;
    //   33: invokevirtual getExtras : ()Landroid/os/Bundle;
    //   36: ldc 'cso'
    //   38: invokevirtual getString : (Ljava/lang/String;)Ljava/lang/String;
    //   41: astore_1
    //   42: aload_1
    //   43: ifnull -> 116
    //   46: aload_1
    //   47: invokevirtual isEmpty : ()Z
    //   50: ifne -> 116
    //   53: new eju
    //   56: dup
    //   57: invokespecial <init> : ()V
    //   60: invokevirtual j : ()Lejm;
    //   63: aload_1
    //   64: ldc yt
    //   66: invokevirtual a : (Ljava/lang/String;Ljava/lang/Class;)Ljava/lang/Object;
    //   69: checkcast yt
    //   72: astore_1
    //   73: aload_0
    //   74: invokevirtual getIntent : ()Landroid/content/Intent;
    //   77: invokevirtual getExtras : ()Landroid/os/Bundle;
    //   80: ldc 'otp'
    //   82: invokevirtual containsKey : (Ljava/lang/String;)Z
    //   85: ifeq -> 101
    //   88: aload_0
    //   89: invokevirtual getIntent : ()Landroid/content/Intent;
    //   92: invokevirtual getExtras : ()Landroid/os/Bundle;
    //   95: ldc 'otp'
    //   97: invokevirtual getString : (Ljava/lang/String;)Ljava/lang/String;
    //   100: astore_2
    //   101: aload_0
    //   102: new ss
    //   105: dup
    //   106: aload_0
    //   107: aload_1
    //   108: aload_2
    //   109: invokespecial <init> : (Lack;Lyt;Ljava/lang/String;)V
    //   112: putfield a : Lss;
    //   115: return
    //   116: aconst_null
    //   117: astore_1
    //   118: goto -> 73
  }
}


/* Location:              C:\Users\devid\Downloads\SAST\Santander\dex2jar-2.0\classes-dex2jar.jar!\br\com\santander\investimentoV2\features\efetivacao\view\EfetivacaoActivity.class
 * Java compiler version: 6 (50.0)
 * JD-Core Version:       1.1.3
 */