package com.santander.app.habilitacaointernacional.activity;

import android.os.Bundle;
import grs;
import inx;
import ioi;
import java.io.Serializable;
import java.util.ArrayList;

public class ConfirmarHabilitacaoInternacionalActivity extends grs implements Serializable {
  private ArrayList<inx> a;
  
  private ArrayList<ioi> b;
  
  private ArrayList<ioi> c = new ArrayList<ioi>();
  
  private String d;
  
  private String e;
  
  private int f;
  
  private String g = "";
  
  protected void onCreate(Bundle paramBundle) {
    // Byte code:
    //   0: aload_0
    //   1: aload_1
    //   2: invokespecial onCreate : (Landroid/os/Bundle;)V
    //   5: aload_0
    //   6: ldc 2130969110
    //   8: invokevirtual setContentView : (I)V
    //   11: aload_0
    //   12: aload_0
    //   13: invokevirtual getIntent : ()Landroid/content/Intent;
    //   16: ldc 'operacao'
    //   18: iconst_0
    //   19: invokevirtual getIntExtra : (Ljava/lang/String;I)I
    //   22: putfield f : I
    //   25: aload_0
    //   26: invokevirtual getSupportActionBar : ()Landroid/support/v7/app/ActionBar;
    //   29: astore_2
    //   30: aload_2
    //   31: aload_0
    //   32: invokevirtual getResources : ()Landroid/content/res/Resources;
    //   35: ldc 2130838158
    //   37: invokevirtual getDrawable : (I)Landroid/graphics/drawable/Drawable;
    //   40: invokevirtual setBackgroundDrawable : (Landroid/graphics/drawable/Drawable;)V
    //   43: aload_2
    //   44: iconst_0
    //   45: invokevirtual setDisplayShowHomeEnabled : (Z)V
    //   48: aload_2
    //   49: iconst_0
    //   50: invokevirtual setDisplayShowTitleEnabled : (Z)V
    //   53: aload_2
    //   54: iconst_1
    //   55: invokevirtual setDisplayShowCustomEnabled : (Z)V
    //   58: aload_0
    //   59: ldc 'layout_inflater'
    //   61: invokevirtual getSystemService : (Ljava/lang/String;)Ljava/lang/Object;
    //   64: checkcast android/view/LayoutInflater
    //   67: ldc 2130969499
    //   69: aconst_null
    //   70: invokevirtual inflate : (ILandroid/view/ViewGroup;)Landroid/view/View;
    //   73: pop
    //   74: ldc ''
    //   76: astore_1
    //   77: aload_0
    //   78: getfield f : I
    //   81: tableswitch default -> 108, 0 -> 269, 1 -> 279, 2 -> 289
    //   108: aload_0
    //   109: aload_2
    //   110: aload_1
    //   111: invokestatic a : (Landroid/app/Activity;Landroid/support/v7/app/ActionBar;Ljava/lang/String;)V
    //   114: aload_0
    //   115: ldc 2131757065
    //   117: invokevirtual findViewById : (I)Landroid/view/View;
    //   120: checkcast android/widget/Button
    //   123: astore_1
    //   124: aload_0
    //   125: ldc 2131757632
    //   127: invokevirtual findViewById : (I)Landroid/view/View;
    //   130: checkcast android/widget/ListView
    //   133: astore_2
    //   134: aload_0
    //   135: aload_0
    //   136: invokevirtual getIntent : ()Landroid/content/Intent;
    //   139: ldc 'cartao'
    //   141: invokevirtual getStringExtra : (Ljava/lang/String;)Ljava/lang/String;
    //   144: putfield d : Ljava/lang/String;
    //   147: aload_0
    //   148: aload_0
    //   149: invokevirtual getIntent : ()Landroid/content/Intent;
    //   152: ldc 'FINALCARTAO'
    //   154: invokevirtual getStringExtra : (Ljava/lang/String;)Ljava/lang/String;
    //   157: putfield g : Ljava/lang/String;
    //   160: aload_0
    //   161: ldc 2131757631
    //   163: invokevirtual findViewById : (I)Landroid/view/View;
    //   166: checkcast android/widget/TextView
    //   169: aload_0
    //   170: getfield g : Ljava/lang/String;
    //   173: invokevirtual setText : (Ljava/lang/CharSequence;)V
    //   176: aload_0
    //   177: aload_0
    //   178: invokevirtual getIntent : ()Landroid/content/Intent;
    //   181: ldc 'passo'
    //   183: invokevirtual getStringExtra : (Ljava/lang/String;)Ljava/lang/String;
    //   186: putfield e : Ljava/lang/String;
    //   189: aload_0
    //   190: getfield e : Ljava/lang/String;
    //   193: ldc '1'
    //   195: invokevirtual equals : (Ljava/lang/Object;)Z
    //   198: ifeq -> 299
    //   201: aload_0
    //   202: new java/util/ArrayList
    //   205: dup
    //   206: invokespecial <init> : ()V
    //   209: putfield a : Ljava/util/ArrayList;
    //   212: aload_0
    //   213: aload_0
    //   214: invokevirtual getIntent : ()Landroid/content/Intent;
    //   217: ldc 'lista'
    //   219: invokevirtual getSerializableExtra : (Ljava/lang/String;)Ljava/io/Serializable;
    //   222: checkcast java/util/ArrayList
    //   225: putfield a : Ljava/util/ArrayList;
    //   228: aload_0
    //   229: getfield e : Ljava/lang/String;
    //   232: ldc '2'
    //   234: invokevirtual equals : (Ljava/lang/Object;)Z
    //   237: ifeq -> 712
    //   240: aload_2
    //   241: new ino
    //   244: dup
    //   245: aload_0
    //   246: getfield a : Ljava/util/ArrayList;
    //   249: aload_0
    //   250: invokespecial <init> : (Ljava/util/ArrayList;Landroid/content/Context;)V
    //   253: invokevirtual setAdapter : (Landroid/widget/ListAdapter;)V
    //   256: aload_1
    //   257: new imn
    //   260: dup
    //   261: aload_0
    //   262: invokespecial <init> : (Lcom/santander/app/habilitacaointernacional/activity/ConfirmarHabilitacaoInternacionalActivity;)V
    //   265: invokevirtual setOnClickListener : (Landroid/view/View$OnClickListener;)V
    //   268: return
    //   269: aload_0
    //   270: ldc 2131297559
    //   272: invokevirtual getString : (I)Ljava/lang/String;
    //   275: astore_1
    //   276: goto -> 108
    //   279: aload_0
    //   280: ldc 2131297558
    //   282: invokevirtual getString : (I)Ljava/lang/String;
    //   285: astore_1
    //   286: goto -> 108
    //   289: aload_0
    //   290: ldc 2131297560
    //   292: invokevirtual getString : (I)Ljava/lang/String;
    //   295: astore_1
    //   296: goto -> 108
    //   299: aload_0
    //   300: getfield e : Ljava/lang/String;
    //   303: ldc '2'
    //   305: invokevirtual equals : (Ljava/lang/Object;)Z
    //   308: ifeq -> 522
    //   311: aload_0
    //   312: aload_0
    //   313: invokevirtual getIntent : ()Landroid/content/Intent;
    //   316: ldc 'lista'
    //   318: invokevirtual getSerializableExtra : (Ljava/lang/String;)Ljava/io/Serializable;
    //   321: checkcast java/util/ArrayList
    //   324: putfield b : Ljava/util/ArrayList;
    //   327: aload_0
    //   328: new java/util/ArrayList
    //   331: dup
    //   332: invokespecial <init> : ()V
    //   335: putfield a : Ljava/util/ArrayList;
    //   338: aload_0
    //   339: getfield b : Ljava/util/ArrayList;
    //   342: invokevirtual iterator : ()Ljava/util/Iterator;
    //   345: astore_3
    //   346: aload_3
    //   347: invokeinterface hasNext : ()Z
    //   352: ifeq -> 228
    //   355: aload_3
    //   356: invokeinterface next : ()Ljava/lang/Object;
    //   361: checkcast ioi
    //   364: astore #4
    //   366: new ioi
    //   369: dup
    //   370: invokespecial <init> : ()V
    //   373: astore #5
    //   375: aload #5
    //   377: aload #4
    //   379: invokevirtual e : ()Z
    //   382: invokevirtual a : (Z)V
    //   385: aload #5
    //   387: aload #4
    //   389: invokevirtual a : ()Ljava/lang/String;
    //   392: invokevirtual a : (Ljava/lang/String;)V
    //   395: aload #5
    //   397: aload #4
    //   399: invokevirtual b : ()Ljava/lang/String;
    //   402: invokevirtual b : (Ljava/lang/String;)V
    //   405: aload #5
    //   407: aload #4
    //   409: invokevirtual c : ()Ljava/lang/String;
    //   412: invokevirtual c : (Ljava/lang/String;)V
    //   415: aload #5
    //   417: aload #4
    //   419: invokevirtual f : ()Ljava/lang/String;
    //   422: invokevirtual e : (Ljava/lang/String;)V
    //   425: aload #5
    //   427: aload #4
    //   429: invokevirtual d : ()Ljava/lang/String;
    //   432: invokevirtual d : (Ljava/lang/String;)V
    //   435: aload #5
    //   437: aload #4
    //   439: invokevirtual g : ()Ljava/lang/String;
    //   442: invokevirtual f : (Ljava/lang/String;)V
    //   445: aload_0
    //   446: getfield c : Ljava/util/ArrayList;
    //   449: aload #5
    //   451: invokevirtual add : (Ljava/lang/Object;)Z
    //   454: pop
    //   455: new inx
    //   458: dup
    //   459: aload #4
    //   461: invokevirtual a : ()Ljava/lang/String;
    //   464: invokevirtual toString : ()Ljava/lang/String;
    //   467: aload #4
    //   469: invokevirtual b : ()Ljava/lang/String;
    //   472: invokevirtual toString : ()Ljava/lang/String;
    //   475: aload #4
    //   477: invokevirtual c : ()Ljava/lang/String;
    //   480: aload #4
    //   482: invokevirtual d : ()Ljava/lang/String;
    //   485: invokevirtual toString : ()Ljava/lang/String;
    //   488: aload #4
    //   490: invokevirtual f : ()Ljava/lang/String;
    //   493: invokevirtual toString : ()Ljava/lang/String;
    //   496: aload #4
    //   498: invokevirtual g : ()Ljava/lang/String;
    //   501: invokevirtual toString : ()Ljava/lang/String;
    //   504: invokespecial <init> : (Ljava/lang/String;Ljava/lang/String;Ljava/lang/String;Ljava/lang/String;Ljava/lang/String;Ljava/lang/String;)V
    //   507: astore #4
    //   509: aload_0
    //   510: getfield a : Ljava/util/ArrayList;
    //   513: aload #4
    //   515: invokevirtual add : (Ljava/lang/Object;)Z
    //   518: pop
    //   519: goto -> 346
    //   522: aload_0
    //   523: getfield e : Ljava/lang/String;
    //   526: ldc '3'
    //   528: invokevirtual equals : (Ljava/lang/Object;)Z
    //   531: ifeq -> 228
    //   534: aload_0
    //   535: aload_0
    //   536: invokevirtual getIntent : ()Landroid/content/Intent;
    //   539: ldc 'lista'
    //   541: invokevirtual getSerializableExtra : (Ljava/lang/String;)Ljava/io/Serializable;
    //   544: checkcast java/util/ArrayList
    //   547: putfield b : Ljava/util/ArrayList;
    //   550: aload_0
    //   551: new java/util/ArrayList
    //   554: dup
    //   555: invokespecial <init> : ()V
    //   558: putfield a : Ljava/util/ArrayList;
    //   561: aload_0
    //   562: getfield b : Ljava/util/ArrayList;
    //   565: invokevirtual iterator : ()Ljava/util/Iterator;
    //   568: astore_3
    //   569: aload_3
    //   570: invokeinterface hasNext : ()Z
    //   575: ifeq -> 228
    //   578: aload_3
    //   579: invokeinterface next : ()Ljava/lang/Object;
    //   584: checkcast ioi
    //   587: astore #4
    //   589: new ioi
    //   592: dup
    //   593: invokespecial <init> : ()V
    //   596: astore #5
    //   598: aload #5
    //   600: aload #4
    //   602: invokevirtual a : ()Ljava/lang/String;
    //   605: invokevirtual a : (Ljava/lang/String;)V
    //   608: aload #5
    //   610: aload #4
    //   612: invokevirtual d : ()Ljava/lang/String;
    //   615: invokevirtual d : (Ljava/lang/String;)V
    //   618: aload #5
    //   620: aload #4
    //   622: invokevirtual c : ()Ljava/lang/String;
    //   625: invokevirtual c : (Ljava/lang/String;)V
    //   628: aload #5
    //   630: aload #4
    //   632: invokevirtual b : ()Ljava/lang/String;
    //   635: invokevirtual b : (Ljava/lang/String;)V
    //   638: aload #5
    //   640: aload #4
    //   642: invokevirtual h : ()Ljava/lang/Boolean;
    //   645: invokevirtual a : (Ljava/lang/Boolean;)V
    //   648: aload_0
    //   649: getfield c : Ljava/util/ArrayList;
    //   652: aload #5
    //   654: invokevirtual add : (Ljava/lang/Object;)Z
    //   657: pop
    //   658: new inx
    //   661: dup
    //   662: aload #4
    //   664: invokevirtual a : ()Ljava/lang/String;
    //   667: invokevirtual toString : ()Ljava/lang/String;
    //   670: aload #4
    //   672: invokevirtual b : ()Ljava/lang/String;
    //   675: invokevirtual toString : ()Ljava/lang/String;
    //   678: aload #4
    //   680: invokevirtual c : ()Ljava/lang/String;
    //   683: invokevirtual toString : ()Ljava/lang/String;
    //   686: aload #4
    //   688: invokevirtual d : ()Ljava/lang/String;
    //   691: invokevirtual toString : ()Ljava/lang/String;
    //   694: invokespecial <init> : (Ljava/lang/String;Ljava/lang/String;Ljava/lang/String;Ljava/lang/String;)V
    //   697: astore #4
    //   699: aload_0
    //   700: getfield a : Ljava/util/ArrayList;
    //   703: aload #4
    //   705: invokevirtual add : (Ljava/lang/Object;)Z
    //   708: pop
    //   709: goto -> 569
    //   712: aload_2
    //   713: new fqk
    //   716: dup
    //   717: aload_0
    //   718: getfield a : Ljava/util/ArrayList;
    //   721: aload_0
    //   722: invokespecial <init> : (Ljava/util/ArrayList;Landroid/content/Context;)V
    //   725: invokevirtual setAdapter : (Landroid/widget/ListAdapter;)V
    //   728: goto -> 256
  }
}


/* Location:              C:\Users\devid\Downloads\SAST\Santander\dex2jar-2.0\classes-dex2jar.jar!\com\santander\app\habilitacaointernacional\activity\ConfirmarHabilitacaoInternacionalActivity.class
 * Java compiler version: 6 (50.0)
 * JD-Core Version:       1.1.3
 */