import android.support.annotation.WorkerThread;
import java.util.Map;

class dbv extends dcc {
  private final Map<cph, dbu> c;
  
  public dbv(dbs paramdbs, Map<cph, dbu> paramMap) {
    super(paramdbs, null);
    this.c = paramMap;
  }
  
  @WorkerThread
  public void a() {
    // Byte code:
    //   0: iconst_1
    //   1: istore #5
    //   3: iconst_0
    //   4: istore #4
    //   6: aload_0
    //   7: getfield c : Ljava/util/Map;
    //   10: invokeinterface keySet : ()Ljava/util/Set;
    //   15: invokeinterface iterator : ()Ljava/util/Iterator;
    //   20: astore #6
    //   22: iconst_1
    //   23: istore_2
    //   24: iconst_0
    //   25: istore_1
    //   26: aload #6
    //   28: invokeinterface hasNext : ()Z
    //   33: ifeq -> 308
    //   36: aload #6
    //   38: invokeinterface next : ()Ljava/lang/Object;
    //   43: checkcast cph
    //   46: astore #7
    //   48: aload #7
    //   50: invokeinterface e : ()Z
    //   55: ifeq -> 156
    //   58: aload_0
    //   59: getfield c : Ljava/util/Map;
    //   62: aload #7
    //   64: invokeinterface get : (Ljava/lang/Object;)Ljava/lang/Object;
    //   69: checkcast dbu
    //   72: invokestatic a : (Ldbu;)Z
    //   75: ifne -> 301
    //   78: iconst_1
    //   79: istore_1
    //   80: iload #5
    //   82: istore_3
    //   83: iload_3
    //   84: ifeq -> 106
    //   87: aload_0
    //   88: getfield a : Ldbs;
    //   91: invokestatic b : (Ldbs;)Lcwn;
    //   94: aload_0
    //   95: getfield a : Ldbs;
    //   98: invokestatic a : (Ldbs;)Landroid/content/Context;
    //   101: invokevirtual a : (Landroid/content/Context;)I
    //   104: istore #4
    //   106: iload #4
    //   108: ifeq -> 171
    //   111: iload_1
    //   112: ifne -> 119
    //   115: iload_2
    //   116: ifeq -> 171
    //   119: new com/google/android/gms/common/ConnectionResult
    //   122: dup
    //   123: iload #4
    //   125: aconst_null
    //   126: invokespecial <init> : (ILandroid/app/PendingIntent;)V
    //   129: astore #6
    //   131: aload_0
    //   132: getfield a : Ldbs;
    //   135: invokestatic d : (Ldbs;)Ldcm;
    //   138: new dbw
    //   141: dup
    //   142: aload_0
    //   143: aload_0
    //   144: getfield a : Ldbs;
    //   147: aload #6
    //   149: invokespecial <init> : (Ldbv;Ldcl;Lcom/google/android/gms/common/ConnectionResult;)V
    //   152: invokevirtual a : (Ldcn;)V
    //   155: return
    //   156: iconst_0
    //   157: istore_3
    //   158: iload_1
    //   159: istore_2
    //   160: iload_3
    //   161: istore_1
    //   162: iload_2
    //   163: istore_3
    //   164: iload_1
    //   165: istore_2
    //   166: iload_3
    //   167: istore_1
    //   168: goto -> 26
    //   171: aload_0
    //   172: getfield a : Ldbs;
    //   175: invokestatic e : (Ldbs;)Z
    //   178: ifeq -> 193
    //   181: aload_0
    //   182: getfield a : Ldbs;
    //   185: invokestatic f : (Ldbs;)Ldpx;
    //   188: invokeinterface l : ()V
    //   193: aload_0
    //   194: getfield c : Ljava/util/Map;
    //   197: invokeinterface keySet : ()Ljava/util/Set;
    //   202: invokeinterface iterator : ()Ljava/util/Iterator;
    //   207: astore #6
    //   209: aload #6
    //   211: invokeinterface hasNext : ()Z
    //   216: ifeq -> 155
    //   219: aload #6
    //   221: invokeinterface next : ()Ljava/lang/Object;
    //   226: checkcast cph
    //   229: astore #7
    //   231: aload_0
    //   232: getfield c : Ljava/util/Map;
    //   235: aload #7
    //   237: invokeinterface get : (Ljava/lang/Object;)Ljava/lang/Object;
    //   242: checkcast cth
    //   245: astore #8
    //   247: aload #7
    //   249: invokeinterface e : ()Z
    //   254: ifeq -> 289
    //   257: iload #4
    //   259: ifeq -> 289
    //   262: aload_0
    //   263: getfield a : Ldbs;
    //   266: invokestatic d : (Ldbs;)Ldcm;
    //   269: new dbx
    //   272: dup
    //   273: aload_0
    //   274: aload_0
    //   275: getfield a : Ldbs;
    //   278: aload #8
    //   280: invokespecial <init> : (Ldbv;Ldcl;Lcth;)V
    //   283: invokevirtual a : (Ldcn;)V
    //   286: goto -> 209
    //   289: aload #7
    //   291: aload #8
    //   293: invokeinterface a : (Lcth;)V
    //   298: goto -> 209
    //   301: iload_2
    //   302: istore_1
    //   303: iconst_1
    //   304: istore_2
    //   305: goto -> 162
    //   308: iload_1
    //   309: istore_3
    //   310: iconst_0
    //   311: istore_1
    //   312: goto -> 83
  }
}


/* Location:              C:\Users\devid\Downloads\SAST\Santander\dex2jar-2.0\classes2-dex2jar.jar!\dbv.class
 * Java compiler version: 6 (50.0)
 * JD-Core Version:       1.1.3
 */