import android.support.annotation.WorkerThread;
import java.net.URL;
import java.util.Map;

@WorkerThread
class dle implements Runnable {
  private final URL b;
  
  private final byte[] c;
  
  private final dlc d;
  
  private final String e;
  
  private final Map<String, String> f;
  
  public dle(dla paramdla, String paramString, URL paramURL, byte[] paramArrayOfbyte, Map<String, String> paramMap, dlc paramdlc) {
    csp.a(paramString);
    csp.a(paramURL);
    csp.a(paramdlc);
    this.b = paramURL;
    this.c = paramArrayOfbyte;
    this.d = paramdlc;
    this.e = paramString;
    this.f = paramMap;
  }
  
  public void run() {
    // Byte code:
    //   0: aload_0
    //   1: getfield a : Ldla;
    //   4: invokevirtual d : ()V
    //   7: iconst_0
    //   8: istore #4
    //   10: iconst_0
    //   11: istore #5
    //   13: iconst_0
    //   14: istore_1
    //   15: aload_0
    //   16: getfield a : Ldla;
    //   19: aload_0
    //   20: getfield b : Ljava/net/URL;
    //   23: invokevirtual a : (Ljava/net/URL;)Ljava/net/HttpURLConnection;
    //   26: astore #6
    //   28: iload_1
    //   29: istore_2
    //   30: iload #5
    //   32: istore_3
    //   33: aload_0
    //   34: getfield f : Ljava/util/Map;
    //   37: ifnull -> 197
    //   40: iload_1
    //   41: istore_2
    //   42: iload #5
    //   44: istore_3
    //   45: aload_0
    //   46: getfield f : Ljava/util/Map;
    //   49: invokeinterface entrySet : ()Ljava/util/Set;
    //   54: invokeinterface iterator : ()Ljava/util/Iterator;
    //   59: astore #7
    //   61: iload_1
    //   62: istore_2
    //   63: iload #5
    //   65: istore_3
    //   66: aload #7
    //   68: invokeinterface hasNext : ()Z
    //   73: ifeq -> 197
    //   76: iload_1
    //   77: istore_2
    //   78: iload #5
    //   80: istore_3
    //   81: aload #7
    //   83: invokeinterface next : ()Ljava/lang/Object;
    //   88: checkcast java/util/Map$Entry
    //   91: astore #8
    //   93: iload_1
    //   94: istore_2
    //   95: iload #5
    //   97: istore_3
    //   98: aload #6
    //   100: aload #8
    //   102: invokeinterface getKey : ()Ljava/lang/Object;
    //   107: checkcast java/lang/String
    //   110: aload #8
    //   112: invokeinterface getValue : ()Ljava/lang/Object;
    //   117: checkcast java/lang/String
    //   120: invokevirtual addRequestProperty : (Ljava/lang/String;Ljava/lang/String;)V
    //   123: goto -> 61
    //   126: astore #8
    //   128: aconst_null
    //   129: astore #9
    //   131: iload_2
    //   132: istore_1
    //   133: aconst_null
    //   134: astore #10
    //   136: aload #6
    //   138: astore #7
    //   140: aload #10
    //   142: astore #6
    //   144: aload #6
    //   146: ifnull -> 154
    //   149: aload #6
    //   151: invokevirtual close : ()V
    //   154: aload #7
    //   156: ifnull -> 164
    //   159: aload #7
    //   161: invokevirtual disconnect : ()V
    //   164: aload_0
    //   165: getfield a : Ldla;
    //   168: invokevirtual t : ()Ldlq;
    //   171: new dld
    //   174: dup
    //   175: aload_0
    //   176: getfield e : Ljava/lang/String;
    //   179: aload_0
    //   180: getfield d : Ldlc;
    //   183: iload_1
    //   184: aload #8
    //   186: aconst_null
    //   187: aload #9
    //   189: aconst_null
    //   190: invokespecial <init> : (Ljava/lang/String;Ldlc;ILjava/lang/Throwable;[BLjava/util/Map;Ldlb;)V
    //   193: invokevirtual a : (Ljava/lang/Runnable;)V
    //   196: return
    //   197: iload_1
    //   198: istore_2
    //   199: iload #5
    //   201: istore_3
    //   202: aload_0
    //   203: getfield c : [B
    //   206: ifnull -> 328
    //   209: iload_1
    //   210: istore_2
    //   211: iload #5
    //   213: istore_3
    //   214: aload_0
    //   215: getfield a : Ldla;
    //   218: invokevirtual q : ()Ldou;
    //   221: aload_0
    //   222: getfield c : [B
    //   225: invokevirtual a : ([B)[B
    //   228: astore #8
    //   230: iload_1
    //   231: istore_2
    //   232: iload #5
    //   234: istore_3
    //   235: aload_0
    //   236: getfield a : Ldla;
    //   239: invokevirtual u : ()Ldkw;
    //   242: invokevirtual D : ()Ldky;
    //   245: ldc 'Uploading data. size'
    //   247: aload #8
    //   249: arraylength
    //   250: invokestatic valueOf : (I)Ljava/lang/Integer;
    //   253: invokevirtual a : (Ljava/lang/String;Ljava/lang/Object;)V
    //   256: iload_1
    //   257: istore_2
    //   258: iload #5
    //   260: istore_3
    //   261: aload #6
    //   263: iconst_1
    //   264: invokevirtual setDoOutput : (Z)V
    //   267: iload_1
    //   268: istore_2
    //   269: iload #5
    //   271: istore_3
    //   272: aload #6
    //   274: ldc 'Content-Encoding'
    //   276: ldc 'gzip'
    //   278: invokevirtual addRequestProperty : (Ljava/lang/String;Ljava/lang/String;)V
    //   281: iload_1
    //   282: istore_2
    //   283: iload #5
    //   285: istore_3
    //   286: aload #6
    //   288: aload #8
    //   290: arraylength
    //   291: invokevirtual setFixedLengthStreamingMode : (I)V
    //   294: iload_1
    //   295: istore_2
    //   296: iload #5
    //   298: istore_3
    //   299: aload #6
    //   301: invokestatic connect : (Ljava/net/HttpURLConnection;)V
    //   304: iload_1
    //   305: istore_2
    //   306: iload #5
    //   308: istore_3
    //   309: aload #6
    //   311: invokevirtual getOutputStream : ()Ljava/io/OutputStream;
    //   314: astore #7
    //   316: aload #7
    //   318: aload #8
    //   320: invokevirtual write : ([B)V
    //   323: aload #7
    //   325: invokevirtual close : ()V
    //   328: iload_1
    //   329: istore_2
    //   330: iload #5
    //   332: istore_3
    //   333: aload #6
    //   335: invokestatic getResponseCode : (Ljava/net/HttpURLConnection;)I
    //   338: istore_1
    //   339: iload_1
    //   340: istore_2
    //   341: iload_1
    //   342: istore_3
    //   343: aload #6
    //   345: invokevirtual getHeaderFields : ()Ljava/util/Map;
    //   348: astore #8
    //   350: aload_0
    //   351: getfield a : Ldla;
    //   354: aload #6
    //   356: invokestatic a : (Ldla;Ljava/net/HttpURLConnection;)[B
    //   359: astore #7
    //   361: aload #6
    //   363: ifnull -> 371
    //   366: aload #6
    //   368: invokevirtual disconnect : ()V
    //   371: aload_0
    //   372: getfield a : Ldla;
    //   375: invokevirtual t : ()Ldlq;
    //   378: new dld
    //   381: dup
    //   382: aload_0
    //   383: getfield e : Ljava/lang/String;
    //   386: aload_0
    //   387: getfield d : Ldlc;
    //   390: iload_1
    //   391: aconst_null
    //   392: aload #7
    //   394: aload #8
    //   396: aconst_null
    //   397: invokespecial <init> : (Ljava/lang/String;Ldlc;ILjava/lang/Throwable;[BLjava/util/Map;Ldlb;)V
    //   400: invokevirtual a : (Ljava/lang/Runnable;)V
    //   403: return
    //   404: astore #6
    //   406: aload_0
    //   407: getfield a : Ldla;
    //   410: invokevirtual u : ()Ldkw;
    //   413: invokevirtual x : ()Ldky;
    //   416: ldc 'Error closing HTTP compressed POST connection output stream. appId'
    //   418: aload_0
    //   419: getfield e : Ljava/lang/String;
    //   422: invokestatic a : (Ljava/lang/String;)Ljava/lang/Object;
    //   425: aload #6
    //   427: invokevirtual a : (Ljava/lang/String;Ljava/lang/Object;Ljava/lang/Object;)V
    //   430: goto -> 154
    //   433: astore #8
    //   435: aconst_null
    //   436: astore #6
    //   438: aconst_null
    //   439: astore #9
    //   441: aconst_null
    //   442: astore #7
    //   444: iload #4
    //   446: istore_1
    //   447: aload #7
    //   449: ifnull -> 457
    //   452: aload #7
    //   454: invokevirtual close : ()V
    //   457: aload #9
    //   459: ifnull -> 467
    //   462: aload #9
    //   464: invokevirtual disconnect : ()V
    //   467: aload_0
    //   468: getfield a : Ldla;
    //   471: invokevirtual t : ()Ldlq;
    //   474: new dld
    //   477: dup
    //   478: aload_0
    //   479: getfield e : Ljava/lang/String;
    //   482: aload_0
    //   483: getfield d : Ldlc;
    //   486: iload_1
    //   487: aconst_null
    //   488: aconst_null
    //   489: aload #6
    //   491: aconst_null
    //   492: invokespecial <init> : (Ljava/lang/String;Ldlc;ILjava/lang/Throwable;[BLjava/util/Map;Ldlb;)V
    //   495: invokevirtual a : (Ljava/lang/Runnable;)V
    //   498: aload #8
    //   500: athrow
    //   501: astore #7
    //   503: aload_0
    //   504: getfield a : Ldla;
    //   507: invokevirtual u : ()Ldkw;
    //   510: invokevirtual x : ()Ldky;
    //   513: ldc 'Error closing HTTP compressed POST connection output stream. appId'
    //   515: aload_0
    //   516: getfield e : Ljava/lang/String;
    //   519: invokestatic a : (Ljava/lang/String;)Ljava/lang/Object;
    //   522: aload #7
    //   524: invokevirtual a : (Ljava/lang/String;Ljava/lang/Object;Ljava/lang/Object;)V
    //   527: goto -> 457
    //   530: astore #8
    //   532: aconst_null
    //   533: astore #10
    //   535: aconst_null
    //   536: astore #7
    //   538: aload #6
    //   540: astore #9
    //   542: iload_3
    //   543: istore_1
    //   544: aload #10
    //   546: astore #6
    //   548: goto -> 447
    //   551: astore #8
    //   553: aconst_null
    //   554: astore #10
    //   556: aload #6
    //   558: astore #9
    //   560: iload #4
    //   562: istore_1
    //   563: aload #10
    //   565: astore #6
    //   567: goto -> 447
    //   570: astore #10
    //   572: aconst_null
    //   573: astore #7
    //   575: aload #6
    //   577: astore #9
    //   579: aload #8
    //   581: astore #6
    //   583: aload #10
    //   585: astore #8
    //   587: goto -> 447
    //   590: astore #8
    //   592: aconst_null
    //   593: astore #9
    //   595: iconst_0
    //   596: istore_1
    //   597: aconst_null
    //   598: astore #6
    //   600: aconst_null
    //   601: astore #7
    //   603: goto -> 144
    //   606: astore #10
    //   608: aconst_null
    //   609: astore #9
    //   611: iconst_0
    //   612: istore_1
    //   613: aload #6
    //   615: astore #8
    //   617: aload #7
    //   619: astore #6
    //   621: aload #8
    //   623: astore #7
    //   625: aload #10
    //   627: astore #8
    //   629: goto -> 144
    //   632: astore #10
    //   634: aload #8
    //   636: astore #9
    //   638: aconst_null
    //   639: astore #8
    //   641: aload #6
    //   643: astore #7
    //   645: aload #8
    //   647: astore #6
    //   649: aload #10
    //   651: astore #8
    //   653: goto -> 144
    // Exception table:
    //   from	to	target	type
    //   15	28	590	java/io/IOException
    //   15	28	433	finally
    //   33	40	126	java/io/IOException
    //   33	40	530	finally
    //   45	61	126	java/io/IOException
    //   45	61	530	finally
    //   66	76	126	java/io/IOException
    //   66	76	530	finally
    //   81	93	126	java/io/IOException
    //   81	93	530	finally
    //   98	123	126	java/io/IOException
    //   98	123	530	finally
    //   149	154	404	java/io/IOException
    //   202	209	126	java/io/IOException
    //   202	209	530	finally
    //   214	230	126	java/io/IOException
    //   214	230	530	finally
    //   235	256	126	java/io/IOException
    //   235	256	530	finally
    //   261	267	126	java/io/IOException
    //   261	267	530	finally
    //   272	281	126	java/io/IOException
    //   272	281	530	finally
    //   286	294	126	java/io/IOException
    //   286	294	530	finally
    //   299	304	126	java/io/IOException
    //   299	304	530	finally
    //   309	316	126	java/io/IOException
    //   309	316	530	finally
    //   316	328	606	java/io/IOException
    //   316	328	551	finally
    //   333	339	126	java/io/IOException
    //   333	339	530	finally
    //   343	350	126	java/io/IOException
    //   343	350	530	finally
    //   350	361	632	java/io/IOException
    //   350	361	570	finally
    //   452	457	501	java/io/IOException
  }
}


/* Location:              C:\Users\devid\Downloads\SAST\Santander\dex2jar-2.0\classes2-dex2jar.jar!\dle.class
 * Java compiler version: 6 (50.0)
 * JD-Core Version:       1.1.3
 */