import java.util.concurrent.BlockingQueue;
import java.util.concurrent.FutureTask;

final class dlu extends Thread {
  private final Object b;
  
  private final BlockingQueue<FutureTask<?>> c;
  
  public dlu(dlq paramdlq, String paramString, BlockingQueue<FutureTask<?>> paramBlockingQueue) {
    csp.a(paramString);
    csp.a(paramBlockingQueue);
    this.b = new Object();
    this.c = paramBlockingQueue;
    setName(paramString);
  }
  
  private void a(InterruptedException paramInterruptedException) {
    this.a.u().z().a(String.valueOf(getName()).concat(" was interrupted"), paramInterruptedException);
  }
  
  public void a() {
    synchronized (this.b) {
      this.b.notifyAll();
      return;
    } 
  }
  
  public void run() {
    // Byte code:
    //   0: iconst_0
    //   1: istore_1
    //   2: iload_1
    //   3: ifne -> 30
    //   6: aload_0
    //   7: getfield a : Ldlq;
    //   10: invokestatic a : (Ldlq;)Ljava/util/concurrent/Semaphore;
    //   13: invokevirtual acquire : ()V
    //   16: iconst_1
    //   17: istore_1
    //   18: goto -> 2
    //   21: astore_3
    //   22: aload_0
    //   23: aload_3
    //   24: invokespecial a : (Ljava/lang/InterruptedException;)V
    //   27: goto -> 2
    //   30: aload_0
    //   31: getfield c : Ljava/util/concurrent/BlockingQueue;
    //   34: invokeinterface poll : ()Ljava/lang/Object;
    //   39: checkcast java/util/concurrent/FutureTask
    //   42: astore_3
    //   43: aload_3
    //   44: ifnull -> 111
    //   47: aload_3
    //   48: invokevirtual run : ()V
    //   51: goto -> 30
    //   54: astore #4
    //   56: aload_0
    //   57: getfield a : Ldlq;
    //   60: invokestatic c : (Ldlq;)Ljava/lang/Object;
    //   63: astore_3
    //   64: aload_3
    //   65: monitorenter
    //   66: aload_0
    //   67: getfield a : Ldlq;
    //   70: invokestatic a : (Ldlq;)Ljava/util/concurrent/Semaphore;
    //   73: invokevirtual release : ()V
    //   76: aload_0
    //   77: getfield a : Ldlq;
    //   80: invokestatic c : (Ldlq;)Ljava/lang/Object;
    //   83: invokevirtual notifyAll : ()V
    //   86: aload_0
    //   87: aload_0
    //   88: getfield a : Ldlq;
    //   91: invokestatic d : (Ldlq;)Ldlu;
    //   94: if_acmpne -> 309
    //   97: aload_0
    //   98: getfield a : Ldlq;
    //   101: aconst_null
    //   102: invokestatic a : (Ldlq;Ldlu;)Ldlu;
    //   105: pop
    //   106: aload_3
    //   107: monitorexit
    //   108: aload #4
    //   110: athrow
    //   111: aload_0
    //   112: getfield b : Ljava/lang/Object;
    //   115: astore_3
    //   116: aload_3
    //   117: monitorenter
    //   118: aload_0
    //   119: getfield c : Ljava/util/concurrent/BlockingQueue;
    //   122: invokeinterface peek : ()Ljava/lang/Object;
    //   127: ifnonnull -> 152
    //   130: aload_0
    //   131: getfield a : Ldlq;
    //   134: invokestatic b : (Ldlq;)Z
    //   137: istore_2
    //   138: iload_2
    //   139: ifne -> 152
    //   142: aload_0
    //   143: getfield b : Ljava/lang/Object;
    //   146: ldc2_w 30000
    //   149: invokevirtual wait : (J)V
    //   152: aload_3
    //   153: monitorexit
    //   154: aload_0
    //   155: getfield a : Ldlq;
    //   158: invokestatic c : (Ldlq;)Ljava/lang/Object;
    //   161: astore_3
    //   162: aload_3
    //   163: monitorenter
    //   164: aload_0
    //   165: getfield c : Ljava/util/concurrent/BlockingQueue;
    //   168: invokeinterface peek : ()Ljava/lang/Object;
    //   173: ifnonnull -> 297
    //   176: aload_3
    //   177: monitorexit
    //   178: aload_0
    //   179: getfield a : Ldlq;
    //   182: invokestatic c : (Ldlq;)Ljava/lang/Object;
    //   185: astore_3
    //   186: aload_3
    //   187: monitorenter
    //   188: aload_0
    //   189: getfield a : Ldlq;
    //   192: invokestatic a : (Ldlq;)Ljava/util/concurrent/Semaphore;
    //   195: invokevirtual release : ()V
    //   198: aload_0
    //   199: getfield a : Ldlq;
    //   202: invokestatic c : (Ldlq;)Ljava/lang/Object;
    //   205: invokevirtual notifyAll : ()V
    //   208: aload_0
    //   209: aload_0
    //   210: getfield a : Ldlq;
    //   213: invokestatic d : (Ldlq;)Ldlu;
    //   216: if_acmpne -> 249
    //   219: aload_0
    //   220: getfield a : Ldlq;
    //   223: aconst_null
    //   224: invokestatic a : (Ldlq;Ldlu;)Ldlu;
    //   227: pop
    //   228: aload_3
    //   229: monitorexit
    //   230: return
    //   231: astore #4
    //   233: aload_0
    //   234: aload #4
    //   236: invokespecial a : (Ljava/lang/InterruptedException;)V
    //   239: goto -> 152
    //   242: astore #4
    //   244: aload_3
    //   245: monitorexit
    //   246: aload #4
    //   248: athrow
    //   249: aload_0
    //   250: aload_0
    //   251: getfield a : Ldlq;
    //   254: invokestatic e : (Ldlq;)Ldlu;
    //   257: if_acmpne -> 279
    //   260: aload_0
    //   261: getfield a : Ldlq;
    //   264: aconst_null
    //   265: invokestatic b : (Ldlq;Ldlu;)Ldlu;
    //   268: pop
    //   269: goto -> 228
    //   272: astore #4
    //   274: aload_3
    //   275: monitorexit
    //   276: aload #4
    //   278: athrow
    //   279: aload_0
    //   280: getfield a : Ldlq;
    //   283: invokevirtual u : ()Ldkw;
    //   286: invokevirtual x : ()Ldky;
    //   289: ldc 'Current scheduler thread is neither worker nor network'
    //   291: invokevirtual a : (Ljava/lang/String;)V
    //   294: goto -> 228
    //   297: aload_3
    //   298: monitorexit
    //   299: goto -> 30
    //   302: astore #4
    //   304: aload_3
    //   305: monitorexit
    //   306: aload #4
    //   308: athrow
    //   309: aload_0
    //   310: aload_0
    //   311: getfield a : Ldlq;
    //   314: invokestatic e : (Ldlq;)Ldlu;
    //   317: if_acmpne -> 339
    //   320: aload_0
    //   321: getfield a : Ldlq;
    //   324: aconst_null
    //   325: invokestatic b : (Ldlq;Ldlu;)Ldlu;
    //   328: pop
    //   329: goto -> 106
    //   332: astore #4
    //   334: aload_3
    //   335: monitorexit
    //   336: aload #4
    //   338: athrow
    //   339: aload_0
    //   340: getfield a : Ldlq;
    //   343: invokevirtual u : ()Ldkw;
    //   346: invokevirtual x : ()Ldky;
    //   349: ldc 'Current scheduler thread is neither worker nor network'
    //   351: invokevirtual a : (Ljava/lang/String;)V
    //   354: goto -> 106
    // Exception table:
    //   from	to	target	type
    //   6	16	21	java/lang/InterruptedException
    //   30	43	54	finally
    //   47	51	54	finally
    //   66	106	332	finally
    //   106	108	332	finally
    //   111	118	54	finally
    //   118	138	242	finally
    //   142	152	231	java/lang/InterruptedException
    //   142	152	242	finally
    //   152	154	242	finally
    //   154	164	54	finally
    //   164	178	302	finally
    //   188	228	272	finally
    //   228	230	272	finally
    //   233	239	242	finally
    //   244	246	242	finally
    //   246	249	54	finally
    //   249	269	272	finally
    //   274	276	272	finally
    //   279	294	272	finally
    //   297	299	302	finally
    //   304	306	302	finally
    //   306	309	54	finally
    //   309	329	332	finally
    //   334	336	332	finally
    //   339	354	332	finally
  }
}


/* Location:              C:\Users\devid\Downloads\SAST\Santander\dex2jar-2.0\classes2-dex2jar.jar!\dlu.class
 * Java compiler version: 6 (50.0)
 * JD-Core Version:       1.1.3
 */