import java.util.concurrent.atomic.AtomicReference;

class dnq implements Runnable {
  dnq(dno paramdno, AtomicReference paramAtomicReference, String paramString1, String paramString2, String paramString3, boolean paramBoolean) {}
  
  public void run() {
    // Byte code:
    //   0: aload_0
    //   1: getfield a : Ljava/util/concurrent/atomic/AtomicReference;
    //   4: astore_1
    //   5: aload_1
    //   6: monitorenter
    //   7: aload_0
    //   8: getfield f : Ldno;
    //   11: invokestatic c : (Ldno;)Ldkp;
    //   14: astore_2
    //   15: aload_2
    //   16: ifnonnull -> 69
    //   19: aload_0
    //   20: getfield f : Ldno;
    //   23: invokevirtual u : ()Ldkw;
    //   26: invokevirtual x : ()Ldky;
    //   29: ldc 'Failed to get user properties'
    //   31: aload_0
    //   32: getfield b : Ljava/lang/String;
    //   35: invokestatic a : (Ljava/lang/String;)Ljava/lang/Object;
    //   38: aload_0
    //   39: getfield c : Ljava/lang/String;
    //   42: aload_0
    //   43: getfield d : Ljava/lang/String;
    //   46: invokevirtual a : (Ljava/lang/String;Ljava/lang/Object;Ljava/lang/Object;Ljava/lang/Object;)V
    //   49: aload_0
    //   50: getfield a : Ljava/util/concurrent/atomic/AtomicReference;
    //   53: invokestatic emptyList : ()Ljava/util/List;
    //   56: invokevirtual set : (Ljava/lang/Object;)V
    //   59: aload_0
    //   60: getfield a : Ljava/util/concurrent/atomic/AtomicReference;
    //   63: invokevirtual notify : ()V
    //   66: aload_1
    //   67: monitorexit
    //   68: return
    //   69: aload_0
    //   70: getfield b : Ljava/lang/String;
    //   73: invokestatic isEmpty : (Ljava/lang/CharSequence;)Z
    //   76: ifeq -> 146
    //   79: aload_0
    //   80: getfield a : Ljava/util/concurrent/atomic/AtomicReference;
    //   83: aload_2
    //   84: aload_0
    //   85: getfield c : Ljava/lang/String;
    //   88: aload_0
    //   89: getfield d : Ljava/lang/String;
    //   92: aload_0
    //   93: getfield e : Z
    //   96: aload_0
    //   97: getfield f : Ldno;
    //   100: invokevirtual i : ()Ldks;
    //   103: aload_0
    //   104: getfield f : Ldno;
    //   107: invokevirtual u : ()Ldkw;
    //   110: invokevirtual E : ()Ljava/lang/String;
    //   113: invokevirtual a : (Ljava/lang/String;)Lcom/google/android/gms/internal/zzatd;
    //   116: invokeinterface a : (Ljava/lang/String;Ljava/lang/String;ZLcom/google/android/gms/internal/zzatd;)Ljava/util/List;
    //   121: invokevirtual set : (Ljava/lang/Object;)V
    //   124: aload_0
    //   125: getfield f : Ldno;
    //   128: invokestatic d : (Ldno;)V
    //   131: aload_0
    //   132: getfield a : Ljava/util/concurrent/atomic/AtomicReference;
    //   135: invokevirtual notify : ()V
    //   138: aload_1
    //   139: monitorexit
    //   140: return
    //   141: astore_2
    //   142: aload_1
    //   143: monitorexit
    //   144: aload_2
    //   145: athrow
    //   146: aload_0
    //   147: getfield a : Ljava/util/concurrent/atomic/AtomicReference;
    //   150: aload_2
    //   151: aload_0
    //   152: getfield b : Ljava/lang/String;
    //   155: aload_0
    //   156: getfield c : Ljava/lang/String;
    //   159: aload_0
    //   160: getfield d : Ljava/lang/String;
    //   163: aload_0
    //   164: getfield e : Z
    //   167: invokeinterface a : (Ljava/lang/String;Ljava/lang/String;Ljava/lang/String;Z)Ljava/util/List;
    //   172: invokevirtual set : (Ljava/lang/Object;)V
    //   175: goto -> 124
    //   178: astore_2
    //   179: aload_0
    //   180: getfield f : Ldno;
    //   183: invokevirtual u : ()Ldkw;
    //   186: invokevirtual x : ()Ldky;
    //   189: ldc 'Failed to get user properties'
    //   191: aload_0
    //   192: getfield b : Ljava/lang/String;
    //   195: invokestatic a : (Ljava/lang/String;)Ljava/lang/Object;
    //   198: aload_0
    //   199: getfield c : Ljava/lang/String;
    //   202: aload_2
    //   203: invokevirtual a : (Ljava/lang/String;Ljava/lang/Object;Ljava/lang/Object;Ljava/lang/Object;)V
    //   206: aload_0
    //   207: getfield a : Ljava/util/concurrent/atomic/AtomicReference;
    //   210: invokestatic emptyList : ()Ljava/util/List;
    //   213: invokevirtual set : (Ljava/lang/Object;)V
    //   216: aload_0
    //   217: getfield a : Ljava/util/concurrent/atomic/AtomicReference;
    //   220: invokevirtual notify : ()V
    //   223: goto -> 138
    //   226: astore_2
    //   227: aload_0
    //   228: getfield a : Ljava/util/concurrent/atomic/AtomicReference;
    //   231: invokevirtual notify : ()V
    //   234: aload_2
    //   235: athrow
    // Exception table:
    //   from	to	target	type
    //   7	15	178	android/os/RemoteException
    //   7	15	226	finally
    //   19	59	178	android/os/RemoteException
    //   19	59	226	finally
    //   59	68	141	finally
    //   69	124	178	android/os/RemoteException
    //   69	124	226	finally
    //   124	131	178	android/os/RemoteException
    //   124	131	226	finally
    //   131	138	141	finally
    //   138	140	141	finally
    //   142	144	141	finally
    //   146	175	178	android/os/RemoteException
    //   146	175	226	finally
    //   179	216	226	finally
    //   216	223	141	finally
    //   227	236	141	finally
  }
}


/* Location:              C:\Users\devid\Downloads\SAST\Santander\dex2jar-2.0\classes2-dex2jar.jar!\dnq.class
 * Java compiler version: 6 (50.0)
 * JD-Core Version:       1.1.3
 */