import java.util.concurrent.atomic.AtomicReference;

class dns implements Runnable {
  dns(dno paramdno, AtomicReference paramAtomicReference, boolean paramBoolean) {}
  
  public void run() {
    // Byte code:
    //   0: aload_0
    //   1: getfield a : Ljava/util/concurrent/atomic/AtomicReference;
    //   4: astore_1
    //   5: aload_1
    //   6: monitorenter
    //   7: aload_0
    //   8: getfield c : Ldno;
    //   11: invokestatic c : (Ldno;)Ldkp;
    //   14: astore_2
    //   15: aload_2
    //   16: ifnonnull -> 44
    //   19: aload_0
    //   20: getfield c : Ldno;
    //   23: invokevirtual u : ()Ldkw;
    //   26: invokevirtual x : ()Ldky;
    //   29: ldc 'Failed to get user properties'
    //   31: invokevirtual a : (Ljava/lang/String;)V
    //   34: aload_0
    //   35: getfield a : Ljava/util/concurrent/atomic/AtomicReference;
    //   38: invokevirtual notify : ()V
    //   41: aload_1
    //   42: monitorexit
    //   43: return
    //   44: aload_0
    //   45: getfield a : Ljava/util/concurrent/atomic/AtomicReference;
    //   48: aload_2
    //   49: aload_0
    //   50: getfield c : Ldno;
    //   53: invokevirtual i : ()Ldks;
    //   56: aconst_null
    //   57: invokevirtual a : (Ljava/lang/String;)Lcom/google/android/gms/internal/zzatd;
    //   60: aload_0
    //   61: getfield b : Z
    //   64: invokeinterface a : (Lcom/google/android/gms/internal/zzatd;Z)Ljava/util/List;
    //   69: invokevirtual set : (Ljava/lang/Object;)V
    //   72: aload_0
    //   73: getfield c : Ldno;
    //   76: invokestatic d : (Ldno;)V
    //   79: aload_0
    //   80: getfield a : Ljava/util/concurrent/atomic/AtomicReference;
    //   83: invokevirtual notify : ()V
    //   86: aload_1
    //   87: monitorexit
    //   88: return
    //   89: astore_2
    //   90: aload_1
    //   91: monitorexit
    //   92: aload_2
    //   93: athrow
    //   94: astore_2
    //   95: aload_0
    //   96: getfield c : Ldno;
    //   99: invokevirtual u : ()Ldkw;
    //   102: invokevirtual x : ()Ldky;
    //   105: ldc 'Failed to get user properties'
    //   107: aload_2
    //   108: invokevirtual a : (Ljava/lang/String;Ljava/lang/Object;)V
    //   111: aload_0
    //   112: getfield a : Ljava/util/concurrent/atomic/AtomicReference;
    //   115: invokevirtual notify : ()V
    //   118: goto -> 86
    //   121: astore_2
    //   122: aload_0
    //   123: getfield a : Ljava/util/concurrent/atomic/AtomicReference;
    //   126: invokevirtual notify : ()V
    //   129: aload_2
    //   130: athrow
    // Exception table:
    //   from	to	target	type
    //   7	15	94	android/os/RemoteException
    //   7	15	121	finally
    //   19	34	94	android/os/RemoteException
    //   19	34	121	finally
    //   34	43	89	finally
    //   44	79	94	android/os/RemoteException
    //   44	79	121	finally
    //   79	86	89	finally
    //   86	88	89	finally
    //   90	92	89	finally
    //   95	111	121	finally
    //   111	118	89	finally
    //   122	131	89	finally
  }
}


/* Location:              C:\Users\devid\Downloads\SAST\Santander\dex2jar-2.0\classes2-dex2jar.jar!\dns.class
 * Java compiler version: 6 (50.0)
 * JD-Core Version:       1.1.3
 */