import java.text.DateFormat;
import java.util.Date;
import java.util.Locale;

public final class emz extends ekn<Date> {
  public static final ekp a = new ena();
  
  private final DateFormat b = DateFormat.getDateTimeInstance(2, 2, Locale.US);
  
  private final DateFormat c = DateFormat.getDateTimeInstance(2, 2);
  
  private Date b(String paramString) {
    // Byte code:
    //   0: aload_0
    //   1: monitorenter
    //   2: aload_0
    //   3: getfield c : Ljava/text/DateFormat;
    //   6: aload_1
    //   7: invokevirtual parse : (Ljava/lang/String;)Ljava/util/Date;
    //   10: astore_2
    //   11: aload_2
    //   12: astore_1
    //   13: aload_0
    //   14: monitorexit
    //   15: aload_1
    //   16: areturn
    //   17: astore_2
    //   18: aload_0
    //   19: getfield b : Ljava/text/DateFormat;
    //   22: aload_1
    //   23: invokevirtual parse : (Ljava/lang/String;)Ljava/util/Date;
    //   26: astore_2
    //   27: aload_2
    //   28: astore_1
    //   29: goto -> 13
    //   32: astore_2
    //   33: aload_1
    //   34: new java/text/ParsePosition
    //   37: dup
    //   38: iconst_0
    //   39: invokespecial <init> : (I)V
    //   42: invokestatic a : (Ljava/lang/String;Ljava/text/ParsePosition;)Ljava/util/Date;
    //   45: astore_2
    //   46: aload_2
    //   47: astore_1
    //   48: goto -> 13
    //   51: astore_2
    //   52: new ekj
    //   55: dup
    //   56: aload_1
    //   57: aload_2
    //   58: invokespecial <init> : (Ljava/lang/String;Ljava/lang/Throwable;)V
    //   61: athrow
    //   62: astore_1
    //   63: aload_0
    //   64: monitorexit
    //   65: aload_1
    //   66: athrow
    // Exception table:
    //   from	to	target	type
    //   2	11	17	java/text/ParseException
    //   2	11	62	finally
    //   18	27	32	java/text/ParseException
    //   18	27	62	finally
    //   33	46	51	java/text/ParseException
    //   33	46	62	finally
    //   52	62	62	finally
  }
  
  public Date a(epo paramepo) {
    if (paramepo.f() == epr.NULL) {
      paramepo.j();
      return null;
    } 
    return b(paramepo.h());
  }
  
  public void a(eps parameps, Date paramDate) {
    // Byte code:
    //   0: aload_0
    //   1: monitorenter
    //   2: aload_2
    //   3: ifnonnull -> 14
    //   6: aload_1
    //   7: invokevirtual f : ()Leps;
    //   10: pop
    //   11: aload_0
    //   12: monitorexit
    //   13: return
    //   14: aload_1
    //   15: aload_0
    //   16: getfield b : Ljava/text/DateFormat;
    //   19: aload_2
    //   20: invokevirtual format : (Ljava/util/Date;)Ljava/lang/String;
    //   23: invokevirtual b : (Ljava/lang/String;)Leps;
    //   26: pop
    //   27: goto -> 11
    //   30: astore_1
    //   31: aload_0
    //   32: monitorexit
    //   33: aload_1
    //   34: athrow
    // Exception table:
    //   from	to	target	type
    //   6	11	30	finally
    //   14	27	30	finally
  }
}


/* Location:              C:\Users\devid\Downloads\SAST\Santander\dex2jar-2.0\classes2-dex2jar.jar!\emz.class
 * Java compiler version: 6 (50.0)
 * JD-Core Version:       1.1.3
 */