import java.sql.Date;
import java.text.DateFormat;
import java.text.SimpleDateFormat;

public final class enp extends ekn<Date> {
  public static final ekp a = new enq();
  
  private final DateFormat b = new SimpleDateFormat("MMM d, yyyy");
  
  public Date a(epo paramepo) {
    // Byte code:
    //   0: aload_0
    //   1: monitorenter
    //   2: aload_1
    //   3: invokevirtual f : ()Lepr;
    //   6: getstatic epr.NULL : Lepr;
    //   9: if_acmpne -> 22
    //   12: aload_1
    //   13: invokevirtual j : ()V
    //   16: aconst_null
    //   17: astore_1
    //   18: aload_0
    //   19: monitorexit
    //   20: aload_1
    //   21: areturn
    //   22: new java/sql/Date
    //   25: dup
    //   26: aload_0
    //   27: getfield b : Ljava/text/DateFormat;
    //   30: aload_1
    //   31: invokevirtual h : ()Ljava/lang/String;
    //   34: invokevirtual parse : (Ljava/lang/String;)Ljava/util/Date;
    //   37: invokevirtual getTime : ()J
    //   40: invokespecial <init> : (J)V
    //   43: astore_1
    //   44: goto -> 18
    //   47: astore_1
    //   48: new ekj
    //   51: dup
    //   52: aload_1
    //   53: invokespecial <init> : (Ljava/lang/Throwable;)V
    //   56: athrow
    //   57: astore_1
    //   58: aload_0
    //   59: monitorexit
    //   60: aload_1
    //   61: athrow
    // Exception table:
    //   from	to	target	type
    //   2	16	57	finally
    //   22	44	47	java/text/ParseException
    //   22	44	57	finally
    //   48	57	57	finally
  }
  
  public void a(eps parameps, Date paramDate) {
    // Byte code:
    //   0: aload_0
    //   1: monitorenter
    //   2: aload_2
    //   3: ifnonnull -> 17
    //   6: aconst_null
    //   7: astore_2
    //   8: aload_1
    //   9: aload_2
    //   10: invokevirtual b : (Ljava/lang/String;)Leps;
    //   13: pop
    //   14: aload_0
    //   15: monitorexit
    //   16: return
    //   17: aload_0
    //   18: getfield b : Ljava/text/DateFormat;
    //   21: aload_2
    //   22: invokevirtual format : (Ljava/util/Date;)Ljava/lang/String;
    //   25: astore_2
    //   26: goto -> 8
    //   29: astore_1
    //   30: aload_0
    //   31: monitorexit
    //   32: aload_1
    //   33: athrow
    // Exception table:
    //   from	to	target	type
    //   8	14	29	finally
    //   17	26	29	finally
  }
}


/* Location:              C:\Users\devid\Downloads\SAST\Santander\dex2jar-2.0\classes2-dex2jar.jar!\enp.class
 * Java compiler version: 6 (50.0)
 * JD-Core Version:       1.1.3
 */