import java.util.Map;

public final class eqt implements eqk {
  public eqm a(epw paramepw) {
    return a(paramepw, null);
  }
  
  public eqm a(epw paramepw, Map<epy, ?> paramMap) {
    // Byte code:
    //   0: aconst_null
    //   1: astore #7
    //   3: new eqy
    //   6: dup
    //   7: aload_1
    //   8: invokevirtual c : ()Lett;
    //   11: invokespecial <init> : (Lett;)V
    //   14: astore #9
    //   16: aload #9
    //   18: iconst_0
    //   19: invokevirtual a : (Z)Leqs;
    //   22: astore #5
    //   24: aload #5
    //   26: invokevirtual e : ()[Leqo;
    //   29: astore_1
    //   30: new eqv
    //   33: dup
    //   34: invokespecial <init> : ()V
    //   37: aload #5
    //   39: invokevirtual a : (Leqs;)Letw;
    //   42: astore #8
    //   44: aconst_null
    //   45: astore #6
    //   47: aload_1
    //   48: astore #5
    //   50: aload #8
    //   52: astore_1
    //   53: aload_1
    //   54: ifnonnull -> 263
    //   57: aload #9
    //   59: iconst_1
    //   60: invokevirtual a : (Z)Leqs;
    //   63: astore_1
    //   64: aload_1
    //   65: invokevirtual e : ()[Leqo;
    //   68: astore #5
    //   70: new eqv
    //   73: dup
    //   74: invokespecial <init> : ()V
    //   77: aload_1
    //   78: invokevirtual a : (Leqs;)Letw;
    //   81: astore_1
    //   82: aload_2
    //   83: ifnull -> 183
    //   86: aload_2
    //   87: getstatic epy.NEED_RESULT_POINT_CALLBACK : Lepy;
    //   90: invokeinterface get : (Ljava/lang/Object;)Ljava/lang/Object;
    //   95: checkcast eqp
    //   98: astore_2
    //   99: aload_2
    //   100: ifnull -> 183
    //   103: aload #5
    //   105: arraylength
    //   106: istore #4
    //   108: iconst_0
    //   109: istore_3
    //   110: iload_3
    //   111: iload #4
    //   113: if_icmpge -> 183
    //   116: aload_2
    //   117: aload #5
    //   119: iload_3
    //   120: aaload
    //   121: invokeinterface a : (Leqo;)V
    //   126: iload_3
    //   127: iconst_1
    //   128: iadd
    //   129: istore_3
    //   130: goto -> 110
    //   133: astore #6
    //   135: aconst_null
    //   136: astore #5
    //   138: aconst_null
    //   139: astore_1
    //   140: goto -> 53
    //   143: astore #6
    //   145: aconst_null
    //   146: astore #5
    //   148: aconst_null
    //   149: astore #8
    //   151: aconst_null
    //   152: astore_1
    //   153: aload #6
    //   155: astore #7
    //   157: aload #8
    //   159: astore #6
    //   161: goto -> 53
    //   164: astore_1
    //   165: aload #6
    //   167: ifnull -> 173
    //   170: aload #6
    //   172: athrow
    //   173: aload #7
    //   175: ifnull -> 181
    //   178: aload #7
    //   180: athrow
    //   181: aload_1
    //   182: athrow
    //   183: new eqm
    //   186: dup
    //   187: aload_1
    //   188: invokevirtual b : ()Ljava/lang/String;
    //   191: aload_1
    //   192: invokevirtual a : ()[B
    //   195: aload #5
    //   197: getstatic epu.AZTEC : Lepu;
    //   200: invokespecial <init> : (Ljava/lang/String;[B[Leqo;Lepu;)V
    //   203: astore_2
    //   204: aload_1
    //   205: invokevirtual c : ()Ljava/util/List;
    //   208: astore #5
    //   210: aload #5
    //   212: ifnull -> 224
    //   215: aload_2
    //   216: getstatic eqn.BYTE_SEGMENTS : Leqn;
    //   219: aload #5
    //   221: invokevirtual a : (Leqn;Ljava/lang/Object;)V
    //   224: aload_1
    //   225: invokevirtual d : ()Ljava/lang/String;
    //   228: astore_1
    //   229: aload_1
    //   230: ifnull -> 241
    //   233: aload_2
    //   234: getstatic eqn.ERROR_CORRECTION_LEVEL : Leqn;
    //   237: aload_1
    //   238: invokevirtual a : (Leqn;Ljava/lang/Object;)V
    //   241: aload_2
    //   242: areturn
    //   243: astore_1
    //   244: goto -> 165
    //   247: astore #6
    //   249: aload_1
    //   250: astore #5
    //   252: goto -> 148
    //   255: astore #6
    //   257: aload_1
    //   258: astore #5
    //   260: goto -> 138
    //   263: goto -> 82
    // Exception table:
    //   from	to	target	type
    //   16	30	133	eqh
    //   16	30	143	eqb
    //   30	44	255	eqh
    //   30	44	247	eqb
    //   57	82	243	eqh
    //   57	82	164	eqb
  }
  
  public void a() {}
}


/* Location:              C:\Users\devid\Downloads\SAST\Santander\dex2jar-2.0\classes2-dex2jar.jar!\eqt.class
 * Java compiler version: 6 (50.0)
 * JD-Core Version:       1.1.3
 */