import java.util.Map;

public final class ewi extends eww {
  static final int[][] a;
  
  private static final float b = 0.25F;
  
  private static final float c = 0.7F;
  
  private static final int d = 98;
  
  private static final int e = 99;
  
  private static final int f = 100;
  
  private static final int g = 101;
  
  private static final int h = 102;
  
  private static final int i = 97;
  
  private static final int j = 96;
  
  private static final int k = 101;
  
  private static final int l = 100;
  
  private static final int m = 103;
  
  private static final int n = 104;
  
  private static final int o = 105;
  
  private static final int p = 106;
  
  static {
    int[] arrayOfInt1 = { 2, 2, 2, 2, 2, 1 };
    int[] arrayOfInt2 = { 1, 3, 1, 2, 2, 2 };
    int[] arrayOfInt3 = { 1, 1, 3, 2, 2, 2 };
    int[] arrayOfInt4 = { 2, 2, 3, 2, 1, 1 };
    int[] arrayOfInt5 = { 3, 1, 2, 1, 3, 1 };
    int[] arrayOfInt6 = { 3, 2, 1, 1, 2, 2 };
    int[] arrayOfInt7 = { 3, 2, 2, 1, 1, 2 };
    int[] arrayOfInt8 = { 2, 1, 2, 1, 2, 3 };
    int[] arrayOfInt9 = { 1, 1, 2, 3, 1, 3 };
    int[] arrayOfInt10 = { 1, 1, 2, 1, 3, 3 };
    int[] arrayOfInt11 = { 1, 1, 3, 3, 2, 1 };
    int[] arrayOfInt12 = { 2, 2, 1, 4, 1, 1 };
    int[] arrayOfInt13 = { 1, 2, 2, 1, 1, 4 };
    int[] arrayOfInt14 = { 1, 2, 2, 4, 1, 1 };
    int[] arrayOfInt15 = { 1, 2, 4, 2, 1, 1 };
    int[] arrayOfInt16 = { 1, 3, 1, 1, 4, 1 };
    int[] arrayOfInt17 = { 4, 1, 1, 1, 1, 3 };
    a = new int[][] { 
        { 2, 1, 2, 2, 2, 2 }, { 2, 2, 2, 1, 2, 2 }, arrayOfInt1, { 1, 2, 1, 2, 2, 3 }, { 1, 2, 1, 3, 2, 2 }, arrayOfInt2, { 1, 2, 2, 2, 1, 3 }, { 1, 2, 2, 3, 1, 2 }, { 1, 3, 2, 2, 1, 2 }, { 2, 2, 1, 2, 1, 3 }, 
        { 2, 2, 1, 3, 1, 2 }, { 2, 3, 1, 2, 1, 2 }, { 1, 1, 2, 2, 3, 2 }, { 1, 2, 2, 1, 3, 2 }, { 1, 2, 2, 2, 3, 1 }, arrayOfInt3, { 1, 2, 3, 1, 2, 2 }, { 1, 2, 3, 2, 2, 1 }, arrayOfInt4, { 2, 2, 1, 1, 3, 2 }, 
        { 2, 2, 1, 2, 3, 1 }, { 2, 1, 3, 2, 1, 2 }, { 2, 2, 3, 1, 1, 2 }, arrayOfInt5, { 3, 1, 1, 2, 2, 2 }, arrayOfInt6, { 3, 2, 1, 2, 2, 1 }, { 3, 1, 2, 2, 1, 2 }, arrayOfInt7, { 3, 2, 2, 2, 1, 1 }, 
        arrayOfInt8, { 2, 1, 2, 3, 2, 1 }, { 2, 3, 2, 1, 2, 1 }, { 1, 1, 1, 3, 2, 3 }, { 1, 3, 1, 1, 2, 3 }, { 1, 3, 1, 3, 2, 1 }, arrayOfInt9, { 1, 3, 2, 1, 1, 3 }, { 1, 3, 2, 3, 1, 1 }, { 2, 1, 1, 3, 1, 3 }, 
        { 2, 3, 1, 1, 1, 3 }, { 2, 3, 1, 3, 1, 1 }, arrayOfInt10, { 1, 1, 2, 3, 3, 1 }, { 1, 3, 2, 1, 3, 1 }, { 1, 1, 3, 1, 2, 3 }, arrayOfInt11, { 1, 3, 3, 1, 2, 1 }, { 3, 1, 3, 1, 2, 1 }, { 2, 1, 1, 3, 3, 1 }, 
        { 2, 3, 1, 1, 3, 1 }, { 2, 1, 3, 1, 1, 3 }, { 2, 1, 3, 3, 1, 1 }, { 2, 1, 3, 1, 3, 1 }, { 3, 1, 1, 1, 2, 3 }, { 3, 1, 1, 3, 2, 1 }, { 3, 3, 1, 1, 2, 1 }, { 3, 1, 2, 1, 1, 3 }, { 3, 1, 2, 3, 1, 1 }, { 3, 3, 2, 1, 1, 1 }, 
        { 3, 1, 4, 1, 1, 1 }, arrayOfInt12, { 4, 3, 1, 1, 1, 1 }, { 1, 1, 1, 2, 2, 4 }, { 1, 1, 1, 4, 2, 2 }, { 1, 2, 1, 1, 2, 4 }, { 1, 2, 1, 4, 2, 1 }, { 1, 4, 1, 1, 2, 2 }, { 1, 4, 1, 2, 2, 1 }, { 1, 1, 2, 2, 1, 4 }, 
        { 1, 1, 2, 4, 1, 2 }, arrayOfInt13, arrayOfInt14, { 1, 4, 2, 1, 1, 2 }, { 1, 4, 2, 2, 1, 1 }, { 2, 4, 1, 2, 1, 1 }, { 2, 2, 1, 1, 1, 4 }, { 4, 1, 3, 1, 1, 1 }, { 2, 4, 1, 1, 1, 2 }, { 1, 3, 4, 1, 1, 1 }, 
        { 1, 1, 1, 2, 4, 2 }, { 1, 2, 1, 1, 4, 2 }, { 1, 2, 1, 2, 4, 1 }, { 1, 1, 4, 2, 1, 2 }, { 1, 2, 4, 1, 1, 2 }, arrayOfInt15, { 4, 1, 1, 2, 1, 2 }, { 4, 2, 1, 1, 1, 2 }, { 4, 2, 1, 2, 1, 1 }, { 2, 1, 2, 1, 4, 1 }, 
        { 2, 1, 4, 1, 2, 1 }, { 4, 1, 2, 1, 2, 1 }, { 1, 1, 1, 1, 4, 3 }, { 1, 1, 1, 3, 4, 1 }, arrayOfInt16, { 1, 1, 4, 1, 1, 3 }, { 1, 1, 4, 3, 1, 1 }, arrayOfInt17, { 4, 1, 1, 3, 1, 1 }, { 1, 1, 3, 1, 4, 1 }, 
        { 1, 1, 4, 1, 3, 1 }, { 3, 1, 1, 1, 4, 1 }, { 4, 1, 1, 1, 3, 1 }, { 2, 1, 1, 4, 1, 2 }, { 2, 1, 1, 2, 1, 4 }, { 2, 1, 1, 2, 3, 2 }, { 2, 3, 3, 1, 1, 1, 2 } };
  }
  
  private static int a(ets paramets, int[] paramArrayOfint, int paramInt) {
    a(paramets, paramInt, paramArrayOfint);
    float f = 0.25F;
    int i = -1;
    paramInt = 0;
    while (paramInt < a.length) {
      float f2 = a(paramArrayOfint, a[paramInt], 0.7F);
      float f1 = f;
      if (f2 < f) {
        i = paramInt;
        f1 = f2;
      } 
      paramInt++;
      f = f1;
    } 
    if (i >= 0)
      return i; 
    throw eqh.a();
  }
  
  private static int[] a(ets paramets) {
    int m = paramets.a();
    int i = paramets.d(0);
    int[] arrayOfInt = new int[6];
    int n = arrayOfInt.length;
    int k = i;
    boolean bool = false;
    for (int j = 0; k < m; j = i1) {
      if (paramets.a(k) ^ bool) {
        arrayOfInt[j] = arrayOfInt[j] + 1;
        int i2 = j;
        j = i;
        i = i2;
      } else {
        if (j == n - 1) {
          float f = 0.25F;
          int i3 = -1;
          int i2;
          for (i2 = 103; i2 <= 105; i2++) {
            float f1 = a(arrayOfInt, a[i2], 0.7F);
            if (f1 < f) {
              i3 = i2;
              f = f1;
            } 
          } 
          if (i3 >= 0 && paramets.a(Math.max(0, i - (k - i) / 2), i, false))
            return new int[] { i, k, i3 }; 
          i2 = arrayOfInt[0] + arrayOfInt[1] + i;
          System.arraycopy(arrayOfInt, 2, arrayOfInt, 0, n - 2);
          arrayOfInt[n - 2] = 0;
          arrayOfInt[n - 1] = 0;
          i = j - 1;
          j = i2;
        } else {
          int i2 = j + 1;
          j = i;
          i = i2;
        } 
        arrayOfInt[i] = 1;
        if (!bool) {
          bool = true;
        } else {
          bool = false;
        } 
      } 
      k++;
      int i1 = i;
      i = j;
    } 
    throw eqh.a();
  }
  
  public eqm a(int paramInt, ets paramets, Map<epy, ?> paramMap) {
    // Byte code:
    //   0: aload_3
    //   1: ifnull -> 88
    //   4: aload_3
    //   5: getstatic epy.ASSUME_GS1 : Lepy;
    //   8: invokeinterface containsKey : (Ljava/lang/Object;)Z
    //   13: ifeq -> 88
    //   16: iconst_1
    //   17: istore #20
    //   19: aload_2
    //   20: invokestatic a : (Lets;)[I
    //   23: astore #28
    //   25: aload #28
    //   27: iconst_2
    //   28: iaload
    //   29: istore #12
    //   31: new java/util/ArrayList
    //   34: dup
    //   35: bipush #20
    //   37: invokespecial <init> : (I)V
    //   40: astore_3
    //   41: aload_3
    //   42: iload #12
    //   44: i2b
    //   45: invokestatic valueOf : (B)Ljava/lang/Byte;
    //   48: invokeinterface add : (Ljava/lang/Object;)Z
    //   53: pop
    //   54: iload #12
    //   56: tableswitch default -> 84, 103 -> 94, 104 -> 272, 105 -> 279
    //   84: invokestatic a : ()Leqb;
    //   87: athrow
    //   88: iconst_0
    //   89: istore #20
    //   91: goto -> 19
    //   94: bipush #101
    //   96: istore #7
    //   98: new java/lang/StringBuilder
    //   101: dup
    //   102: bipush #20
    //   104: invokespecial <init> : (I)V
    //   107: astore #27
    //   109: aload #28
    //   111: iconst_0
    //   112: iaload
    //   113: istore #17
    //   115: aload #28
    //   117: iconst_1
    //   118: iaload
    //   119: istore #13
    //   121: bipush #6
    //   123: newarray int
    //   125: astore #29
    //   127: iconst_1
    //   128: istore #11
    //   130: iconst_0
    //   131: istore #16
    //   133: iconst_0
    //   134: istore #10
    //   136: iconst_0
    //   137: istore #21
    //   139: iconst_0
    //   140: istore #14
    //   142: iconst_0
    //   143: istore #18
    //   145: iconst_0
    //   146: istore #15
    //   148: iconst_0
    //   149: istore #8
    //   151: iload #7
    //   153: istore #9
    //   155: iload #16
    //   157: istore #7
    //   159: iload #8
    //   161: ifne -> 1892
    //   164: iconst_0
    //   165: istore #26
    //   167: iconst_0
    //   168: istore #25
    //   170: aload_2
    //   171: aload #29
    //   173: iload #13
    //   175: invokestatic a : (Lets;[II)I
    //   178: istore #24
    //   180: aload_3
    //   181: iload #24
    //   183: i2b
    //   184: invokestatic valueOf : (B)Ljava/lang/Byte;
    //   187: invokeinterface add : (Ljava/lang/Object;)Z
    //   192: pop
    //   193: iload #24
    //   195: bipush #106
    //   197: if_icmpeq -> 203
    //   200: iconst_1
    //   201: istore #11
    //   203: iload #14
    //   205: istore #23
    //   207: iload #12
    //   209: istore #22
    //   211: iload #24
    //   213: bipush #106
    //   215: if_icmpeq -> 234
    //   218: iload #14
    //   220: iconst_1
    //   221: iadd
    //   222: istore #23
    //   224: iload #12
    //   226: iload #23
    //   228: iload #24
    //   230: imul
    //   231: iadd
    //   232: istore #22
    //   234: aload #29
    //   236: arraylength
    //   237: istore #14
    //   239: iconst_0
    //   240: istore #12
    //   242: iload #13
    //   244: istore #16
    //   246: iload #12
    //   248: iload #14
    //   250: if_icmpge -> 286
    //   253: iload #16
    //   255: aload #29
    //   257: iload #12
    //   259: iaload
    //   260: iadd
    //   261: istore #16
    //   263: iload #12
    //   265: iconst_1
    //   266: iadd
    //   267: istore #12
    //   269: goto -> 246
    //   272: bipush #100
    //   274: istore #7
    //   276: goto -> 98
    //   279: bipush #99
    //   281: istore #7
    //   283: goto -> 98
    //   286: iload #24
    //   288: tableswitch default -> 316, 103 -> 462, 104 -> 462, 105 -> 462
    //   316: iload #9
    //   318: tableswitch default -> 344, 99 -> 1528, 100 -> 1036, 101 -> 466
    //   344: iload #11
    //   346: istore #12
    //   348: iload #9
    //   350: istore #14
    //   352: iconst_0
    //   353: istore #11
    //   355: iload #10
    //   357: istore #17
    //   359: iload #12
    //   361: istore #10
    //   363: iload #8
    //   365: istore #12
    //   367: iload #7
    //   369: istore #9
    //   371: iload #17
    //   373: istore #8
    //   375: iload #14
    //   377: istore #7
    //   379: iload #7
    //   381: istore #14
    //   383: iload #21
    //   385: ifeq -> 399
    //   388: iload #7
    //   390: bipush #101
    //   392: if_icmpne -> 1885
    //   395: bipush #100
    //   397: istore #14
    //   399: iload #11
    //   401: istore #21
    //   403: iload #14
    //   405: istore #11
    //   407: iload #9
    //   409: istore #7
    //   411: iload #15
    //   413: istore #18
    //   415: iload #24
    //   417: istore #15
    //   419: iload #10
    //   421: istore #17
    //   423: iload #12
    //   425: istore #9
    //   427: iload #23
    //   429: istore #14
    //   431: iload #22
    //   433: istore #12
    //   435: iload #8
    //   437: istore #10
    //   439: iload #9
    //   441: istore #8
    //   443: iload #11
    //   445: istore #9
    //   447: iload #17
    //   449: istore #11
    //   451: iload #13
    //   453: istore #17
    //   455: iload #16
    //   457: istore #13
    //   459: goto -> 159
    //   462: invokestatic a : ()Leqb;
    //   465: athrow
    //   466: iload #24
    //   468: bipush #64
    //   470: if_icmpge -> 548
    //   473: iload #10
    //   475: iload #7
    //   477: if_icmpne -> 529
    //   480: aload #27
    //   482: iload #24
    //   484: bipush #32
    //   486: iadd
    //   487: i2c
    //   488: invokevirtual append : (C)Ljava/lang/StringBuilder;
    //   491: pop
    //   492: iload #9
    //   494: istore #14
    //   496: iconst_0
    //   497: istore #17
    //   499: iload #7
    //   501: istore #9
    //   503: iconst_0
    //   504: istore #18
    //   506: iload #11
    //   508: istore #10
    //   510: iload #8
    //   512: istore #12
    //   514: iload #14
    //   516: istore #7
    //   518: iload #18
    //   520: istore #8
    //   522: iload #17
    //   524: istore #11
    //   526: goto -> 379
    //   529: aload #27
    //   531: iload #24
    //   533: bipush #32
    //   535: iadd
    //   536: sipush #128
    //   539: iadd
    //   540: i2c
    //   541: invokevirtual append : (C)Ljava/lang/StringBuilder;
    //   544: pop
    //   545: goto -> 492
    //   548: iload #24
    //   550: bipush #96
    //   552: if_icmpge -> 626
    //   555: iload #10
    //   557: iload #7
    //   559: if_icmpne -> 611
    //   562: aload #27
    //   564: iload #24
    //   566: bipush #64
    //   568: isub
    //   569: i2c
    //   570: invokevirtual append : (C)Ljava/lang/StringBuilder;
    //   573: pop
    //   574: iload #9
    //   576: istore #14
    //   578: iconst_0
    //   579: istore #17
    //   581: iload #7
    //   583: istore #9
    //   585: iconst_0
    //   586: istore #18
    //   588: iload #11
    //   590: istore #10
    //   592: iload #8
    //   594: istore #12
    //   596: iload #14
    //   598: istore #7
    //   600: iload #18
    //   602: istore #8
    //   604: iload #17
    //   606: istore #11
    //   608: goto -> 379
    //   611: aload #27
    //   613: iload #24
    //   615: bipush #64
    //   617: iadd
    //   618: i2c
    //   619: invokevirtual append : (C)Ljava/lang/StringBuilder;
    //   622: pop
    //   623: goto -> 574
    //   626: iload #11
    //   628: istore #17
    //   630: iload #24
    //   632: bipush #106
    //   634: if_icmpeq -> 640
    //   637: iconst_0
    //   638: istore #17
    //   640: iload #10
    //   642: istore #11
    //   644: iload #7
    //   646: istore #14
    //   648: iload #25
    //   650: istore #19
    //   652: iload #8
    //   654: istore #18
    //   656: iload #9
    //   658: istore #12
    //   660: iload #24
    //   662: tableswitch default -> 720, 96 -> 740, 97 -> 740, 98 -> 946, 99 -> 991, 100 -> 968, 101 -> 862, 102 -> 767, 103 -> 740, 104 -> 740, 105 -> 740, 106 -> 1014
    //   720: iload #9
    //   722: istore #12
    //   724: iload #8
    //   726: istore #18
    //   728: iload #25
    //   730: istore #19
    //   732: iload #7
    //   734: istore #14
    //   736: iload #10
    //   738: istore #11
    //   740: iload #12
    //   742: istore #7
    //   744: iload #14
    //   746: istore #9
    //   748: iload #11
    //   750: istore #8
    //   752: iload #17
    //   754: istore #10
    //   756: iload #18
    //   758: istore #12
    //   760: iload #19
    //   762: istore #11
    //   764: goto -> 379
    //   767: iload #10
    //   769: istore #11
    //   771: iload #7
    //   773: istore #14
    //   775: iload #25
    //   777: istore #19
    //   779: iload #8
    //   781: istore #18
    //   783: iload #9
    //   785: istore #12
    //   787: iload #20
    //   789: ifeq -> 740
    //   792: aload #27
    //   794: invokevirtual length : ()I
    //   797: ifne -> 831
    //   800: aload #27
    //   802: ldc ']C1'
    //   804: invokevirtual append : (Ljava/lang/String;)Ljava/lang/StringBuilder;
    //   807: pop
    //   808: iload #10
    //   810: istore #11
    //   812: iload #7
    //   814: istore #14
    //   816: iload #25
    //   818: istore #19
    //   820: iload #8
    //   822: istore #18
    //   824: iload #9
    //   826: istore #12
    //   828: goto -> 740
    //   831: aload #27
    //   833: bipush #29
    //   835: invokevirtual append : (C)Ljava/lang/StringBuilder;
    //   838: pop
    //   839: iload #10
    //   841: istore #11
    //   843: iload #7
    //   845: istore #14
    //   847: iload #25
    //   849: istore #19
    //   851: iload #8
    //   853: istore #18
    //   855: iload #9
    //   857: istore #12
    //   859: goto -> 740
    //   862: iload #7
    //   864: ifne -> 893
    //   867: iload #10
    //   869: ifeq -> 893
    //   872: iconst_1
    //   873: istore #14
    //   875: iconst_0
    //   876: istore #11
    //   878: iload #25
    //   880: istore #19
    //   882: iload #8
    //   884: istore #18
    //   886: iload #9
    //   888: istore #12
    //   890: goto -> 740
    //   893: iload #7
    //   895: ifeq -> 924
    //   898: iload #10
    //   900: ifeq -> 924
    //   903: iconst_0
    //   904: istore #14
    //   906: iconst_0
    //   907: istore #11
    //   909: iload #25
    //   911: istore #19
    //   913: iload #8
    //   915: istore #18
    //   917: iload #9
    //   919: istore #12
    //   921: goto -> 740
    //   924: iconst_1
    //   925: istore #11
    //   927: iload #7
    //   929: istore #14
    //   931: iload #25
    //   933: istore #19
    //   935: iload #8
    //   937: istore #18
    //   939: iload #9
    //   941: istore #12
    //   943: goto -> 740
    //   946: iconst_1
    //   947: istore #19
    //   949: bipush #100
    //   951: istore #12
    //   953: iload #10
    //   955: istore #11
    //   957: iload #7
    //   959: istore #14
    //   961: iload #8
    //   963: istore #18
    //   965: goto -> 740
    //   968: bipush #100
    //   970: istore #12
    //   972: iload #10
    //   974: istore #11
    //   976: iload #7
    //   978: istore #14
    //   980: iload #25
    //   982: istore #19
    //   984: iload #8
    //   986: istore #18
    //   988: goto -> 740
    //   991: bipush #99
    //   993: istore #12
    //   995: iload #10
    //   997: istore #11
    //   999: iload #7
    //   1001: istore #14
    //   1003: iload #25
    //   1005: istore #19
    //   1007: iload #8
    //   1009: istore #18
    //   1011: goto -> 740
    //   1014: iconst_1
    //   1015: istore #18
    //   1017: iload #10
    //   1019: istore #11
    //   1021: iload #7
    //   1023: istore #14
    //   1025: iload #25
    //   1027: istore #19
    //   1029: iload #9
    //   1031: istore #12
    //   1033: goto -> 740
    //   1036: iload #24
    //   1038: bipush #96
    //   1040: if_icmpge -> 1118
    //   1043: iload #10
    //   1045: iload #7
    //   1047: if_icmpne -> 1099
    //   1050: aload #27
    //   1052: iload #24
    //   1054: bipush #32
    //   1056: iadd
    //   1057: i2c
    //   1058: invokevirtual append : (C)Ljava/lang/StringBuilder;
    //   1061: pop
    //   1062: iload #9
    //   1064: istore #14
    //   1066: iconst_0
    //   1067: istore #17
    //   1069: iload #7
    //   1071: istore #9
    //   1073: iconst_0
    //   1074: istore #18
    //   1076: iload #11
    //   1078: istore #10
    //   1080: iload #8
    //   1082: istore #12
    //   1084: iload #14
    //   1086: istore #7
    //   1088: iload #18
    //   1090: istore #8
    //   1092: iload #17
    //   1094: istore #11
    //   1096: goto -> 379
    //   1099: aload #27
    //   1101: iload #24
    //   1103: bipush #32
    //   1105: iadd
    //   1106: sipush #128
    //   1109: iadd
    //   1110: i2c
    //   1111: invokevirtual append : (C)Ljava/lang/StringBuilder;
    //   1114: pop
    //   1115: goto -> 1062
    //   1118: iload #11
    //   1120: istore #17
    //   1122: iload #24
    //   1124: bipush #106
    //   1126: if_icmpeq -> 1132
    //   1129: iconst_0
    //   1130: istore #17
    //   1132: iload #10
    //   1134: istore #11
    //   1136: iload #7
    //   1138: istore #14
    //   1140: iload #26
    //   1142: istore #19
    //   1144: iload #8
    //   1146: istore #18
    //   1148: iload #9
    //   1150: istore #12
    //   1152: iload #24
    //   1154: tableswitch default -> 1212, 96 -> 1232, 97 -> 1232, 98 -> 1438, 99 -> 1483, 100 -> 1354, 101 -> 1460, 102 -> 1259, 103 -> 1232, 104 -> 1232, 105 -> 1232, 106 -> 1506
    //   1212: iload #9
    //   1214: istore #12
    //   1216: iload #8
    //   1218: istore #18
    //   1220: iload #26
    //   1222: istore #19
    //   1224: iload #7
    //   1226: istore #14
    //   1228: iload #10
    //   1230: istore #11
    //   1232: iload #12
    //   1234: istore #7
    //   1236: iload #14
    //   1238: istore #9
    //   1240: iload #11
    //   1242: istore #8
    //   1244: iload #17
    //   1246: istore #10
    //   1248: iload #18
    //   1250: istore #12
    //   1252: iload #19
    //   1254: istore #11
    //   1256: goto -> 379
    //   1259: iload #10
    //   1261: istore #11
    //   1263: iload #7
    //   1265: istore #14
    //   1267: iload #26
    //   1269: istore #19
    //   1271: iload #8
    //   1273: istore #18
    //   1275: iload #9
    //   1277: istore #12
    //   1279: iload #20
    //   1281: ifeq -> 1232
    //   1284: aload #27
    //   1286: invokevirtual length : ()I
    //   1289: ifne -> 1323
    //   1292: aload #27
    //   1294: ldc ']C1'
    //   1296: invokevirtual append : (Ljava/lang/String;)Ljava/lang/StringBuilder;
    //   1299: pop
    //   1300: iload #10
    //   1302: istore #11
    //   1304: iload #7
    //   1306: istore #14
    //   1308: iload #26
    //   1310: istore #19
    //   1312: iload #8
    //   1314: istore #18
    //   1316: iload #9
    //   1318: istore #12
    //   1320: goto -> 1232
    //   1323: aload #27
    //   1325: bipush #29
    //   1327: invokevirtual append : (C)Ljava/lang/StringBuilder;
    //   1330: pop
    //   1331: iload #10
    //   1333: istore #11
    //   1335: iload #7
    //   1337: istore #14
    //   1339: iload #26
    //   1341: istore #19
    //   1343: iload #8
    //   1345: istore #18
    //   1347: iload #9
    //   1349: istore #12
    //   1351: goto -> 1232
    //   1354: iload #7
    //   1356: ifne -> 1385
    //   1359: iload #10
    //   1361: ifeq -> 1385
    //   1364: iconst_1
    //   1365: istore #14
    //   1367: iconst_0
    //   1368: istore #11
    //   1370: iload #26
    //   1372: istore #19
    //   1374: iload #8
    //   1376: istore #18
    //   1378: iload #9
    //   1380: istore #12
    //   1382: goto -> 1232
    //   1385: iload #7
    //   1387: ifeq -> 1416
    //   1390: iload #10
    //   1392: ifeq -> 1416
    //   1395: iconst_0
    //   1396: istore #14
    //   1398: iconst_0
    //   1399: istore #11
    //   1401: iload #26
    //   1403: istore #19
    //   1405: iload #8
    //   1407: istore #18
    //   1409: iload #9
    //   1411: istore #12
    //   1413: goto -> 1232
    //   1416: iconst_1
    //   1417: istore #11
    //   1419: iload #7
    //   1421: istore #14
    //   1423: iload #26
    //   1425: istore #19
    //   1427: iload #8
    //   1429: istore #18
    //   1431: iload #9
    //   1433: istore #12
    //   1435: goto -> 1232
    //   1438: iconst_1
    //   1439: istore #19
    //   1441: bipush #101
    //   1443: istore #12
    //   1445: iload #10
    //   1447: istore #11
    //   1449: iload #7
    //   1451: istore #14
    //   1453: iload #8
    //   1455: istore #18
    //   1457: goto -> 1232
    //   1460: bipush #101
    //   1462: istore #12
    //   1464: iload #10
    //   1466: istore #11
    //   1468: iload #7
    //   1470: istore #14
    //   1472: iload #26
    //   1474: istore #19
    //   1476: iload #8
    //   1478: istore #18
    //   1480: goto -> 1232
    //   1483: bipush #99
    //   1485: istore #12
    //   1487: iload #10
    //   1489: istore #11
    //   1491: iload #7
    //   1493: istore #14
    //   1495: iload #26
    //   1497: istore #19
    //   1499: iload #8
    //   1501: istore #18
    //   1503: goto -> 1232
    //   1506: iconst_1
    //   1507: istore #18
    //   1509: iload #10
    //   1511: istore #11
    //   1513: iload #7
    //   1515: istore #14
    //   1517: iload #26
    //   1519: istore #19
    //   1521: iload #9
    //   1523: istore #12
    //   1525: goto -> 1232
    //   1528: iload #24
    //   1530: bipush #100
    //   1532: if_icmpge -> 1596
    //   1535: iload #24
    //   1537: bipush #10
    //   1539: if_icmpge -> 1550
    //   1542: aload #27
    //   1544: bipush #48
    //   1546: invokevirtual append : (C)Ljava/lang/StringBuilder;
    //   1549: pop
    //   1550: aload #27
    //   1552: iload #24
    //   1554: invokevirtual append : (I)Ljava/lang/StringBuilder;
    //   1557: pop
    //   1558: iload #9
    //   1560: istore #14
    //   1562: iconst_0
    //   1563: istore #18
    //   1565: iload #7
    //   1567: istore #9
    //   1569: iload #10
    //   1571: istore #17
    //   1573: iload #11
    //   1575: istore #10
    //   1577: iload #8
    //   1579: istore #12
    //   1581: iload #14
    //   1583: istore #7
    //   1585: iload #17
    //   1587: istore #8
    //   1589: iload #18
    //   1591: istore #11
    //   1593: goto -> 379
    //   1596: iload #24
    //   1598: bipush #106
    //   1600: if_icmpeq -> 1606
    //   1603: iconst_0
    //   1604: istore #11
    //   1606: iload #24
    //   1608: tableswitch default -> 1652, 100 -> 1659, 101 -> 1806, 102 -> 1697, 103 -> 1652, 104 -> 1652, 105 -> 1652, 106 -> 1844
    //   1652: iload #11
    //   1654: istore #12
    //   1656: goto -> 348
    //   1659: bipush #100
    //   1661: istore #18
    //   1663: iconst_0
    //   1664: istore #17
    //   1666: iload #7
    //   1668: istore #9
    //   1670: iload #10
    //   1672: istore #14
    //   1674: iload #11
    //   1676: istore #10
    //   1678: iload #8
    //   1680: istore #12
    //   1682: iload #18
    //   1684: istore #7
    //   1686: iload #14
    //   1688: istore #8
    //   1690: iload #17
    //   1692: istore #11
    //   1694: goto -> 379
    //   1697: iload #11
    //   1699: istore #12
    //   1701: iload #20
    //   1703: ifeq -> 348
    //   1706: aload #27
    //   1708: invokevirtual length : ()I
    //   1711: ifne -> 1760
    //   1714: aload #27
    //   1716: ldc ']C1'
    //   1718: invokevirtual append : (Ljava/lang/String;)Ljava/lang/StringBuilder;
    //   1721: pop
    //   1722: iload #9
    //   1724: istore #14
    //   1726: iconst_0
    //   1727: istore #18
    //   1729: iload #7
    //   1731: istore #9
    //   1733: iload #10
    //   1735: istore #17
    //   1737: iload #11
    //   1739: istore #10
    //   1741: iload #8
    //   1743: istore #12
    //   1745: iload #14
    //   1747: istore #7
    //   1749: iload #17
    //   1751: istore #8
    //   1753: iload #18
    //   1755: istore #11
    //   1757: goto -> 379
    //   1760: aload #27
    //   1762: bipush #29
    //   1764: invokevirtual append : (C)Ljava/lang/StringBuilder;
    //   1767: pop
    //   1768: iload #9
    //   1770: istore #14
    //   1772: iconst_0
    //   1773: istore #18
    //   1775: iload #7
    //   1777: istore #9
    //   1779: iload #10
    //   1781: istore #17
    //   1783: iload #11
    //   1785: istore #10
    //   1787: iload #8
    //   1789: istore #12
    //   1791: iload #14
    //   1793: istore #7
    //   1795: iload #17
    //   1797: istore #8
    //   1799: iload #18
    //   1801: istore #11
    //   1803: goto -> 379
    //   1806: bipush #101
    //   1808: istore #18
    //   1810: iconst_0
    //   1811: istore #17
    //   1813: iload #7
    //   1815: istore #9
    //   1817: iload #10
    //   1819: istore #14
    //   1821: iload #11
    //   1823: istore #10
    //   1825: iload #8
    //   1827: istore #12
    //   1829: iload #18
    //   1831: istore #7
    //   1833: iload #14
    //   1835: istore #8
    //   1837: iload #17
    //   1839: istore #11
    //   1841: goto -> 379
    //   1844: iload #9
    //   1846: istore #8
    //   1848: iconst_0
    //   1849: istore #14
    //   1851: iload #7
    //   1853: istore #9
    //   1855: iload #10
    //   1857: istore #12
    //   1859: iload #11
    //   1861: istore #10
    //   1863: iconst_1
    //   1864: istore #17
    //   1866: iload #8
    //   1868: istore #7
    //   1870: iload #12
    //   1872: istore #8
    //   1874: iload #14
    //   1876: istore #11
    //   1878: iload #17
    //   1880: istore #12
    //   1882: goto -> 379
    //   1885: bipush #101
    //   1887: istore #14
    //   1889: goto -> 399
    //   1892: aload_2
    //   1893: iload #13
    //   1895: invokevirtual e : (I)I
    //   1898: istore #7
    //   1900: aload_2
    //   1901: iload #7
    //   1903: aload_2
    //   1904: invokevirtual a : ()I
    //   1907: iload #7
    //   1909: iload #17
    //   1911: isub
    //   1912: iconst_2
    //   1913: idiv
    //   1914: iload #7
    //   1916: iadd
    //   1917: invokestatic min : (II)I
    //   1920: iconst_0
    //   1921: invokevirtual a : (IIZ)Z
    //   1924: ifne -> 1931
    //   1927: invokestatic a : ()Leqh;
    //   1930: athrow
    //   1931: iload #12
    //   1933: iload #14
    //   1935: iload #18
    //   1937: imul
    //   1938: isub
    //   1939: bipush #103
    //   1941: irem
    //   1942: iload #18
    //   1944: if_icmpeq -> 1951
    //   1947: invokestatic a : ()Lepx;
    //   1950: athrow
    //   1951: aload #27
    //   1953: invokevirtual length : ()I
    //   1956: istore #7
    //   1958: iload #7
    //   1960: ifne -> 1967
    //   1963: invokestatic a : ()Leqh;
    //   1966: athrow
    //   1967: iload #7
    //   1969: ifle -> 1996
    //   1972: iload #11
    //   1974: ifeq -> 1996
    //   1977: iload #9
    //   1979: bipush #99
    //   1981: if_icmpne -> 2075
    //   1984: aload #27
    //   1986: iload #7
    //   1988: iconst_2
    //   1989: isub
    //   1990: iload #7
    //   1992: invokevirtual delete : (II)Ljava/lang/StringBuilder;
    //   1995: pop
    //   1996: aload #28
    //   1998: iconst_1
    //   1999: iaload
    //   2000: aload #28
    //   2002: iconst_0
    //   2003: iaload
    //   2004: iadd
    //   2005: i2f
    //   2006: fconst_2
    //   2007: fdiv
    //   2008: fstore #4
    //   2010: iload #17
    //   2012: i2f
    //   2013: fstore #5
    //   2015: iload #13
    //   2017: iload #17
    //   2019: isub
    //   2020: i2f
    //   2021: fconst_2
    //   2022: fdiv
    //   2023: fstore #6
    //   2025: aload_3
    //   2026: invokeinterface size : ()I
    //   2031: istore #8
    //   2033: iload #8
    //   2035: newarray byte
    //   2037: astore_2
    //   2038: iconst_0
    //   2039: istore #7
    //   2041: iload #7
    //   2043: iload #8
    //   2045: if_icmpge -> 2090
    //   2048: aload_2
    //   2049: iload #7
    //   2051: aload_3
    //   2052: iload #7
    //   2054: invokeinterface get : (I)Ljava/lang/Object;
    //   2059: checkcast java/lang/Byte
    //   2062: invokevirtual byteValue : ()B
    //   2065: bastore
    //   2066: iload #7
    //   2068: iconst_1
    //   2069: iadd
    //   2070: istore #7
    //   2072: goto -> 2041
    //   2075: aload #27
    //   2077: iload #7
    //   2079: iconst_1
    //   2080: isub
    //   2081: iload #7
    //   2083: invokevirtual delete : (II)Ljava/lang/StringBuilder;
    //   2086: pop
    //   2087: goto -> 1996
    //   2090: aload #27
    //   2092: invokevirtual toString : ()Ljava/lang/String;
    //   2095: astore_3
    //   2096: new eqo
    //   2099: dup
    //   2100: fload #4
    //   2102: iload_1
    //   2103: i2f
    //   2104: invokespecial <init> : (FF)V
    //   2107: astore #27
    //   2109: new eqo
    //   2112: dup
    //   2113: fload #5
    //   2115: fload #6
    //   2117: fadd
    //   2118: iload_1
    //   2119: i2f
    //   2120: invokespecial <init> : (FF)V
    //   2123: astore #28
    //   2125: getstatic epu.CODE_128 : Lepu;
    //   2128: astore #29
    //   2130: new eqm
    //   2133: dup
    //   2134: aload_3
    //   2135: aload_2
    //   2136: iconst_2
    //   2137: anewarray eqo
    //   2140: dup
    //   2141: iconst_0
    //   2142: aload #27
    //   2144: aastore
    //   2145: dup
    //   2146: iconst_1
    //   2147: aload #28
    //   2149: aastore
    //   2150: aload #29
    //   2152: invokespecial <init> : (Ljava/lang/String;[B[Leqo;Lepu;)V
    //   2155: areturn
  }
}


/* Location:              C:\Users\devid\Downloads\SAST\Santander\dex2jar-2.0\classes2-dex2jar.jar!\ewi.class
 * Java compiler version: 6 (50.0)
 * JD-Core Version:       1.1.3
 */