import java.util.ArrayList;
import java.util.Collection;
import java.util.List;
import java.util.Map;

public final class exk extends exg {
  private static final int[] a = new int[] { 1, 10, 34, 70, 126 };
  
  private static final int[] b = new int[] { 4, 20, 48, 81 };
  
  private static final int[] c = new int[] { 0, 161, 961, 2015, 2715 };
  
  private static final int[] d = new int[] { 0, 336, 1036, 1516 };
  
  private static final int[] e = new int[] { 8, 6, 4, 3, 1 };
  
  private static final int[] f = new int[] { 2, 4, 6, 8 };
  
  private static final int[][] g = new int[][] { { 3, 8, 2, 1 }, { 3, 5, 5, 1 }, { 3, 3, 7, 1 }, { 3, 1, 9, 1 }, { 2, 7, 4, 1 }, { 2, 5, 6, 1 }, { 2, 3, 8, 1 }, { 1, 5, 7, 1 }, { 1, 3, 9, 1 } };
  
  private final List<exj> h = new ArrayList<exj>();
  
  private final List<exj> i = new ArrayList<exj>();
  
  private static eqm a(exj paramexj1, exj paramexj2) {
    String str2 = String.valueOf(4537077L * paramexj1.a() + paramexj2.a());
    StringBuilder stringBuilder = new StringBuilder(14);
    int i;
    for (i = 13 - str2.length(); i > 0; i--)
      stringBuilder.append('0'); 
    stringBuilder.append(str2);
    i = 0;
    int j = 0;
    while (i < 13) {
      int m = stringBuilder.charAt(i) - 48;
      int k = m;
      if ((i & 0x1) == 0)
        k = m * 3; 
      j += k;
      i++;
    } 
    j = 10 - j % 10;
    i = j;
    if (j == 10)
      i = 0; 
    stringBuilder.append(i);
    eqo[] arrayOfEqo2 = paramexj1.c().c();
    eqo[] arrayOfEqo1 = paramexj2.c().c();
    String str1 = String.valueOf(stringBuilder.toString());
    eqo eqo1 = arrayOfEqo2[0];
    eqo eqo3 = arrayOfEqo2[1];
    eqo eqo4 = arrayOfEqo1[0];
    eqo eqo2 = arrayOfEqo1[1];
    epu epu = epu.RSS_14;
    return new eqm(str1, null, new eqo[] { eqo1, eqo3, eqo4, eqo2 }, epu);
  }
  
  private exh a(ets paramets, exi paramexi, boolean paramBoolean) {
    // Byte code:
    //   0: aload_0
    //   1: invokevirtual c : ()[I
    //   4: astore #11
    //   6: aload #11
    //   8: iconst_0
    //   9: iconst_0
    //   10: iastore
    //   11: aload #11
    //   13: iconst_1
    //   14: iconst_0
    //   15: iastore
    //   16: aload #11
    //   18: iconst_2
    //   19: iconst_0
    //   20: iastore
    //   21: aload #11
    //   23: iconst_3
    //   24: iconst_0
    //   25: iastore
    //   26: aload #11
    //   28: iconst_4
    //   29: iconst_0
    //   30: iastore
    //   31: aload #11
    //   33: iconst_5
    //   34: iconst_0
    //   35: iastore
    //   36: aload #11
    //   38: bipush #6
    //   40: iconst_0
    //   41: iastore
    //   42: aload #11
    //   44: bipush #7
    //   46: iconst_0
    //   47: iastore
    //   48: iload_3
    //   49: ifeq -> 184
    //   52: aload_1
    //   53: aload_2
    //   54: invokevirtual b : ()[I
    //   57: iconst_0
    //   58: iaload
    //   59: aload #11
    //   61: invokestatic b : (Lets;I[I)V
    //   64: iload_3
    //   65: ifeq -> 254
    //   68: bipush #16
    //   70: istore #7
    //   72: aload #11
    //   74: invokestatic a : ([I)I
    //   77: i2f
    //   78: iload #7
    //   80: i2f
    //   81: fdiv
    //   82: fstore #4
    //   84: aload_0
    //   85: invokevirtual f : ()[I
    //   88: astore_1
    //   89: aload_0
    //   90: invokevirtual g : ()[I
    //   93: astore_2
    //   94: aload_0
    //   95: invokevirtual d : ()[F
    //   98: astore #12
    //   100: aload_0
    //   101: invokevirtual e : ()[F
    //   104: astore #13
    //   106: iconst_0
    //   107: istore #8
    //   109: iload #8
    //   111: aload #11
    //   113: arraylength
    //   114: if_icmpge -> 299
    //   117: aload #11
    //   119: iload #8
    //   121: iaload
    //   122: i2f
    //   123: fload #4
    //   125: fdiv
    //   126: fstore #5
    //   128: ldc 0.5
    //   130: fload #5
    //   132: fadd
    //   133: f2i
    //   134: istore #9
    //   136: iload #9
    //   138: iconst_1
    //   139: if_icmpge -> 261
    //   142: iconst_1
    //   143: istore #6
    //   145: iload #8
    //   147: iconst_2
    //   148: idiv
    //   149: istore #9
    //   151: iload #8
    //   153: iconst_1
    //   154: iand
    //   155: ifne -> 279
    //   158: aload_1
    //   159: iload #9
    //   161: iload #6
    //   163: iastore
    //   164: aload #12
    //   166: iload #9
    //   168: fload #5
    //   170: iload #6
    //   172: i2f
    //   173: fsub
    //   174: fastore
    //   175: iload #8
    //   177: iconst_1
    //   178: iadd
    //   179: istore #8
    //   181: goto -> 109
    //   184: aload_1
    //   185: aload_2
    //   186: invokevirtual b : ()[I
    //   189: iconst_1
    //   190: iaload
    //   191: iconst_1
    //   192: iadd
    //   193: aload #11
    //   195: invokestatic a : (Lets;I[I)V
    //   198: iconst_0
    //   199: istore #7
    //   201: aload #11
    //   203: arraylength
    //   204: iconst_1
    //   205: isub
    //   206: istore #6
    //   208: iload #7
    //   210: iload #6
    //   212: if_icmpge -> 64
    //   215: aload #11
    //   217: iload #7
    //   219: iaload
    //   220: istore #8
    //   222: aload #11
    //   224: iload #7
    //   226: aload #11
    //   228: iload #6
    //   230: iaload
    //   231: iastore
    //   232: aload #11
    //   234: iload #6
    //   236: iload #8
    //   238: iastore
    //   239: iload #7
    //   241: iconst_1
    //   242: iadd
    //   243: istore #7
    //   245: iload #6
    //   247: iconst_1
    //   248: isub
    //   249: istore #6
    //   251: goto -> 208
    //   254: bipush #15
    //   256: istore #7
    //   258: goto -> 72
    //   261: iload #9
    //   263: istore #6
    //   265: iload #9
    //   267: bipush #8
    //   269: if_icmple -> 145
    //   272: bipush #8
    //   274: istore #6
    //   276: goto -> 145
    //   279: aload_2
    //   280: iload #9
    //   282: iload #6
    //   284: iastore
    //   285: aload #13
    //   287: iload #9
    //   289: fload #5
    //   291: iload #6
    //   293: i2f
    //   294: fsub
    //   295: fastore
    //   296: goto -> 175
    //   299: aload_0
    //   300: iload_3
    //   301: iload #7
    //   303: invokespecial a : (ZI)V
    //   306: aload_1
    //   307: arraylength
    //   308: iconst_1
    //   309: isub
    //   310: istore #8
    //   312: iconst_0
    //   313: istore #7
    //   315: iconst_0
    //   316: istore #6
    //   318: iload #8
    //   320: iflt -> 361
    //   323: aload_1
    //   324: iload #8
    //   326: iaload
    //   327: istore #10
    //   329: aload_1
    //   330: iload #8
    //   332: iaload
    //   333: istore #9
    //   335: iload #8
    //   337: iconst_1
    //   338: isub
    //   339: istore #8
    //   341: iload #7
    //   343: bipush #9
    //   345: imul
    //   346: iload #10
    //   348: iadd
    //   349: istore #7
    //   351: iload #9
    //   353: iload #6
    //   355: iadd
    //   356: istore #6
    //   358: goto -> 318
    //   361: iconst_0
    //   362: istore #10
    //   364: iconst_0
    //   365: istore #8
    //   367: aload_2
    //   368: arraylength
    //   369: iconst_1
    //   370: isub
    //   371: istore #9
    //   373: iload #9
    //   375: iflt -> 408
    //   378: iload #10
    //   380: bipush #9
    //   382: imul
    //   383: aload_2
    //   384: iload #9
    //   386: iaload
    //   387: iadd
    //   388: istore #10
    //   390: iload #8
    //   392: aload_2
    //   393: iload #9
    //   395: iaload
    //   396: iadd
    //   397: istore #8
    //   399: iload #9
    //   401: iconst_1
    //   402: isub
    //   403: istore #9
    //   405: goto -> 373
    //   408: iload #7
    //   410: iload #10
    //   412: iconst_3
    //   413: imul
    //   414: iadd
    //   415: istore #7
    //   417: iload_3
    //   418: ifeq -> 512
    //   421: iload #6
    //   423: iconst_1
    //   424: iand
    //   425: ifne -> 441
    //   428: iload #6
    //   430: bipush #12
    //   432: if_icmpgt -> 441
    //   435: iload #6
    //   437: iconst_4
    //   438: if_icmpge -> 445
    //   441: invokestatic a : ()Leqh;
    //   444: athrow
    //   445: bipush #12
    //   447: iload #6
    //   449: isub
    //   450: iconst_2
    //   451: idiv
    //   452: istore #6
    //   454: getstatic exk.e : [I
    //   457: iload #6
    //   459: iaload
    //   460: istore #9
    //   462: aload_1
    //   463: iload #9
    //   465: iconst_0
    //   466: invokestatic a : ([IIZ)I
    //   469: istore #8
    //   471: aload_2
    //   472: bipush #9
    //   474: iload #9
    //   476: isub
    //   477: iconst_1
    //   478: invokestatic a : ([IIZ)I
    //   481: istore #9
    //   483: new exh
    //   486: dup
    //   487: iload #8
    //   489: getstatic exk.a : [I
    //   492: iload #6
    //   494: iaload
    //   495: imul
    //   496: iload #9
    //   498: iadd
    //   499: getstatic exk.c : [I
    //   502: iload #6
    //   504: iaload
    //   505: iadd
    //   506: iload #7
    //   508: invokespecial <init> : (II)V
    //   511: areturn
    //   512: iload #8
    //   514: iconst_1
    //   515: iand
    //   516: ifne -> 532
    //   519: iload #8
    //   521: bipush #10
    //   523: if_icmpgt -> 532
    //   526: iload #8
    //   528: iconst_4
    //   529: if_icmpge -> 536
    //   532: invokestatic a : ()Leqh;
    //   535: athrow
    //   536: bipush #10
    //   538: iload #8
    //   540: isub
    //   541: iconst_2
    //   542: idiv
    //   543: istore #6
    //   545: getstatic exk.f : [I
    //   548: iload #6
    //   550: iaload
    //   551: istore #8
    //   553: new exh
    //   556: dup
    //   557: aload_1
    //   558: iload #8
    //   560: iconst_1
    //   561: invokestatic a : ([IIZ)I
    //   564: aload_2
    //   565: bipush #9
    //   567: iload #8
    //   569: isub
    //   570: iconst_0
    //   571: invokestatic a : ([IIZ)I
    //   574: getstatic exk.b : [I
    //   577: iload #6
    //   579: iaload
    //   580: imul
    //   581: iadd
    //   582: getstatic exk.d : [I
    //   585: iload #6
    //   587: iaload
    //   588: iadd
    //   589: iload #7
    //   591: invokespecial <init> : (II)V
    //   594: areturn
  }
  
  private exi a(ets paramets, int paramInt, boolean paramBoolean, int[] paramArrayOfint) {
    boolean bool = paramets.a(paramArrayOfint[0]);
    int i;
    for (i = paramArrayOfint[0] - 1; i >= 0 && paramets.a(i) ^ bool; i--);
    int k = i + 1;
    i = paramArrayOfint[0];
    int[] arrayOfInt = b();
    System.arraycopy(arrayOfInt, 0, arrayOfInt, 1, arrayOfInt.length - 1);
    arrayOfInt[0] = i - k;
    int m = a(arrayOfInt, g);
    int j = paramArrayOfint[1];
    if (paramBoolean) {
      i = paramets.a() - 1 - k;
      j = paramets.a() - 1 - j;
      return new exi(m, new int[] { k, paramArrayOfint[1] }, i, j, paramInt);
    } 
    i = k;
    return new exi(m, new int[] { k, paramArrayOfint[1] }, i, j, paramInt);
  }
  
  private exj a(ets paramets, boolean paramBoolean, int paramInt, Map<epy, ?> paramMap) {
    try {
      eqp eqp;
      int[] arrayOfInt = a(paramets, 0, paramBoolean);
      exi exi = a(paramets, paramInt, paramBoolean, arrayOfInt);
      if (paramMap == null) {
        paramMap = null;
      } else {
        eqp = (eqp)paramMap.get(epy.NEED_RESULT_POINT_CALLBACK);
      } 
      if (eqp != null) {
        float f2 = (arrayOfInt[0] + arrayOfInt[1]) / 2.0F;
        float f1 = f2;
        if (paramBoolean)
          f1 = (paramets.a() - 1) - f2; 
        eqp.a(new eqo(f1, paramInt));
      } 
      exh exh2 = a(paramets, exi, true);
      exh exh1 = a(paramets, exi, false);
      return new exj(exh2.a() * 1597 + exh1.a(), exh2.b() + exh1.b() * 4, exi);
    } catch (eqh eqh) {
      return null;
    } 
  }
  
  private static void a(Collection<exj> paramCollection, exj paramexj) {
    // Byte code:
    //   0: aload_1
    //   1: ifnonnull -> 5
    //   4: return
    //   5: aload_0
    //   6: invokeinterface iterator : ()Ljava/util/Iterator;
    //   11: astore_3
    //   12: aload_3
    //   13: invokeinterface hasNext : ()Z
    //   18: ifeq -> 64
    //   21: aload_3
    //   22: invokeinterface next : ()Ljava/lang/Object;
    //   27: checkcast exj
    //   30: astore #4
    //   32: aload #4
    //   34: invokevirtual a : ()I
    //   37: aload_1
    //   38: invokevirtual a : ()I
    //   41: if_icmpne -> 12
    //   44: aload #4
    //   46: invokevirtual e : ()V
    //   49: iconst_1
    //   50: istore_2
    //   51: iload_2
    //   52: ifne -> 4
    //   55: aload_0
    //   56: aload_1
    //   57: invokeinterface add : (Ljava/lang/Object;)Z
    //   62: pop
    //   63: return
    //   64: iconst_0
    //   65: istore_2
    //   66: goto -> 51
  }
  
  private void a(boolean paramBoolean, int paramInt) {
    // Byte code:
    //   0: iconst_0
    //   1: istore #5
    //   3: iconst_1
    //   4: istore #10
    //   6: aload_0
    //   7: invokevirtual f : ()[I
    //   10: invokestatic a : ([I)I
    //   13: istore #11
    //   15: aload_0
    //   16: invokevirtual g : ()[I
    //   19: invokestatic a : ([I)I
    //   22: istore #12
    //   24: iload #11
    //   26: iload #12
    //   28: iadd
    //   29: iload_2
    //   30: isub
    //   31: istore #13
    //   33: iload_1
    //   34: ifeq -> 109
    //   37: iconst_1
    //   38: istore_2
    //   39: iload #11
    //   41: iconst_1
    //   42: iand
    //   43: iload_2
    //   44: if_icmpne -> 114
    //   47: iconst_1
    //   48: istore #8
    //   50: iload #12
    //   52: iconst_1
    //   53: iand
    //   54: iconst_1
    //   55: if_icmpne -> 120
    //   58: iconst_1
    //   59: istore #9
    //   61: iload_1
    //   62: ifeq -> 158
    //   65: iload #11
    //   67: bipush #12
    //   69: if_icmple -> 126
    //   72: iconst_1
    //   73: istore #4
    //   75: iconst_0
    //   76: istore_3
    //   77: iload #12
    //   79: bipush #12
    //   81: if_icmple -> 140
    //   84: iconst_0
    //   85: istore_2
    //   86: iconst_1
    //   87: istore #5
    //   89: iload #13
    //   91: iconst_1
    //   92: if_icmpne -> 259
    //   95: iload #8
    //   97: ifeq -> 234
    //   100: iload #9
    //   102: ifeq -> 217
    //   105: invokestatic a : ()Leqh;
    //   108: athrow
    //   109: iconst_0
    //   110: istore_2
    //   111: goto -> 39
    //   114: iconst_0
    //   115: istore #8
    //   117: goto -> 50
    //   120: iconst_0
    //   121: istore #9
    //   123: goto -> 61
    //   126: iload #11
    //   128: iconst_4
    //   129: if_icmpge -> 484
    //   132: iconst_0
    //   133: istore #4
    //   135: iconst_1
    //   136: istore_3
    //   137: goto -> 77
    //   140: iload #4
    //   142: istore #7
    //   144: iload_3
    //   145: istore #6
    //   147: iload #12
    //   149: iconst_4
    //   150: if_icmpge -> 464
    //   153: iconst_1
    //   154: istore_2
    //   155: goto -> 89
    //   158: iload #11
    //   160: bipush #11
    //   162: if_icmple -> 185
    //   165: iconst_1
    //   166: istore #4
    //   168: iconst_0
    //   169: istore_3
    //   170: iload #12
    //   172: bipush #10
    //   174: if_icmple -> 199
    //   177: iconst_0
    //   178: istore_2
    //   179: iconst_1
    //   180: istore #5
    //   182: goto -> 89
    //   185: iload #11
    //   187: iconst_5
    //   188: if_icmpge -> 476
    //   191: iconst_0
    //   192: istore #4
    //   194: iconst_1
    //   195: istore_3
    //   196: goto -> 170
    //   199: iload #4
    //   201: istore #7
    //   203: iload_3
    //   204: istore #6
    //   206: iload #12
    //   208: iconst_4
    //   209: if_icmpge -> 464
    //   212: iconst_1
    //   213: istore_2
    //   214: goto -> 89
    //   217: iload_2
    //   218: istore #4
    //   220: iconst_1
    //   221: istore_2
    //   222: iload_3
    //   223: ifeq -> 394
    //   226: iload_2
    //   227: ifeq -> 383
    //   230: invokestatic a : ()Leqh;
    //   233: athrow
    //   234: iload #9
    //   236: ifne -> 243
    //   239: invokestatic a : ()Leqh;
    //   242: athrow
    //   243: iconst_1
    //   244: istore #5
    //   246: iload #4
    //   248: istore #6
    //   250: iload_2
    //   251: istore #4
    //   253: iload #6
    //   255: istore_2
    //   256: goto -> 222
    //   259: iload #13
    //   261: iconst_m1
    //   262: if_icmpne -> 315
    //   265: iload #8
    //   267: ifeq -> 296
    //   270: iload #9
    //   272: ifeq -> 279
    //   275: invokestatic a : ()Leqh;
    //   278: athrow
    //   279: iload #4
    //   281: istore_3
    //   282: iconst_1
    //   283: istore #6
    //   285: iload_2
    //   286: istore #4
    //   288: iload_3
    //   289: istore_2
    //   290: iload #6
    //   292: istore_3
    //   293: goto -> 222
    //   296: iload #9
    //   298: ifne -> 305
    //   301: invokestatic a : ()Leqh;
    //   304: athrow
    //   305: iload #4
    //   307: istore_2
    //   308: iload #10
    //   310: istore #4
    //   312: goto -> 222
    //   315: iload #13
    //   317: ifne -> 379
    //   320: iload #8
    //   322: ifeq -> 370
    //   325: iload #9
    //   327: ifne -> 334
    //   330: invokestatic a : ()Leqh;
    //   333: athrow
    //   334: iload #11
    //   336: iload #12
    //   338: if_icmpge -> 361
    //   341: iconst_1
    //   342: istore #5
    //   344: iload #4
    //   346: istore_3
    //   347: iconst_1
    //   348: istore #6
    //   350: iload_2
    //   351: istore #4
    //   353: iload_3
    //   354: istore_2
    //   355: iload #6
    //   357: istore_3
    //   358: goto -> 222
    //   361: iconst_1
    //   362: istore_2
    //   363: iload #10
    //   365: istore #4
    //   367: goto -> 222
    //   370: iload #9
    //   372: ifeq -> 451
    //   375: invokestatic a : ()Leqh;
    //   378: athrow
    //   379: invokestatic a : ()Leqh;
    //   382: athrow
    //   383: aload_0
    //   384: invokevirtual f : ()[I
    //   387: aload_0
    //   388: invokevirtual d : ()[F
    //   391: invokestatic a : ([I[F)V
    //   394: iload_2
    //   395: ifeq -> 409
    //   398: aload_0
    //   399: invokevirtual f : ()[I
    //   402: aload_0
    //   403: invokevirtual d : ()[F
    //   406: invokestatic b : ([I[F)V
    //   409: iload #4
    //   411: ifeq -> 434
    //   414: iload #5
    //   416: ifeq -> 423
    //   419: invokestatic a : ()Leqh;
    //   422: athrow
    //   423: aload_0
    //   424: invokevirtual g : ()[I
    //   427: aload_0
    //   428: invokevirtual d : ()[F
    //   431: invokestatic a : ([I[F)V
    //   434: iload #5
    //   436: ifeq -> 450
    //   439: aload_0
    //   440: invokevirtual g : ()[I
    //   443: aload_0
    //   444: invokevirtual e : ()[F
    //   447: invokestatic b : ([I[F)V
    //   450: return
    //   451: iload #4
    //   453: istore #6
    //   455: iload_2
    //   456: istore #4
    //   458: iload #6
    //   460: istore_2
    //   461: goto -> 222
    //   464: iconst_0
    //   465: istore_2
    //   466: iload #7
    //   468: istore #4
    //   470: iload #6
    //   472: istore_3
    //   473: goto -> 89
    //   476: iconst_0
    //   477: istore #4
    //   479: iconst_0
    //   480: istore_3
    //   481: goto -> 170
    //   484: iconst_0
    //   485: istore #4
    //   487: iconst_0
    //   488: istore_3
    //   489: goto -> 77
  }
  
  private int[] a(ets paramets, int paramInt, boolean paramBoolean) {
    int[] arrayOfInt = b();
    arrayOfInt[0] = 0;
    arrayOfInt[1] = 0;
    arrayOfInt[2] = 0;
    arrayOfInt[3] = 0;
    int i = paramets.a();
    boolean bool = false;
    while (true) {
      if (paramInt < i) {
        if (!paramets.a(paramInt)) {
          bool = true;
        } else {
          bool = false;
        } 
        if (paramBoolean != bool) {
          paramInt++;
          continue;
        } 
      } 
      int k = paramInt;
      int j = 0;
      paramBoolean = bool;
      while (k < i) {
        int m;
        if (paramets.a(k) ^ paramBoolean) {
          arrayOfInt[j] = arrayOfInt[j] + 1;
          m = j;
          j = paramInt;
        } else {
          if (j == 3) {
            if (b(arrayOfInt))
              return new int[] { paramInt, k }; 
            m = paramInt + arrayOfInt[0] + arrayOfInt[1];
            arrayOfInt[0] = arrayOfInt[2];
            arrayOfInt[1] = arrayOfInt[3];
            arrayOfInt[2] = 0;
            arrayOfInt[3] = 0;
            paramInt = j - 1;
            j = m;
          } else {
            m = j + 1;
            j = paramInt;
            paramInt = m;
          } 
          arrayOfInt[paramInt] = 1;
          if (!paramBoolean) {
            paramBoolean = true;
            m = paramInt;
          } else {
            paramBoolean = false;
            m = paramInt;
          } 
        } 
        k++;
        paramInt = j;
        j = m;
      } 
      throw eqh.a();
    } 
  }
  
  private static boolean b(exj paramexj1, exj paramexj2) {
    int k = paramexj1.b();
    int m = paramexj2.b();
    int j = paramexj1.c().a() * 9 + paramexj2.c().a();
    int i = j;
    if (j > 72)
      i = j - 1; 
    j = i;
    if (i > 8)
      j = i - 1; 
    return ((k + m * 16) % 79 == j);
  }
  
  public eqm a(int paramInt, ets paramets, Map<epy, ?> paramMap) {
    exj exj2 = a(paramets, false, paramInt, paramMap);
    a(this.h, exj2);
    paramets.e();
    exj exj1 = a(paramets, true, paramInt, paramMap);
    a(this.i, exj1);
    paramets.e();
    int i = this.h.size();
    for (paramInt = 0; paramInt < i; paramInt++) {
      exj exj = this.h.get(paramInt);
      if (exj.d() > 1) {
        int k = this.i.size();
        int j;
        for (j = 0; j < k; j++) {
          exj1 = this.i.get(j);
          if (exj1.d() > 1 && b(exj, exj1))
            return a(exj, exj1); 
        } 
      } 
    } 
    throw eqh.a();
  }
  
  public void a() {
    this.h.clear();
    this.i.clear();
  }
}


/* Location:              C:\Users\devid\Downloads\SAST\Santander\dex2jar-2.0\classes2-dex2jar.jar!\exk.class
 * Java compiler version: 6 (50.0)
 * JD-Core Version:       1.1.3
 */