import java.util.ArrayList;
import java.util.Collections;
import java.util.List;
import java.util.Map;

public final class exp extends exg {
  private static final int[] a = new int[] { 7, 5, 4, 3, 1 };
  
  private static final int[] b = new int[] { 4, 20, 52, 104, 204 };
  
  private static final int[] c = new int[] { 0, 348, 1388, 2948, 3988 };
  
  private static final int[][] d;
  
  private static final int[][] e;
  
  private static final int f = 0;
  
  private static final int g = 1;
  
  private static final int h = 2;
  
  private static final int i = 3;
  
  private static final int j = 4;
  
  private static final int k = 5;
  
  private static final int[][] l;
  
  private static final int m = 11;
  
  private final List<exn> n = new ArrayList<exn>(11);
  
  private final List<exo> o = new ArrayList<exo>();
  
  private final int[] p = new int[2];
  
  private boolean q;
  
  static {
    int[] arrayOfInt1 = { 3, 6, 4, 1 };
    int[] arrayOfInt2 = { 3, 4, 6, 1 };
    int[] arrayOfInt3 = { 2, 6, 5, 1 };
    int[] arrayOfInt4 = { 2, 2, 9, 1 };
    d = new int[][] { { 1, 8, 4, 1 }, arrayOfInt1, arrayOfInt2, { 3, 2, 8, 1 }, arrayOfInt3, arrayOfInt4 };
    arrayOfInt1 = new int[] { 1, 3, 9, 27, 81, 32, 96, 77 };
    arrayOfInt2 = new int[] { 20, 60, 180, 118, 143, 7, 21, 63 };
    arrayOfInt3 = new int[] { 193, 157, 49, 147, 19, 57, 171, 91 };
    arrayOfInt4 = new int[] { 62, 186, 136, 197, 169, 85, 44, 132 };
    int[] arrayOfInt5 = { 185, 133, 188, 142, 4, 12, 36, 108 };
    int[] arrayOfInt6 = { 113, 128, 173, 97, 80, 29, 87, 50 };
    int[] arrayOfInt7 = { 150, 28, 84, 41, 123, 158, 52, 156 };
    int[] arrayOfInt8 = { 46, 138, 203, 187, 139, 206, 196, 166 };
    int[] arrayOfInt9 = { 76, 17, 51, 153, 37, 111, 122, 155 };
    int[] arrayOfInt10 = { 43, 129, 176, 106, 107, 110, 119, 146 };
    int[] arrayOfInt11 = { 16, 48, 144, 10, 30, 90, 59, 177 };
    int[] arrayOfInt12 = { 70, 210, 208, 202, 184, 130, 179, 115 };
    int[] arrayOfInt13 = { 134, 191, 151, 31, 93, 68, 204, 190 };
    int[] arrayOfInt14 = { 148, 22, 66, 198, 172, 94, 71, 2 };
    int[] arrayOfInt15 = { 6, 18, 54, 162, 64, 192, 154, 40 };
    int[] arrayOfInt16 = { 120, 149, 25, 75, 14, 42, 126, 167 };
    int[] arrayOfInt17 = { 103, 98, 83, 38, 114, 131, 182, 124 };
    int[] arrayOfInt18 = { 161, 61, 183, 127, 170, 88, 53, 159 };
    e = new int[][] { 
        arrayOfInt1, arrayOfInt2, { 189, 145, 13, 39, 117, 140, 209, 205 }, arrayOfInt3, arrayOfInt4, arrayOfInt5, arrayOfInt6, arrayOfInt7, arrayOfInt8, arrayOfInt9, 
        arrayOfInt10, arrayOfInt11, { 109, 116, 137, 200, 178, 112, 125, 164 }, arrayOfInt12, arrayOfInt13, arrayOfInt14, arrayOfInt15, arrayOfInt16, { 79, 26, 78, 23, 69, 207, 199, 175 }, arrayOfInt17, 
        arrayOfInt18, { 55, 165, 73, 8, 24, 72, 5, 15 }, { 45, 135, 194, 160, 58, 174, 100, 89 } };
    arrayOfInt1 = new int[] { 0, 1, 1 };
    arrayOfInt2 = new int[] { 0, 4, 1, 3, 3, 5 };
    arrayOfInt3 = new int[] { 0, 0, 1, 1, 2, 2, 3, 3 };
    arrayOfInt4 = new int[] { 0, 0, 1, 1, 2, 2, 3, 4, 4 };
    arrayOfInt5 = new int[] { 
        0, 0, 1, 1, 2, 3, 3, 4, 4, 5, 
        5 };
    l = new int[][] { { 0, 0 }, arrayOfInt1, { 0, 2, 1, 3 }, { 0, 4, 1, 3, 2 }, arrayOfInt2, { 0, 4, 1, 3, 4, 5, 5 }, arrayOfInt3, arrayOfInt4, { 0, 0, 1, 1, 2, 2, 3, 4, 5, 5 }, arrayOfInt5 };
  }
  
  private static int a(ets paramets, int paramInt) {
    return paramets.a(paramInt) ? paramets.d(paramets.e(paramInt)) : paramets.e(paramets.d(paramInt));
  }
  
  static eqm a(List<exn> paramList) {
    String str = exz.a(exm.a(paramList)).a();
    eqo[] arrayOfEqo1 = ((exn)paramList.get(0)).d().c();
    eqo[] arrayOfEqo2 = ((exn)paramList.get(paramList.size() - 1)).d().c();
    eqo eqo1 = arrayOfEqo1[0];
    eqo eqo2 = arrayOfEqo1[1];
    eqo eqo3 = arrayOfEqo2[0];
    eqo eqo4 = arrayOfEqo2[1];
    epu epu = epu.RSS_EXPANDED;
    return new eqm(str, null, new eqo[] { eqo1, eqo2, eqo3, eqo4 }, epu);
  }
  
  private exi a(ets paramets, int paramInt, boolean paramBoolean) {
    int i;
    int j;
    int k;
    if (paramBoolean) {
      for (i = this.p[0] - 1; i >= 0 && !paramets.a(i); i--);
      k = this.p[0] - ++i;
      j = this.p[1];
    } else {
      i = this.p[0];
      j = paramets.e(this.p[1] + 1);
      k = j - this.p[1];
    } 
    int[] arrayOfInt = b();
    System.arraycopy(arrayOfInt, 0, arrayOfInt, 1, arrayOfInt.length - 1);
    arrayOfInt[0] = k;
    try {
      k = a(arrayOfInt, d);
      return new exi(k, new int[] { i, j }, i, j, paramInt);
    } catch (eqh eqh) {
      return null;
    } 
  }
  
  private List<exn> a(List<exo> paramList, int paramInt) {
    while (true) {
      if (paramInt < this.o.size()) {
        exo exo = this.o.get(paramInt);
        this.n.clear();
        int j = paramList.size();
        for (int i = 0; i < j; i++)
          this.n.addAll(((exo)paramList.get(i)).a()); 
        this.n.addAll(exo.a());
        if (b(this.n)) {
          if (i())
            return this.n; 
          ArrayList<exo> arrayList = new ArrayList();
          arrayList.addAll(paramList);
          arrayList.add(exo);
          try {
            return a(arrayList, paramInt + 1);
          } catch (eqh eqh) {}
        } 
        paramInt++;
        continue;
      } 
      throw eqh.a();
    } 
  }
  
  private List<exn> a(boolean paramBoolean) {
    List<exn> list1 = null;
    List<exn> list2 = null;
    if (this.o.size() > 25) {
      this.o.clear();
      return list2;
    } 
    this.n.clear();
    if (paramBoolean)
      Collections.reverse(this.o); 
    try {
      list2 = a(new ArrayList<exo>(), 0);
      list1 = list2;
      list2 = list1;
      if (paramBoolean) {
        Collections.reverse(this.o);
        return list1;
      } 
    } catch (eqh eqh) {}
    return (List<exn>)eqh;
  }
  
  private void a(int paramInt) {
    int i;
    boolean bool1;
    int j;
    boolean bool3;
    boolean bool2 = false;
    boolean bool4 = true;
    int k = a(f());
    int m = a(g());
    int n = k + m - paramInt;
    if ((k & 0x1) == 1) {
      j = 1;
    } else {
      j = 0;
    } 
    if ((m & 0x1) == 0) {
      bool3 = true;
    } else {
      bool3 = false;
    } 
    if (k > 13) {
      i = 1;
      paramInt = 0;
    } else if (k < 4) {
      i = 0;
      paramInt = 1;
    } else {
      i = 0;
      paramInt = 0;
    } 
    if (m > 13) {
      bool1 = false;
      bool2 = true;
    } else if (m < 4) {
      bool1 = true;
    } else {
      bool1 = false;
    } 
    if (n == 1) {
      if (j) {
        if (bool3)
          throw eqh.a(); 
        j = 1;
        i = paramInt;
        paramInt = j;
      } else {
        if (!bool3)
          throw eqh.a(); 
        bool2 = true;
        j = paramInt;
        paramInt = i;
        i = j;
      } 
    } else if (n == -1) {
      if (j != 0) {
        if (bool3)
          throw eqh.a(); 
        paramInt = i;
        i = 1;
      } else {
        if (!bool3)
          throw eqh.a(); 
        j = paramInt;
        bool1 = bool4;
        paramInt = i;
        i = j;
      } 
    } else if (n == 0) {
      if (j != 0) {
        if (!bool3)
          throw eqh.a(); 
        if (k < m) {
          bool2 = true;
          paramInt = i;
          i = 1;
        } else {
          j = 1;
          i = paramInt;
          bool1 = bool4;
          paramInt = j;
        } 
      } else {
        if (bool3)
          throw eqh.a(); 
        j = paramInt;
        paramInt = i;
        i = j;
      } 
    } else {
      throw eqh.a();
    } 
    if (i != 0) {
      if (paramInt != 0)
        throw eqh.a(); 
      a(f(), d());
    } 
    if (paramInt != 0)
      b(f(), d()); 
    if (bool1) {
      if (bool2)
        throw eqh.a(); 
      a(g(), d());
    } 
    if (bool2)
      b(g(), e()); 
  }
  
  private void a(int paramInt, boolean paramBoolean) {
    boolean bool2 = false;
    boolean bool1 = false;
    int i = 0;
    while (true) {
      boolean bool = bool2;
      if (i < this.o.size()) {
        exo exo = this.o.get(i);
        if (exo.b() > paramInt) {
          bool = exo.a(this.n);
        } else {
          bool1 = exo.a(this.n);
          i++;
          continue;
        } 
      } 
      if (!bool && !bool1 && !a(this.n, this.o)) {
        this.o.add(i, new exo(this.n, paramInt, paramBoolean));
        a(this.n, this.o);
        return;
      } 
      return;
    } 
  }
  
  private static void a(List<exn> paramList, List<exo> paramList1) {
    // Byte code:
    //   0: aload_1
    //   1: invokeinterface iterator : ()Ljava/util/Iterator;
    //   6: astore_1
    //   7: aload_1
    //   8: invokeinterface hasNext : ()Z
    //   13: ifeq -> 131
    //   16: aload_1
    //   17: invokeinterface next : ()Ljava/lang/Object;
    //   22: checkcast exo
    //   25: astore_3
    //   26: aload_3
    //   27: invokevirtual a : ()Ljava/util/List;
    //   30: invokeinterface size : ()I
    //   35: aload_0
    //   36: invokeinterface size : ()I
    //   41: if_icmpeq -> 7
    //   44: aload_3
    //   45: invokevirtual a : ()Ljava/util/List;
    //   48: invokeinterface iterator : ()Ljava/util/Iterator;
    //   53: astore_3
    //   54: aload_3
    //   55: invokeinterface hasNext : ()Z
    //   60: ifeq -> 137
    //   63: aload_3
    //   64: invokeinterface next : ()Ljava/lang/Object;
    //   69: checkcast exn
    //   72: astore #4
    //   74: aload_0
    //   75: invokeinterface iterator : ()Ljava/util/Iterator;
    //   80: astore #5
    //   82: aload #5
    //   84: invokeinterface hasNext : ()Z
    //   89: ifeq -> 132
    //   92: aload #4
    //   94: aload #5
    //   96: invokeinterface next : ()Ljava/lang/Object;
    //   101: checkcast exn
    //   104: invokevirtual equals : (Ljava/lang/Object;)Z
    //   107: ifeq -> 82
    //   110: iconst_1
    //   111: istore_2
    //   112: iload_2
    //   113: ifne -> 54
    //   116: iconst_0
    //   117: istore_2
    //   118: iload_2
    //   119: ifeq -> 7
    //   122: aload_1
    //   123: invokeinterface remove : ()V
    //   128: goto -> 7
    //   131: return
    //   132: iconst_0
    //   133: istore_2
    //   134: goto -> 112
    //   137: iconst_1
    //   138: istore_2
    //   139: goto -> 118
  }
  
  private static boolean a(exi paramexi, boolean paramBoolean1, boolean paramBoolean2) {
    return (paramexi.a() != 0 || !paramBoolean1 || !paramBoolean2);
  }
  
  private static boolean a(Iterable<exn> paramIterable, Iterable<exo> paramIterable1) {
    // Byte code:
    //   0: aload_1
    //   1: invokeinterface iterator : ()Ljava/util/Iterator;
    //   6: astore_1
    //   7: aload_1
    //   8: invokeinterface hasNext : ()Z
    //   13: ifeq -> 109
    //   16: aload_1
    //   17: invokeinterface next : ()Ljava/lang/Object;
    //   22: checkcast exo
    //   25: astore_3
    //   26: aload_0
    //   27: invokeinterface iterator : ()Ljava/util/Iterator;
    //   32: astore #4
    //   34: aload #4
    //   36: invokeinterface hasNext : ()Z
    //   41: ifeq -> 116
    //   44: aload #4
    //   46: invokeinterface next : ()Ljava/lang/Object;
    //   51: checkcast exn
    //   54: astore #5
    //   56: aload_3
    //   57: invokevirtual a : ()Ljava/util/List;
    //   60: invokeinterface iterator : ()Ljava/util/Iterator;
    //   65: astore #6
    //   67: aload #6
    //   69: invokeinterface hasNext : ()Z
    //   74: ifeq -> 111
    //   77: aload #5
    //   79: aload #6
    //   81: invokeinterface next : ()Ljava/lang/Object;
    //   86: checkcast exn
    //   89: invokevirtual equals : (Ljava/lang/Object;)Z
    //   92: ifeq -> 67
    //   95: iconst_1
    //   96: istore_2
    //   97: iload_2
    //   98: ifne -> 34
    //   101: iconst_0
    //   102: istore_2
    //   103: iload_2
    //   104: ifeq -> 7
    //   107: iconst_1
    //   108: ireturn
    //   109: iconst_0
    //   110: ireturn
    //   111: iconst_0
    //   112: istore_2
    //   113: goto -> 97
    //   116: iconst_1
    //   117: istore_2
    //   118: goto -> 103
  }
  
  private void b(ets paramets, List<exn> paramList, int paramInt) {
    int[] arrayOfInt = b();
    arrayOfInt[0] = 0;
    arrayOfInt[1] = 0;
    arrayOfInt[2] = 0;
    arrayOfInt[3] = 0;
    int i = paramets.a();
    if (paramInt < 0)
      if (paramList.isEmpty()) {
        paramInt = 0;
      } else {
        paramInt = ((exn)paramList.get(paramList.size() - 1)).d().b()[1];
      }  
    if (paramList.size() % 2 != 0) {
      bool1 = true;
    } else {
      bool1 = false;
    } 
    boolean bool2 = bool1;
    if (this.q)
      if (!bool1) {
        bool2 = true;
      } else {
        bool2 = false;
      }  
    boolean bool1 = false;
    while (true) {
      if (paramInt < i) {
        if (!paramets.a(paramInt)) {
          bool1 = true;
        } else {
          bool1 = false;
        } 
        if (bool1) {
          paramInt++;
          continue;
        } 
      } 
      int j = paramInt;
      int k = 0;
      boolean bool = bool1;
      while (j < i) {
        int m;
        if (paramets.a(j) ^ bool) {
          arrayOfInt[k] = arrayOfInt[k] + 1;
          bool1 = bool;
          n = paramInt;
        } else {
          if (k == 3) {
            if (bool2)
              c(arrayOfInt); 
            if (b(arrayOfInt)) {
              this.p[0] = paramInt;
              this.p[1] = j;
              return;
            } 
            if (bool2)
              c(arrayOfInt); 
            m = paramInt + arrayOfInt[0] + arrayOfInt[1];
            arrayOfInt[0] = arrayOfInt[2];
            arrayOfInt[1] = arrayOfInt[3];
            arrayOfInt[2] = 0;
            arrayOfInt[3] = 0;
            paramInt = k - 1;
          } else {
            k++;
            m = paramInt;
            paramInt = k;
          } 
          arrayOfInt[paramInt] = 1;
          if (n == 0) {
            boolean bool3 = true;
            n = m;
            k = paramInt;
            m = bool3;
          } else {
            boolean bool3 = false;
            n = m;
            k = paramInt;
            m = bool3;
          } 
        } 
        j++;
        paramInt = n;
        int n = m;
      } 
      throw eqh.a();
    } 
  }
  
  private static boolean b(List<exn> paramList) {
    // Byte code:
    //   0: iconst_0
    //   1: istore #5
    //   3: getstatic exp.l : [[I
    //   6: astore #6
    //   8: aload #6
    //   10: arraylength
    //   11: istore_3
    //   12: iconst_0
    //   13: istore_1
    //   14: iload #5
    //   16: istore #4
    //   18: iload_1
    //   19: iload_3
    //   20: if_icmpge -> 92
    //   23: aload #6
    //   25: iload_1
    //   26: aaload
    //   27: astore #7
    //   29: aload_0
    //   30: invokeinterface size : ()I
    //   35: aload #7
    //   37: arraylength
    //   38: if_icmple -> 48
    //   41: iload_1
    //   42: iconst_1
    //   43: iadd
    //   44: istore_1
    //   45: goto -> 14
    //   48: iconst_0
    //   49: istore_2
    //   50: iload_2
    //   51: aload_0
    //   52: invokeinterface size : ()I
    //   57: if_icmpge -> 102
    //   60: aload_0
    //   61: iload_2
    //   62: invokeinterface get : (I)Ljava/lang/Object;
    //   67: checkcast exn
    //   70: invokevirtual d : ()Lexi;
    //   73: invokevirtual a : ()I
    //   76: aload #7
    //   78: iload_2
    //   79: iaload
    //   80: if_icmpeq -> 95
    //   83: iconst_0
    //   84: istore_2
    //   85: iload_2
    //   86: ifeq -> 41
    //   89: iconst_1
    //   90: istore #4
    //   92: iload #4
    //   94: ireturn
    //   95: iload_2
    //   96: iconst_1
    //   97: iadd
    //   98: istore_2
    //   99: goto -> 50
    //   102: iconst_1
    //   103: istore_2
    //   104: goto -> 85
  }
  
  private static void c(int[] paramArrayOfint) {
    int j = paramArrayOfint.length;
    for (int i = 0; i < j / 2; i++) {
      int k = paramArrayOfint[i];
      paramArrayOfint[i] = paramArrayOfint[j - i - 1];
      paramArrayOfint[j - i - 1] = k;
    } 
  }
  
  private boolean i() {
    boolean bool = true;
    exn exn = this.n.get(0);
    exh exh1 = exn.b();
    exh exh2 = exn.c();
    if (exh2 == null)
      return false; 
    int i = exh2.b();
    int j = 2;
    for (int k = 1; k < this.n.size(); k++) {
      exn exn1 = this.n.get(k);
      int m = i + exn1.b().b();
      int n = j + 1;
      exh exh = exn1.c();
      j = n;
      i = m;
      if (exh != null) {
        i = m + exh.b();
        j = n + 1;
      } 
    } 
    if (i % 211 + (j - 4) * 211 != exh1.a())
      bool = false; 
    return bool;
  }
  
  public eqm a(int paramInt, ets paramets, Map<epy, ?> paramMap) {
    this.n.clear();
    this.q = false;
    try {
      return a(a(paramInt, paramets));
    } catch (eqh eqh) {
      this.n.clear();
      this.q = true;
      return a(a(paramInt, paramets));
    } 
  }
  
  exh a(ets paramets, exi paramexi, boolean paramBoolean1, boolean paramBoolean2) {
    // Byte code:
    //   0: aload_0
    //   1: invokevirtual c : ()[I
    //   4: astore #13
    //   6: aload #13
    //   8: iconst_0
    //   9: iconst_0
    //   10: iastore
    //   11: aload #13
    //   13: iconst_1
    //   14: iconst_0
    //   15: iastore
    //   16: aload #13
    //   18: iconst_2
    //   19: iconst_0
    //   20: iastore
    //   21: aload #13
    //   23: iconst_3
    //   24: iconst_0
    //   25: iastore
    //   26: aload #13
    //   28: iconst_4
    //   29: iconst_0
    //   30: iastore
    //   31: aload #13
    //   33: iconst_5
    //   34: iconst_0
    //   35: iastore
    //   36: aload #13
    //   38: bipush #6
    //   40: iconst_0
    //   41: iastore
    //   42: aload #13
    //   44: bipush #7
    //   46: iconst_0
    //   47: iastore
    //   48: iload #4
    //   50: ifeq -> 119
    //   53: aload_1
    //   54: aload_2
    //   55: invokevirtual b : ()[I
    //   58: iconst_0
    //   59: iaload
    //   60: aload #13
    //   62: invokestatic b : (Lets;I[I)V
    //   65: aload #13
    //   67: invokestatic a : ([I)I
    //   70: i2f
    //   71: bipush #17
    //   73: i2f
    //   74: fdiv
    //   75: fstore #5
    //   77: aload_2
    //   78: invokevirtual b : ()[I
    //   81: iconst_1
    //   82: iaload
    //   83: aload_2
    //   84: invokevirtual b : ()[I
    //   87: iconst_0
    //   88: iaload
    //   89: isub
    //   90: i2f
    //   91: ldc_w 15.0
    //   94: fdiv
    //   95: fstore #6
    //   97: fload #5
    //   99: fload #6
    //   101: fsub
    //   102: invokestatic abs : (F)F
    //   105: fload #6
    //   107: fdiv
    //   108: ldc_w 0.3
    //   111: fcmpl
    //   112: ifle -> 187
    //   115: invokestatic a : ()Leqh;
    //   118: athrow
    //   119: aload_1
    //   120: aload_2
    //   121: invokevirtual b : ()[I
    //   124: iconst_1
    //   125: iaload
    //   126: aload #13
    //   128: invokestatic a : (Lets;I[I)V
    //   131: iconst_0
    //   132: istore #8
    //   134: aload #13
    //   136: arraylength
    //   137: iconst_1
    //   138: isub
    //   139: istore #7
    //   141: iload #8
    //   143: iload #7
    //   145: if_icmpge -> 65
    //   148: aload #13
    //   150: iload #8
    //   152: iaload
    //   153: istore #9
    //   155: aload #13
    //   157: iload #8
    //   159: aload #13
    //   161: iload #7
    //   163: iaload
    //   164: iastore
    //   165: aload #13
    //   167: iload #7
    //   169: iload #9
    //   171: iastore
    //   172: iload #8
    //   174: iconst_1
    //   175: iadd
    //   176: istore #8
    //   178: iload #7
    //   180: iconst_1
    //   181: isub
    //   182: istore #7
    //   184: goto -> 141
    //   187: aload_0
    //   188: invokevirtual f : ()[I
    //   191: astore_1
    //   192: aload_0
    //   193: invokevirtual g : ()[I
    //   196: astore #14
    //   198: aload_0
    //   199: invokevirtual d : ()[F
    //   202: astore #15
    //   204: aload_0
    //   205: invokevirtual e : ()[F
    //   208: astore #16
    //   210: iconst_0
    //   211: istore #8
    //   213: iload #8
    //   215: aload #13
    //   217: arraylength
    //   218: if_icmpge -> 356
    //   221: fconst_1
    //   222: aload #13
    //   224: iload #8
    //   226: iaload
    //   227: i2f
    //   228: fmul
    //   229: fload #5
    //   231: fdiv
    //   232: fstore #6
    //   234: ldc_w 0.5
    //   237: fload #6
    //   239: fadd
    //   240: f2i
    //   241: istore #9
    //   243: iload #9
    //   245: iconst_1
    //   246: if_icmpge -> 304
    //   249: fload #6
    //   251: ldc_w 0.3
    //   254: fcmpg
    //   255: ifge -> 262
    //   258: invokestatic a : ()Leqh;
    //   261: athrow
    //   262: iconst_1
    //   263: istore #7
    //   265: iload #8
    //   267: iconst_2
    //   268: idiv
    //   269: istore #9
    //   271: iload #8
    //   273: iconst_1
    //   274: iand
    //   275: ifne -> 335
    //   278: aload_1
    //   279: iload #9
    //   281: iload #7
    //   283: iastore
    //   284: aload #15
    //   286: iload #9
    //   288: fload #6
    //   290: iload #7
    //   292: i2f
    //   293: fsub
    //   294: fastore
    //   295: iload #8
    //   297: iconst_1
    //   298: iadd
    //   299: istore #8
    //   301: goto -> 213
    //   304: iload #9
    //   306: istore #7
    //   308: iload #9
    //   310: bipush #8
    //   312: if_icmple -> 265
    //   315: fload #6
    //   317: ldc_w 8.7
    //   320: fcmpl
    //   321: ifle -> 328
    //   324: invokestatic a : ()Leqh;
    //   327: athrow
    //   328: bipush #8
    //   330: istore #7
    //   332: goto -> 265
    //   335: aload #14
    //   337: iload #9
    //   339: iload #7
    //   341: iastore
    //   342: aload #16
    //   344: iload #9
    //   346: fload #6
    //   348: iload #7
    //   350: i2f
    //   351: fsub
    //   352: fastore
    //   353: goto -> 295
    //   356: aload_0
    //   357: bipush #17
    //   359: invokespecial a : (I)V
    //   362: aload_2
    //   363: invokevirtual a : ()I
    //   366: istore #9
    //   368: iload_3
    //   369: ifeq -> 479
    //   372: iconst_0
    //   373: istore #7
    //   375: iload #4
    //   377: ifeq -> 485
    //   380: iconst_0
    //   381: istore #8
    //   383: iload #8
    //   385: iload #9
    //   387: iconst_4
    //   388: imul
    //   389: iload #7
    //   391: iadd
    //   392: iadd
    //   393: iconst_1
    //   394: isub
    //   395: istore #12
    //   397: aload_1
    //   398: arraylength
    //   399: istore #7
    //   401: iconst_0
    //   402: istore #8
    //   404: iload #7
    //   406: iconst_1
    //   407: isub
    //   408: istore #9
    //   410: iconst_0
    //   411: istore #7
    //   413: iload #9
    //   415: iflt -> 491
    //   418: iload #7
    //   420: istore #10
    //   422: aload_2
    //   423: iload_3
    //   424: iload #4
    //   426: invokestatic a : (Lexi;ZZ)Z
    //   429: ifeq -> 453
    //   432: iload #7
    //   434: getstatic exp.e : [[I
    //   437: iload #12
    //   439: aaload
    //   440: iload #9
    //   442: iconst_2
    //   443: imul
    //   444: iaload
    //   445: aload_1
    //   446: iload #9
    //   448: iaload
    //   449: imul
    //   450: iadd
    //   451: istore #10
    //   453: aload_1
    //   454: iload #9
    //   456: iaload
    //   457: istore #7
    //   459: iload #9
    //   461: iconst_1
    //   462: isub
    //   463: istore #9
    //   465: iload #7
    //   467: iload #8
    //   469: iadd
    //   470: istore #8
    //   472: iload #10
    //   474: istore #7
    //   476: goto -> 413
    //   479: iconst_2
    //   480: istore #7
    //   482: goto -> 375
    //   485: iconst_1
    //   486: istore #8
    //   488: goto -> 383
    //   491: aload #14
    //   493: arraylength
    //   494: istore #10
    //   496: iconst_0
    //   497: istore #9
    //   499: iload #10
    //   501: iconst_1
    //   502: isub
    //   503: istore #10
    //   505: iload #10
    //   507: iflt -> 561
    //   510: iload #9
    //   512: istore #11
    //   514: aload_2
    //   515: iload_3
    //   516: iload #4
    //   518: invokestatic a : (Lexi;ZZ)Z
    //   521: ifeq -> 548
    //   524: iload #9
    //   526: getstatic exp.e : [[I
    //   529: iload #12
    //   531: aaload
    //   532: iload #10
    //   534: iconst_2
    //   535: imul
    //   536: iconst_1
    //   537: iadd
    //   538: iaload
    //   539: aload #14
    //   541: iload #10
    //   543: iaload
    //   544: imul
    //   545: iadd
    //   546: istore #11
    //   548: iload #10
    //   550: iconst_1
    //   551: isub
    //   552: istore #10
    //   554: iload #11
    //   556: istore #9
    //   558: goto -> 505
    //   561: iload #8
    //   563: iconst_1
    //   564: iand
    //   565: ifne -> 581
    //   568: iload #8
    //   570: bipush #13
    //   572: if_icmpgt -> 581
    //   575: iload #8
    //   577: iconst_4
    //   578: if_icmpge -> 585
    //   581: invokestatic a : ()Leqh;
    //   584: athrow
    //   585: bipush #13
    //   587: iload #8
    //   589: isub
    //   590: iconst_2
    //   591: idiv
    //   592: istore #8
    //   594: getstatic exp.a : [I
    //   597: iload #8
    //   599: iaload
    //   600: istore #11
    //   602: aload_1
    //   603: iload #11
    //   605: iconst_1
    //   606: invokestatic a : ([IIZ)I
    //   609: istore #10
    //   611: aload #14
    //   613: bipush #9
    //   615: iload #11
    //   617: isub
    //   618: iconst_0
    //   619: invokestatic a : ([IIZ)I
    //   622: istore #11
    //   624: getstatic exp.b : [I
    //   627: iload #8
    //   629: iaload
    //   630: istore #12
    //   632: new exh
    //   635: dup
    //   636: getstatic exp.c : [I
    //   639: iload #8
    //   641: iaload
    //   642: iload #10
    //   644: iload #12
    //   646: imul
    //   647: iload #11
    //   649: iadd
    //   650: iadd
    //   651: iload #7
    //   653: iload #9
    //   655: iadd
    //   656: invokespecial <init> : (II)V
    //   659: areturn
  }
  
  exn a(ets paramets, List<exn> paramList, int paramInt) {
    boolean bool2;
    exi exi;
    exh exh;
    if (paramList.size() % 2 == 0) {
      bool2 = true;
    } else {
      bool2 = false;
    } 
    if (this.q)
      if (!bool2) {
        bool2 = true;
      } else {
        bool2 = false;
      }  
    int i = -1;
    boolean bool1 = true;
    while (true) {
      boolean bool;
      b(paramets, paramList, i);
      exi = a(paramets, paramInt, bool2);
      if (exi == null) {
        i = a(paramets, this.p[0]);
        bool = bool1;
      } else {
        bool = false;
      } 
      bool1 = bool;
      if (!bool) {
        exh = a(paramets, exi, bool2, true);
        if (!paramList.isEmpty() && ((exn)paramList.get(paramList.size() - 1)).e())
          throw eqh.a(); 
        break;
      } 
    } 
    try {
      exh exh1 = a(paramets, exi, bool2, false);
    } catch (eqh eqh) {
      eqh = null;
    } 
    return new exn(exh, (exh)eqh, exi, true);
  }
  
  List<exn> a(int paramInt, ets paramets) {
    try {
      while (true) {
        exn exn = a(paramets, this.n, paramInt);
        this.n.add(exn);
      } 
    } catch (eqh eqh) {
      boolean bool;
      if (this.n.isEmpty())
        throw eqh; 
      if (i())
        return this.n; 
      if (!this.o.isEmpty()) {
        bool = true;
      } else {
        bool = false;
      } 
      a(paramInt, false);
      if (bool) {
        List<exn> list2 = a(false);
        List<exn> list1 = list2;
        if (list2 == null) {
          list2 = a(true);
          list1 = list2;
          if (list2 == null)
            throw eqh.a(); 
        } 
        return list1;
      } 
      throw eqh.a();
    } 
  }
  
  public void a() {
    this.n.clear();
    this.o.clear();
  }
  
  List<exo> h() {
    return this.o;
  }
}


/* Location:              C:\Users\devid\Downloads\SAST\Santander\dex2jar-2.0\classes2-dex2jar.jar!\exp.class
 * Java compiler version: 6 (50.0)
 * JD-Core Version:       1.1.3
 */