import android.view.View;
import com.santander.app.dpp.DPPPreenchimentoActivity;

public class hdw implements View.OnClickListener {
  public hdw(DPPPreenchimentoActivity paramDPPPreenchimentoActivity) {}
  
  public void onClick(View paramView) {
    // Byte code:
    //   0: aload_0
    //   1: getfield a : Lcom/santander/app/dpp/DPPPreenchimentoActivity;
    //   4: iconst_0
    //   5: invokestatic a : (Lcom/santander/app/dpp/DPPPreenchimentoActivity;Z)Z
    //   8: pop
    //   9: ldc 'Investimentos_Poupanca_DepositoProgramado_Acao'
    //   11: ldc 'Terceiros'
    //   13: invokestatic d : (Ljava/lang/String;Ljava/lang/String;)V
    //   16: aload_0
    //   17: getfield a : Lcom/santander/app/dpp/DPPPreenchimentoActivity;
    //   20: invokestatic c : (Lcom/santander/app/dpp/DPPPreenchimentoActivity;)I
    //   23: iconst_1
    //   24: if_icmpeq -> 60
    //   27: aload_0
    //   28: getfield a : Lcom/santander/app/dpp/DPPPreenchimentoActivity;
    //   31: getfield c : Landroid/widget/LinearLayout;
    //   34: iconst_4
    //   35: invokevirtual setVisibility : (I)V
    //   38: aload_0
    //   39: getfield a : Lcom/santander/app/dpp/DPPPreenchimentoActivity;
    //   42: getfield d : Landroid/widget/LinearLayout;
    //   45: iconst_0
    //   46: invokevirtual setVisibility : (I)V
    //   49: aload_0
    //   50: getfield a : Lcom/santander/app/dpp/DPPPreenchimentoActivity;
    //   53: getfield f : Landroid/widget/LinearLayout;
    //   56: iconst_0
    //   57: invokevirtual setVisibility : (I)V
    //   60: new java/util/Vector
    //   63: dup
    //   64: invokespecial <init> : ()V
    //   67: astore_1
    //   68: aload_0
    //   69: getfield a : Lcom/santander/app/dpp/DPPPreenchimentoActivity;
    //   72: invokestatic e : (Lcom/santander/app/dpp/DPPPreenchimentoActivity;)Ljava/util/ArrayList;
    //   75: ifnull -> 271
    //   78: iconst_0
    //   79: istore_2
    //   80: iload_2
    //   81: aload_0
    //   82: getfield a : Lcom/santander/app/dpp/DPPPreenchimentoActivity;
    //   85: invokestatic e : (Lcom/santander/app/dpp/DPPPreenchimentoActivity;)Ljava/util/ArrayList;
    //   88: invokevirtual size : ()I
    //   91: if_icmpge -> 271
    //   94: aload_0
    //   95: getfield a : Lcom/santander/app/dpp/DPPPreenchimentoActivity;
    //   98: invokestatic e : (Lcom/santander/app/dpp/DPPPreenchimentoActivity;)Ljava/util/ArrayList;
    //   101: iload_2
    //   102: invokevirtual get : (I)Ljava/lang/Object;
    //   105: checkcast heq
    //   108: invokevirtual o : ()Ljava/lang/String;
    //   111: ldc 'T'
    //   113: invokevirtual equals : (Ljava/lang/Object;)Z
    //   116: ifeq -> 257
    //   119: new ftl
    //   122: dup
    //   123: invokespecial <init> : ()V
    //   126: astore #4
    //   128: aload #4
    //   130: invokevirtual c : ()Lftj;
    //   133: aload_0
    //   134: getfield a : Lcom/santander/app/dpp/DPPPreenchimentoActivity;
    //   137: invokestatic e : (Lcom/santander/app/dpp/DPPPreenchimentoActivity;)Ljava/util/ArrayList;
    //   140: iload_2
    //   141: invokevirtual get : (I)Ljava/lang/Object;
    //   144: checkcast heq
    //   147: invokevirtual d : ()Ljava/lang/String;
    //   150: invokevirtual a : (Ljava/lang/String;)V
    //   153: aload #4
    //   155: invokevirtual c : ()Lftj;
    //   158: aload_0
    //   159: getfield a : Lcom/santander/app/dpp/DPPPreenchimentoActivity;
    //   162: invokestatic e : (Lcom/santander/app/dpp/DPPPreenchimentoActivity;)Ljava/util/ArrayList;
    //   165: iload_2
    //   166: invokevirtual get : (I)Ljava/lang/Object;
    //   169: checkcast heq
    //   172: invokevirtual g : ()Ljava/lang/String;
    //   175: invokevirtual d : (Ljava/lang/String;)V
    //   178: iconst_0
    //   179: istore_3
    //   180: iload_3
    //   181: aload_1
    //   182: invokevirtual size : ()I
    //   185: if_icmpge -> 335
    //   188: aload_1
    //   189: iload_3
    //   190: invokevirtual get : (I)Ljava/lang/Object;
    //   193: checkcast ftl
    //   196: invokevirtual c : ()Lftj;
    //   199: invokevirtual a : ()Ljava/lang/String;
    //   202: aload #4
    //   204: invokevirtual c : ()Lftj;
    //   207: invokevirtual a : ()Ljava/lang/String;
    //   210: invokevirtual equals : (Ljava/lang/Object;)Z
    //   213: ifeq -> 264
    //   216: aload_1
    //   217: iload_3
    //   218: invokevirtual get : (I)Ljava/lang/Object;
    //   221: checkcast ftl
    //   224: invokevirtual c : ()Lftj;
    //   227: invokevirtual d : ()Ljava/lang/String;
    //   230: aload #4
    //   232: invokevirtual c : ()Lftj;
    //   235: invokevirtual d : ()Ljava/lang/String;
    //   238: invokevirtual equals : (Ljava/lang/Object;)Z
    //   241: ifeq -> 264
    //   244: iconst_1
    //   245: istore_3
    //   246: iload_3
    //   247: ifne -> 257
    //   250: aload_1
    //   251: aload #4
    //   253: invokevirtual add : (Ljava/lang/Object;)Z
    //   256: pop
    //   257: iload_2
    //   258: iconst_1
    //   259: iadd
    //   260: istore_2
    //   261: goto -> 80
    //   264: iload_3
    //   265: iconst_1
    //   266: iadd
    //   267: istore_3
    //   268: goto -> 180
    //   271: aload_1
    //   272: invokevirtual isEmpty : ()Z
    //   275: ifeq -> 323
    //   278: aload_0
    //   279: getfield a : Lcom/santander/app/dpp/DPPPreenchimentoActivity;
    //   282: ldc 2131757115
    //   284: invokevirtual findViewById : (I)Landroid/view/View;
    //   287: iconst_4
    //   288: invokevirtual setVisibility : (I)V
    //   291: aload_0
    //   292: getfield a : Lcom/santander/app/dpp/DPPPreenchimentoActivity;
    //   295: ldc 2131757116
    //   297: invokevirtual findViewById : (I)Landroid/view/View;
    //   300: iconst_4
    //   301: invokevirtual setVisibility : (I)V
    //   304: aload_0
    //   305: getfield a : Lcom/santander/app/dpp/DPPPreenchimentoActivity;
    //   308: iconst_1
    //   309: invokestatic b : (Lcom/santander/app/dpp/DPPPreenchimentoActivity;Z)Z
    //   312: pop
    //   313: aload_0
    //   314: getfield a : Lcom/santander/app/dpp/DPPPreenchimentoActivity;
    //   317: aload_1
    //   318: iconst_0
    //   319: invokestatic a : (Lcom/santander/app/dpp/DPPPreenchimentoActivity;Ljava/util/Vector;Z)V
    //   322: return
    //   323: aload_0
    //   324: getfield a : Lcom/santander/app/dpp/DPPPreenchimentoActivity;
    //   327: iconst_0
    //   328: invokestatic b : (Lcom/santander/app/dpp/DPPPreenchimentoActivity;Z)Z
    //   331: pop
    //   332: goto -> 313
    //   335: iconst_0
    //   336: istore_3
    //   337: goto -> 246
  }
}


/* Location:              C:\Users\devid\Downloads\SAST\Santander\dex2jar-2.0\classes2-dex2jar.jar!\hdw.class
 * Java compiler version: 6 (50.0)
 * JD-Core Version:       1.1.3
 */