import java.util.Calendar;
import java.util.List;
import java.util.regex.Matcher;
import java.util.regex.Pattern;

public class kxn implements kxm {
  private String a(String paramString) {
    Matcher matcher = Pattern.compile("\\d\\d\\d\\d-\\d\\d-\\d\\d \\d\\d:\\d\\d").matcher(paramString);
    while (matcher.find()) {
      String str1;
      String str2 = matcher.group();
      Calendar calendar = Calendar.getInstance();
      calendar.setTime(mhj.a(str2, "yyyy-MM-dd HH:mm"));
      if (calendar.get(11) < 12 || (calendar.get(11) == 12 && calendar.get(12) == 0)) {
        str1 = str2.replaceAll("\\d\\d:\\d\\d", "Período da manhã");
      } else {
        str1 = str2.replaceAll("\\d\\d:\\d\\d", "Período da tarde");
      } 
      paramString = paramString.replace(str2, str1);
    } 
    return paramString;
  }
  
  public void a(String paramString1, String paramString2, kxl<List<kps>> paramkxl, kxl<String> paramkxl1) {
    // Byte code:
    //   0: new org/json/JSONObject
    //   3: dup
    //   4: invokespecial <init> : ()V
    //   7: astore #5
    //   9: aload #5
    //   11: ldc 'X-Application-Key'
    //   13: invokestatic a : ()Lmzx;
    //   16: invokevirtual c : ()Ljava/util/Properties;
    //   19: ldc 'appKey'
    //   21: invokevirtual get : (Ljava/lang/Object;)Ljava/lang/Object;
    //   24: invokestatic valueOf : (Ljava/lang/Object;)Ljava/lang/String;
    //   27: invokevirtual put : (Ljava/lang/String;Ljava/lang/Object;)Lorg/json/JSONObject;
    //   30: pop
    //   31: aload #5
    //   33: ldc 'Content-Type'
    //   35: ldc 'application/json'
    //   37: invokevirtual put : (Ljava/lang/String;Ljava/lang/Object;)Lorg/json/JSONObject;
    //   40: pop
    //   41: new org/json/JSONObject
    //   44: dup
    //   45: invokespecial <init> : ()V
    //   48: astore #6
    //   50: new org/json/JSONObject
    //   53: dup
    //   54: invokespecial <init> : ()V
    //   57: astore #7
    //   59: aload #7
    //   61: ldc 'id'
    //   63: aload_1
    //   64: invokevirtual put : (Ljava/lang/String;Ljava/lang/Object;)Lorg/json/JSONObject;
    //   67: pop
    //   68: aload #6
    //   70: ldc 'certificate'
    //   72: aload #7
    //   74: invokevirtual put : (Ljava/lang/String;Ljava/lang/Object;)Lorg/json/JSONObject;
    //   77: pop
    //   78: new org/json/JSONObject
    //   81: dup
    //   82: invokespecial <init> : ()V
    //   85: astore_1
    //   86: aload_1
    //   87: ldc 'code'
    //   89: ldc '1060'
    //   91: invokevirtual put : (Ljava/lang/String;Ljava/lang/Object;)Lorg/json/JSONObject;
    //   94: pop
    //   95: aload #6
    //   97: ldc 'plan'
    //   99: aload_1
    //   100: invokevirtual put : (Ljava/lang/String;Ljava/lang/Object;)Lorg/json/JSONObject;
    //   103: pop
    //   104: new org/json/JSONObject
    //   107: dup
    //   108: invokespecial <init> : ()V
    //   111: astore_1
    //   112: aload_1
    //   113: ldc 'code'
    //   115: aload_2
    //   116: invokevirtual put : (Ljava/lang/String;Ljava/lang/Object;)Lorg/json/JSONObject;
    //   119: pop
    //   120: aload #6
    //   122: ldc 'product'
    //   124: aload_1
    //   125: invokevirtual put : (Ljava/lang/String;Ljava/lang/Object;)Lorg/json/JSONObject;
    //   128: pop
    //   129: invokestatic a : ()Lgnp;
    //   132: getstatic kwr.INSURANCE_GET_SUBSERVICES : Lkwr;
    //   135: invokevirtual getEndpoint : ()Ljava/lang/String;
    //   138: getstatic im.POST : Lim;
    //   141: aload #5
    //   143: aload #6
    //   145: iconst_1
    //   146: invokevirtual a : (Ljava/lang/String;Lim;Lorg/json/JSONObject;Lorg/json/JSONObject;Z)Lir;
    //   149: astore_1
    //   150: new gnv
    //   153: dup
    //   154: new kxo
    //   157: dup
    //   158: aload_0
    //   159: aload #4
    //   161: aload_3
    //   162: invokespecial <init> : (Lkxn;Lkxl;Lkxl;)V
    //   165: aload_1
    //   166: invokespecial <init> : (Lgkw;Lir;)V
    //   169: astore_2
    //   170: invokestatic a : ()Lgnp;
    //   173: invokevirtual b : ()Lie;
    //   176: ifnull -> 230
    //   179: invokestatic a : ()Lgnp;
    //   182: invokevirtual b : ()Lie;
    //   185: aload_1
    //   186: aload_2
    //   187: invokevirtual a : (Lir;Lih;)V
    //   190: return
    //   191: astore #6
    //   193: aload #6
    //   195: invokevirtual printStackTrace : ()V
    //   198: goto -> 41
    //   201: astore_1
    //   202: aload_1
    //   203: invokevirtual printStackTrace : ()V
    //   206: goto -> 129
    //   209: astore_1
    //   210: ldc 'ERROR_SERV'
    //   212: aload_1
    //   213: invokevirtual getMessage : ()Ljava/lang/String;
    //   216: invokestatic e : (Ljava/lang/String;Ljava/lang/String;)I
    //   219: pop
    //   220: aload #4
    //   222: ldc ''
    //   224: invokeinterface a : (Ljava/lang/Object;)V
    //   229: return
    //   230: aload #4
    //   232: ldc ''
    //   234: invokeinterface a : (Ljava/lang/Object;)V
    //   239: return
    // Exception table:
    //   from	to	target	type
    //   9	41	191	org/json/JSONException
    //   50	129	201	org/json/JSONException
    //   179	190	209	java/lang/Exception
  }
  
  public void a(String paramString, kxl<List<kpo>> paramkxl, kxl<String> paramkxl1) {
    // Byte code:
    //   0: new org/json/JSONObject
    //   3: dup
    //   4: invokespecial <init> : ()V
    //   7: astore #4
    //   9: aload #4
    //   11: ldc 'X-Application-Key'
    //   13: invokestatic a : ()Lmzx;
    //   16: invokevirtual c : ()Ljava/util/Properties;
    //   19: ldc 'appKey'
    //   21: invokevirtual get : (Ljava/lang/Object;)Ljava/lang/Object;
    //   24: invokestatic valueOf : (Ljava/lang/Object;)Ljava/lang/String;
    //   27: invokevirtual put : (Ljava/lang/String;Ljava/lang/Object;)Lorg/json/JSONObject;
    //   30: pop
    //   31: aload #4
    //   33: ldc 'Content-Type'
    //   35: ldc 'application/json'
    //   37: invokevirtual put : (Ljava/lang/String;Ljava/lang/Object;)Lorg/json/JSONObject;
    //   40: pop
    //   41: getstatic kwr.INSURANCE_GET_SCHEDULING_SITUATION : Lkwr;
    //   44: invokevirtual getEndpoint : ()Ljava/lang/String;
    //   47: iconst_1
    //   48: anewarray java/lang/Object
    //   51: dup
    //   52: iconst_0
    //   53: aload_1
    //   54: aastore
    //   55: invokestatic format : (Ljava/lang/String;[Ljava/lang/Object;)Ljava/lang/String;
    //   58: astore_1
    //   59: invokestatic a : ()Lgnp;
    //   62: aload_1
    //   63: getstatic im.GET : Lim;
    //   66: aload #4
    //   68: new org/json/JSONObject
    //   71: dup
    //   72: invokespecial <init> : ()V
    //   75: iconst_1
    //   76: invokevirtual a : (Ljava/lang/String;Lim;Lorg/json/JSONObject;Lorg/json/JSONObject;Z)Lir;
    //   79: astore_1
    //   80: new gnv
    //   83: dup
    //   84: new kxr
    //   87: dup
    //   88: aload_0
    //   89: aload_3
    //   90: aload_2
    //   91: invokespecial <init> : (Lkxn;Lkxl;Lkxl;)V
    //   94: aload_1
    //   95: invokespecial <init> : (Lgkw;Lir;)V
    //   98: astore_2
    //   99: invokestatic a : ()Lgnp;
    //   102: invokevirtual b : ()Lie;
    //   105: ifnull -> 150
    //   108: invokestatic a : ()Lgnp;
    //   111: invokevirtual b : ()Lie;
    //   114: aload_1
    //   115: aload_2
    //   116: invokevirtual a : (Lir;Lih;)V
    //   119: return
    //   120: astore #5
    //   122: aload #5
    //   124: invokevirtual printStackTrace : ()V
    //   127: goto -> 41
    //   130: astore_1
    //   131: ldc 'ERROR_SERV'
    //   133: aload_1
    //   134: invokevirtual getMessage : ()Ljava/lang/String;
    //   137: invokestatic e : (Ljava/lang/String;Ljava/lang/String;)I
    //   140: pop
    //   141: aload_3
    //   142: ldc ''
    //   144: invokeinterface a : (Ljava/lang/Object;)V
    //   149: return
    //   150: aload_3
    //   151: ldc ''
    //   153: invokeinterface a : (Ljava/lang/Object;)V
    //   158: return
    // Exception table:
    //   from	to	target	type
    //   9	41	120	org/json/JSONException
    //   108	119	130	java/lang/Exception
  }
  
  public void a(koj paramkoj, kxl<List<kon>> paramkxl, kxl<String> paramkxl1) {
    // Byte code:
    //   0: new org/json/JSONObject
    //   3: dup
    //   4: invokespecial <init> : ()V
    //   7: astore #4
    //   9: aload #4
    //   11: ldc 'X-Application-Key'
    //   13: invokestatic a : ()Lmzx;
    //   16: invokevirtual c : ()Ljava/util/Properties;
    //   19: ldc 'appKey'
    //   21: invokevirtual get : (Ljava/lang/Object;)Ljava/lang/Object;
    //   24: invokestatic valueOf : (Ljava/lang/Object;)Ljava/lang/String;
    //   27: invokevirtual put : (Ljava/lang/String;Ljava/lang/Object;)Lorg/json/JSONObject;
    //   30: pop
    //   31: aload #4
    //   33: ldc 'Content-Type'
    //   35: ldc 'application/json'
    //   37: invokevirtual put : (Ljava/lang/String;Ljava/lang/Object;)Lorg/json/JSONObject;
    //   40: pop
    //   41: getstatic kwr.INSURANCE_GET_SUBSERVICES_EVENTS : Lkwr;
    //   44: invokevirtual getEndpoint : ()Ljava/lang/String;
    //   47: iconst_3
    //   48: anewarray java/lang/Object
    //   51: dup
    //   52: iconst_0
    //   53: aload_1
    //   54: invokevirtual a : ()Ljava/lang/String;
    //   57: aastore
    //   58: dup
    //   59: iconst_1
    //   60: aload_1
    //   61: invokevirtual b : ()Ljava/lang/String;
    //   64: aastore
    //   65: dup
    //   66: iconst_2
    //   67: aload_1
    //   68: invokevirtual c : ()Ljava/lang/String;
    //   71: aastore
    //   72: invokestatic format : (Ljava/lang/String;[Ljava/lang/Object;)Ljava/lang/String;
    //   75: astore_1
    //   76: invokestatic a : ()Lgnp;
    //   79: aload_1
    //   80: getstatic im.GET : Lim;
    //   83: aload #4
    //   85: new org/json/JSONObject
    //   88: dup
    //   89: invokespecial <init> : ()V
    //   92: iconst_1
    //   93: invokevirtual a : (Ljava/lang/String;Lim;Lorg/json/JSONObject;Lorg/json/JSONObject;Z)Lir;
    //   96: astore_1
    //   97: new gnv
    //   100: dup
    //   101: new kxp
    //   104: dup
    //   105: aload_0
    //   106: aload_3
    //   107: aload_2
    //   108: invokespecial <init> : (Lkxn;Lkxl;Lkxl;)V
    //   111: aload_1
    //   112: invokespecial <init> : (Lgkw;Lir;)V
    //   115: astore_2
    //   116: invokestatic a : ()Lgnp;
    //   119: invokevirtual b : ()Lie;
    //   122: ifnull -> 167
    //   125: invokestatic a : ()Lgnp;
    //   128: invokevirtual b : ()Lie;
    //   131: aload_1
    //   132: aload_2
    //   133: invokevirtual a : (Lir;Lih;)V
    //   136: return
    //   137: astore #5
    //   139: aload #5
    //   141: invokevirtual printStackTrace : ()V
    //   144: goto -> 41
    //   147: astore_1
    //   148: ldc 'ERROR_SERV'
    //   150: aload_1
    //   151: invokevirtual getMessage : ()Ljava/lang/String;
    //   154: invokestatic e : (Ljava/lang/String;Ljava/lang/String;)I
    //   157: pop
    //   158: aload_3
    //   159: ldc ''
    //   161: invokeinterface a : (Ljava/lang/Object;)V
    //   166: return
    //   167: aload_3
    //   168: ldc ''
    //   170: invokeinterface a : (Ljava/lang/Object;)V
    //   175: return
    // Exception table:
    //   from	to	target	type
    //   9	41	137	org/json/JSONException
    //   125	136	147	java/lang/Exception
  }
  
  public void a(koo paramkoo, kxl<String> paramkxl1, kxl<String> paramkxl2) {
    // Byte code:
    //   0: new org/json/JSONObject
    //   3: dup
    //   4: invokespecial <init> : ()V
    //   7: astore #4
    //   9: aload #4
    //   11: ldc 'X-Application-Key'
    //   13: invokestatic a : ()Lmzx;
    //   16: invokevirtual c : ()Ljava/util/Properties;
    //   19: ldc 'appKey'
    //   21: invokevirtual get : (Ljava/lang/Object;)Ljava/lang/Object;
    //   24: invokestatic valueOf : (Ljava/lang/Object;)Ljava/lang/String;
    //   27: invokevirtual put : (Ljava/lang/String;Ljava/lang/Object;)Lorg/json/JSONObject;
    //   30: pop
    //   31: aload #4
    //   33: ldc 'Content-Type'
    //   35: ldc 'application/json'
    //   37: invokevirtual put : (Ljava/lang/String;Ljava/lang/Object;)Lorg/json/JSONObject;
    //   40: pop
    //   41: invokestatic a : ()Lnab;
    //   44: astore #5
    //   46: aload_1
    //   47: aload #5
    //   49: aload_1
    //   50: invokevirtual a : ()Ljava/lang/String;
    //   53: invokevirtual b : (Ljava/lang/String;)Ljava/lang/String;
    //   56: invokevirtual c : (Ljava/lang/String;)V
    //   59: aload_1
    //   60: aload #5
    //   62: aload_1
    //   63: invokevirtual e : ()Ljava/lang/String;
    //   66: invokevirtual b : (Ljava/lang/String;)Ljava/lang/String;
    //   69: invokevirtual l : (Ljava/lang/String;)V
    //   72: aload_1
    //   73: aload #5
    //   75: aload_1
    //   76: invokevirtual g : ()Ljava/lang/String;
    //   79: invokevirtual b : (Ljava/lang/String;)Ljava/lang/String;
    //   82: invokevirtual n : (Ljava/lang/String;)V
    //   85: aload_1
    //   86: aload #5
    //   88: aload_1
    //   89: invokevirtual f : ()Ljava/lang/String;
    //   92: invokevirtual b : (Ljava/lang/String;)Ljava/lang/String;
    //   95: invokevirtual m : (Ljava/lang/String;)V
    //   98: aload_1
    //   99: aload #5
    //   101: aload_1
    //   102: invokevirtual b : ()Ljava/lang/String;
    //   105: invokevirtual b : (Ljava/lang/String;)Ljava/lang/String;
    //   108: aload #5
    //   110: aload_1
    //   111: invokevirtual c : ()Ljava/lang/String;
    //   114: invokevirtual b : (Ljava/lang/String;)Ljava/lang/String;
    //   117: invokevirtual a : (Ljava/lang/String;Ljava/lang/String;)V
    //   120: getstatic kwr.INSURANCE_SCHEDULE_ASSISTANCE : Lkwr;
    //   123: invokevirtual getEndpoint : ()Ljava/lang/String;
    //   126: astore #5
    //   128: aload_1
    //   129: invokevirtual toString : ()Ljava/lang/String;
    //   132: astore_1
    //   133: new org/json/JSONObject
    //   136: dup
    //   137: aload_1
    //   138: invokespecial <init> : (Ljava/lang/String;)V
    //   141: astore_1
    //   142: invokestatic a : ()Lgnp;
    //   145: aload #5
    //   147: getstatic im.POST : Lim;
    //   150: aload #4
    //   152: aload_1
    //   153: iconst_1
    //   154: invokevirtual a : (Ljava/lang/String;Lim;Lorg/json/JSONObject;Lorg/json/JSONObject;Z)Lir;
    //   157: astore_1
    //   158: new gnv
    //   161: dup
    //   162: new kxs
    //   165: dup
    //   166: aload_0
    //   167: aload_3
    //   168: aload_2
    //   169: invokespecial <init> : (Lkxn;Lkxl;Lkxl;)V
    //   172: aload_1
    //   173: invokespecial <init> : (Lgkw;Lir;)V
    //   176: astore_2
    //   177: invokestatic a : ()Lgnp;
    //   180: invokevirtual b : ()Lie;
    //   183: ifnull -> 240
    //   186: invokestatic a : ()Lgnp;
    //   189: invokevirtual b : ()Lie;
    //   192: aload_1
    //   193: aload_2
    //   194: invokevirtual a : (Lir;Lih;)V
    //   197: return
    //   198: astore #5
    //   200: aload #5
    //   202: invokevirtual printStackTrace : ()V
    //   205: goto -> 41
    //   208: astore_1
    //   209: new org/json/JSONObject
    //   212: dup
    //   213: invokespecial <init> : ()V
    //   216: astore_1
    //   217: goto -> 142
    //   220: astore_1
    //   221: ldc 'ERROR_SERV'
    //   223: aload_1
    //   224: invokevirtual getMessage : ()Ljava/lang/String;
    //   227: invokestatic e : (Ljava/lang/String;Ljava/lang/String;)I
    //   230: pop
    //   231: aload_3
    //   232: ldc ''
    //   234: invokeinterface a : (Ljava/lang/Object;)V
    //   239: return
    //   240: aload_3
    //   241: ldc ''
    //   243: invokeinterface a : (Ljava/lang/Object;)V
    //   248: return
    // Exception table:
    //   from	to	target	type
    //   9	41	198	org/json/JSONException
    //   133	142	208	org/json/JSONException
    //   186	197	220	java/lang/Exception
  }
  
  public void a(kxl<List<kph>> paramkxl, kxl<String> paramkxl1) {
    // Byte code:
    //   0: new org/json/JSONObject
    //   3: dup
    //   4: invokespecial <init> : ()V
    //   7: astore_3
    //   8: aload_3
    //   9: ldc 'X-Application-Key'
    //   11: invokestatic a : ()Lmzx;
    //   14: invokevirtual c : ()Ljava/util/Properties;
    //   17: ldc 'appKey'
    //   19: invokevirtual get : (Ljava/lang/Object;)Ljava/lang/Object;
    //   22: invokestatic valueOf : (Ljava/lang/Object;)Ljava/lang/String;
    //   25: invokevirtual put : (Ljava/lang/String;Ljava/lang/Object;)Lorg/json/JSONObject;
    //   28: pop
    //   29: aload_3
    //   30: ldc 'Content-Type'
    //   32: ldc 'application/json'
    //   34: invokevirtual put : (Ljava/lang/String;Ljava/lang/Object;)Lorg/json/JSONObject;
    //   37: pop
    //   38: invokestatic a : ()Lgnp;
    //   41: getstatic kwr.INSURANCE_GET_SCHEDULING_LIST : Lkwr;
    //   44: invokevirtual getEndpoint : ()Ljava/lang/String;
    //   47: getstatic im.POST : Lim;
    //   50: aload_3
    //   51: new org/json/JSONObject
    //   54: dup
    //   55: invokespecial <init> : ()V
    //   58: iconst_1
    //   59: invokevirtual a : (Ljava/lang/String;Lim;Lorg/json/JSONObject;Lorg/json/JSONObject;Z)Lir;
    //   62: astore_3
    //   63: new gnv
    //   66: dup
    //   67: new kxq
    //   70: dup
    //   71: aload_0
    //   72: aload_2
    //   73: aload_1
    //   74: invokespecial <init> : (Lkxn;Lkxl;Lkxl;)V
    //   77: aload_3
    //   78: invokespecial <init> : (Lgkw;Lir;)V
    //   81: astore_1
    //   82: invokestatic a : ()Lgnp;
    //   85: invokevirtual b : ()Lie;
    //   88: ifnull -> 133
    //   91: invokestatic a : ()Lgnp;
    //   94: invokevirtual b : ()Lie;
    //   97: aload_3
    //   98: aload_1
    //   99: invokevirtual a : (Lir;Lih;)V
    //   102: return
    //   103: astore #4
    //   105: aload #4
    //   107: invokevirtual printStackTrace : ()V
    //   110: goto -> 38
    //   113: astore_1
    //   114: ldc 'ERROR_SERV'
    //   116: aload_1
    //   117: invokevirtual getMessage : ()Ljava/lang/String;
    //   120: invokestatic e : (Ljava/lang/String;Ljava/lang/String;)I
    //   123: pop
    //   124: aload_2
    //   125: ldc ''
    //   127: invokeinterface a : (Ljava/lang/Object;)V
    //   132: return
    //   133: aload_2
    //   134: ldc ''
    //   136: invokeinterface a : (Ljava/lang/Object;)V
    //   141: return
    // Exception table:
    //   from	to	target	type
    //   8	38	103	org/json/JSONException
    //   91	102	113	java/lang/Exception
  }
  
  public void b(String paramString1, String paramString2, kxl<String> paramkxl1, kxl<String> paramkxl2) {
    // Byte code:
    //   0: new org/json/JSONObject
    //   3: dup
    //   4: invokespecial <init> : ()V
    //   7: astore #5
    //   9: aload #5
    //   11: ldc 'X-Application-Key'
    //   13: invokestatic a : ()Lmzx;
    //   16: invokevirtual c : ()Ljava/util/Properties;
    //   19: ldc 'appKey'
    //   21: invokevirtual get : (Ljava/lang/Object;)Ljava/lang/Object;
    //   24: invokestatic valueOf : (Ljava/lang/Object;)Ljava/lang/String;
    //   27: invokevirtual put : (Ljava/lang/String;Ljava/lang/Object;)Lorg/json/JSONObject;
    //   30: pop
    //   31: aload #5
    //   33: ldc 'Content-Type'
    //   35: ldc 'application/json'
    //   37: invokevirtual put : (Ljava/lang/String;Ljava/lang/Object;)Lorg/json/JSONObject;
    //   40: pop
    //   41: getstatic kwr.INSURANCE_RESCHEDULE_ASSISTANCE : Lkwr;
    //   44: invokevirtual getEndpoint : ()Ljava/lang/String;
    //   47: astore #6
    //   49: new org/json/JSONObject
    //   52: dup
    //   53: invokespecial <init> : ()V
    //   56: astore #7
    //   58: new org/json/JSONObject
    //   61: dup
    //   62: invokespecial <init> : ()V
    //   65: astore #8
    //   67: aload #8
    //   69: ldc_w 'number'
    //   72: aload_1
    //   73: invokevirtual put : (Ljava/lang/String;Ljava/lang/Object;)Lorg/json/JSONObject;
    //   76: pop
    //   77: aload #8
    //   79: ldc_w 'rescheduleDate'
    //   82: aload_2
    //   83: invokevirtual put : (Ljava/lang/String;Ljava/lang/Object;)Lorg/json/JSONObject;
    //   86: pop
    //   87: aload #7
    //   89: ldc_w 'scheduling'
    //   92: aload #8
    //   94: invokevirtual put : (Ljava/lang/String;Ljava/lang/Object;)Lorg/json/JSONObject;
    //   97: pop
    //   98: invokestatic a : ()Lgnp;
    //   101: aload #6
    //   103: getstatic im.PUT : Lim;
    //   106: aload #5
    //   108: aload #7
    //   110: iconst_1
    //   111: invokevirtual a : (Ljava/lang/String;Lim;Lorg/json/JSONObject;Lorg/json/JSONObject;Z)Lir;
    //   114: astore_1
    //   115: new gnv
    //   118: dup
    //   119: new kxt
    //   122: dup
    //   123: aload_0
    //   124: aload #4
    //   126: aload_3
    //   127: invokespecial <init> : (Lkxn;Lkxl;Lkxl;)V
    //   130: aload_1
    //   131: invokespecial <init> : (Lgkw;Lir;)V
    //   134: astore_2
    //   135: invokestatic a : ()Lgnp;
    //   138: invokevirtual b : ()Lie;
    //   141: ifnull -> 195
    //   144: invokestatic a : ()Lgnp;
    //   147: invokevirtual b : ()Lie;
    //   150: aload_1
    //   151: aload_2
    //   152: invokevirtual a : (Lir;Lih;)V
    //   155: return
    //   156: astore #6
    //   158: aload #6
    //   160: invokevirtual printStackTrace : ()V
    //   163: goto -> 41
    //   166: astore_1
    //   167: aload_1
    //   168: invokevirtual printStackTrace : ()V
    //   171: goto -> 98
    //   174: astore_1
    //   175: ldc 'ERROR_SERV'
    //   177: aload_1
    //   178: invokevirtual getMessage : ()Ljava/lang/String;
    //   181: invokestatic e : (Ljava/lang/String;Ljava/lang/String;)I
    //   184: pop
    //   185: aload #4
    //   187: ldc ''
    //   189: invokeinterface a : (Ljava/lang/Object;)V
    //   194: return
    //   195: aload #4
    //   197: ldc ''
    //   199: invokeinterface a : (Ljava/lang/Object;)V
    //   204: return
    // Exception table:
    //   from	to	target	type
    //   9	41	156	org/json/JSONException
    //   67	98	166	org/json/JSONException
    //   144	155	174	java/lang/Exception
  }
  
  public void b(String paramString, kxl<String> paramkxl1, kxl<String> paramkxl2) {
    // Byte code:
    //   0: new org/json/JSONObject
    //   3: dup
    //   4: invokespecial <init> : ()V
    //   7: astore #4
    //   9: aload #4
    //   11: ldc 'X-Application-Key'
    //   13: invokestatic a : ()Lmzx;
    //   16: invokevirtual c : ()Ljava/util/Properties;
    //   19: ldc 'appKey'
    //   21: invokevirtual get : (Ljava/lang/Object;)Ljava/lang/Object;
    //   24: invokestatic valueOf : (Ljava/lang/Object;)Ljava/lang/String;
    //   27: invokevirtual put : (Ljava/lang/String;Ljava/lang/Object;)Lorg/json/JSONObject;
    //   30: pop
    //   31: aload #4
    //   33: ldc 'Content-Type'
    //   35: ldc 'application/json'
    //   37: invokevirtual put : (Ljava/lang/String;Ljava/lang/Object;)Lorg/json/JSONObject;
    //   40: pop
    //   41: getstatic kwr.INSURANCE_CANCEL_ASSISTANCE : Lkwr;
    //   44: invokevirtual getEndpoint : ()Ljava/lang/String;
    //   47: astore #5
    //   49: new org/json/JSONObject
    //   52: dup
    //   53: invokespecial <init> : ()V
    //   56: astore #6
    //   58: new org/json/JSONObject
    //   61: dup
    //   62: invokespecial <init> : ()V
    //   65: astore #7
    //   67: aload #7
    //   69: ldc_w 'number'
    //   72: aload_1
    //   73: invokevirtual put : (Ljava/lang/String;Ljava/lang/Object;)Lorg/json/JSONObject;
    //   76: pop
    //   77: aload #6
    //   79: ldc_w 'scheduling'
    //   82: aload #7
    //   84: invokevirtual put : (Ljava/lang/String;Ljava/lang/Object;)Lorg/json/JSONObject;
    //   87: pop
    //   88: invokestatic a : ()Lgnp;
    //   91: aload #5
    //   93: getstatic im.PUT : Lim;
    //   96: aload #4
    //   98: aload #6
    //   100: iconst_1
    //   101: invokevirtual a : (Ljava/lang/String;Lim;Lorg/json/JSONObject;Lorg/json/JSONObject;Z)Lir;
    //   104: astore_1
    //   105: new gnv
    //   108: dup
    //   109: new kxu
    //   112: dup
    //   113: aload_0
    //   114: aload_3
    //   115: aload_2
    //   116: invokespecial <init> : (Lkxn;Lkxl;Lkxl;)V
    //   119: aload_1
    //   120: invokespecial <init> : (Lgkw;Lir;)V
    //   123: astore_2
    //   124: invokestatic a : ()Lgnp;
    //   127: invokevirtual b : ()Lie;
    //   130: ifnull -> 183
    //   133: invokestatic a : ()Lgnp;
    //   136: invokevirtual b : ()Lie;
    //   139: aload_1
    //   140: aload_2
    //   141: invokevirtual a : (Lir;Lih;)V
    //   144: return
    //   145: astore #5
    //   147: aload #5
    //   149: invokevirtual printStackTrace : ()V
    //   152: goto -> 41
    //   155: astore_1
    //   156: aload_1
    //   157: invokevirtual printStackTrace : ()V
    //   160: goto -> 88
    //   163: astore_1
    //   164: ldc 'ERROR_SERV'
    //   166: aload_1
    //   167: invokevirtual getMessage : ()Ljava/lang/String;
    //   170: invokestatic e : (Ljava/lang/String;Ljava/lang/String;)I
    //   173: pop
    //   174: aload_3
    //   175: ldc ''
    //   177: invokeinterface a : (Ljava/lang/Object;)V
    //   182: return
    //   183: aload_3
    //   184: ldc ''
    //   186: invokeinterface a : (Ljava/lang/Object;)V
    //   191: return
    // Exception table:
    //   from	to	target	type
    //   9	41	145	org/json/JSONException
    //   67	88	155	org/json/JSONException
    //   133	144	163	java/lang/Exception
  }
}


/* Location:              C:\Users\devid\Downloads\SAST\Santander\dex2jar-2.0\classes2-dex2jar.jar!\kxn.class
 * Java compiler version: 6 (50.0)
 * JD-Core Version:       1.1.3
 */