import android.support.annotation.DrawableRes;
import android.support.v7.widget.RecyclerView;
import android.view.LayoutInflater;
import android.view.ViewGroup;
import java.util.List;

public class lau extends RecyclerView.Adapter<lax> {
  private law a;
  
  private List<kon> b;
  
  public lau(List<kon> paramList) {
    this.b = paramList;
  }
  
  @DrawableRes
  private int a(String paramString) {
    // Byte code:
    //   0: ldc 2130838527
    //   2: istore_3
    //   3: aload_1
    //   4: invokevirtual hashCode : ()I
    //   7: lookupswitch default -> 200, 48626 -> 312, 48627 -> 326, 48628 -> 340, 48629 -> 354, 48630 -> 368, 48631 -> 382, 48632 -> 396, 48633 -> 411, 48634 -> 426, 48656 -> 441, 48657 -> 456, 48658 -> 471, 48659 -> 486, 48660 -> 501, 48661 -> 516, 48662 -> 531, 48663 -> 546, 48664 -> 561, 48665 -> 576, 48687 -> 591, 48688 -> 606, 48689 -> 621, 48690 -> 636
    //   200: iconst_m1
    //   201: istore_2
    //   202: iload_2
    //   203: tableswitch default -> 308, 0 -> 651, 1 -> 654, 2 -> 657, 3 -> 310, 4 -> 660, 5 -> 663, 6 -> 310, 7 -> 666, 8 -> 669, 9 -> 672, 10 -> 675, 11 -> 678, 12 -> 681, 13 -> 684, 14 -> 687, 15 -> 690, 16 -> 693, 17 -> 696, 18 -> 699, 19 -> 702, 20 -> 705, 21 -> 708, 22 -> 711
    //   308: iconst_m1
    //   309: istore_3
    //   310: iload_3
    //   311: ireturn
    //   312: aload_1
    //   313: ldc '101'
    //   315: invokevirtual equals : (Ljava/lang/Object;)Z
    //   318: ifeq -> 200
    //   321: iconst_0
    //   322: istore_2
    //   323: goto -> 202
    //   326: aload_1
    //   327: ldc '102'
    //   329: invokevirtual equals : (Ljava/lang/Object;)Z
    //   332: ifeq -> 200
    //   335: iconst_1
    //   336: istore_2
    //   337: goto -> 202
    //   340: aload_1
    //   341: ldc '103'
    //   343: invokevirtual equals : (Ljava/lang/Object;)Z
    //   346: ifeq -> 200
    //   349: iconst_2
    //   350: istore_2
    //   351: goto -> 202
    //   354: aload_1
    //   355: ldc '104'
    //   357: invokevirtual equals : (Ljava/lang/Object;)Z
    //   360: ifeq -> 200
    //   363: iconst_3
    //   364: istore_2
    //   365: goto -> 202
    //   368: aload_1
    //   369: ldc '105'
    //   371: invokevirtual equals : (Ljava/lang/Object;)Z
    //   374: ifeq -> 200
    //   377: iconst_4
    //   378: istore_2
    //   379: goto -> 202
    //   382: aload_1
    //   383: ldc '106'
    //   385: invokevirtual equals : (Ljava/lang/Object;)Z
    //   388: ifeq -> 200
    //   391: iconst_5
    //   392: istore_2
    //   393: goto -> 202
    //   396: aload_1
    //   397: ldc '107'
    //   399: invokevirtual equals : (Ljava/lang/Object;)Z
    //   402: ifeq -> 200
    //   405: bipush #6
    //   407: istore_2
    //   408: goto -> 202
    //   411: aload_1
    //   412: ldc '108'
    //   414: invokevirtual equals : (Ljava/lang/Object;)Z
    //   417: ifeq -> 200
    //   420: bipush #7
    //   422: istore_2
    //   423: goto -> 202
    //   426: aload_1
    //   427: ldc '109'
    //   429: invokevirtual equals : (Ljava/lang/Object;)Z
    //   432: ifeq -> 200
    //   435: bipush #8
    //   437: istore_2
    //   438: goto -> 202
    //   441: aload_1
    //   442: ldc '110'
    //   444: invokevirtual equals : (Ljava/lang/Object;)Z
    //   447: ifeq -> 200
    //   450: bipush #9
    //   452: istore_2
    //   453: goto -> 202
    //   456: aload_1
    //   457: ldc '111'
    //   459: invokevirtual equals : (Ljava/lang/Object;)Z
    //   462: ifeq -> 200
    //   465: bipush #10
    //   467: istore_2
    //   468: goto -> 202
    //   471: aload_1
    //   472: ldc '112'
    //   474: invokevirtual equals : (Ljava/lang/Object;)Z
    //   477: ifeq -> 200
    //   480: bipush #11
    //   482: istore_2
    //   483: goto -> 202
    //   486: aload_1
    //   487: ldc '113'
    //   489: invokevirtual equals : (Ljava/lang/Object;)Z
    //   492: ifeq -> 200
    //   495: bipush #12
    //   497: istore_2
    //   498: goto -> 202
    //   501: aload_1
    //   502: ldc '114'
    //   504: invokevirtual equals : (Ljava/lang/Object;)Z
    //   507: ifeq -> 200
    //   510: bipush #13
    //   512: istore_2
    //   513: goto -> 202
    //   516: aload_1
    //   517: ldc '115'
    //   519: invokevirtual equals : (Ljava/lang/Object;)Z
    //   522: ifeq -> 200
    //   525: bipush #14
    //   527: istore_2
    //   528: goto -> 202
    //   531: aload_1
    //   532: ldc '116'
    //   534: invokevirtual equals : (Ljava/lang/Object;)Z
    //   537: ifeq -> 200
    //   540: bipush #15
    //   542: istore_2
    //   543: goto -> 202
    //   546: aload_1
    //   547: ldc '117'
    //   549: invokevirtual equals : (Ljava/lang/Object;)Z
    //   552: ifeq -> 200
    //   555: bipush #16
    //   557: istore_2
    //   558: goto -> 202
    //   561: aload_1
    //   562: ldc '118'
    //   564: invokevirtual equals : (Ljava/lang/Object;)Z
    //   567: ifeq -> 200
    //   570: bipush #17
    //   572: istore_2
    //   573: goto -> 202
    //   576: aload_1
    //   577: ldc '119'
    //   579: invokevirtual equals : (Ljava/lang/Object;)Z
    //   582: ifeq -> 200
    //   585: bipush #18
    //   587: istore_2
    //   588: goto -> 202
    //   591: aload_1
    //   592: ldc '120'
    //   594: invokevirtual equals : (Ljava/lang/Object;)Z
    //   597: ifeq -> 200
    //   600: bipush #19
    //   602: istore_2
    //   603: goto -> 202
    //   606: aload_1
    //   607: ldc '121'
    //   609: invokevirtual equals : (Ljava/lang/Object;)Z
    //   612: ifeq -> 200
    //   615: bipush #20
    //   617: istore_2
    //   618: goto -> 202
    //   621: aload_1
    //   622: ldc '122'
    //   624: invokevirtual equals : (Ljava/lang/Object;)Z
    //   627: ifeq -> 200
    //   630: bipush #21
    //   632: istore_2
    //   633: goto -> 202
    //   636: aload_1
    //   637: ldc '123'
    //   639: invokevirtual equals : (Ljava/lang/Object;)Z
    //   642: ifeq -> 200
    //   645: bipush #22
    //   647: istore_2
    //   648: goto -> 202
    //   651: ldc 2130838349
    //   653: ireturn
    //   654: ldc 2130838601
    //   656: ireturn
    //   657: ldc 2130838648
    //   659: ireturn
    //   660: ldc 2130838388
    //   662: ireturn
    //   663: ldc 2130838636
    //   665: ireturn
    //   666: ldc 2130838636
    //   668: ireturn
    //   669: ldc 2130838439
    //   671: ireturn
    //   672: ldc 2130838683
    //   674: ireturn
    //   675: ldc 2130838426
    //   677: ireturn
    //   678: ldc 2130838652
    //   680: ireturn
    //   681: ldc 2130838481
    //   683: ireturn
    //   684: ldc 2130838399
    //   686: ireturn
    //   687: ldc 2130838574
    //   689: ireturn
    //   690: ldc 2130838608
    //   692: ireturn
    //   693: ldc 2130838684
    //   695: ireturn
    //   696: ldc 2130838670
    //   698: ireturn
    //   699: ldc 2130838686
    //   701: ireturn
    //   702: ldc 2130838685
    //   704: ireturn
    //   705: ldc 2130838599
    //   707: ireturn
    //   708: ldc 2130838652
    //   710: ireturn
    //   711: ldc 2130838640
    //   713: ireturn
  }
  
  public lax a(ViewGroup paramViewGroup, int paramInt) {
    return new lax(LayoutInflater.from(paramViewGroup.getContext()).inflate(2130969325, paramViewGroup, false));
  }
  
  public void a(law paramlaw) {
    this.a = paramlaw;
  }
  
  public void a(lax paramlax, int paramInt) {
    kon kon = this.b.get(paramInt);
    lav lav = new lav(this, kon);
    paramlax.c.setOnClickListener(lav);
    paramlax.b.setOnClickListener(lav);
    paramlax.a.setOnClickListener(lav);
    paramInt = a(kon.a());
    if (paramInt != -1)
      paramlax.c.setImageResource(paramInt); 
    paramlax.d.setText(kon.c());
  }
  
  public int getItemCount() {
    return this.b.size();
  }
}


/* Location:              C:\Users\devid\Downloads\SAST\Santander\dex2jar-2.0\classes2-dex2jar.jar!\lau.class
 * Java compiler version: 6 (50.0)
 * JD-Core Version:       1.1.3
 */