import android.content.BroadcastReceiver;
import android.content.Context;
import android.content.Intent;

class nkp extends BroadcastReceiver {
  nkp(nko paramnko, nhp paramnhp) {}
  
  private void a() {
    this.a.b(new nht(nko.b(this.b)));
  }
  
  public void onReceive(Context paramContext, Intent paramIntent) {
    // Byte code:
    //   0: iconst_0
    //   1: istore #7
    //   3: aload_2
    //   4: ifnonnull -> 8
    //   7: return
    //   8: aload_2
    //   9: ldc 'level'
    //   11: iconst_m1
    //   12: invokevirtual getIntExtra : (Ljava/lang/String;I)I
    //   15: istore_3
    //   16: aload_2
    //   17: ldc 'scale'
    //   19: iconst_m1
    //   20: invokevirtual getIntExtra : (Ljava/lang/String;I)I
    //   23: istore #4
    //   25: aload_2
    //   26: ldc 'status'
    //   28: iconst_m1
    //   29: invokevirtual getIntExtra : (Ljava/lang/String;I)I
    //   32: istore #5
    //   34: iload_3
    //   35: iconst_m1
    //   36: if_icmpeq -> 156
    //   39: iload #4
    //   41: iconst_m1
    //   42: if_icmpeq -> 156
    //   45: iload #4
    //   47: ifeq -> 156
    //   50: aload_0
    //   51: getfield b : Lnko;
    //   54: iload_3
    //   55: i2f
    //   56: iload #4
    //   58: i2f
    //   59: fdiv
    //   60: ldc 100.0
    //   62: fmul
    //   63: invokestatic round : (F)I
    //   66: invokestatic a : (Lnko;I)I
    //   69: pop
    //   70: aload_0
    //   71: getfield b : Lnko;
    //   74: invokestatic a : (Lnko;)I
    //   77: bipush #15
    //   79: if_icmpgt -> 150
    //   82: iconst_1
    //   83: istore #6
    //   85: aload_0
    //   86: getfield b : Lnko;
    //   89: invokestatic b : (Lnko;)Z
    //   92: iload #6
    //   94: ixor
    //   95: ifeq -> 112
    //   98: aload_0
    //   99: getfield b : Lnko;
    //   102: iload #6
    //   104: invokestatic a : (Lnko;Z)Z
    //   107: pop
    //   108: aload_0
    //   109: invokespecial a : ()V
    //   112: iload #5
    //   114: iconst_m1
    //   115: if_icmpeq -> 7
    //   118: aload_0
    //   119: getfield b : Lnko;
    //   122: astore_1
    //   123: iload #5
    //   125: iconst_2
    //   126: if_icmpeq -> 139
    //   129: iload #7
    //   131: istore #6
    //   133: iload #5
    //   135: iconst_5
    //   136: if_icmpne -> 142
    //   139: iconst_1
    //   140: istore #6
    //   142: aload_1
    //   143: iload #6
    //   145: invokestatic b : (Lnko;Z)Z
    //   148: pop
    //   149: return
    //   150: iconst_0
    //   151: istore #6
    //   153: goto -> 85
    //   156: aload_0
    //   157: getfield b : Lnko;
    //   160: iconst_m1
    //   161: invokestatic a : (Lnko;I)I
    //   164: pop
    //   165: aload_0
    //   166: getfield b : Lnko;
    //   169: iconst_0
    //   170: invokestatic a : (Lnko;Z)Z
    //   173: pop
    //   174: aload_0
    //   175: invokespecial a : ()V
    //   178: goto -> 112
  }
}


/* Location:              C:\Users\devid\Downloads\SAST\Santander\dex2jar-2.0\classes2-dex2jar.jar!\nkp.class
 * Java compiler version: 6 (50.0)
 * JD-Core Version:       1.1.3
 */