import java.util.concurrent.ScheduledExecutorService;

final class nku {
  private static ScheduledExecutorService a;
  
  static nhp a(nhc paramnhc) {
    // Byte code:
    //   0: ldc nku
    //   2: monitorenter
    //   3: getstatic nku.a : Ljava/util/concurrent/ScheduledExecutorService;
    //   6: ifnonnull -> 15
    //   9: invokestatic newSingleThreadScheduledExecutor : ()Ljava/util/concurrent/ScheduledExecutorService;
    //   12: putstatic nku.a : Ljava/util/concurrent/ScheduledExecutorService;
    //   15: new nkv
    //   18: dup
    //   19: aload_0
    //   20: invokespecial <init> : (Lnhc;)V
    //   23: astore_0
    //   24: ldc nku
    //   26: monitorexit
    //   27: aload_0
    //   28: areturn
    //   29: astore_0
    //   30: ldc nku
    //   32: monitorexit
    //   33: aload_0
    //   34: athrow
    // Exception table:
    //   from	to	target	type
    //   3	15	29	finally
    //   15	24	29	finally
  }
}


/* Location:              C:\Users\devid\Downloads\SAST\Santander\dex2jar-2.0\classes2-dex2jar.jar!\nku.class
 * Java compiler version: 6 (50.0)
 * JD-Core Version:       1.1.3
 */