import java.io.InputStream;
import java.io.OutputStream;
import java.net.HttpURLConnection;
import java.security.SecureRandom;
import java.util.Timer;
import java.util.TimerTask;
import javax.net.ssl.HttpsURLConnection;
import javax.net.ssl.SSLContext;
import javax.net.ssl.TrustManager;

public class p {
  public static final int a = 2301;
  
  public static final int b = 2302;
  
  public static final int c = 2303;
  
  public static final int d = 2304;
  
  public static final int e = 2305;
  
  public static final int f = 2306;
  
  public static final int g = 2307;
  
  public static final int h = 2308;
  
  public static final int i = 2309;
  
  public static final int j = 2310;
  
  public static final int k = 2314;
  
  public static final int l = 2315;
  
  public static final int m = 2800;
  
  private static final String n = "POST";
  
  private static int o = 30000;
  
  private static HttpURLConnection p = null;
  
  private static InputStream q = null;
  
  private static OutputStream r = null;
  
  private static Timer s = null;
  
  private static TimerTask t = null;
  
  private static void a() {
    q q = new q();
    try {
      SSLContext sSLContext = SSLContext.getInstance("TLS");
      SecureRandom secureRandom = new SecureRandom();
      sSLContext.init(null, new TrustManager[] { q }, secureRandom);
      HttpsURLConnection.setDefaultSSLSocketFactory(sSLContext.getSocketFactory());
      return;
    } catch (Exception exception) {
      return;
    } 
  }
  
  public static void a(bgf parambgf, String paramString, bft parambft) {
    // Byte code:
    //   0: iconst_1
    //   1: istore_3
    //   2: aload_0
    //   3: invokevirtual a : ()Ljava/lang/String;
    //   6: astore #7
    //   8: aload #7
    //   10: ldc 'http://'
    //   12: ldc ''
    //   14: invokevirtual replace : (Ljava/lang/CharSequence;Ljava/lang/CharSequence;)Ljava/lang/String;
    //   17: ldc 'https://'
    //   19: ldc ''
    //   21: invokevirtual replace : (Ljava/lang/CharSequence;Ljava/lang/CharSequence;)Ljava/lang/String;
    //   24: ldc ':'
    //   26: invokevirtual contains : (Ljava/lang/CharSequence;)Z
    //   29: ifeq -> 95
    //   32: ldc ''
    //   34: aload_0
    //   35: invokevirtual c : ()Ljava/lang/String;
    //   38: invokevirtual concat : (Ljava/lang/String;)Ljava/lang/String;
    //   41: astore #6
    //   43: aload #7
    //   45: aload #6
    //   47: invokevirtual concat : (Ljava/lang/String;)Ljava/lang/String;
    //   50: astore #6
    //   52: new java/net/URL
    //   55: dup
    //   56: aload #6
    //   58: invokespecial <init> : (Ljava/lang/String;)V
    //   61: astore #6
    //   63: iconst_2
    //   64: istore_3
    //   65: aload #6
    //   67: ifnonnull -> 121
    //   70: new java/net/MalformedURLException
    //   73: dup
    //   74: invokespecial <init> : ()V
    //   77: athrow
    //   78: astore_0
    //   79: iconst_3
    //   80: istore_3
    //   81: aload_2
    //   82: sipush #2301
    //   85: aload_0
    //   86: invokeinterface a : (ILjava/lang/Exception;)V
    //   91: invokestatic c : ()V
    //   94: return
    //   95: ldc ''
    //   97: ldc ':'
    //   99: invokevirtual concat : (Ljava/lang/String;)Ljava/lang/String;
    //   102: aload_0
    //   103: invokevirtual b : ()Ljava/lang/String;
    //   106: invokevirtual concat : (Ljava/lang/String;)Ljava/lang/String;
    //   109: aload_0
    //   110: invokevirtual c : ()Ljava/lang/String;
    //   113: invokevirtual concat : (Ljava/lang/String;)Ljava/lang/String;
    //   116: astore #6
    //   118: goto -> 43
    //   121: iconst_4
    //   122: istore_3
    //   123: aload #6
    //   125: invokevirtual getProtocol : ()Ljava/lang/String;
    //   128: invokevirtual toLowerCase : ()Ljava/lang/String;
    //   131: ldc 'https'
    //   133: invokevirtual equals : (Ljava/lang/Object;)Z
    //   136: istore #5
    //   138: iload #5
    //   140: ifeq -> 152
    //   143: invokestatic a : ()V
    //   146: ldc2_w 50
    //   149: invokestatic sleep : (J)V
    //   152: bipush #8
    //   154: istore_3
    //   155: aload #6
    //   157: invokestatic openConnection : (Ljava/net/URL;)Ljava/net/URLConnection;
    //   160: astore #6
    //   162: aload #6
    //   164: ifnonnull -> 192
    //   167: bipush #11
    //   169: istore_3
    //   170: aload_2
    //   171: sipush #2302
    //   174: aconst_null
    //   175: invokeinterface a : (ILjava/lang/Exception;)V
    //   180: invokestatic c : ()V
    //   183: return
    //   184: astore #6
    //   186: aconst_null
    //   187: astore #6
    //   189: goto -> 162
    //   192: bipush #12
    //   194: istore #4
    //   196: iload #4
    //   198: istore_3
    //   199: aload #6
    //   201: instanceof java/net/HttpURLConnection
    //   204: ifne -> 235
    //   207: iload #4
    //   209: istore_3
    //   210: aload #6
    //   212: instanceof javax/net/ssl/HttpsURLConnection
    //   215: ifne -> 235
    //   218: bipush #13
    //   220: istore_3
    //   221: aload_2
    //   222: sipush #2303
    //   225: aconst_null
    //   226: invokeinterface a : (ILjava/lang/Exception;)V
    //   231: invokestatic c : ()V
    //   234: return
    //   235: iload #4
    //   237: istore_3
    //   238: new java/lang/StringBuilder
    //   241: dup
    //   242: ldc '<?xml version="1.0" encoding="UTF-8"?><S:Envelope xmlns:S="http://schemas.xmlsoap.org/soap/envelope/"><S:Header/><S:Body><tns:'
    //   244: invokespecial <init> : (Ljava/lang/String;)V
    //   247: aload_0
    //   248: invokevirtual g : ()Ljava/lang/String;
    //   251: invokevirtual append : (Ljava/lang/String;)Ljava/lang/StringBuilder;
    //   254: ldc ' xmlns:tns="'
    //   256: invokevirtual append : (Ljava/lang/String;)Ljava/lang/StringBuilder;
    //   259: aload_0
    //   260: invokevirtual d : ()Ljava/lang/String;
    //   263: invokevirtual append : (Ljava/lang/String;)Ljava/lang/StringBuilder;
    //   266: ldc '"><'
    //   268: invokevirtual append : (Ljava/lang/String;)Ljava/lang/StringBuilder;
    //   271: aload_0
    //   272: invokevirtual e : ()Ljava/lang/String;
    //   275: invokevirtual append : (Ljava/lang/String;)Ljava/lang/StringBuilder;
    //   278: ldc '>'
    //   280: invokevirtual append : (Ljava/lang/String;)Ljava/lang/StringBuilder;
    //   283: aload_1
    //   284: invokevirtual append : (Ljava/lang/String;)Ljava/lang/StringBuilder;
    //   287: ldc '</'
    //   289: invokevirtual append : (Ljava/lang/String;)Ljava/lang/StringBuilder;
    //   292: aload_0
    //   293: invokevirtual e : ()Ljava/lang/String;
    //   296: invokevirtual append : (Ljava/lang/String;)Ljava/lang/StringBuilder;
    //   299: ldc '></tns:'
    //   301: invokevirtual append : (Ljava/lang/String;)Ljava/lang/StringBuilder;
    //   304: aload_0
    //   305: invokevirtual g : ()Ljava/lang/String;
    //   308: invokevirtual append : (Ljava/lang/String;)Ljava/lang/StringBuilder;
    //   311: ldc '></S:Body></S:Envelope>'
    //   313: invokevirtual append : (Ljava/lang/String;)Ljava/lang/StringBuilder;
    //   316: invokevirtual toString : ()Ljava/lang/String;
    //   319: astore_1
    //   320: iload #4
    //   322: istore_3
    //   323: aload #6
    //   325: ldc 'Content-Type'
    //   327: ldc 'text/xml;charset=utf-8'
    //   329: invokevirtual addRequestProperty : (Ljava/lang/String;Ljava/lang/String;)V
    //   332: iload #4
    //   334: istore_3
    //   335: aload #6
    //   337: ldc 'Content-Length'
    //   339: aload_1
    //   340: invokevirtual length : ()I
    //   343: invokestatic valueOf : (I)Ljava/lang/String;
    //   346: invokevirtual addRequestProperty : (Ljava/lang/String;Ljava/lang/String;)V
    //   349: iload #4
    //   351: istore_3
    //   352: aload #6
    //   354: ldc 'SOAPAction'
    //   356: new java/lang/StringBuilder
    //   359: dup
    //   360: invokespecial <init> : ()V
    //   363: aload_0
    //   364: invokevirtual d : ()Ljava/lang/String;
    //   367: invokevirtual append : (Ljava/lang/String;)Ljava/lang/StringBuilder;
    //   370: aload_0
    //   371: invokevirtual g : ()Ljava/lang/String;
    //   374: invokevirtual append : (Ljava/lang/String;)Ljava/lang/StringBuilder;
    //   377: invokevirtual toString : ()Ljava/lang/String;
    //   380: invokevirtual addRequestProperty : (Ljava/lang/String;Ljava/lang/String;)V
    //   383: aload #6
    //   385: ifnull -> 544
    //   388: iload #5
    //   390: ifeq -> 800
    //   393: bipush #16
    //   395: istore_3
    //   396: aload #6
    //   398: checkcast javax/net/ssl/HttpsURLConnection
    //   401: astore #6
    //   403: bipush #17
    //   405: istore_3
    //   406: aload #6
    //   408: new r
    //   411: dup
    //   412: invokespecial <init> : ()V
    //   415: invokevirtual setHostnameVerifier : (Ljavax/net/ssl/HostnameVerifier;)V
    //   418: bipush #18
    //   420: istore_3
    //   421: aload #6
    //   423: iconst_0
    //   424: invokevirtual setAllowUserInteraction : (Z)V
    //   427: bipush #19
    //   429: istore_3
    //   430: aload #6
    //   432: iconst_1
    //   433: invokevirtual setInstanceFollowRedirects : (Z)V
    //   436: bipush #20
    //   438: istore_3
    //   439: aload #6
    //   441: ldc 'POST'
    //   443: invokevirtual setRequestMethod : (Ljava/lang/String;)V
    //   446: bipush #21
    //   448: istore #4
    //   450: iload #4
    //   452: istore_3
    //   453: aload #6
    //   455: getstatic p.o : I
    //   458: invokevirtual setConnectTimeout : (I)V
    //   461: iload #4
    //   463: istore_3
    //   464: aload #6
    //   466: getstatic p.o : I
    //   469: invokevirtual setReadTimeout : (I)V
    //   472: bipush #22
    //   474: istore_3
    //   475: aload #6
    //   477: iconst_1
    //   478: invokevirtual setDoOutput : (Z)V
    //   481: bipush #25
    //   483: istore #4
    //   485: iload #4
    //   487: istore_3
    //   488: aload #6
    //   490: invokevirtual connect : ()V
    //   493: bipush #23
    //   495: istore_3
    //   496: aload #6
    //   498: putstatic p.p : Ljava/net/HttpURLConnection;
    //   501: getstatic p.p : Ljava/net/HttpURLConnection;
    //   504: invokevirtual getOutputStream : ()Ljava/io/OutputStream;
    //   507: putstatic p.r : Ljava/io/OutputStream;
    //   510: getstatic p.r : Ljava/io/OutputStream;
    //   513: aload_1
    //   514: ldc_w 'utf-8'
    //   517: invokevirtual getBytes : (Ljava/lang/String;)[B
    //   520: invokevirtual write : ([B)V
    //   523: getstatic p.p : Ljava/net/HttpURLConnection;
    //   526: invokestatic getResponseCode : (Ljava/net/HttpURLConnection;)I
    //   529: istore_3
    //   530: iload_3
    //   531: sipush #200
    //   534: if_icmpeq -> 544
    //   537: iload_3
    //   538: sipush #200
    //   541: if_icmpne -> 1001
    //   544: bipush #50
    //   546: istore_3
    //   547: getstatic p.p : Ljava/net/HttpURLConnection;
    //   550: invokevirtual getInputStream : ()Ljava/io/InputStream;
    //   553: putstatic p.q : Ljava/io/InputStream;
    //   556: bipush #51
    //   558: istore #4
    //   560: iload #4
    //   562: istore_3
    //   563: sipush #2000
    //   566: newarray char
    //   568: astore_1
    //   569: iload #4
    //   571: istore_3
    //   572: new java/io/InputStreamReader
    //   575: dup
    //   576: getstatic p.q : Ljava/io/InputStream;
    //   579: invokespecial <init> : (Ljava/io/InputStream;)V
    //   582: astore #7
    //   584: bipush #52
    //   586: istore_3
    //   587: new java/lang/StringBuffer
    //   590: dup
    //   591: invokespecial <init> : ()V
    //   594: astore #6
    //   596: aload #7
    //   598: aload_1
    //   599: invokevirtual read : ([C)I
    //   602: istore_3
    //   603: iload_3
    //   604: ifgt -> 1031
    //   607: aconst_null
    //   608: checkcast [C
    //   611: astore_1
    //   612: bipush #53
    //   614: istore_3
    //   615: aload #6
    //   617: invokevirtual length : ()I
    //   620: ifle -> 1209
    //   623: bipush #54
    //   625: istore #4
    //   627: iload #4
    //   629: istore_3
    //   630: aload #6
    //   632: invokevirtual toString : ()Ljava/lang/String;
    //   635: astore_1
    //   636: iload #4
    //   638: istore_3
    //   639: aload_0
    //   640: invokevirtual f : ()Ljava/lang/String;
    //   643: astore_0
    //   644: iload #4
    //   646: istore_3
    //   647: aload_1
    //   648: new java/lang/StringBuilder
    //   651: dup
    //   652: ldc_w '<'
    //   655: invokespecial <init> : (Ljava/lang/String;)V
    //   658: aload_0
    //   659: invokevirtual append : (Ljava/lang/String;)Ljava/lang/StringBuilder;
    //   662: ldc '>'
    //   664: invokevirtual append : (Ljava/lang/String;)Ljava/lang/StringBuilder;
    //   667: invokevirtual toString : ()Ljava/lang/String;
    //   670: invokevirtual split : (Ljava/lang/String;)[Ljava/lang/String;
    //   673: astore_1
    //   674: aload_1
    //   675: ifnonnull -> 1090
    //   678: iload #4
    //   680: istore_3
    //   681: aload_2
    //   682: sipush #2307
    //   685: aconst_null
    //   686: invokeinterface a : (ILjava/lang/Exception;)V
    //   691: invokestatic c : ()V
    //   694: return
    //   695: astore_0
    //   696: iload #4
    //   698: istore_3
    //   699: aload_2
    //   700: sipush #2309
    //   703: aload_0
    //   704: invokeinterface a : (ILjava/lang/Exception;)V
    //   709: invokestatic c : ()V
    //   712: return
    //   713: astore_0
    //   714: iload #4
    //   716: istore_3
    //   717: aload_2
    //   718: sipush #2310
    //   721: aload_0
    //   722: invokeinterface a : (ILjava/lang/Exception;)V
    //   727: invokestatic c : ()V
    //   730: return
    //   731: astore_0
    //   732: iload #4
    //   734: istore_3
    //   735: aload_2
    //   736: sipush #2315
    //   739: aload_0
    //   740: invokeinterface a : (ILjava/lang/Exception;)V
    //   745: invokestatic c : ()V
    //   748: return
    //   749: astore_0
    //   750: iload #4
    //   752: istore_3
    //   753: aload_0
    //   754: invokevirtual getMessage : ()Ljava/lang/String;
    //   757: ldc_w 'Illegal character in authority at index'
    //   760: invokevirtual contains : (Ljava/lang/CharSequence;)Z
    //   763: ifeq -> 783
    //   766: iload #4
    //   768: istore_3
    //   769: aload_2
    //   770: sipush #2301
    //   773: aload_0
    //   774: invokeinterface a : (ILjava/lang/Exception;)V
    //   779: invokestatic c : ()V
    //   782: return
    //   783: iload #4
    //   785: istore_3
    //   786: aload_2
    //   787: sipush #2304
    //   790: aload_0
    //   791: invokeinterface a : (ILjava/lang/Exception;)V
    //   796: invokestatic c : ()V
    //   799: return
    //   800: bipush #30
    //   802: istore_3
    //   803: aload #6
    //   805: checkcast java/net/HttpURLConnection
    //   808: putstatic p.p : Ljava/net/HttpURLConnection;
    //   811: bipush #31
    //   813: istore_3
    //   814: getstatic p.p : Ljava/net/HttpURLConnection;
    //   817: iconst_0
    //   818: invokevirtual setAllowUserInteraction : (Z)V
    //   821: bipush #32
    //   823: istore_3
    //   824: getstatic p.p : Ljava/net/HttpURLConnection;
    //   827: iconst_1
    //   828: invokevirtual setInstanceFollowRedirects : (Z)V
    //   831: bipush #33
    //   833: istore_3
    //   834: getstatic p.p : Ljava/net/HttpURLConnection;
    //   837: ldc 'POST'
    //   839: invokevirtual setRequestMethod : (Ljava/lang/String;)V
    //   842: bipush #34
    //   844: istore #4
    //   846: iload #4
    //   848: istore_3
    //   849: getstatic p.p : Ljava/net/HttpURLConnection;
    //   852: getstatic p.o : I
    //   855: invokevirtual setConnectTimeout : (I)V
    //   858: iload #4
    //   860: istore_3
    //   861: getstatic p.p : Ljava/net/HttpURLConnection;
    //   864: getstatic p.o : I
    //   867: invokevirtual setReadTimeout : (I)V
    //   870: bipush #35
    //   872: istore_3
    //   873: getstatic p.p : Ljava/net/HttpURLConnection;
    //   876: iconst_1
    //   877: invokevirtual setDoOutput : (Z)V
    //   880: bipush #36
    //   882: istore #4
    //   884: iload #4
    //   886: istore_3
    //   887: getstatic p.p : Ljava/net/HttpURLConnection;
    //   890: invokestatic connect : (Ljava/net/HttpURLConnection;)V
    //   893: goto -> 501
    //   896: astore_0
    //   897: iload #4
    //   899: istore_3
    //   900: aload_2
    //   901: sipush #2309
    //   904: aload_0
    //   905: invokeinterface a : (ILjava/lang/Exception;)V
    //   910: invokestatic c : ()V
    //   913: return
    //   914: astore_0
    //   915: iload #4
    //   917: istore_3
    //   918: aload_2
    //   919: sipush #2310
    //   922: aload_0
    //   923: invokeinterface a : (ILjava/lang/Exception;)V
    //   928: invokestatic c : ()V
    //   931: return
    //   932: astore_0
    //   933: iload #4
    //   935: istore_3
    //   936: aload_2
    //   937: sipush #2315
    //   940: aload_0
    //   941: invokeinterface a : (ILjava/lang/Exception;)V
    //   946: invokestatic c : ()V
    //   949: return
    //   950: astore_0
    //   951: iload #4
    //   953: istore_3
    //   954: aload_0
    //   955: invokevirtual getMessage : ()Ljava/lang/String;
    //   958: ldc_w 'Illegal character in authority at index'
    //   961: invokevirtual contains : (Ljava/lang/CharSequence;)Z
    //   964: ifeq -> 984
    //   967: iload #4
    //   969: istore_3
    //   970: aload_2
    //   971: sipush #2301
    //   974: aload_0
    //   975: invokeinterface a : (ILjava/lang/Exception;)V
    //   980: invokestatic c : ()V
    //   983: return
    //   984: iload #4
    //   986: istore_3
    //   987: aload_2
    //   988: sipush #2304
    //   991: aload_0
    //   992: invokeinterface a : (ILjava/lang/Exception;)V
    //   997: invokestatic c : ()V
    //   1000: return
    //   1001: aload_2
    //   1002: iload_3
    //   1003: aconst_null
    //   1004: invokeinterface a : (ILjava/lang/Exception;)V
    //   1009: invokestatic c : ()V
    //   1012: return
    //   1013: astore_0
    //   1014: bipush #44
    //   1016: istore_3
    //   1017: aload_2
    //   1018: sipush #2305
    //   1021: aload_0
    //   1022: invokeinterface a : (ILjava/lang/Exception;)V
    //   1027: invokestatic c : ()V
    //   1030: return
    //   1031: aload #6
    //   1033: aload_1
    //   1034: iconst_0
    //   1035: iload_3
    //   1036: invokestatic copyValueOf : ([CII)Ljava/lang/String;
    //   1039: invokevirtual append : (Ljava/lang/String;)Ljava/lang/StringBuffer;
    //   1042: pop
    //   1043: aconst_null
    //   1044: checkcast [C
    //   1047: astore_1
    //   1048: sipush #2000
    //   1051: newarray char
    //   1053: astore_1
    //   1054: goto -> 596
    //   1057: astore_0
    //   1058: aconst_null
    //   1059: checkcast [C
    //   1062: astore_1
    //   1063: aload_0
    //   1064: athrow
    //   1065: astore_0
    //   1066: bipush #52
    //   1068: istore_3
    //   1069: aload_0
    //   1070: invokevirtual printStackTrace : ()V
    //   1073: bipush #55
    //   1075: istore_3
    //   1076: aload_2
    //   1077: sipush #2308
    //   1080: aload_0
    //   1081: invokeinterface a : (ILjava/lang/Exception;)V
    //   1086: invokestatic c : ()V
    //   1089: return
    //   1090: iload #4
    //   1092: istore_3
    //   1093: aload_1
    //   1094: arraylength
    //   1095: iconst_2
    //   1096: if_icmpge -> 1116
    //   1099: iload #4
    //   1101: istore_3
    //   1102: aload_2
    //   1103: sipush #2307
    //   1106: aconst_null
    //   1107: invokeinterface a : (ILjava/lang/Exception;)V
    //   1112: invokestatic c : ()V
    //   1115: return
    //   1116: iload #4
    //   1118: istore_3
    //   1119: aload_1
    //   1120: iconst_1
    //   1121: aaload
    //   1122: new java/lang/StringBuilder
    //   1125: dup
    //   1126: ldc '</'
    //   1128: invokespecial <init> : (Ljava/lang/String;)V
    //   1131: aload_0
    //   1132: invokevirtual append : (Ljava/lang/String;)Ljava/lang/StringBuilder;
    //   1135: ldc '>'
    //   1137: invokevirtual append : (Ljava/lang/String;)Ljava/lang/StringBuilder;
    //   1140: invokevirtual toString : ()Ljava/lang/String;
    //   1143: invokevirtual split : (Ljava/lang/String;)[Ljava/lang/String;
    //   1146: astore_0
    //   1147: aload_0
    //   1148: ifnonnull -> 1168
    //   1151: iload #4
    //   1153: istore_3
    //   1154: aload_2
    //   1155: sipush #2307
    //   1158: aconst_null
    //   1159: invokeinterface a : (ILjava/lang/Exception;)V
    //   1164: invokestatic c : ()V
    //   1167: return
    //   1168: iload #4
    //   1170: istore_3
    //   1171: aload_0
    //   1172: arraylength
    //   1173: ifne -> 1193
    //   1176: iload #4
    //   1178: istore_3
    //   1179: aload_2
    //   1180: sipush #2307
    //   1183: aconst_null
    //   1184: invokeinterface a : (ILjava/lang/Exception;)V
    //   1189: invokestatic c : ()V
    //   1192: return
    //   1193: iload #4
    //   1195: istore_3
    //   1196: aload_2
    //   1197: aload_0
    //   1198: iconst_0
    //   1199: aaload
    //   1200: invokeinterface a : (Ljava/lang/String;)V
    //   1205: invokestatic c : ()V
    //   1208: return
    //   1209: bipush #55
    //   1211: istore_3
    //   1212: aload_2
    //   1213: sipush #2307
    //   1216: aconst_null
    //   1217: invokeinterface a : (ILjava/lang/Exception;)V
    //   1222: invokestatic c : ()V
    //   1225: return
    //   1226: astore_0
    //   1227: aload_2
    //   1228: iload_3
    //   1229: aload_0
    //   1230: invokeinterface a : (ILjava/lang/Exception;)V
    //   1235: invokestatic c : ()V
    //   1238: return
    //   1239: astore_0
    //   1240: invokestatic c : ()V
    //   1243: aload_0
    //   1244: athrow
    //   1245: astore #7
    //   1247: goto -> 152
    //   1250: astore #7
    //   1252: goto -> 152
    //   1255: astore_0
    //   1256: goto -> 1069
    //   1259: astore_1
    //   1260: goto -> 523
    // Exception table:
    //   from	to	target	type
    //   52	63	78	java/net/MalformedURLException
    //   52	63	1226	java/lang/Exception
    //   52	63	1239	finally
    //   70	78	78	java/net/MalformedURLException
    //   70	78	1226	java/lang/Exception
    //   70	78	1239	finally
    //   81	91	1226	java/lang/Exception
    //   81	91	1239	finally
    //   123	138	1226	java/lang/Exception
    //   123	138	1239	finally
    //   143	146	1245	java/lang/Exception
    //   143	146	1239	finally
    //   146	152	1250	java/lang/Exception
    //   146	152	1239	finally
    //   155	162	184	java/io/IOException
    //   155	162	1226	java/lang/Exception
    //   155	162	1239	finally
    //   170	180	1226	java/lang/Exception
    //   170	180	1239	finally
    //   199	207	1226	java/lang/Exception
    //   199	207	1239	finally
    //   210	218	1226	java/lang/Exception
    //   210	218	1239	finally
    //   221	231	1226	java/lang/Exception
    //   221	231	1239	finally
    //   238	320	1226	java/lang/Exception
    //   238	320	1239	finally
    //   323	332	1226	java/lang/Exception
    //   323	332	1239	finally
    //   335	349	1226	java/lang/Exception
    //   335	349	1239	finally
    //   352	383	1226	java/lang/Exception
    //   352	383	1239	finally
    //   396	403	1226	java/lang/Exception
    //   396	403	1239	finally
    //   406	418	1226	java/lang/Exception
    //   406	418	1239	finally
    //   421	427	1226	java/lang/Exception
    //   421	427	1239	finally
    //   430	436	1226	java/lang/Exception
    //   430	436	1239	finally
    //   439	446	1226	java/lang/Exception
    //   439	446	1239	finally
    //   453	461	1226	java/lang/Exception
    //   453	461	1239	finally
    //   464	472	1226	java/lang/Exception
    //   464	472	1239	finally
    //   475	481	1226	java/lang/Exception
    //   475	481	1239	finally
    //   488	493	695	java/lang/SecurityException
    //   488	493	713	java/net/SocketTimeoutException
    //   488	493	731	java/net/UnknownHostException
    //   488	493	749	java/io/IOException
    //   488	493	1226	java/lang/Exception
    //   488	493	1239	finally
    //   496	501	1226	java/lang/Exception
    //   496	501	1239	finally
    //   501	523	1259	java/lang/Exception
    //   501	523	1239	finally
    //   523	530	1013	java/lang/Exception
    //   523	530	1239	finally
    //   547	556	1255	java/lang/Exception
    //   547	556	1239	finally
    //   563	569	1255	java/lang/Exception
    //   563	569	1239	finally
    //   572	584	1255	java/lang/Exception
    //   572	584	1239	finally
    //   587	596	1255	java/lang/Exception
    //   587	596	1239	finally
    //   596	603	1057	finally
    //   607	612	1065	java/lang/Exception
    //   607	612	1239	finally
    //   615	623	1255	java/lang/Exception
    //   615	623	1239	finally
    //   630	636	1255	java/lang/Exception
    //   630	636	1239	finally
    //   639	644	1255	java/lang/Exception
    //   639	644	1239	finally
    //   647	674	1255	java/lang/Exception
    //   647	674	1239	finally
    //   681	691	1255	java/lang/Exception
    //   681	691	1239	finally
    //   699	709	1226	java/lang/Exception
    //   699	709	1239	finally
    //   717	727	1226	java/lang/Exception
    //   717	727	1239	finally
    //   735	745	1226	java/lang/Exception
    //   735	745	1239	finally
    //   753	766	1226	java/lang/Exception
    //   753	766	1239	finally
    //   769	779	1226	java/lang/Exception
    //   769	779	1239	finally
    //   786	796	1226	java/lang/Exception
    //   786	796	1239	finally
    //   803	811	1226	java/lang/Exception
    //   803	811	1239	finally
    //   814	821	1226	java/lang/Exception
    //   814	821	1239	finally
    //   824	831	1226	java/lang/Exception
    //   824	831	1239	finally
    //   834	842	1226	java/lang/Exception
    //   834	842	1239	finally
    //   849	858	1226	java/lang/Exception
    //   849	858	1239	finally
    //   861	870	1226	java/lang/Exception
    //   861	870	1239	finally
    //   873	880	1226	java/lang/Exception
    //   873	880	1239	finally
    //   887	893	896	java/lang/SecurityException
    //   887	893	914	java/net/SocketTimeoutException
    //   887	893	932	java/net/UnknownHostException
    //   887	893	950	java/io/IOException
    //   887	893	1226	java/lang/Exception
    //   887	893	1239	finally
    //   900	910	1226	java/lang/Exception
    //   900	910	1239	finally
    //   918	928	1226	java/lang/Exception
    //   918	928	1239	finally
    //   936	946	1226	java/lang/Exception
    //   936	946	1239	finally
    //   954	967	1226	java/lang/Exception
    //   954	967	1239	finally
    //   970	980	1226	java/lang/Exception
    //   970	980	1239	finally
    //   987	997	1226	java/lang/Exception
    //   987	997	1239	finally
    //   1001	1009	1013	java/lang/Exception
    //   1001	1009	1239	finally
    //   1017	1027	1226	java/lang/Exception
    //   1017	1027	1239	finally
    //   1031	1054	1057	finally
    //   1058	1065	1065	java/lang/Exception
    //   1058	1065	1239	finally
    //   1069	1073	1226	java/lang/Exception
    //   1069	1073	1239	finally
    //   1076	1086	1226	java/lang/Exception
    //   1076	1086	1239	finally
    //   1093	1099	1255	java/lang/Exception
    //   1093	1099	1239	finally
    //   1102	1112	1255	java/lang/Exception
    //   1102	1112	1239	finally
    //   1119	1147	1255	java/lang/Exception
    //   1119	1147	1239	finally
    //   1154	1164	1255	java/lang/Exception
    //   1154	1164	1239	finally
    //   1171	1176	1255	java/lang/Exception
    //   1171	1176	1239	finally
    //   1179	1189	1255	java/lang/Exception
    //   1179	1189	1239	finally
    //   1196	1205	1255	java/lang/Exception
    //   1196	1205	1239	finally
    //   1212	1222	1255	java/lang/Exception
    //   1212	1222	1239	finally
    //   1227	1235	1239	finally
  }
  
  private static boolean b() {
    return false;
  }
  
  private static void c() {
    synchronized (new p()) {
      TimerTask timerTask = t;
      if (timerTask != null)
        try {
          t.cancel();
        } catch (Exception exception) {} 
      Timer timer = s;
      if (timer != null)
        try {
          s.cancel();
        } catch (Exception exception) {} 
      OutputStream outputStream = r;
      if (outputStream != null) {
        try {
          r.close();
        } catch (Exception exception) {}
        r = null;
      } 
      InputStream inputStream = q;
      if (inputStream != null) {
        try {
          q.close();
        } catch (Exception exception) {}
        q = null;
      } 
      d();
      return;
    } 
  }
  
  private static void d() {
    if (p != null) {
      try {
        p.disconnect();
      } catch (Exception exception) {}
    } else {
      return;
    } 
    p = null;
  }
}


/* Location:              C:\Users\devid\Downloads\SAST\Santander\dex2jar-2.0\classes2-dex2jar.jar!\p.class
 * Java compiler version: 6 (50.0)
 * JD-Core Version:       1.1.3
 */