public class ak implements x {
  public static final int H = 1;
  
  private static final int I = 19;
  
  private static final int J = 11;
  
  private static final int K = 1;
  
  private int L = 1;
  
  private int M = 0;
  
  private String N = "";
  
  private String O = "";
  
  private int P = 0;
  
  private String Q = "";
  
  private String R = "";
  
  private String S = "";
  
  private String T = "";
  
  private String U = "";
  
  private String V = "";
  
  private int W = 0;
  
  private int X = 0;
  
  private int Y = 0;
  
  private int Z = 0;
  
  private int aa = 0;
  
  private int ab = 0;
  
  private int ac = 0;
  
  private String ad = "";
  
  private String ae = "";
  
  private String af = "";
  
  private int ag = 0;
  
  private int ah = 0;
  
  private int ai = 1;
  
  private int aj = 1;
  
  private int ak = 0;
  
  private int al = 0;
  
  private int am = 0;
  
  private int an = 0;
  
  private int ao = 1;
  
  private int ap = 1;
  
  private int aq = 1;
  
  private int ar = 1;
  
  private int as = 1;
  
  private int at = 1;
  
  private String au = "";
  
  private int av = 1;
  
  private String aw = "";
  
  private String ax = "";
  
  public ak() {
    this.L = 1;
    this.ad = "";
    this.ag = 0;
    this.ah = 0;
    this.M = 0;
    this.S = "";
    this.T = "";
    this.U = "";
    this.O = "";
    this.W = 0;
    this.Y = 0;
    this.X = 0;
    this.Z = 0;
    this.aa = 0;
    this.ab = 0;
    this.ac = 0;
    this.ai = 1;
    this.aj = 1;
    this.ak = 1;
    this.al = 1;
    this.am = 1;
    this.an = 1;
    this.ao = 1;
    this.ap = 1;
    this.ar = 1;
    this.as = 1;
    this.aq = 1;
    this.P = 0;
    this.at = 1;
    this.av = 1;
    this.au = "";
    this.aw = "";
    this.af = "";
    this.ae = "";
    l("");
  }
  
  private static String P() {
    return "#";
  }
  
  public static int a(ak paramak, bl parambl, StringBuffer paramStringBuffer) {
    // Byte code:
    //   0: new java/lang/StringBuilder
    //   3: dup
    //   4: invokespecial <init> : ()V
    //   7: astore #4
    //   9: invokestatic P : ()Ljava/lang/String;
    //   12: astore #5
    //   14: new java/util/Random
    //   17: dup
    //   18: invokestatic currentTimeMillis : ()J
    //   21: invokespecial <init> : (J)V
    //   24: ldc 1000000
    //   26: invokevirtual nextInt : (I)I
    //   29: istore_3
    //   30: aload #4
    //   32: iload_3
    //   33: invokevirtual append : (I)Ljava/lang/StringBuilder;
    //   36: pop
    //   37: aload #4
    //   39: aload #5
    //   41: invokevirtual append : (Ljava/lang/String;)Ljava/lang/StringBuilder;
    //   44: pop
    //   45: aload #4
    //   47: aload_0
    //   48: invokevirtual f : ()I
    //   51: invokevirtual append : (I)Ljava/lang/StringBuilder;
    //   54: pop
    //   55: aload #4
    //   57: aload #5
    //   59: invokevirtual append : (Ljava/lang/String;)Ljava/lang/StringBuilder;
    //   62: pop
    //   63: aload #4
    //   65: aload_0
    //   66: invokevirtual K : ()I
    //   69: invokevirtual append : (I)Ljava/lang/StringBuilder;
    //   72: pop
    //   73: aload #4
    //   75: aload #5
    //   77: invokevirtual append : (Ljava/lang/String;)Ljava/lang/StringBuilder;
    //   80: pop
    //   81: aload #4
    //   83: aload_0
    //   84: invokevirtual u : ()Ljava/lang/String;
    //   87: invokevirtual append : (Ljava/lang/String;)Ljava/lang/StringBuilder;
    //   90: pop
    //   91: aload #4
    //   93: aload #5
    //   95: invokevirtual append : (Ljava/lang/String;)Ljava/lang/StringBuilder;
    //   98: pop
    //   99: aload #4
    //   101: aload_0
    //   102: invokevirtual v : ()I
    //   105: invokevirtual append : (I)Ljava/lang/StringBuilder;
    //   108: pop
    //   109: aload #4
    //   111: aload #5
    //   113: invokevirtual append : (Ljava/lang/String;)Ljava/lang/StringBuilder;
    //   116: pop
    //   117: aload #4
    //   119: aload_0
    //   120: invokevirtual w : ()I
    //   123: invokevirtual append : (I)Ljava/lang/StringBuilder;
    //   126: pop
    //   127: aload #4
    //   129: aload #5
    //   131: invokevirtual append : (Ljava/lang/String;)Ljava/lang/StringBuilder;
    //   134: pop
    //   135: aload #4
    //   137: aload_0
    //   138: invokevirtual L : ()I
    //   141: invokevirtual append : (I)Ljava/lang/StringBuilder;
    //   144: pop
    //   145: aload #4
    //   147: aload #5
    //   149: invokevirtual append : (Ljava/lang/String;)Ljava/lang/StringBuilder;
    //   152: pop
    //   153: aload #4
    //   155: aload_0
    //   156: invokevirtual M : ()Ljava/lang/String;
    //   159: invokevirtual append : (Ljava/lang/String;)Ljava/lang/StringBuilder;
    //   162: pop
    //   163: aload #4
    //   165: aload #5
    //   167: invokevirtual append : (Ljava/lang/String;)Ljava/lang/StringBuilder;
    //   170: pop
    //   171: aload #4
    //   173: aload_0
    //   174: invokevirtual N : ()Ljava/lang/String;
    //   177: invokevirtual append : (Ljava/lang/String;)Ljava/lang/StringBuilder;
    //   180: pop
    //   181: aload #4
    //   183: aload #5
    //   185: invokevirtual append : (Ljava/lang/String;)Ljava/lang/StringBuilder;
    //   188: pop
    //   189: aload #4
    //   191: aload_0
    //   192: invokevirtual h : ()Ljava/lang/String;
    //   195: invokevirtual append : (Ljava/lang/String;)Ljava/lang/StringBuilder;
    //   198: pop
    //   199: aload #4
    //   201: aload #5
    //   203: invokevirtual append : (Ljava/lang/String;)Ljava/lang/StringBuilder;
    //   206: pop
    //   207: aload #4
    //   209: aload_0
    //   210: invokevirtual i : ()I
    //   213: invokevirtual append : (I)Ljava/lang/StringBuilder;
    //   216: pop
    //   217: aload #4
    //   219: aload #5
    //   221: invokevirtual append : (Ljava/lang/String;)Ljava/lang/StringBuilder;
    //   224: pop
    //   225: aload #4
    //   227: aload_0
    //   228: invokevirtual l : ()Ljava/lang/String;
    //   231: invokevirtual append : (Ljava/lang/String;)Ljava/lang/StringBuilder;
    //   234: pop
    //   235: aload #4
    //   237: aload #5
    //   239: invokevirtual append : (Ljava/lang/String;)Ljava/lang/StringBuilder;
    //   242: pop
    //   243: aload #4
    //   245: aload_0
    //   246: invokevirtual j : ()Ljava/lang/String;
    //   249: invokevirtual append : (Ljava/lang/String;)Ljava/lang/StringBuilder;
    //   252: pop
    //   253: aload #4
    //   255: aload #5
    //   257: invokevirtual append : (Ljava/lang/String;)Ljava/lang/StringBuilder;
    //   260: pop
    //   261: aload #4
    //   263: aload_0
    //   264: invokevirtual k : ()Ljava/lang/String;
    //   267: invokevirtual append : (Ljava/lang/String;)Ljava/lang/StringBuilder;
    //   270: pop
    //   271: aload #4
    //   273: aload #5
    //   275: invokevirtual append : (Ljava/lang/String;)Ljava/lang/StringBuilder;
    //   278: pop
    //   279: aload #4
    //   281: aload_0
    //   282: invokevirtual m : ()Ljava/lang/String;
    //   285: invokevirtual append : (Ljava/lang/String;)Ljava/lang/StringBuilder;
    //   288: pop
    //   289: aload #4
    //   291: aload #5
    //   293: invokevirtual append : (Ljava/lang/String;)Ljava/lang/StringBuilder;
    //   296: pop
    //   297: aload #4
    //   299: aload_0
    //   300: invokevirtual o : ()I
    //   303: invokevirtual append : (I)Ljava/lang/StringBuilder;
    //   306: pop
    //   307: aload #4
    //   309: aload #5
    //   311: invokevirtual append : (Ljava/lang/String;)Ljava/lang/StringBuilder;
    //   314: pop
    //   315: aload_0
    //   316: invokevirtual g : ()Ljava/lang/String;
    //   319: astore #6
    //   321: aload #6
    //   323: invokevirtual length : ()I
    //   326: ifle -> 343
    //   329: aload #4
    //   331: aload #6
    //   333: invokevirtual getBytes : ()[B
    //   336: invokestatic b : ([B)Ljava/lang/String;
    //   339: invokevirtual append : (Ljava/lang/String;)Ljava/lang/StringBuilder;
    //   342: pop
    //   343: aload #4
    //   345: aload #5
    //   347: invokevirtual append : (Ljava/lang/String;)Ljava/lang/StringBuilder;
    //   350: pop
    //   351: aload #4
    //   353: aload_0
    //   354: invokevirtual t : ()I
    //   357: invokevirtual append : (I)Ljava/lang/StringBuilder;
    //   360: pop
    //   361: aload #4
    //   363: aload #5
    //   365: invokevirtual append : (Ljava/lang/String;)Ljava/lang/StringBuilder;
    //   368: pop
    //   369: aload_0
    //   370: invokevirtual J : ()Ljava/lang/String;
    //   373: astore #6
    //   375: aload #6
    //   377: invokevirtual length : ()I
    //   380: ifle -> 397
    //   383: aload #4
    //   385: aload #6
    //   387: invokevirtual getBytes : ()[B
    //   390: invokestatic b : ([B)Ljava/lang/String;
    //   393: invokevirtual append : (Ljava/lang/String;)Ljava/lang/StringBuilder;
    //   396: pop
    //   397: aload #4
    //   399: aload #5
    //   401: invokevirtual append : (Ljava/lang/String;)Ljava/lang/StringBuilder;
    //   404: pop
    //   405: aload_0
    //   406: invokevirtual H : ()Ljava/lang/String;
    //   409: astore #6
    //   411: aload #6
    //   413: invokevirtual length : ()I
    //   416: ifle -> 433
    //   419: aload #4
    //   421: aload #6
    //   423: invokevirtual getBytes : ()[B
    //   426: invokestatic b : ([B)Ljava/lang/String;
    //   429: invokevirtual append : (Ljava/lang/String;)Ljava/lang/StringBuilder;
    //   432: pop
    //   433: aload #4
    //   435: aload #5
    //   437: invokevirtual append : (Ljava/lang/String;)Ljava/lang/StringBuilder;
    //   440: pop
    //   441: aload_0
    //   442: invokevirtual I : ()Ljava/lang/String;
    //   445: astore_0
    //   446: aload_0
    //   447: invokevirtual length : ()I
    //   450: ifle -> 466
    //   453: aload #4
    //   455: aload_0
    //   456: invokevirtual getBytes : ()[B
    //   459: invokestatic b : ([B)Ljava/lang/String;
    //   462: invokevirtual append : (Ljava/lang/String;)Ljava/lang/StringBuilder;
    //   465: pop
    //   466: aload_1
    //   467: aload #4
    //   469: invokevirtual toString : ()Ljava/lang/String;
    //   472: invokeinterface a : (Ljava/lang/String;)Ljava/lang/String;
    //   477: astore_0
    //   478: aload_0
    //   479: aload_1
    //   480: new ak
    //   483: dup
    //   484: invokespecial <init> : ()V
    //   487: invokestatic a : (Ljava/lang/String;Lbl;Lak;)I
    //   490: ifeq -> 511
    //   493: sipush #1317
    //   496: ireturn
    //   497: astore #6
    //   499: invokestatic currentTimeMillis : ()J
    //   502: l2i
    //   503: ldc_w 1234567
    //   506: idiv
    //   507: istore_3
    //   508: goto -> 30
    //   511: aload_2
    //   512: aload_0
    //   513: invokevirtual append : (Ljava/lang/String;)Ljava/lang/StringBuffer;
    //   516: pop
    //   517: iconst_0
    //   518: ireturn
    //   519: astore_0
    //   520: sipush #1300
    //   523: ireturn
    // Exception table:
    //   from	to	target	type
    //   9	14	519	java/lang/Exception
    //   14	30	497	java/lang/Exception
    //   30	343	519	java/lang/Exception
    //   343	397	519	java/lang/Exception
    //   397	433	519	java/lang/Exception
    //   433	466	519	java/lang/Exception
    //   466	493	519	java/lang/Exception
    //   499	508	519	java/lang/Exception
    //   511	517	519	java/lang/Exception
  }
  
  public static int a(String paramString, bl parambl, ak paramak) {
    // Byte code:
    //   0: aload_0
    //   1: ifnonnull -> 8
    //   4: sipush #1310
    //   7: ireturn
    //   8: invokestatic P : ()Ljava/lang/String;
    //   11: astore_3
    //   12: aload_1
    //   13: aload_0
    //   14: invokeinterface b : (Ljava/lang/String;)Ljava/lang/String;
    //   19: aload_3
    //   20: invokestatic a : (Ljava/lang/String;Ljava/lang/String;)Ljava/util/Vector;
    //   23: astore_0
    //   24: aload_2
    //   25: aload_0
    //   26: iconst_1
    //   27: invokevirtual elementAt : (I)Ljava/lang/Object;
    //   30: checkcast java/lang/String
    //   33: invokestatic parseInt : (Ljava/lang/String;)I
    //   36: invokespecial z : (I)V
    //   39: aload_0
    //   40: iconst_2
    //   41: invokevirtual elementAt : (I)Ljava/lang/Object;
    //   44: checkcast java/lang/String
    //   47: invokestatic parseInt : (Ljava/lang/String;)I
    //   50: iconst_1
    //   51: if_icmpne -> 839
    //   54: aload_0
    //   55: invokevirtual size : ()I
    //   58: bipush #19
    //   60: if_icmpge -> 67
    //   63: sipush #1310
    //   66: ireturn
    //   67: aload_2
    //   68: aload_0
    //   69: iconst_3
    //   70: invokevirtual elementAt : (I)Ljava/lang/Object;
    //   73: checkcast java/lang/String
    //   76: invokevirtual g : (Ljava/lang/String;)V
    //   79: aload_2
    //   80: aload_0
    //   81: iconst_4
    //   82: invokevirtual elementAt : (I)Ljava/lang/Object;
    //   85: checkcast java/lang/String
    //   88: invokestatic parseInt : (Ljava/lang/String;)I
    //   91: invokevirtual i : (I)V
    //   94: aload_2
    //   95: aload_0
    //   96: iconst_5
    //   97: invokevirtual elementAt : (I)Ljava/lang/Object;
    //   100: checkcast java/lang/String
    //   103: invokestatic parseInt : (Ljava/lang/String;)I
    //   106: invokevirtual j : (I)V
    //   109: aload_2
    //   110: aload_0
    //   111: bipush #6
    //   113: invokevirtual elementAt : (I)Ljava/lang/Object;
    //   116: checkcast java/lang/String
    //   119: invokestatic parseInt : (Ljava/lang/String;)I
    //   122: invokevirtual x : (I)V
    //   125: aload_2
    //   126: aload_0
    //   127: bipush #7
    //   129: invokevirtual elementAt : (I)Ljava/lang/Object;
    //   132: checkcast java/lang/String
    //   135: invokevirtual m : (Ljava/lang/String;)V
    //   138: aload_2
    //   139: aload_0
    //   140: bipush #8
    //   142: invokevirtual elementAt : (I)Ljava/lang/Object;
    //   145: checkcast java/lang/String
    //   148: invokevirtual n : (Ljava/lang/String;)V
    //   151: aload_2
    //   152: aload_0
    //   153: bipush #9
    //   155: invokevirtual elementAt : (I)Ljava/lang/Object;
    //   158: checkcast java/lang/String
    //   161: invokevirtual b : (Ljava/lang/String;)V
    //   164: aload_2
    //   165: aload_0
    //   166: bipush #10
    //   168: invokevirtual elementAt : (I)Ljava/lang/Object;
    //   171: checkcast java/lang/String
    //   174: invokestatic parseInt : (Ljava/lang/String;)I
    //   177: invokevirtual a : (I)V
    //   180: aload_2
    //   181: aload_0
    //   182: bipush #11
    //   184: invokevirtual elementAt : (I)Ljava/lang/Object;
    //   187: checkcast java/lang/String
    //   190: invokevirtual e : (Ljava/lang/String;)V
    //   193: aload_2
    //   194: aload_0
    //   195: bipush #12
    //   197: invokevirtual elementAt : (I)Ljava/lang/Object;
    //   200: checkcast java/lang/String
    //   203: invokevirtual c : (Ljava/lang/String;)V
    //   206: aload_2
    //   207: aload_0
    //   208: bipush #13
    //   210: invokevirtual elementAt : (I)Ljava/lang/Object;
    //   213: checkcast java/lang/String
    //   216: invokevirtual d : (Ljava/lang/String;)V
    //   219: aload_2
    //   220: aload_0
    //   221: bipush #14
    //   223: invokevirtual elementAt : (I)Ljava/lang/Object;
    //   226: checkcast java/lang/String
    //   229: invokevirtual f : (Ljava/lang/String;)V
    //   232: aload_2
    //   233: aload_0
    //   234: bipush #15
    //   236: invokevirtual elementAt : (I)Ljava/lang/Object;
    //   239: checkcast java/lang/String
    //   242: invokestatic parseInt : (Ljava/lang/String;)I
    //   245: invokevirtual c : (I)V
    //   248: aload_0
    //   249: bipush #16
    //   251: invokevirtual elementAt : (I)Ljava/lang/Object;
    //   254: checkcast java/lang/String
    //   257: astore #4
    //   259: aload #4
    //   261: invokevirtual length : ()I
    //   264: ifle -> 279
    //   267: aload_2
    //   268: aload #4
    //   270: invokevirtual getBytes : ()[B
    //   273: invokestatic d : ([B)Ljava/lang/String;
    //   276: invokevirtual a : (Ljava/lang/String;)V
    //   279: aload_2
    //   280: aload_0
    //   281: bipush #17
    //   283: invokevirtual elementAt : (I)Ljava/lang/Object;
    //   286: checkcast java/lang/String
    //   289: invokestatic parseInt : (Ljava/lang/String;)I
    //   292: invokevirtual h : (I)V
    //   295: aload_0
    //   296: bipush #18
    //   298: invokevirtual elementAt : (I)Ljava/lang/Object;
    //   301: checkcast java/lang/String
    //   304: astore #4
    //   306: aload #4
    //   308: invokevirtual length : ()I
    //   311: ifle -> 326
    //   314: aload_2
    //   315: aload #4
    //   317: invokevirtual getBytes : ()[B
    //   320: invokestatic d : ([B)Ljava/lang/String;
    //   323: invokevirtual l : (Ljava/lang/String;)V
    //   326: aload_0
    //   327: bipush #19
    //   329: invokevirtual elementAt : (I)Ljava/lang/Object;
    //   332: checkcast java/lang/String
    //   335: astore #4
    //   337: aload #4
    //   339: invokevirtual length : ()I
    //   342: ifle -> 357
    //   345: aload_2
    //   346: aload #4
    //   348: invokevirtual getBytes : ()[B
    //   351: invokestatic d : ([B)Ljava/lang/String;
    //   354: invokevirtual j : (Ljava/lang/String;)V
    //   357: aload_0
    //   358: bipush #20
    //   360: invokevirtual elementAt : (I)Ljava/lang/Object;
    //   363: checkcast java/lang/String
    //   366: astore_0
    //   367: aload_0
    //   368: invokevirtual length : ()I
    //   371: ifle -> 385
    //   374: aload_2
    //   375: aload_0
    //   376: invokevirtual getBytes : ()[B
    //   379: invokestatic d : ([B)Ljava/lang/String;
    //   382: invokevirtual k : (Ljava/lang/String;)V
    //   385: aload_2
    //   386: invokevirtual L : ()I
    //   389: ifeq -> 843
    //   392: aload_2
    //   393: invokevirtual M : ()Ljava/lang/String;
    //   396: invokevirtual length : ()I
    //   399: bipush #40
    //   401: if_icmpeq -> 429
    //   404: sipush #1310
    //   407: ireturn
    //   408: astore #4
    //   410: aload_2
    //   411: ldc ''
    //   413: invokevirtual j : (Ljava/lang/String;)V
    //   416: goto -> 357
    //   419: astore_0
    //   420: aload_2
    //   421: ldc ''
    //   423: invokevirtual k : (Ljava/lang/String;)V
    //   426: goto -> 385
    //   429: aload_2
    //   430: invokevirtual N : ()Ljava/lang/String;
    //   433: invokevirtual length : ()I
    //   436: iconst_2
    //   437: if_icmple -> 843
    //   440: aload_1
    //   441: aload_2
    //   442: invokevirtual N : ()Ljava/lang/String;
    //   445: invokeinterface d : (Ljava/lang/String;)Ljava/lang/String;
    //   450: aload_3
    //   451: invokestatic a : (Ljava/lang/String;Ljava/lang/String;)Ljava/util/Vector;
    //   454: astore_0
    //   455: aload_0
    //   456: invokevirtual size : ()I
    //   459: bipush #11
    //   461: if_icmpge -> 468
    //   464: sipush #1310
    //   467: ireturn
    //   468: aload_2
    //   469: aload_0
    //   470: iconst_0
    //   471: invokevirtual elementAt : (I)Ljava/lang/Object;
    //   474: checkcast java/lang/String
    //   477: invokestatic parseInt : (Ljava/lang/String;)I
    //   480: invokevirtual b : (I)V
    //   483: aload_2
    //   484: invokevirtual n : ()I
    //   487: ifne -> 703
    //   490: aload_2
    //   491: iconst_2
    //   492: invokevirtual e : (I)V
    //   495: aload_2
    //   496: aload_0
    //   497: iconst_1
    //   498: invokevirtual elementAt : (I)Ljava/lang/Object;
    //   501: checkcast java/lang/String
    //   504: invokestatic parseInt : (Ljava/lang/String;)I
    //   507: invokevirtual d : (I)V
    //   510: aload_2
    //   511: aload_0
    //   512: iconst_2
    //   513: invokevirtual elementAt : (I)Ljava/lang/Object;
    //   516: checkcast java/lang/String
    //   519: invokestatic parseInt : (Ljava/lang/String;)I
    //   522: invokevirtual q : (I)V
    //   525: aload_2
    //   526: aload_0
    //   527: iconst_3
    //   528: invokevirtual elementAt : (I)Ljava/lang/Object;
    //   531: checkcast java/lang/String
    //   534: invokestatic parseInt : (Ljava/lang/String;)I
    //   537: invokevirtual k : (I)V
    //   540: aload_2
    //   541: aload_0
    //   542: iconst_4
    //   543: invokevirtual elementAt : (I)Ljava/lang/Object;
    //   546: checkcast java/lang/String
    //   549: invokestatic parseInt : (Ljava/lang/String;)I
    //   552: invokevirtual l : (I)V
    //   555: aload_2
    //   556: aload_0
    //   557: iconst_5
    //   558: invokevirtual elementAt : (I)Ljava/lang/Object;
    //   561: checkcast java/lang/String
    //   564: invokestatic parseInt : (Ljava/lang/String;)I
    //   567: invokevirtual r : (I)V
    //   570: aload_2
    //   571: aload_0
    //   572: bipush #6
    //   574: invokevirtual elementAt : (I)Ljava/lang/Object;
    //   577: checkcast java/lang/String
    //   580: invokestatic parseInt : (Ljava/lang/String;)I
    //   583: invokevirtual n : (I)V
    //   586: aload_2
    //   587: aload_0
    //   588: bipush #7
    //   590: invokevirtual elementAt : (I)Ljava/lang/Object;
    //   593: checkcast java/lang/String
    //   596: invokestatic parseInt : (Ljava/lang/String;)I
    //   599: invokevirtual m : (I)V
    //   602: aload_2
    //   603: aload_0
    //   604: bipush #8
    //   606: invokevirtual elementAt : (I)Ljava/lang/Object;
    //   609: checkcast java/lang/String
    //   612: invokestatic parseInt : (Ljava/lang/String;)I
    //   615: invokevirtual s : (I)V
    //   618: aload_2
    //   619: aload_0
    //   620: bipush #9
    //   622: invokevirtual elementAt : (I)Ljava/lang/Object;
    //   625: checkcast java/lang/String
    //   628: invokevirtual i : (Ljava/lang/String;)V
    //   631: aload_0
    //   632: invokevirtual size : ()I
    //   635: bipush #17
    //   637: if_icmpge -> 726
    //   640: aload_2
    //   641: iconst_1
    //   642: invokevirtual r : (I)V
    //   645: aload_2
    //   646: iconst_1
    //   647: invokevirtual u : (I)V
    //   650: aload_2
    //   651: aload_2
    //   652: invokevirtual A : ()I
    //   655: invokevirtual p : (I)V
    //   658: aload_2
    //   659: aload_2
    //   660: invokevirtual z : ()I
    //   663: invokevirtual o : (I)V
    //   666: aload_2
    //   667: iconst_1
    //   668: invokevirtual v : (I)V
    //   671: aload_2
    //   672: ldc_w 'MQ=='
    //   675: invokevirtual h : (Ljava/lang/String;)V
    //   678: aload_2
    //   679: iconst_1
    //   680: invokevirtual s : (I)V
    //   683: aload_2
    //   684: ldc_w 'MQ=='
    //   687: invokevirtual i : (Ljava/lang/String;)V
    //   690: aload_2
    //   691: iconst_0
    //   692: invokevirtual f : (I)V
    //   695: aload_2
    //   696: iconst_0
    //   697: invokevirtual g : (I)V
    //   700: goto -> 843
    //   703: aload_2
    //   704: invokevirtual n : ()I
    //   707: ifle -> 718
    //   710: aload_2
    //   711: iconst_1
    //   712: invokevirtual e : (I)V
    //   715: goto -> 495
    //   718: aload_2
    //   719: iconst_0
    //   720: invokevirtual e : (I)V
    //   723: goto -> 495
    //   726: aload_2
    //   727: aload_0
    //   728: bipush #10
    //   730: invokevirtual elementAt : (I)Ljava/lang/Object;
    //   733: checkcast java/lang/String
    //   736: invokestatic parseInt : (Ljava/lang/String;)I
    //   739: invokevirtual u : (I)V
    //   742: aload_2
    //   743: aload_0
    //   744: bipush #11
    //   746: invokevirtual elementAt : (I)Ljava/lang/Object;
    //   749: checkcast java/lang/String
    //   752: invokestatic parseInt : (Ljava/lang/String;)I
    //   755: invokevirtual p : (I)V
    //   758: aload_2
    //   759: aload_0
    //   760: bipush #12
    //   762: invokevirtual elementAt : (I)Ljava/lang/Object;
    //   765: checkcast java/lang/String
    //   768: invokestatic parseInt : (Ljava/lang/String;)I
    //   771: invokevirtual o : (I)V
    //   774: aload_2
    //   775: aload_0
    //   776: bipush #13
    //   778: invokevirtual elementAt : (I)Ljava/lang/Object;
    //   781: checkcast java/lang/String
    //   784: invokestatic parseInt : (Ljava/lang/String;)I
    //   787: invokevirtual v : (I)V
    //   790: aload_2
    //   791: aload_0
    //   792: bipush #14
    //   794: invokevirtual elementAt : (I)Ljava/lang/Object;
    //   797: checkcast java/lang/String
    //   800: invokevirtual h : (Ljava/lang/String;)V
    //   803: aload_2
    //   804: aload_0
    //   805: bipush #15
    //   807: invokevirtual elementAt : (I)Ljava/lang/Object;
    //   810: checkcast java/lang/String
    //   813: invokestatic parseInt : (Ljava/lang/String;)I
    //   816: invokevirtual f : (I)V
    //   819: aload_2
    //   820: aload_0
    //   821: bipush #16
    //   823: invokevirtual elementAt : (I)Ljava/lang/Object;
    //   826: checkcast java/lang/String
    //   829: invokestatic parseInt : (Ljava/lang/String;)I
    //   832: invokevirtual g : (I)V
    //   835: goto -> 843
    //   838: astore_0
    //   839: sipush #1310
    //   842: ireturn
    //   843: iconst_0
    //   844: ireturn
    // Exception table:
    //   from	to	target	type
    //   8	63	838	java/lang/Exception
    //   67	279	838	java/lang/Exception
    //   279	326	838	java/lang/Exception
    //   326	357	408	java/lang/Exception
    //   357	385	419	java/lang/Exception
    //   385	404	838	java/lang/Exception
    //   410	416	838	java/lang/Exception
    //   420	426	838	java/lang/Exception
    //   429	464	838	java/lang/Exception
    //   468	495	838	java/lang/Exception
    //   495	700	838	java/lang/Exception
    //   703	715	838	java/lang/Exception
    //   718	723	838	java/lang/Exception
    //   726	835	838	java/lang/Exception
  }
  
  private boolean y(int paramInt) {
    return (paramInt == 1);
  }
  
  private void z(int paramInt) {
    this.L = paramInt;
  }
  
  public int A() {
    return this.al;
  }
  
  public int B() {
    return this.am;
  }
  
  public int C() {
    return this.an;
  }
  
  public int D() {
    return this.at;
  }
  
  public String E() {
    return this.au;
  }
  
  public int F() {
    return this.av;
  }
  
  public String G() {
    return this.aw;
  }
  
  public String H() {
    return this.ae;
  }
  
  public String I() {
    return this.af;
  }
  
  public String J() {
    return this.ax;
  }
  
  public int K() {
    return 1;
  }
  
  public int L() {
    return this.M;
  }
  
  public String M() {
    return this.Q;
  }
  
  public String N() {
    return this.R;
  }
  
  public int O() {
    return this.ac;
  }
  
  public void a(int paramInt) {
    this.P = paramInt;
  }
  
  public void a(String paramString) {
    this.N = paramString;
  }
  
  public boolean a() {
    return y(this.ao);
  }
  
  public void b(int paramInt) {
    this.W = paramInt;
  }
  
  public void b(String paramString) {
    this.O = paramString;
  }
  
  public boolean b() {
    return y(this.ap);
  }
  
  public void c(int paramInt) {
    this.X = paramInt;
  }
  
  public void c(String paramString) {
    this.S = paramString;
  }
  
  public boolean c() {
    return y(this.aq);
  }
  
  public void d(int paramInt) {
    this.Y = paramInt;
  }
  
  public void d(String paramString) {
    this.T = paramString;
  }
  
  public boolean d() {
    return y(this.ar);
  }
  
  public void e(int paramInt) {
    this.Z = paramInt;
  }
  
  public void e(String paramString) {
    this.U = paramString;
  }
  
  public boolean e() {
    return y(this.as);
  }
  
  public int f() {
    return this.L;
  }
  
  public void f(int paramInt) {
    this.aa = paramInt;
  }
  
  public void f(String paramString) {
    this.V = paramString;
  }
  
  public String g() {
    return this.N;
  }
  
  public void g(int paramInt) {
    this.ab = paramInt;
  }
  
  public void g(String paramString) {
    this.ad = paramString;
  }
  
  public String h() {
    return this.O;
  }
  
  public void h(int paramInt) {
    this.ac = paramInt;
  }
  
  public void h(String paramString) {
    this.aw = paramString;
  }
  
  public int i() {
    return this.P;
  }
  
  public void i(int paramInt) {
    this.ag = paramInt;
  }
  
  public void i(String paramString) {
    this.au = paramString;
  }
  
  public String j() {
    return this.S;
  }
  
  public void j(int paramInt) {
    this.ah = paramInt;
  }
  
  public void j(String paramString) {
    this.ae = paramString;
  }
  
  public String k() {
    return this.T;
  }
  
  public void k(int paramInt) {
    this.ai = paramInt;
  }
  
  public void k(String paramString) {
    this.af = paramString;
  }
  
  public String l() {
    return this.U;
  }
  
  public void l(int paramInt) {
    this.aj = paramInt;
  }
  
  public void l(String paramString) {
    this.ax = paramString;
  }
  
  public String m() {
    return this.V;
  }
  
  public void m(int paramInt) {
    this.ak = paramInt;
  }
  
  public void m(String paramString) {
    this.Q = paramString;
  }
  
  public int n() {
    return this.W;
  }
  
  public void n(int paramInt) {
    this.al = paramInt;
  }
  
  public void n(String paramString) {
    this.R = paramString;
  }
  
  public int o() {
    return this.X;
  }
  
  public void o(int paramInt) {
    this.am = paramInt;
  }
  
  public int p() {
    return this.Y;
  }
  
  public void p(int paramInt) {
    this.an = paramInt;
  }
  
  public int q() {
    return this.Z;
  }
  
  public void q(int paramInt) {
    this.ao = paramInt;
  }
  
  public int r() {
    return this.aa;
  }
  
  public void r(int paramInt) {
    this.ap = paramInt;
  }
  
  public int s() {
    return this.ab;
  }
  
  public void s(int paramInt) {
    this.ar = paramInt;
  }
  
  public int t() {
    return this.ac;
  }
  
  public void t(int paramInt) {
    this.at = paramInt;
  }
  
  public String u() {
    return this.ad;
  }
  
  public void u(int paramInt) {
    this.aq = paramInt;
  }
  
  public int v() {
    return this.ag;
  }
  
  public void v(int paramInt) {
    this.as = paramInt;
  }
  
  public int w() {
    return this.ah;
  }
  
  public void w(int paramInt) {
    this.av = paramInt;
  }
  
  public int x() {
    return this.ai;
  }
  
  public void x(int paramInt) {
    this.M = paramInt;
  }
  
  public int y() {
    return this.aj;
  }
  
  public int z() {
    return this.ak;
  }
}


/* Location:              C:\Users\devid\Downloads\SAST\Santander\dex2jar-2.0\classes-dex2jar.jar!\ak.class
 * Java compiler version: 6 (50.0)
 * JD-Core Version:       1.1.3
 */