import org.json.JSONObject;

class bch {
  static bcf a(JSONObject paramJSONObject, awr paramawr) {
    // Byte code:
    //   0: aload_0
    //   1: ldc 'nm'
    //   3: invokevirtual optString : (Ljava/lang/String;)Ljava/lang/String;
    //   6: astore #8
    //   8: aload_0
    //   9: ldc 'g'
    //   11: invokevirtual optJSONObject : (Ljava/lang/String;)Lorg/json/JSONObject;
    //   14: astore #4
    //   16: aload #4
    //   18: astore_3
    //   19: aload #4
    //   21: ifnull -> 61
    //   24: aload #4
    //   26: astore_3
    //   27: aload #4
    //   29: ldc 'k'
    //   31: invokevirtual has : (Ljava/lang/String;)Z
    //   34: ifeq -> 61
    //   37: aload #4
    //   39: ldc 'p'
    //   41: invokevirtual optInt : (Ljava/lang/String;)I
    //   44: istore_2
    //   45: aload #4
    //   47: ldc 'k'
    //   49: invokevirtual optJSONObject : (Ljava/lang/String;)Lorg/json/JSONObject;
    //   52: astore_3
    //   53: aload_3
    //   54: ldc 'p'
    //   56: iload_2
    //   57: invokevirtual put : (Ljava/lang/String;I)Lorg/json/JSONObject;
    //   60: pop
    //   61: aload_3
    //   62: ifnull -> 223
    //   65: aload_3
    //   66: aload_1
    //   67: invokestatic a : (Lorg/json/JSONObject;Lawr;)Lbas;
    //   70: astore_3
    //   71: aload_0
    //   72: ldc 'o'
    //   74: invokevirtual optJSONObject : (Ljava/lang/String;)Lorg/json/JSONObject;
    //   77: astore #4
    //   79: aload #4
    //   81: ifnull -> 217
    //   84: aload #4
    //   86: aload_1
    //   87: invokestatic a : (Lorg/json/JSONObject;Lawr;)Lbaw;
    //   90: astore #4
    //   92: aload_0
    //   93: ldc 'r'
    //   95: iconst_1
    //   96: invokevirtual optInt : (Ljava/lang/String;I)I
    //   99: iconst_1
    //   100: if_icmpne -> 185
    //   103: getstatic android/graphics/Path$FillType.WINDING : Landroid/graphics/Path$FillType;
    //   106: astore #5
    //   108: aload_0
    //   109: ldc 't'
    //   111: iconst_1
    //   112: invokevirtual optInt : (Ljava/lang/String;I)I
    //   115: iconst_1
    //   116: if_icmpne -> 193
    //   119: getstatic bcl.Linear : Lbcl;
    //   122: astore #6
    //   124: aload_0
    //   125: ldc 's'
    //   127: invokevirtual optJSONObject : (Ljava/lang/String;)Lorg/json/JSONObject;
    //   130: astore #7
    //   132: aload #7
    //   134: ifnull -> 211
    //   137: aload #7
    //   139: aload_1
    //   140: invokestatic a : (Lorg/json/JSONObject;Lawr;)Lbbc;
    //   143: astore #7
    //   145: aload_0
    //   146: ldc 'e'
    //   148: invokevirtual optJSONObject : (Ljava/lang/String;)Lorg/json/JSONObject;
    //   151: astore_0
    //   152: aload_0
    //   153: ifnull -> 206
    //   156: aload_0
    //   157: aload_1
    //   158: invokestatic a : (Lorg/json/JSONObject;Lawr;)Lbbc;
    //   161: astore_0
    //   162: new bcf
    //   165: dup
    //   166: aload #8
    //   168: aload #6
    //   170: aload #5
    //   172: aload_3
    //   173: aload #4
    //   175: aload #7
    //   177: aload_0
    //   178: aconst_null
    //   179: aconst_null
    //   180: aconst_null
    //   181: invokespecial <init> : (Ljava/lang/String;Lbcl;Landroid/graphics/Path$FillType;Lbas;Lbaw;Lbbc;Lbbc;Lbao;Lbao;Lbcg;)V
    //   184: areturn
    //   185: getstatic android/graphics/Path$FillType.EVEN_ODD : Landroid/graphics/Path$FillType;
    //   188: astore #5
    //   190: goto -> 108
    //   193: getstatic bcl.Radial : Lbcl;
    //   196: astore #6
    //   198: goto -> 124
    //   201: astore #4
    //   203: goto -> 61
    //   206: aconst_null
    //   207: astore_0
    //   208: goto -> 162
    //   211: aconst_null
    //   212: astore #7
    //   214: goto -> 145
    //   217: aconst_null
    //   218: astore #4
    //   220: goto -> 92
    //   223: aconst_null
    //   224: astore_3
    //   225: goto -> 71
    // Exception table:
    //   from	to	target	type
    //   53	61	201	org/json/JSONException
  }
}


/* Location:              C:\Users\devid\Downloads\SAST\Santander\dex2jar-2.0\classes-dex2jar.jar!\bch.class
 * Java compiler version: 6 (50.0)
 * JD-Core Version:       1.1.3
 */