import org.json.JSONObject;

class bck {
  static bci a(JSONObject paramJSONObject, awr paramawr) {
    // Byte code:
    //   0: aload_0
    //   1: ldc 'nm'
    //   3: invokevirtual optString : (Ljava/lang/String;)Ljava/lang/String;
    //   6: astore #9
    //   8: aload_0
    //   9: ldc 'g'
    //   11: invokevirtual optJSONObject : (Ljava/lang/String;)Lorg/json/JSONObject;
    //   14: astore_3
    //   15: aload_3
    //   16: astore #4
    //   18: aload_3
    //   19: ifnull -> 42
    //   22: aload_3
    //   23: astore #4
    //   25: aload_3
    //   26: ldc 'k'
    //   28: invokevirtual has : (Ljava/lang/String;)Z
    //   31: ifeq -> 42
    //   34: aload_3
    //   35: ldc 'k'
    //   37: invokevirtual optJSONObject : (Ljava/lang/String;)Lorg/json/JSONObject;
    //   40: astore #4
    //   42: aconst_null
    //   43: astore_3
    //   44: aload #4
    //   46: ifnull -> 56
    //   49: aload #4
    //   51: aload_1
    //   52: invokestatic a : (Lorg/json/JSONObject;Lawr;)Lbas;
    //   55: astore_3
    //   56: aload_0
    //   57: ldc 'o'
    //   59: invokevirtual optJSONObject : (Ljava/lang/String;)Lorg/json/JSONObject;
    //   62: astore #5
    //   64: aconst_null
    //   65: astore #4
    //   67: aload #5
    //   69: ifnull -> 80
    //   72: aload #5
    //   74: aload_1
    //   75: invokestatic a : (Lorg/json/JSONObject;Lawr;)Lbaw;
    //   78: astore #4
    //   80: aload_0
    //   81: ldc 't'
    //   83: iconst_1
    //   84: invokevirtual optInt : (Ljava/lang/String;I)I
    //   87: iconst_1
    //   88: if_icmpne -> 276
    //   91: getstatic bcl.Linear : Lbcl;
    //   94: astore #5
    //   96: aload_0
    //   97: ldc 's'
    //   99: invokevirtual optJSONObject : (Ljava/lang/String;)Lorg/json/JSONObject;
    //   102: astore #7
    //   104: aconst_null
    //   105: astore #6
    //   107: aload #7
    //   109: ifnull -> 120
    //   112: aload #7
    //   114: aload_1
    //   115: invokestatic a : (Lorg/json/JSONObject;Lawr;)Lbbc;
    //   118: astore #6
    //   120: aload_0
    //   121: ldc 'e'
    //   123: invokevirtual optJSONObject : (Ljava/lang/String;)Lorg/json/JSONObject;
    //   126: astore #8
    //   128: aconst_null
    //   129: astore #7
    //   131: aload #8
    //   133: ifnull -> 144
    //   136: aload #8
    //   138: aload_1
    //   139: invokestatic a : (Lorg/json/JSONObject;Lawr;)Lbbc;
    //   142: astore #7
    //   144: aload_0
    //   145: ldc 'w'
    //   147: invokevirtual optJSONObject : (Ljava/lang/String;)Lorg/json/JSONObject;
    //   150: aload_1
    //   151: invokestatic a : (Lorg/json/JSONObject;Lawr;)Lbao;
    //   154: astore #10
    //   156: invokestatic values : ()[Lbdr;
    //   159: aload_0
    //   160: ldc 'lc'
    //   162: invokevirtual optInt : (Ljava/lang/String;)I
    //   165: iconst_1
    //   166: isub
    //   167: aaload
    //   168: astore #11
    //   170: invokestatic values : ()[Lbds;
    //   173: aload_0
    //   174: ldc 'lj'
    //   176: invokevirtual optInt : (Ljava/lang/String;)I
    //   179: iconst_1
    //   180: isub
    //   181: aaload
    //   182: astore #12
    //   184: aconst_null
    //   185: astore #8
    //   187: new java/util/ArrayList
    //   190: dup
    //   191: invokespecial <init> : ()V
    //   194: astore #13
    //   196: aload_0
    //   197: ldc 'd'
    //   199: invokevirtual has : (Ljava/lang/String;)Z
    //   202: ifeq -> 362
    //   205: aload_0
    //   206: ldc 'd'
    //   208: invokevirtual optJSONArray : (Ljava/lang/String;)Lorg/json/JSONArray;
    //   211: astore #14
    //   213: aconst_null
    //   214: astore_0
    //   215: iconst_0
    //   216: istore_2
    //   217: iload_2
    //   218: aload #14
    //   220: invokevirtual length : ()I
    //   223: if_icmpge -> 332
    //   226: aload #14
    //   228: iload_2
    //   229: invokevirtual optJSONObject : (I)Lorg/json/JSONObject;
    //   232: astore #15
    //   234: aload #15
    //   236: ldc 'n'
    //   238: invokevirtual optString : (Ljava/lang/String;)Ljava/lang/String;
    //   241: astore #16
    //   243: aload #16
    //   245: ldc 'o'
    //   247: invokevirtual equals : (Ljava/lang/Object;)Z
    //   250: ifeq -> 284
    //   253: aload #15
    //   255: ldc 'v'
    //   257: invokevirtual optJSONObject : (Ljava/lang/String;)Lorg/json/JSONObject;
    //   260: aload_1
    //   261: invokestatic a : (Lorg/json/JSONObject;Lawr;)Lbao;
    //   264: astore #8
    //   266: iload_2
    //   267: iconst_1
    //   268: iadd
    //   269: istore_2
    //   270: aload #8
    //   272: astore_0
    //   273: goto -> 217
    //   276: getstatic bcl.Radial : Lbcl;
    //   279: astore #5
    //   281: goto -> 96
    //   284: aload #16
    //   286: ldc 'd'
    //   288: invokevirtual equals : (Ljava/lang/Object;)Z
    //   291: ifne -> 307
    //   294: aload_0
    //   295: astore #8
    //   297: aload #16
    //   299: ldc 'g'
    //   301: invokevirtual equals : (Ljava/lang/Object;)Z
    //   304: ifeq -> 266
    //   307: aload #13
    //   309: aload #15
    //   311: ldc 'v'
    //   313: invokevirtual optJSONObject : (Ljava/lang/String;)Lorg/json/JSONObject;
    //   316: aload_1
    //   317: invokestatic a : (Lorg/json/JSONObject;Lawr;)Lbao;
    //   320: invokeinterface add : (Ljava/lang/Object;)Z
    //   325: pop
    //   326: aload_0
    //   327: astore #8
    //   329: goto -> 266
    //   332: aload #13
    //   334: invokeinterface size : ()I
    //   339: iconst_1
    //   340: if_icmpne -> 359
    //   343: aload #13
    //   345: aload #13
    //   347: iconst_0
    //   348: invokeinterface get : (I)Ljava/lang/Object;
    //   353: invokeinterface add : (Ljava/lang/Object;)Z
    //   358: pop
    //   359: aload_0
    //   360: astore #8
    //   362: new bci
    //   365: dup
    //   366: aload #9
    //   368: aload #5
    //   370: aload_3
    //   371: aload #4
    //   373: aload #6
    //   375: aload #7
    //   377: aload #10
    //   379: aload #11
    //   381: aload #12
    //   383: aload #13
    //   385: aload #8
    //   387: aconst_null
    //   388: invokespecial <init> : (Ljava/lang/String;Lbcl;Lbas;Lbaw;Lbbc;Lbbc;Lbao;Lbdr;Lbds;Ljava/util/List;Lbao;Lbcj;)V
    //   391: areturn
  }
}


/* Location:              C:\Users\devid\Downloads\SAST\Santander\dex2jar-2.0\classes-dex2jar.jar!\bck.class
 * Java compiler version: 6 (50.0)
 * JD-Core Version:       1.1.3
 */