import java.util.HashMap;
import java.util.Set;

class bkp {
  private final HashMap<bkf, bls> a = new HashMap<bkf, bls>();
  
  private bls b(bkf parambkf) {
    // Byte code:
    //   0: aload_0
    //   1: monitorenter
    //   2: aload_0
    //   3: getfield a : Ljava/util/HashMap;
    //   6: aload_1
    //   7: invokevirtual get : (Ljava/lang/Object;)Ljava/lang/Object;
    //   10: checkcast bls
    //   13: astore_3
    //   14: aload_3
    //   15: astore_2
    //   16: aload_3
    //   17: ifnonnull -> 40
    //   20: invokestatic h : ()Landroid/content/Context;
    //   23: astore_2
    //   24: new bls
    //   27: dup
    //   28: aload_2
    //   29: invokestatic a : (Landroid/content/Context;)Lbmv;
    //   32: aload_2
    //   33: invokestatic d : (Landroid/content/Context;)Ljava/lang/String;
    //   36: invokespecial <init> : (Lbmv;Ljava/lang/String;)V
    //   39: astore_2
    //   40: aload_0
    //   41: getfield a : Ljava/util/HashMap;
    //   44: aload_1
    //   45: aload_2
    //   46: invokevirtual put : (Ljava/lang/Object;Ljava/lang/Object;)Ljava/lang/Object;
    //   49: pop
    //   50: aload_0
    //   51: monitorexit
    //   52: aload_2
    //   53: areturn
    //   54: astore_1
    //   55: aload_0
    //   56: monitorexit
    //   57: aload_1
    //   58: athrow
    // Exception table:
    //   from	to	target	type
    //   2	14	54	finally
    //   20	40	54	finally
    //   40	50	54	finally
  }
  
  public bls a(bkf parambkf) {
    // Byte code:
    //   0: aload_0
    //   1: monitorenter
    //   2: aload_0
    //   3: getfield a : Ljava/util/HashMap;
    //   6: aload_1
    //   7: invokevirtual get : (Ljava/lang/Object;)Ljava/lang/Object;
    //   10: checkcast bls
    //   13: astore_1
    //   14: aload_0
    //   15: monitorexit
    //   16: aload_1
    //   17: areturn
    //   18: astore_1
    //   19: aload_0
    //   20: monitorexit
    //   21: aload_1
    //   22: athrow
    // Exception table:
    //   from	to	target	type
    //   2	14	18	finally
  }
  
  public Set<bkf> a() {
    // Byte code:
    //   0: aload_0
    //   1: monitorenter
    //   2: aload_0
    //   3: getfield a : Ljava/util/HashMap;
    //   6: invokevirtual keySet : ()Ljava/util/Set;
    //   9: astore_1
    //   10: aload_0
    //   11: monitorexit
    //   12: aload_1
    //   13: areturn
    //   14: astore_1
    //   15: aload_0
    //   16: monitorexit
    //   17: aload_1
    //   18: athrow
    // Exception table:
    //   from	to	target	type
    //   2	10	14	finally
  }
  
  public void a(bkf parambkf, bkl parambkl) {
    // Byte code:
    //   0: aload_0
    //   1: monitorenter
    //   2: aload_0
    //   3: aload_1
    //   4: invokespecial b : (Lbkf;)Lbls;
    //   7: aload_2
    //   8: invokevirtual a : (Lbkl;)V
    //   11: aload_0
    //   12: monitorexit
    //   13: return
    //   14: astore_1
    //   15: aload_0
    //   16: monitorexit
    //   17: aload_1
    //   18: athrow
    // Exception table:
    //   from	to	target	type
    //   2	11	14	finally
  }
  
  public void a(blp paramblp) {
    // Byte code:
    //   0: aload_0
    //   1: monitorenter
    //   2: aload_1
    //   3: ifnonnull -> 9
    //   6: aload_0
    //   7: monitorexit
    //   8: return
    //   9: aload_1
    //   10: invokevirtual a : ()Ljava/util/Set;
    //   13: invokeinterface iterator : ()Ljava/util/Iterator;
    //   18: astore_2
    //   19: aload_2
    //   20: invokeinterface hasNext : ()Z
    //   25: ifeq -> 6
    //   28: aload_2
    //   29: invokeinterface next : ()Ljava/lang/Object;
    //   34: checkcast bkf
    //   37: astore #4
    //   39: aload_0
    //   40: aload #4
    //   42: invokespecial b : (Lbkf;)Lbls;
    //   45: astore_3
    //   46: aload_1
    //   47: aload #4
    //   49: invokevirtual a : (Lbkf;)Ljava/util/List;
    //   52: invokeinterface iterator : ()Ljava/util/Iterator;
    //   57: astore #4
    //   59: aload #4
    //   61: invokeinterface hasNext : ()Z
    //   66: ifeq -> 19
    //   69: aload_3
    //   70: aload #4
    //   72: invokeinterface next : ()Ljava/lang/Object;
    //   77: checkcast bkl
    //   80: invokevirtual a : (Lbkl;)V
    //   83: goto -> 59
    //   86: astore_1
    //   87: aload_0
    //   88: monitorexit
    //   89: aload_1
    //   90: athrow
    // Exception table:
    //   from	to	target	type
    //   9	19	86	finally
    //   19	59	86	finally
    //   59	83	86	finally
  }
  
  public int b() {
    // Byte code:
    //   0: aload_0
    //   1: monitorenter
    //   2: aload_0
    //   3: getfield a : Ljava/util/HashMap;
    //   6: invokevirtual values : ()Ljava/util/Collection;
    //   9: invokeinterface iterator : ()Ljava/util/Iterator;
    //   14: astore_3
    //   15: iconst_0
    //   16: istore_1
    //   17: aload_3
    //   18: invokeinterface hasNext : ()Z
    //   23: ifeq -> 46
    //   26: aload_3
    //   27: invokeinterface next : ()Ljava/lang/Object;
    //   32: checkcast bls
    //   35: invokevirtual a : ()I
    //   38: istore_2
    //   39: iload_2
    //   40: iload_1
    //   41: iadd
    //   42: istore_1
    //   43: goto -> 17
    //   46: aload_0
    //   47: monitorexit
    //   48: iload_1
    //   49: ireturn
    //   50: astore_3
    //   51: aload_0
    //   52: monitorexit
    //   53: aload_3
    //   54: athrow
    // Exception table:
    //   from	to	target	type
    //   2	15	50	finally
    //   17	39	50	finally
  }
}


/* Location:              C:\Users\devid\Downloads\SAST\Santander\dex2jar-2.0\classes-dex2jar.jar!\bkp.class
 * Java compiler version: 6 (50.0)
 * JD-Core Version:       1.1.3
 */