class bkx {
  private static final String a = bkx.class.getName();
  
  private static final String b = "AppEventsLogger.persistedevents";
  
  public static blp a() {
    // Byte code:
    //   0: aconst_null
    //   1: astore_1
    //   2: ldc bkx
    //   4: monitorenter
    //   5: invokestatic a : ()V
    //   8: invokestatic h : ()Landroid/content/Context;
    //   11: astore_3
    //   12: new bky
    //   15: dup
    //   16: new java/io/BufferedInputStream
    //   19: dup
    //   20: aload_3
    //   21: ldc 'AppEventsLogger.persistedevents'
    //   23: invokevirtual openFileInput : (Ljava/lang/String;)Ljava/io/FileInputStream;
    //   26: invokespecial <init> : (Ljava/io/InputStream;)V
    //   29: invokespecial <init> : (Ljava/io/InputStream;)V
    //   32: astore_0
    //   33: aload_0
    //   34: astore_1
    //   35: aload_0
    //   36: invokevirtual readObject : ()Ljava/lang/Object;
    //   39: checkcast blp
    //   42: astore_2
    //   43: aload_0
    //   44: invokestatic a : (Ljava/io/Closeable;)V
    //   47: aload_3
    //   48: ldc 'AppEventsLogger.persistedevents'
    //   50: invokevirtual getFileStreamPath : (Ljava/lang/String;)Ljava/io/File;
    //   53: invokevirtual delete : ()Z
    //   56: pop
    //   57: aload_2
    //   58: astore_0
    //   59: aload_0
    //   60: astore_1
    //   61: aload_0
    //   62: ifnonnull -> 73
    //   65: new blp
    //   68: dup
    //   69: invokespecial <init> : ()V
    //   72: astore_1
    //   73: ldc bkx
    //   75: monitorexit
    //   76: aload_1
    //   77: areturn
    //   78: astore_0
    //   79: getstatic bkx.a : Ljava/lang/String;
    //   82: ldc 'Got unexpected exception when removing events file: '
    //   84: aload_0
    //   85: invokestatic w : (Ljava/lang/String;Ljava/lang/String;Ljava/lang/Throwable;)I
    //   88: pop
    //   89: aload_2
    //   90: astore_0
    //   91: goto -> 59
    //   94: astore_0
    //   95: ldc bkx
    //   97: monitorexit
    //   98: aload_0
    //   99: athrow
    //   100: astore_0
    //   101: aconst_null
    //   102: astore_0
    //   103: aload_0
    //   104: invokestatic a : (Ljava/io/Closeable;)V
    //   107: aload_3
    //   108: ldc 'AppEventsLogger.persistedevents'
    //   110: invokevirtual getFileStreamPath : (Ljava/lang/String;)Ljava/io/File;
    //   113: invokevirtual delete : ()Z
    //   116: pop
    //   117: aconst_null
    //   118: astore_0
    //   119: goto -> 59
    //   122: astore_0
    //   123: getstatic bkx.a : Ljava/lang/String;
    //   126: ldc 'Got unexpected exception when removing events file: '
    //   128: aload_0
    //   129: invokestatic w : (Ljava/lang/String;Ljava/lang/String;Ljava/lang/Throwable;)I
    //   132: pop
    //   133: aconst_null
    //   134: astore_0
    //   135: goto -> 59
    //   138: astore_2
    //   139: aconst_null
    //   140: astore_0
    //   141: aload_0
    //   142: astore_1
    //   143: getstatic bkx.a : Ljava/lang/String;
    //   146: ldc 'Got unexpected exception while reading events: '
    //   148: aload_2
    //   149: invokestatic w : (Ljava/lang/String;Ljava/lang/String;Ljava/lang/Throwable;)I
    //   152: pop
    //   153: aload_0
    //   154: invokestatic a : (Ljava/io/Closeable;)V
    //   157: aload_3
    //   158: ldc 'AppEventsLogger.persistedevents'
    //   160: invokevirtual getFileStreamPath : (Ljava/lang/String;)Ljava/io/File;
    //   163: invokevirtual delete : ()Z
    //   166: pop
    //   167: aconst_null
    //   168: astore_0
    //   169: goto -> 59
    //   172: astore_0
    //   173: getstatic bkx.a : Ljava/lang/String;
    //   176: ldc 'Got unexpected exception when removing events file: '
    //   178: aload_0
    //   179: invokestatic w : (Ljava/lang/String;Ljava/lang/String;Ljava/lang/Throwable;)I
    //   182: pop
    //   183: aconst_null
    //   184: astore_0
    //   185: goto -> 59
    //   188: aload_1
    //   189: invokestatic a : (Ljava/io/Closeable;)V
    //   192: aload_3
    //   193: ldc 'AppEventsLogger.persistedevents'
    //   195: invokevirtual getFileStreamPath : (Ljava/lang/String;)Ljava/io/File;
    //   198: invokevirtual delete : ()Z
    //   201: pop
    //   202: aload_0
    //   203: athrow
    //   204: astore_1
    //   205: getstatic bkx.a : Ljava/lang/String;
    //   208: ldc 'Got unexpected exception when removing events file: '
    //   210: aload_1
    //   211: invokestatic w : (Ljava/lang/String;Ljava/lang/String;Ljava/lang/Throwable;)I
    //   214: pop
    //   215: goto -> 202
    //   218: astore_0
    //   219: goto -> 188
    //   222: astore_2
    //   223: goto -> 141
    //   226: astore_1
    //   227: goto -> 103
    //   230: astore_0
    //   231: goto -> 188
    // Exception table:
    //   from	to	target	type
    //   5	12	94	finally
    //   12	33	100	java/io/FileNotFoundException
    //   12	33	138	java/lang/Exception
    //   12	33	230	finally
    //   35	43	226	java/io/FileNotFoundException
    //   35	43	222	java/lang/Exception
    //   35	43	218	finally
    //   43	47	94	finally
    //   47	57	78	java/lang/Exception
    //   47	57	94	finally
    //   65	73	94	finally
    //   79	89	94	finally
    //   103	107	94	finally
    //   107	117	122	java/lang/Exception
    //   107	117	94	finally
    //   123	133	94	finally
    //   143	153	218	finally
    //   153	157	94	finally
    //   157	167	172	java/lang/Exception
    //   157	167	94	finally
    //   173	183	94	finally
    //   188	192	94	finally
    //   192	202	204	java/lang/Exception
    //   192	202	94	finally
    //   202	204	94	finally
    //   205	215	94	finally
  }
  
  public static void a(bkf parambkf, bls parambls) {
    // Byte code:
    //   0: ldc bkx
    //   2: monitorenter
    //   3: invokestatic a : ()V
    //   6: invokestatic a : ()Lblp;
    //   9: astore_2
    //   10: aload_2
    //   11: aload_0
    //   12: invokevirtual b : (Lbkf;)Z
    //   15: ifeq -> 41
    //   18: aload_2
    //   19: aload_0
    //   20: invokevirtual a : (Lbkf;)Ljava/util/List;
    //   23: aload_1
    //   24: invokevirtual b : ()Ljava/util/List;
    //   27: invokeinterface addAll : (Ljava/util/Collection;)Z
    //   32: pop
    //   33: aload_2
    //   34: invokestatic a : (Lblp;)V
    //   37: ldc bkx
    //   39: monitorexit
    //   40: return
    //   41: aload_2
    //   42: aload_0
    //   43: aload_1
    //   44: invokevirtual b : ()Ljava/util/List;
    //   47: invokevirtual a : (Lbkf;Ljava/util/List;)V
    //   50: goto -> 33
    //   53: astore_0
    //   54: ldc bkx
    //   56: monitorexit
    //   57: aload_0
    //   58: athrow
    // Exception table:
    //   from	to	target	type
    //   3	33	53	finally
    //   33	37	53	finally
    //   41	50	53	finally
  }
  
  public static void a(bkp parambkp) {
    // Byte code:
    //   0: ldc bkx
    //   2: monitorenter
    //   3: invokestatic a : ()V
    //   6: invokestatic a : ()Lblp;
    //   9: astore_1
    //   10: aload_0
    //   11: invokevirtual a : ()Ljava/util/Set;
    //   14: invokeinterface iterator : ()Ljava/util/Iterator;
    //   19: astore_2
    //   20: aload_2
    //   21: invokeinterface hasNext : ()Z
    //   26: ifeq -> 61
    //   29: aload_2
    //   30: invokeinterface next : ()Ljava/lang/Object;
    //   35: checkcast bkf
    //   38: astore_3
    //   39: aload_1
    //   40: aload_3
    //   41: aload_0
    //   42: aload_3
    //   43: invokevirtual a : (Lbkf;)Lbls;
    //   46: invokevirtual b : ()Ljava/util/List;
    //   49: invokevirtual a : (Lbkf;Ljava/util/List;)V
    //   52: goto -> 20
    //   55: astore_0
    //   56: ldc bkx
    //   58: monitorexit
    //   59: aload_0
    //   60: athrow
    //   61: aload_1
    //   62: invokestatic a : (Lblp;)V
    //   65: ldc bkx
    //   67: monitorexit
    //   68: return
    // Exception table:
    //   from	to	target	type
    //   3	20	55	finally
    //   20	52	55	finally
    //   61	65	55	finally
  }
  
  private static void a(blp paramblp) {
    // Byte code:
    //   0: invokestatic h : ()Landroid/content/Context;
    //   3: astore #4
    //   5: new java/io/ObjectOutputStream
    //   8: dup
    //   9: new java/io/BufferedOutputStream
    //   12: dup
    //   13: aload #4
    //   15: ldc 'AppEventsLogger.persistedevents'
    //   17: iconst_0
    //   18: invokevirtual openFileOutput : (Ljava/lang/String;I)Ljava/io/FileOutputStream;
    //   21: invokespecial <init> : (Ljava/io/OutputStream;)V
    //   24: invokespecial <init> : (Ljava/io/OutputStream;)V
    //   27: astore_2
    //   28: aload_2
    //   29: astore_1
    //   30: aload_2
    //   31: aload_0
    //   32: invokevirtual writeObject : (Ljava/lang/Object;)V
    //   35: aload_2
    //   36: invokestatic a : (Ljava/io/Closeable;)V
    //   39: return
    //   40: astore_3
    //   41: aconst_null
    //   42: astore_0
    //   43: aload_0
    //   44: astore_1
    //   45: getstatic bkx.a : Ljava/lang/String;
    //   48: ldc 'Got unexpected exception while persisting events: '
    //   50: aload_3
    //   51: invokestatic w : (Ljava/lang/String;Ljava/lang/String;Ljava/lang/Throwable;)I
    //   54: pop
    //   55: aload_0
    //   56: astore_1
    //   57: aload #4
    //   59: ldc 'AppEventsLogger.persistedevents'
    //   61: invokevirtual getFileStreamPath : (Ljava/lang/String;)Ljava/io/File;
    //   64: invokevirtual delete : ()Z
    //   67: pop
    //   68: aload_0
    //   69: invokestatic a : (Ljava/io/Closeable;)V
    //   72: return
    //   73: astore_0
    //   74: aconst_null
    //   75: astore_1
    //   76: aload_1
    //   77: invokestatic a : (Ljava/io/Closeable;)V
    //   80: aload_0
    //   81: athrow
    //   82: astore_0
    //   83: goto -> 76
    //   86: astore_1
    //   87: goto -> 68
    //   90: astore_3
    //   91: aload_2
    //   92: astore_0
    //   93: goto -> 43
    // Exception table:
    //   from	to	target	type
    //   5	28	40	java/lang/Exception
    //   5	28	73	finally
    //   30	35	90	java/lang/Exception
    //   30	35	82	finally
    //   45	55	82	finally
    //   57	68	86	java/lang/Exception
    //   57	68	82	finally
  }
}


/* Location:              C:\Users\devid\Downloads\SAST\Santander\dex2jar-2.0\classes-dex2jar.jar!\bkx.class
 * Java compiler version: 6 (50.0)
 * JD-Core Version:       1.1.3
 */