public class bnm {
  public static <T> void a(bnp<T> parambnp, bnt parambnt, bns parambns) {
    // Byte code:
    //   0: new bpw
    //   3: dup
    //   4: iconst_0
    //   5: invokestatic valueOf : (Z)Ljava/lang/Boolean;
    //   8: invokespecial <init> : (Ljava/lang/Object;)V
    //   11: astore #4
    //   13: new bpw
    //   16: dup
    //   17: iconst_1
    //   18: invokestatic valueOf : (I)Ljava/lang/Integer;
    //   21: invokespecial <init> : (Ljava/lang/Object;)V
    //   24: astore_3
    //   25: new bnn
    //   28: dup
    //   29: aload #4
    //   31: aload_3
    //   32: aload_2
    //   33: invokespecial <init> : (Lbpw;Lbpw;Lbns;)V
    //   36: astore_2
    //   37: aload_0
    //   38: invokeinterface a : ()Ljava/util/Iterator;
    //   43: astore #4
    //   45: new java/util/LinkedList
    //   48: dup
    //   49: invokespecial <init> : ()V
    //   52: astore #5
    //   54: aload #4
    //   56: invokeinterface hasNext : ()Z
    //   61: ifeq -> 82
    //   64: aload #5
    //   66: aload #4
    //   68: invokeinterface next : ()Ljava/lang/Object;
    //   73: invokeinterface add : (Ljava/lang/Object;)Z
    //   78: pop
    //   79: goto -> 54
    //   82: aload #5
    //   84: invokeinterface iterator : ()Ljava/util/Iterator;
    //   89: astore #4
    //   91: aload #4
    //   93: invokeinterface hasNext : ()Z
    //   98: ifeq -> 174
    //   101: aload #4
    //   103: invokeinterface next : ()Ljava/lang/Object;
    //   108: astore #6
    //   110: aload_0
    //   111: aload #6
    //   113: invokeinterface a : (Ljava/lang/Object;)Ljava/lang/Object;
    //   118: astore #5
    //   120: new bno
    //   123: dup
    //   124: aload_0
    //   125: aload #6
    //   127: aload_2
    //   128: invokespecial <init> : (Lbnp;Ljava/lang/Object;Lbns;)V
    //   131: astore #6
    //   133: aload_3
    //   134: getfield a : Ljava/lang/Object;
    //   137: checkcast java/lang/Integer
    //   140: astore #7
    //   142: aload_3
    //   143: aload_3
    //   144: getfield a : Ljava/lang/Object;
    //   147: checkcast java/lang/Integer
    //   150: invokevirtual intValue : ()I
    //   153: iconst_1
    //   154: iadd
    //   155: invokestatic valueOf : (I)Ljava/lang/Integer;
    //   158: putfield a : Ljava/lang/Object;
    //   161: aload_1
    //   162: aload #5
    //   164: aload #6
    //   166: invokeinterface a : (Ljava/lang/Object;Lbnr;)V
    //   171: goto -> 91
    //   174: aload_2
    //   175: invokeinterface a : ()V
    //   180: return
  }
}


/* Location:              C:\Users\devid\Downloads\SAST\Santander\dex2jar-2.0\classes-dex2jar.jar!\bnm.class
 * Java compiler version: 6 (50.0)
 * JD-Core Version:       1.1.3
 */