import android.content.res.AssetManager;
import android.os.Environment;
import android.util.Log;
import com.github.mikephil.charting.data.BarEntry;
import com.github.mikephil.charting.data.Entry;
import java.io.BufferedReader;
import java.io.File;
import java.io.FileReader;
import java.io.IOException;
import java.util.ArrayList;
import java.util.List;

public class ckx {
  private static final String a = "MPChart-FileUtils";
  
  public static List<Entry> a(AssetManager paramAssetManager, String paramString) {
    // Byte code:
    //   0: new java/util/ArrayList
    //   3: dup
    //   4: invokespecial <init> : ()V
    //   7: astore #4
    //   9: new java/io/BufferedReader
    //   12: dup
    //   13: new java/io/InputStreamReader
    //   16: dup
    //   17: aload_0
    //   18: aload_1
    //   19: invokevirtual open : (Ljava/lang/String;)Ljava/io/InputStream;
    //   22: ldc 'UTF-8'
    //   24: invokespecial <init> : (Ljava/io/InputStream;Ljava/lang/String;)V
    //   27: invokespecial <init> : (Ljava/io/Reader;)V
    //   30: astore_1
    //   31: aload_1
    //   32: astore_0
    //   33: aload_1
    //   34: invokevirtual readLine : ()Ljava/lang/String;
    //   37: astore_3
    //   38: aload_3
    //   39: ifnull -> 194
    //   42: aload_1
    //   43: astore_0
    //   44: aload_3
    //   45: ldc '#'
    //   47: invokevirtual split : (Ljava/lang/String;)[Ljava/lang/String;
    //   50: astore_3
    //   51: aload_1
    //   52: astore_0
    //   53: aload_3
    //   54: arraylength
    //   55: iconst_2
    //   56: if_icmpgt -> 98
    //   59: aload_1
    //   60: astore_0
    //   61: aload #4
    //   63: new com/github/mikephil/charting/data/Entry
    //   66: dup
    //   67: aload_3
    //   68: iconst_1
    //   69: aaload
    //   70: invokestatic parseFloat : (Ljava/lang/String;)F
    //   73: aload_3
    //   74: iconst_0
    //   75: aaload
    //   76: invokestatic parseFloat : (Ljava/lang/String;)F
    //   79: invokespecial <init> : (FF)V
    //   82: invokeinterface add : (Ljava/lang/Object;)Z
    //   87: pop
    //   88: aload_1
    //   89: astore_0
    //   90: aload_1
    //   91: invokevirtual readLine : ()Ljava/lang/String;
    //   94: astore_3
    //   95: goto -> 38
    //   98: aload_1
    //   99: astore_0
    //   100: aload_3
    //   101: arraylength
    //   102: iconst_1
    //   103: isub
    //   104: newarray float
    //   106: astore #5
    //   108: iconst_0
    //   109: istore_2
    //   110: aload_1
    //   111: astore_0
    //   112: iload_2
    //   113: aload #5
    //   115: arraylength
    //   116: if_icmpge -> 138
    //   119: aload_1
    //   120: astore_0
    //   121: aload #5
    //   123: iload_2
    //   124: aload_3
    //   125: iload_2
    //   126: aaload
    //   127: invokestatic parseFloat : (Ljava/lang/String;)F
    //   130: fastore
    //   131: iload_2
    //   132: iconst_1
    //   133: iadd
    //   134: istore_2
    //   135: goto -> 110
    //   138: aload_1
    //   139: astore_0
    //   140: aload #4
    //   142: new com/github/mikephil/charting/data/BarEntry
    //   145: dup
    //   146: aload_3
    //   147: aload_3
    //   148: arraylength
    //   149: iconst_1
    //   150: isub
    //   151: aaload
    //   152: invokestatic parseInt : (Ljava/lang/String;)I
    //   155: i2f
    //   156: aload #5
    //   158: invokespecial <init> : (F[F)V
    //   161: invokeinterface add : (Ljava/lang/Object;)Z
    //   166: pop
    //   167: goto -> 88
    //   170: astore_3
    //   171: aload_1
    //   172: astore_0
    //   173: ldc 'MPChart-FileUtils'
    //   175: aload_3
    //   176: invokevirtual toString : ()Ljava/lang/String;
    //   179: invokestatic e : (Ljava/lang/String;Ljava/lang/String;)I
    //   182: pop
    //   183: aload_1
    //   184: ifnull -> 191
    //   187: aload_1
    //   188: invokevirtual close : ()V
    //   191: aload #4
    //   193: areturn
    //   194: aload_1
    //   195: ifnull -> 191
    //   198: aload_1
    //   199: invokevirtual close : ()V
    //   202: aload #4
    //   204: areturn
    //   205: astore_0
    //   206: ldc 'MPChart-FileUtils'
    //   208: aload_0
    //   209: invokevirtual toString : ()Ljava/lang/String;
    //   212: invokestatic e : (Ljava/lang/String;Ljava/lang/String;)I
    //   215: pop
    //   216: aload #4
    //   218: areturn
    //   219: astore_0
    //   220: ldc 'MPChart-FileUtils'
    //   222: aload_0
    //   223: invokevirtual toString : ()Ljava/lang/String;
    //   226: invokestatic e : (Ljava/lang/String;Ljava/lang/String;)I
    //   229: pop
    //   230: aload #4
    //   232: areturn
    //   233: astore_1
    //   234: aconst_null
    //   235: astore_0
    //   236: aload_0
    //   237: ifnull -> 244
    //   240: aload_0
    //   241: invokevirtual close : ()V
    //   244: aload_1
    //   245: athrow
    //   246: astore_0
    //   247: ldc 'MPChart-FileUtils'
    //   249: aload_0
    //   250: invokevirtual toString : ()Ljava/lang/String;
    //   253: invokestatic e : (Ljava/lang/String;Ljava/lang/String;)I
    //   256: pop
    //   257: goto -> 244
    //   260: astore_1
    //   261: goto -> 236
    //   264: astore_3
    //   265: aconst_null
    //   266: astore_1
    //   267: goto -> 171
    // Exception table:
    //   from	to	target	type
    //   9	31	264	java/io/IOException
    //   9	31	233	finally
    //   33	38	170	java/io/IOException
    //   33	38	260	finally
    //   44	51	170	java/io/IOException
    //   44	51	260	finally
    //   53	59	170	java/io/IOException
    //   53	59	260	finally
    //   61	88	170	java/io/IOException
    //   61	88	260	finally
    //   90	95	170	java/io/IOException
    //   90	95	260	finally
    //   100	108	170	java/io/IOException
    //   100	108	260	finally
    //   112	119	170	java/io/IOException
    //   112	119	260	finally
    //   121	131	170	java/io/IOException
    //   121	131	260	finally
    //   140	167	170	java/io/IOException
    //   140	167	260	finally
    //   173	183	260	finally
    //   187	191	219	java/io/IOException
    //   198	202	205	java/io/IOException
    //   240	244	246	java/io/IOException
  }
  
  public static List<Entry> a(String paramString) {
    File file = new File(Environment.getExternalStorageDirectory(), paramString);
    ArrayList<Entry> arrayList = new ArrayList();
    try {
      BufferedReader bufferedReader = new BufferedReader(new FileReader(file));
      while (true) {
        String[] arrayOfString;
        String str = bufferedReader.readLine();
        if (str != null) {
          arrayOfString = str.split("#");
          if (arrayOfString.length <= 2) {
            arrayList.add(new Entry(Float.parseFloat(arrayOfString[0]), Integer.parseInt(arrayOfString[1])));
            continue;
          } 
        } else {
          return arrayList;
        } 
        float[] arrayOfFloat = new float[arrayOfString.length - 1];
        for (int i = 0; i < arrayOfFloat.length; i++)
          arrayOfFloat[i] = Float.parseFloat(arrayOfString[i]); 
        arrayList.add(new BarEntry(Integer.parseInt(arrayOfString[arrayOfString.length - 1]), arrayOfFloat));
      } 
    } catch (IOException iOException) {
      Log.e("MPChart-FileUtils", iOException.toString());
    } 
    return arrayList;
  }
  
  public static void a(List<Entry> paramList, String paramString) {
    // Byte code:
    //   0: new java/io/File
    //   3: dup
    //   4: invokestatic getExternalStorageDirectory : ()Ljava/io/File;
    //   7: aload_1
    //   8: invokespecial <init> : (Ljava/io/File;Ljava/lang/String;)V
    //   11: astore_1
    //   12: aload_1
    //   13: invokevirtual exists : ()Z
    //   16: ifne -> 24
    //   19: aload_1
    //   20: invokevirtual createNewFile : ()Z
    //   23: pop
    //   24: new java/io/BufferedWriter
    //   27: dup
    //   28: new java/io/FileWriter
    //   31: dup
    //   32: aload_1
    //   33: iconst_1
    //   34: invokespecial <init> : (Ljava/io/File;Z)V
    //   37: invokespecial <init> : (Ljava/io/Writer;)V
    //   40: astore_1
    //   41: aload_0
    //   42: invokeinterface iterator : ()Ljava/util/Iterator;
    //   47: astore_0
    //   48: aload_0
    //   49: invokeinterface hasNext : ()Z
    //   54: ifeq -> 134
    //   57: aload_0
    //   58: invokeinterface next : ()Ljava/lang/Object;
    //   63: checkcast com/github/mikephil/charting/data/Entry
    //   66: astore_2
    //   67: aload_1
    //   68: new java/lang/StringBuilder
    //   71: dup
    //   72: invokespecial <init> : ()V
    //   75: aload_2
    //   76: invokevirtual c : ()F
    //   79: invokevirtual append : (F)Ljava/lang/StringBuilder;
    //   82: ldc '#'
    //   84: invokevirtual append : (Ljava/lang/String;)Ljava/lang/StringBuilder;
    //   87: aload_2
    //   88: invokevirtual k : ()F
    //   91: invokevirtual append : (F)Ljava/lang/StringBuilder;
    //   94: invokevirtual toString : ()Ljava/lang/String;
    //   97: invokevirtual append : (Ljava/lang/CharSequence;)Ljava/io/Writer;
    //   100: pop
    //   101: aload_1
    //   102: invokevirtual newLine : ()V
    //   105: goto -> 48
    //   108: astore_0
    //   109: ldc 'MPChart-FileUtils'
    //   111: aload_0
    //   112: invokevirtual toString : ()Ljava/lang/String;
    //   115: invokestatic e : (Ljava/lang/String;Ljava/lang/String;)I
    //   118: pop
    //   119: return
    //   120: astore_2
    //   121: ldc 'MPChart-FileUtils'
    //   123: aload_2
    //   124: invokevirtual toString : ()Ljava/lang/String;
    //   127: invokestatic e : (Ljava/lang/String;Ljava/lang/String;)I
    //   130: pop
    //   131: goto -> 24
    //   134: aload_1
    //   135: invokevirtual close : ()V
    //   138: return
    // Exception table:
    //   from	to	target	type
    //   19	24	120	java/io/IOException
    //   24	48	108	java/io/IOException
    //   48	105	108	java/io/IOException
    //   134	138	108	java/io/IOException
  }
  
  public static List<BarEntry> b(AssetManager paramAssetManager, String paramString) {
    // Byte code:
    //   0: new java/util/ArrayList
    //   3: dup
    //   4: invokespecial <init> : ()V
    //   7: astore_3
    //   8: new java/io/BufferedReader
    //   11: dup
    //   12: new java/io/InputStreamReader
    //   15: dup
    //   16: aload_0
    //   17: aload_1
    //   18: invokevirtual open : (Ljava/lang/String;)Ljava/io/InputStream;
    //   21: ldc 'UTF-8'
    //   23: invokespecial <init> : (Ljava/io/InputStream;Ljava/lang/String;)V
    //   26: invokespecial <init> : (Ljava/io/Reader;)V
    //   29: astore_1
    //   30: aload_1
    //   31: astore_0
    //   32: aload_1
    //   33: invokevirtual readLine : ()Ljava/lang/String;
    //   36: astore_2
    //   37: aload_2
    //   38: ifnull -> 88
    //   41: aload_1
    //   42: astore_0
    //   43: aload_2
    //   44: ldc '#'
    //   46: invokevirtual split : (Ljava/lang/String;)[Ljava/lang/String;
    //   49: astore_2
    //   50: aload_1
    //   51: astore_0
    //   52: aload_3
    //   53: new com/github/mikephil/charting/data/BarEntry
    //   56: dup
    //   57: aload_2
    //   58: iconst_1
    //   59: aaload
    //   60: invokestatic parseFloat : (Ljava/lang/String;)F
    //   63: aload_2
    //   64: iconst_0
    //   65: aaload
    //   66: invokestatic parseFloat : (Ljava/lang/String;)F
    //   69: invokespecial <init> : (FF)V
    //   72: invokeinterface add : (Ljava/lang/Object;)Z
    //   77: pop
    //   78: aload_1
    //   79: astore_0
    //   80: aload_1
    //   81: invokevirtual readLine : ()Ljava/lang/String;
    //   84: astore_2
    //   85: goto -> 37
    //   88: aload_1
    //   89: ifnull -> 96
    //   92: aload_1
    //   93: invokevirtual close : ()V
    //   96: aload_3
    //   97: areturn
    //   98: astore_0
    //   99: ldc 'MPChart-FileUtils'
    //   101: aload_0
    //   102: invokevirtual toString : ()Ljava/lang/String;
    //   105: invokestatic e : (Ljava/lang/String;Ljava/lang/String;)I
    //   108: pop
    //   109: aload_3
    //   110: areturn
    //   111: astore_2
    //   112: aconst_null
    //   113: astore_1
    //   114: aload_1
    //   115: astore_0
    //   116: ldc 'MPChart-FileUtils'
    //   118: aload_2
    //   119: invokevirtual toString : ()Ljava/lang/String;
    //   122: invokestatic e : (Ljava/lang/String;Ljava/lang/String;)I
    //   125: pop
    //   126: aload_1
    //   127: ifnull -> 96
    //   130: aload_1
    //   131: invokevirtual close : ()V
    //   134: aload_3
    //   135: areturn
    //   136: astore_0
    //   137: ldc 'MPChart-FileUtils'
    //   139: aload_0
    //   140: invokevirtual toString : ()Ljava/lang/String;
    //   143: invokestatic e : (Ljava/lang/String;Ljava/lang/String;)I
    //   146: pop
    //   147: aload_3
    //   148: areturn
    //   149: astore_1
    //   150: aconst_null
    //   151: astore_0
    //   152: aload_0
    //   153: ifnull -> 160
    //   156: aload_0
    //   157: invokevirtual close : ()V
    //   160: aload_1
    //   161: athrow
    //   162: astore_0
    //   163: ldc 'MPChart-FileUtils'
    //   165: aload_0
    //   166: invokevirtual toString : ()Ljava/lang/String;
    //   169: invokestatic e : (Ljava/lang/String;Ljava/lang/String;)I
    //   172: pop
    //   173: goto -> 160
    //   176: astore_1
    //   177: goto -> 152
    //   180: astore_2
    //   181: goto -> 114
    // Exception table:
    //   from	to	target	type
    //   8	30	111	java/io/IOException
    //   8	30	149	finally
    //   32	37	180	java/io/IOException
    //   32	37	176	finally
    //   43	50	180	java/io/IOException
    //   43	50	176	finally
    //   52	78	180	java/io/IOException
    //   52	78	176	finally
    //   80	85	180	java/io/IOException
    //   80	85	176	finally
    //   92	96	98	java/io/IOException
    //   116	126	176	finally
    //   130	134	136	java/io/IOException
    //   156	160	162	java/io/IOException
  }
}


/* Location:              C:\Users\devid\Downloads\SAST\Santander\dex2jar-2.0\classes-dex2jar.jar!\ckx.class
 * Java compiler version: 6 (50.0)
 * JD-Core Version:       1.1.3
 */