import android.content.Context;
import android.content.Intent;
import android.content.pm.PackageInfo;
import android.content.pm.PackageManager;
import android.os.Build;
import android.util.Log;
import java.io.ByteArrayInputStream;
import java.io.UnsupportedEncodingException;
import java.security.cert.CertificateException;
import java.security.cert.CertificateExpiredException;
import java.security.cert.CertificateFactory;
import java.security.cert.CertificateNotYetValidException;
import java.security.cert.X509Certificate;
import java.util.Arrays;

public final class cna {
  static final byte[][] a = new byte[][] { a("0\004C0\003+ \003\002\001\002\002\t\000ÂàFdJ00\r\006\t*H÷\r\001\001\004\005\0000t1\0130\t\006\003U\004\006\023\002US1\0230\021\006\003U\004\b\023\nCalifornia1\0260\024\006\003U\004\007\023\rMountain View1\0240\022\006\003U\004\n\023\013Google Inc.1\0200\016\006\003U\004\013\023\007Android1\0200\016\006\003U\004\003\023\007Android0\036\027\r080821231334Z\027\r360107231334Z0t1\0130\t\006\003U\004\006\023\002US1\0230\021\006\003U\004\b\023\nCalifornia1\0260\024\006\003U\004\007\023\rMountain View1\0240\022\006\003U\004\n\023\013Google Inc.1\0200\016\006\003U\004\013\023\007Android1\0200\016\006\003U\004\003\023\007Android0\001 0\r\006\t*H÷\r\001\001\001\005\000\003\001\r\0000\001\b\002\001\001\000«V.\000Ø;¢\b®\no\022N)Ú\021ò«VÐXâÌ©\023\003é·TÓrö@§\033\035Ë\023\tgbNFV§wj\031=²å¿·$©\036w\030\016jG¤;3Ù`w\0301EÌß{.XftÉáV[\037LjYU¿òQ¦=«ùÅ\\'\"\"Rèuäø\025Jd_qhÀ±¿Æ\022ê¿xWi»4ªyÜ~.¢vL®\007ØÁqT×î_d¥\032D¦\002ÂI\005AWÜ\002Í_\\\016Uûï\031ûã'ð±Q\026Å o\031ÑõÄÛÂÖ¹?hÌ)yÇ\016\030«k;ÕÛU*\016;LßXûíÁº5à\003Á´±\rÒD¨î$ÿý38r«R!^Ú°ü\r\013\024[j¡y\002\001\003£Ù0Ö0\035\006\003U\035\016\004\026\004\024Ç}Â!\027V%Óßkãä×¥0¦\006\003U\035#\0040\024Ç}Â!\027V%Óßkãä×¥¡x¤v0t1\0130\t\006\003U\004\006\023\002US1\0230\021\006\003U\004\b\023\nCalifornia1\0260\024\006\003U\004\007\023\rMountain View1\0240\022\006\003U\004\n\023\013Google Inc.1\0200\016\006\003U\004\013\023\007Android1\0200\016\006\003U\004\003\023\007Android\t\000ÂàFdJ00\f\006\003U\035\023\004\0050\003\001\001ÿ0\r\006\t*H÷\r\001\001\004\005\000\003\001\001\000mÒRÎï0,6\nªÎÏòÌ©\004»]z\026aø®F²B\004ÐÿJhÇí\032S\036ÄYZb<æ\007c±g)zzãW\022Ä\007ò\bðË\020)\022M{\020b\031ÀÊ>³ù­_¸qï&âñmDÈÙ l²ð\005»?âËD~s\020v­E³?`\tê\031Áaæ&Aª'\035ýR(ÅÅ]ÛE'XÖaöÌ\fÌ·5.BLÄ6\\R52÷2Q7Y<JãAôÛAíÚ\r\013\020q§Ä@ðþ \034¶'ÊgCiÐ½/Ù\021ÿ\006Í¿,ú\020Ü\017:ãWbHÇïÆLqD\027B÷\005ÉÞW:õ[9\r×ý¹A1]_u0\021&ÿb\024\020Ài0"), a("0\004¨0\003 \003\002\001\002\002\t\000Õ¸l}ÓNõ0\r\006\t*H÷\r\001\001\004\005\00001\0130\t\006\003U\004\006\023\002US1\0230\021\006\003U\004\b\023\nCalifornia1\0260\024\006\003U\004\007\023\rMountain View1\0200\016\006\003U\004\n\023\007Android1\0200\016\006\003U\004\013\023\007Android1\0200\016\006\003U\004\003\023\007Android1\"0 \006\t*H÷\r\001\t\001\026\023android@android.com0\036\027\r080415233656Z\027\r350901233656Z01\0130\t\006\003U\004\006\023\002US1\0230\021\006\003U\004\b\023\nCalifornia1\0260\024\006\003U\004\007\023\rMountain View1\0200\016\006\003U\004\n\023\007Android1\0200\016\006\003U\004\013\023\007Android1\0200\016\006\003U\004\003\023\007Android1\"0 \006\t*H÷\r\001\t\001\026\023android@android.com0\001 0\r\006\t*H÷\r\001\001\001\005\000\003\001\r\0000\001\b\002\001\001\000ÖÎ.\b\n¿â1MÑ³ÏÓ\030\\´=3ú\ftá½¶ÑÛ\023ö,\\9ßVøF=e¾ÀóÊBk\007Å¨íZ9ÁgçkÉ¹'K\013\"\000\031©)\025årÅm*0\033£oÅü\021:ÖËt5¡m#«}úîáeäß\037\n½§\nQlN\005\021Ê|\fU\027[ÃuùHÅj®\b¤O¦¤Ý}¿,\n5\"­\006¸Ì\030^±Uyîøm\b\013\035aÀù¯±ÂëÑ\007êE«Ûh£Ç^TÇlSÔ\013\022\035ç»Ó\016b\f\030áªaÛ¼Ý<d_/UóÔÃuì@p©?qQØ6pÁj\032¾^òÑ\030á¸®ó)ðf¿láD¬èm\034\033\017\002\001\003£ü0ù0\035\006\003U\035\016\004\026\004\024\034Å¾LC<a:\025°L¼\003òOà²0É\006\003U\035#\004Á0¾\024\034Å¾LC<a:\025°L¼\003òOà²¡¤01\0130\t\006\003U\004\006\023\002US1\0230\021\006\003U\004\b\023\nCalifornia1\0260\024\006\003U\004\007\023\rMountain View1\0200\016\006\003U\004\n\023\007Android1\0200\016\006\003U\004\013\023\007Android1\0200\016\006\003U\004\003\023\007Android1\"0 \006\t*H÷\r\001\t\001\026\023android@android.com\t\000Õ¸l}ÓNõ0\f\006\003U\035\023\004\0050\003\001\001ÿ0\r\006\t*H÷\r\001\001\004\005\000\003\001\001\000\031Ó\fñ\005ûx?L\r}Ò##=@zÏÎ\000\b\035[×ÆéÖí k\016\021 \006Al¢D\023ÒkJ àõ$ÊÒ»\\nL¡\001j\025n¡ì]ÉZ^:\001\0006ôHÕ\020¿.\036ag:;åm¯\013w±Â)ãÂUãèL]#ïº\tËñ; +NZ\"É2cHJ#Òü)ú\0319u3¯Øª\026\017BÂÐ\026>fCéÁ/ Á33[Àÿk\"ÞÑ­DB)¥9©Nï­«ÐeÎÒK>QåÝ{fx{ï\022þû¤Ä#ûOøÌIL\002ðõ\005\026\022ÿe)9>FêÅ»!òwÁQª_*¦'Ñè§\n¶\0035iÞ;¿ÿ|©Ú>\022Cö\013") };
  
  static final byte[][] b = new byte[][] { a("0\002R0\001»\002\004I4~0\r\006\t*H÷\r\001\001\004\005\0000p1\0130\t\006\003U\004\006\023\002US1\0130\t\006\003U\004\b\023\002CA1\0260\024\006\003U\004\007\023\rMountain View1\0240\022\006\003U\004\n\023\013Google, Inc1\0240\022\006\003U\004\013\023\013Google, Inc1\0200\016\006\003U\004\003\023\007Unknown0\036\027\r081202020758Z\027\r360419020758Z0p1\0130\t\006\003U\004\006\023\002US1\0130\t\006\003U\004\b\023\002CA1\0260\024\006\003U\004\007\023\rMountain View1\0240\022\006\003U\004\n\023\013Google, Inc1\0240\022\006\003U\004\013\023\013Google, Inc1\0200\016\006\003U\004\003\023\007Unknown00\r\006\t*H÷\r\001\001\001\005\000\003\0000\002\000H\003\031ù±G&8N\004SÑ\013¿Ç{%\004¤± |LlDº¼\000­Æa\017¦¶«-¨\0163òîñk&£ö¸[úÊû¾³ôÉO~\"§àë§\\í=Ò)úseô\025\026AZ©Áa}ÕÎ\031ºè »Øü\027©´½&@Q!ªÛwÞ´\000\0238\024\030.Å\"üX\r\002\003\001\000\0010\r\006\t*H÷\r\001\001\004\005\000\003\000@fÖ1ÚCÝÐaÒ&às¹Ä¹øµä¾<¾P\036ß\034o©YÀÎ`\\OÒ¬m\034ÎÞ Glº±èò :ÿw\027­e-Ì\007\bÑ!m¨DWY&IàéÓÄ»Lõ¡±ÔüA¼¹XOdæ_A\r\005)ý[h\024\035\nÑÛ\021Ë*\r÷ê\f±-³¤"), a("0\004¨0\003 \003\002\001\002\002\t\000~OòÖµÞ0\r\006\t*H÷\r\001\001\005\005\00001\0130\t\006\003U\004\006\023\002US1\0230\021\006\003U\004\b\023\nCalifornia1\0260\024\006\003U\004\007\023\rMountain View1\0200\016\006\003U\004\n\023\007Android1\0200\016\006\003U\004\013\023\007Android1\0200\016\006\003U\004\003\023\007Android1\"0 \006\t*H÷\r\001\t\001\026\023android@android.com0\036\027\r100120010135Z\027\r370607010135Z01\0130\t\006\003U\004\006\023\002US1\0230\021\006\003U\004\b\023\nCalifornia1\0260\024\006\003U\004\007\023\rMountain View1\0200\016\006\003U\004\n\023\007Android1\0200\016\006\003U\004\013\023\007Android1\0200\016\006\003U\004\003\023\007Android1\"0 \006\t*H÷\r\001\t\001\026\023android@android.com0\001 0\r\006\t*H÷\r\001\001\001\005\000\003\001\r\0000\001\b\002\001\001\000Ø(q|6Ñ\027\017ÔM\n{\017\007\021&è[¿ß3°4`\000ZÌûe¥Û ²Cß`±¿\006ß\035\\\n3âÑcõ\023ß\035\"SAê<3y\"è\\\002ì4ÎÙL¸\007#¦#ÿK¯û´åïæw;>¢¾¸¼²\002gÏçQ\037.ù«uþ\036)Ï¼M\b:\037\022R\000wsò\026[i{\000£ Á:Ì0ò!cÁn=J²\0246LEÀC\0242p9ñÚ\t`ñ³ü\030¶V\020Æ\"_Ç\020+|o\023¤]$ãàÅNgã[g\b'\023ÒÖðWÝ4WÑÄþÝì:O?#\005\031§\n(64¬5£J½¡}Z\n\tûø\006\013\003j'x`cú\f7¹çò¡\016v¼w\002\001\003£ü0ù0\035\006\003U\035\016\004\026\004\024µÇù\022ox\r:ûÊess?õ\"k\02770É\006\003U\035#\004Á0¾\024µÇù\022ox\r:ûÊess?õ\"k\0277¡¤01\0130\t\006\003U\004\006\023\002US1\0230\021\006\003U\004\b\023\nCalifornia1\0260\024\006\003U\004\007\023\rMountain View1\0200\016\006\003U\004\n\023\007Android1\0200\016\006\003U\004\013\023\007Android1\0200\016\006\003U\004\003\023\007Android1\"0 \006\t*H÷\r\001\t\001\026\023android@android.com\t\000~OòÖµÞ0\f\006\003U\035\023\004\0050\003\001\001ÿ0\r\006\t*H÷\r\001\001\005\005\000\003\001\001\000L>§e}&æ»×\021\f\031ß\037¡\t}3\017iÞ¿ÊÛF£~å³\017»4{\034uU¼»<T\024F_y*\002ÐÛå¦Ga³yG«kÿ°ºÆ¢Á Íøbøw©g\rýo\006.@nÎ\030\006\f`Iü6'\021qåoË¡Ræ\005ÎÎY\037Äô©+3ºØ\031mwoU·Ð\032Ï1Ý×\fì·xv\006e\020ùI¥RJ11³ËeAÏ5B\016¼ÄR%Y?Bfi\005rfbO³ÏÛR\027\035\021\034n\003F\026øQ!\030Ð¢¦\023×ðÍ\021ÛÕ#ZT¥JÂQçÒ,Dj?î\024\022\020éDGK@c\007»&+OkÓU\034sQÿ¢`[\005â$×\025Øzö") };
  
  static final byte[][] c = new byte[][] { a("0\002§0\002e \003\002\001\002\002\004P\005|B0\013\006\007*HÎ8\004\003\005\000071\0130\t\006\003U\004\006\023\002US1\0200\016\006\003U\004\n\023\007Android1\0260\024\006\003U\004\003\023\rAndroid Debug0\036\027\r120717145250Z\027\r220715145250Z071\0130\t\006\003U\004\006\023\002US1\0200\016\006\003U\004\n\023\007Android1\0260\024\006\003U\004\003\023\rAndroid Debug0\001·0\001,\006\007*HÎ8\004\0010\001\037\002\000ýS\035u\022)RßJ.ìäçö\021·R<ïD\000Ã\036?¶Q&iE]@\"QûY=Xú¿Åõº0öËUl×;\0354oòf`·kP¥¤è\004{\020\"ÂO»©×þ·Æ\033ø;WçÆ¨¦\025\017\004ûöÓÅ\036Ã\0025T\023Z\0262öuó®+a×*ïò\"\003\031ÑH\001Ç\002\025\000`P\025#\013Ì²¹¢ë\013ðX\034õ\002\000÷á Ö=ÞË¼«\\6¸W¹y¯»ú:êùWL\013=\007gQYWºÔYOæq\007\020´I\026q#èL(\026\023·Ï\t2È¦á<\026zT|(à£®\036+³¦un£\013ú!5bñûbz\001$;Ì¤ñ¾¨Q¨ßáZå\006f^{U%d\001L;þÏI*\003\000\002jÑ\033×ÕfÒzô9À.Ah¬ýE´¾¼{\034wTi?\rB¤üá\0208BO¦Ñ0RNïöñ78c/¦7)þMF ¸feîðA\0279\001\003[\034j£\030\030\r0:¨ÌY#àjo«úuh<E;²\007w|òýçÏ±\02408\024ª\035÷´=[\"+W\006´0\013\006\007*HÎ8\004\003\005\000\003/\0000,\002\024\tÒÑ°G\002)µ¾Ò&aÑ\022òpÅæ\035\002\024gP\002\006§Pºx®Ç\027O\026\004ê¢÷") };
  
  static final byte[][] d = new byte[][] { a("0\004L0\0034 \003\002\001\002\002\t\000¨Í\027É=¥Ù0\r\006\t*H÷\r\001\001\005\005\0000w1\0130\t\006\003U\004\006\023\002US1\0230\021\006\003U\004\b\023\nCalifornia1\0260\024\006\003U\004\007\023\rMountain View1\0240\022\006\003U\004\n\023\013Google Inc.1\0200\016\006\003U\004\013\023\007Android1\0230\021\006\003U\004\003\023\nGoogle NFC0\036\027\r110324010653Z\027\r380809010653Z0w1\0130\t\006\003U\004\006\023\002US1\0230\021\006\003U\004\b\023\nCalifornia1\0260\024\006\003U\004\007\023\rMountain View1\0240\022\006\003U\004\n\023\013Google Inc.1\0200\016\006\003U\004\013\023\007Android1\0230\021\006\003U\004\003\023\nGoogle NFC0\001 0\r\006\t*H÷\r\001\001\001\005\000\003\001\r\0000\001\b\002\001\001\000Ã\017­Ù´\tj,XjZ5kú\002iXøÿ\f]úõI&ØpÞè!¥>\037[\027\017ÉbE£É§ËE'\005;ã^4óÒK\"ì\fRn&teàhuêb\037ù@ã4[ I\007ÌTt:ÍªÎeV_HºtÍA!ÍÈvß5\"ºÛ\t\\ Ù4Åj>\\9>åðà/àb\037\0375¨$%,o¦¶3§hk>Ha-\006©ÏoI¿ñ\035](þ\024¬WbCÝ)êý¹\rã&5\023©\005¬¯ ~Fu\nZ·¿w&/G°?Z<nm{Q4?iÇ÷%÷\013Ì\033JÕ%\013pZæè>â®7þW\001¼½²oîýÿö\017j[ßµ¶G\002\001\003£Ü0Ù0\035\006\003U\035\016\004\026\004\024\034ÎÎ\016êMÁ\022\037ÇQ_\r\n\fràÉm0©\006\003U\035#\004¡0\024\034ÎÎ\016êMÁ\022\037ÇQ_\r\n\fràÉm¡{¤y0w1\0130\t\006\003U\004\006\023\002US1\0230\021\006\003U\004\b\023\nCalifornia1\0260\024\006\003U\004\007\023\rMountain View1\0240\022\006\003U\004\n\023\013Google Inc.1\0200\016\006\003U\004\013\023\007Android1\0230\021\006\003U\004\003\023\nGoogle NFC\t\000¨Í\027É=¥Ù0\f\006\003U\035\023\004\0050\003\001\001ÿ0\r\006\t*H÷\r\001\001\005\005\000\003\001\001\000¤pÇ(áÓ\033\006Ù¯jçhµe\004lWkCrI1×]L¡\f2\025 Ó<Ïí*¦Tb#Lù¶ù\020ÌgkËÖÀgcWO»x3\022uÜ\\óº©\030×\005\037û¢­èó\003ÍèÙæ\004\037Û|*I²\"ÆÿB+ñUi¸^îí°J£\bsÛæKtøòÂöÄ\001$ª¨Ñx\r\030Q+T\nÝ(³éX\031q¤\027\rØhÏ_1äG\022²Â;µ\0207×ï¦å½³^,ëk°\"cl\027¥j¼zP%\013Òí{1UZ\030E.\0272\032\rRö?t-tÿyXj\\»¯q¨KÏtC\020éé'Y\000¢=Ð\006`\f\"8Ù\013/³rßÛºu½."), a("0\004L0\0034 \003\002\001\002\002\t\000Þv\004\035vPÀ0\r\006\t*H÷\r\001\001\005\005\0000w1\0130\t\006\003U\004\006\023\002US1\0230\021\006\003U\004\b\023\nCalifornia1\0260\024\006\003U\004\007\023\rMountain View1\0240\022\006\003U\004\n\023\013Google Inc.1\0200\016\006\003U\004\013\023\007Android1\0230\021\006\003U\004\003\023\nGoogle NFC0\036\027\r110324010324Z\027\r380809010324Z0w1\0130\t\006\003U\004\006\023\002US1\0230\021\006\003U\004\b\023\nCalifornia1\0260\024\006\003U\004\007\023\rMountain View1\0240\022\006\003U\004\n\023\013Google Inc.1\0200\016\006\003U\004\013\023\007Android1\0230\021\006\003U\004\003\023\nGoogle NFC0\001 0\r\006\t*H÷\r\001\001\001\005\000\003\001\r\0000\001\b\002\001\001\000æÿ=ïé*¡\rqë\017¦@À6·âCîíh¦¤v=Ç¥*1u|ÚÆ\037å\020»sÇ\026ä\000\001\004&[4ÎÎôÄ+ñá7Ð¨vð(\"»Áù½Õ×\023²ö©5£yÒË©ÉoÒÐx|\021ñë\031T\b¦ r³Klú\ná'gé\000u0\026i¡\034ïFÎ÷Ç\004mÞ1û`(M\022\n°çÞ\035c?\007h}FQ\023ÿýÆ¼ |©\004¸¾\035 ª{NuoC`d¾\\®<hè»yBÍõ\026\007É0¢üÚe[uÐuº­\006ç9½\013¢\037@BÂÀ¨ZZ°ÐgÆÃìI! B¬c§å;Tle´`´ãæâ>\037wÏçöÞtK\032e\002\001\003£Ü0Ù0\035\006\003U\035\016\004\026\004\024¢èd°]\b\\4Û\n\000P\021zì0©\006\003U\035#\004¡0\024¢èd°]\b\\4Û\n\000P\021zì¡{¤y0w1\0130\t\006\003U\004\006\023\002US1\0230\021\006\003U\004\b\023\nCalifornia1\0260\024\006\003U\004\007\023\rMountain View1\0240\022\006\003U\004\n\023\013Google Inc.1\0200\016\006\003U\004\013\023\007Android1\0230\021\006\003U\004\003\023\nGoogle NFC\t\000Þv\004\035vPÀ0\f\006\003U\035\023\004\0050\003\001\001ÿ0\r\006\t*H÷\r\001\001\005\005\000\003\001\001\0007q\fè|<Rê0ÆébÙKM_\022Â]&\025AýµU]\022Îó¸1,?]ö¨ªàL¹³\005ä'ý\035-\031áÒxñ<R\017\030!\002cØÔ½6QHØØº&Ø¹¿\tõý>»\016£ÂðÉ7o\036\037Êvó¦¤\005B\b\033u*z·Vé«DÚA«ÈáèøÂu§CûsæPqW\fËkzÝ!¹ÆäVá,\"=\\\007JßUö«Ú&-dê\nEîÍ´\022~uÇSÃÿ0ËÆxµ\034R\024rñ}¢\n\rÆ'J¢F44Á©¶\024ßi}õÊ\001ç¢\\}³û\005]eV\004°\0358«ºW³¡p>ÂçJÓ4") };
  
  static final byte[][] e;
  
  public static boolean f;
  
  public static boolean g;
  
  static boolean h;
  
  private static final byte[][] i = a(new byte[][][] { a, b, c, d });
  
  private static final byte[][] j = new byte[][] { a[0], b[0], d[0] };
  
  private static int k;
  
  private static final Object l;
  
  static {
    e = new byte[][] { a("0\002_0\001È \003\002\001\002\002\004K\031±0\r\006\t*H÷\r\001\001\005\005\0000t1\0130\t\006\003U\004\006\023\002US1\0230\021\006\003U\004\b\023\nCalifornia1\0260\024\006\003U\004\007\023\rMountain View1\0250\023\006\003U\004\n\023\fGoogle, Inc.1\0200\016\006\003U\004\013\023\007Unknown1\0170\r\006\003U\004\003\023\006Bazaar0\036\027\r091205010429Z\027\r370422010429Z0t1\0130\t\006\003U\004\006\023\002US1\0230\021\006\003U\004\b\023\nCalifornia1\0260\024\006\003U\004\007\023\rMountain View1\0250\023\006\003U\004\n\023\fGoogle, Inc.1\0200\016\006\003U\004\013\023\007Unknown1\0170\r\006\003U\004\003\023\006Bazaar00\r\006\t*H÷\r\001\001\001\005\000\003\0000\002\000©\bÞã54w\tÝK%\036z)¨G7k.\\º[[Õ\004>\001\002\031\024\023ú3ªåD;\003SJÎJ­oP\022IÙv£~LÌá×\033§¾>ugMµñ\007Zsp\001FH§Îp<-Ç4\005\022¯l[(«ÕOd\021È1¢P\017(\002ÑlæÑopªü¢eA{9\002\003\001\000\0010\r\006\t*H÷\r\001\001\005\005\000\003\000IÆóAG\001#b:'Oéá7=u1Ì\rüé§jæûp[@L½\033Á\026«\030»\021Ãx¿´ólÁLì\035,ÅQj\016ÎÔ\007NµhPd\000¯øÜÈïT\004\022\002ýïñýàó#\020rýÌÞJ6àÆÃù¸³ª\rh<:¿Ú·»2é¾^6\031ºÝ:Ì\003j­µ¦\031¯P") };
    f = false;
    g = false;
    h = false;
    k = -1;
    l = new Object();
  }
  
  public static int a(Context paramContext) {
    PackageManager packageManager = paramContext.getPackageManager();
    try {
      paramContext.getResources().getString(cmv.a);
      if (System.currentTimeMillis() < 1227312000288L)
        return 12; 
    } catch (Throwable throwable) {
      Log.e("GooglePlayServicesUtil", "The Google Play services resources were not found. Check your project configuration to ensure that the resources are included.");
      if (System.currentTimeMillis() < 1227312000288L)
        return 12; 
    } 
    c(paramContext);
    try {
      PackageInfo packageInfo = packageManager.getPackageInfo("com.google.android.gms", 64);
      try {
        PackageInfo packageInfo1 = packageManager.getPackageInfo("com.android.vending", 64);
        byte[] arrayOfByte = a(packageInfo1, a);
        if (arrayOfByte == null) {
          Log.w("GooglePlayServicesUtil", "Google Play Store signature invalid.");
          return 9;
        } 
      } catch (android.content.pm.PackageManager.NameNotFoundException nameNotFoundException) {
        Log.w("GooglePlayServicesUtil", "Google Play Store is missing.");
        return 9;
      } 
    } catch (android.content.pm.PackageManager.NameNotFoundException nameNotFoundException) {
      Log.w("GooglePlayServicesUtil", "Google Play services is missing.");
      return 1;
    } 
  }
  
  public static Intent a(Context paramContext, int paramInt1, int paramInt2) {
    switch (paramInt1) {
      default:
        return null;
      case 1:
      case 2:
        return a(paramInt2) ? (d(paramContext) ? cnd.c("com.google.android.gms") : cnd.b("com.google.android.apps.bazaar")) : cnd.b("com.google.android.gms");
      case 3:
        return cnd.a("com.google.android.gms");
      case 12:
        break;
    } 
    return cnd.a();
  }
  
  public static boolean a() {
    return f ? g : "user".equals(Build.TYPE);
  }
  
  static boolean a(int paramInt) {
    boolean bool2 = true;
    boolean bool1 = bool2;
    switch (b(paramInt)) {
      default:
        bool1 = false;
      case 1:
        return bool1;
      case 0:
        bool1 = bool2;
        if (a())
          return false; 
      case 2:
        break;
    } 
    return false;
  }
  
  private static byte[] a(PackageInfo paramPackageInfo, byte[]... paramVarArgs) {
    CertificateFactory certificateFactory;
    try {
      certificateFactory = CertificateFactory.getInstance("X509");
      if (paramPackageInfo.signatures.length != 1) {
        Log.w("GooglePlayServicesUtil", "Package has more than one signature.");
        return null;
      } 
    } catch (CertificateException certificateException) {
      Log.w("GooglePlayServicesUtil", "Could not get certificate instance.");
      return null;
    } 
    ByteArrayInputStream byteArrayInputStream = new ByteArrayInputStream(((PackageInfo)certificateException).signatures[0].toByteArray());
    try {
      X509Certificate x509Certificate = (X509Certificate)certificateFactory.generateCertificate(byteArrayInputStream);
      try {
        x509Certificate.checkValidity();
        byte[] arrayOfByte = ((PackageInfo)certificateException).signatures[0].toByteArray();
        for (int i = 0; i < paramVarArgs.length; i++) {
          byte[] arrayOfByte1 = paramVarArgs[i];
          if (Arrays.equals(arrayOfByte1, arrayOfByte))
            return arrayOfByte1; 
        } 
      } catch (CertificateExpiredException certificateExpiredException) {
        Log.w("GooglePlayServicesUtil", "Certificate has expired.");
        return null;
      } catch (CertificateNotYetValidException certificateNotYetValidException) {
        Log.w("GooglePlayServicesUtil", "Certificate is not yet valid.");
        return null;
      } 
    } catch (CertificateException certificateException1) {
      Log.w("GooglePlayServicesUtil", "Could not generate certificate.");
      return null;
    } 
  }
  
  private static byte[] a(String paramString) {
    try {
      return paramString.getBytes("ISO-8859-1");
    } catch (UnsupportedEncodingException unsupportedEncodingException) {
      throw new AssertionError(unsupportedEncodingException);
    } 
  }
  
  private static byte[][] a(byte[][]... paramVarArgs) {
    int k = paramVarArgs.length;
    int i = 0;
    int j = 0;
    while (i < k) {
      j += (paramVarArgs[i]).length;
      i++;
    } 
    byte[][] arrayOfByte = new byte[j][];
    int m = paramVarArgs.length;
    j = 0;
    i = 0;
    while (j < m) {
      byte[][] arrayOfByte1 = paramVarArgs[j];
      k = 0;
      while (k < arrayOfByte1.length) {
        arrayOfByte[i] = arrayOfByte1[k];
        k++;
        i++;
      } 
      j++;
    } 
    return arrayOfByte;
  }
  
  private static int b(int paramInt) {
    int i = paramInt;
    if (paramInt == -1)
      i = 2; 
    return i;
  }
  
  public static void b(Context paramContext) {
    int i = a(paramContext);
    if (i != 0) {
      Intent intent = a(paramContext, i, -1);
      Log.e("GooglePlayServicesUtil", "GooglePlayServices not available due to error " + i);
      if (intent == null)
        throw new cmy(i); 
      throw new cmz(i, "Google Play Services not available", intent);
    } 
  }
  
  private static void c(Context paramContext) {
    // Byte code:
    //   0: aconst_null
    //   1: astore_2
    //   2: aload_0
    //   3: invokevirtual getPackageManager : ()Landroid/content/pm/PackageManager;
    //   6: aload_0
    //   7: invokevirtual getPackageName : ()Ljava/lang/String;
    //   10: sipush #128
    //   13: invokevirtual getApplicationInfo : (Ljava/lang/String;I)Landroid/content/pm/ApplicationInfo;
    //   16: astore_0
    //   17: aload_0
    //   18: getfield metaData : Landroid/os/Bundle;
    //   21: astore_0
    //   22: aload_0
    //   23: ifnull -> 115
    //   26: aload_0
    //   27: ldc_w 'com.google.android.gms.version'
    //   30: invokevirtual getInt : (Ljava/lang/String;)I
    //   33: istore_1
    //   34: iload_1
    //   35: ldc 4323000
    //   37: if_icmpne -> 57
    //   40: return
    //   41: astore_0
    //   42: ldc 'GooglePlayServicesUtil'
    //   44: ldc_w 'This should never happen.'
    //   47: aload_0
    //   48: invokestatic wtf : (Ljava/lang/String;Ljava/lang/String;Ljava/lang/Throwable;)I
    //   51: pop
    //   52: aload_2
    //   53: astore_0
    //   54: goto -> 17
    //   57: new java/lang/IllegalStateException
    //   60: dup
    //   61: new java/lang/StringBuilder
    //   64: dup
    //   65: invokespecial <init> : ()V
    //   68: ldc_w 'The meta-data tag in your app's AndroidManifest.xml does not have the right value.  Expected 4323000 but found '
    //   71: invokevirtual append : (Ljava/lang/String;)Ljava/lang/StringBuilder;
    //   74: iload_1
    //   75: invokevirtual append : (I)Ljava/lang/StringBuilder;
    //   78: ldc_w '.  You must have the'
    //   81: invokevirtual append : (Ljava/lang/String;)Ljava/lang/StringBuilder;
    //   84: ldc_w ' following declaration within the <application> element: '
    //   87: invokevirtual append : (Ljava/lang/String;)Ljava/lang/StringBuilder;
    //   90: ldc_w '    <meta-data android:name="'
    //   93: invokevirtual append : (Ljava/lang/String;)Ljava/lang/StringBuilder;
    //   96: ldc_w 'com.google.android.gms.version'
    //   99: invokevirtual append : (Ljava/lang/String;)Ljava/lang/StringBuilder;
    //   102: ldc_w '" android:value="@integer/google_play_services_version" />'
    //   105: invokevirtual append : (Ljava/lang/String;)Ljava/lang/StringBuilder;
    //   108: invokevirtual toString : ()Ljava/lang/String;
    //   111: invokespecial <init> : (Ljava/lang/String;)V
    //   114: athrow
    //   115: new java/lang/IllegalStateException
    //   118: dup
    //   119: ldc_w 'A required meta-data tag in your app's AndroidManifest.xml does not exist.  You must have the following declaration within the <application> element:     <meta-data android:name="com.google.android.gms.version" android:value="@integer/google_play_services_version" />'
    //   122: invokespecial <init> : (Ljava/lang/String;)V
    //   125: athrow
    // Exception table:
    //   from	to	target	type
    //   2	17	41	android/content/pm/PackageManager$NameNotFoundException
  }
  
  private static boolean d(Context paramContext) {
    boolean bool = false;
    if (f)
      return h; 
    try {
      byte[] arrayOfByte = a(paramContext.getPackageManager().getPackageInfo("com.google.android.apps.bazaar", 64), e);
      return (arrayOfByte != null) ? true : bool;
    } catch (android.content.pm.PackageManager.NameNotFoundException nameNotFoundException) {
      return false;
    } 
  }
}


/* Location:              C:\Users\devid\Downloads\SAST\Santander\dex2jar-2.0\classes-dex2jar.jar!\cna.class
 * Java compiler version: 6 (50.0)
 * JD-Core Version:       1.1.3
 */