package com.datami.smi.c;

import android.annotation.SuppressLint;
import android.app.AlarmManager;
import android.app.PendingIntent;
import android.content.Context;
import android.content.Intent;
import android.content.SharedPreferences;
import android.provider.Settings;
import android.util.Log;
import com.datami.smi.NWChangeReceiver;
import com.datami.smi.SmiSdk;
import com.datami.smi.b.k;
import com.datami.smi.g.c;
import java.util.GregorianCalendar;
import org.json.JSONException;
import org.json.JSONObject;

public final class d extends Thread {
  private static final String a = "[dmi]GlobalDiscovery";
  
  private static int b;
  
  private static boolean e;
  
  private static boolean f;
  
  private static final byte[] g = new byte[] { 
      65, -49, 111, 97, 1, 14, 1, -2, 4, -18, 
      13, -5, 21, 6, 4, -12, 0, 12, -75, 69, 
      6, 11, -15, 13, 8, -16, 14, 8, -88, 83, 
      -12, 15, -2, 0, 0, 2, 5, -13, -68, 81, 
      -14, 18, 2, -9, 6, -6, -70, 71, -4, 9, 
      4, -6, 0, -41, -25, -2, -67, 86, -4, -11, 
      -2, 20, -14, 0, -2, 20, -18, 13, -3, -59, 
      71, -13, -1, 19, -2, -12, -55, 63, -5, 21, 
      -2, -67, 71, -4, 9, 4, -6, 0, -67, 88, 
      -13, 12, -11, -71, 70, 14, 1, -2, 4, -55, 
      -25, 3, 0, -2, -2, -67, 81, -14, 18, 2, 
      -13, -68, 84, 3, -17, 1, 3, 15, 1, -12, 
      16, -8, -11, -4, -1, 7, 6, 4, -12, 0, 
      12, -75, 69, 6, 11, -15, 13, 8, -16, 14, 
      8, -88, 83, -12, 15, -2, 0, 0, 6, -13, 
      -42, -25, -21, -13, 18, -13, 14, 5, -12, -5, 
      3, 15, -6, 6, -6, -7, 3, 3, 18, -10, 
      7, 0, 11, -2, 15, 16, 1, -38, 28, 1, 
      3, 11, -3, -6, 19, -10, 2, 6, -6, -70, 
      71, -4, 9, 4, -6, 0, -67, 27, -25, 20, 
      1, 20, -77, 79, -2, -67, 70, 14, 1, -2, 
      4, -55, -25, 6, 4, -12, 0, 12, -75, 69, 
      6, 11, -15, 13, 8, -16, 14, 8, -88, 86, 
      -2, -5, -75, -4, 2, -3, 14, 1, -2, 4, 
      -18, 15, 7, -11, -7, 13, -5, 21, 13, 1, 
      -3, -47, 84, 2, -18, 20, 2, -1, -82, 36, 
      45, -10, 2, -68, 27, -25, -9, 1, 11, 2, 
      -10, -66, 81, -14, 18, 2, -9, 6, -6, -70, 
      71, -4, 9, 4, -6, 0, -41, -25, 13, -2, 
      1, -6, -1, 18, -4, 4, -2, -67, 84, 2, 
      -18, 20, 2, -1, -82, 80, -3, -7, 15, 1, 
      -17, 7, -1, -5, 7, 8, 12, -11, 13, -1, 
      3, 6, 4, -12, 0, 12, -75, 69, 6, 11, 
      -15, 13, 8, -16, 14, 8, -88, 69, -2, 20, 
      -18, -64, 86, -4, -11, -2, 20, -14, 0, -67, 
      88, -13, 12, -11, -71, 70, 14, 1, -2, 4, 
      -81, 83, -12, 15, -2, 0, 0, 6, -13, 10, 
      10, -3, -11, -21, 38, 4, -12, 0, 12, -39, 
      38, 11, -15, 13, 8, -16, 14, 8, 9, 10, 
      3, -14, 8, -7, 8, 0, -8, 9, 10, -14, 
      3, 8, -2, -67, 84, 3, -17, 1, 3, 15, 
      1, -12, 16, -8, -6, 6, -6, 13, 1, -3, 
      -53, -10, 1, 54, 6, 11, -15, 13, 8, -16, 
      14, 8, -74, 54, 10, 4, 7, -16, 10, -3, 
      -58, 55, -2, 20, -18, 13, -3, -58, 54, 13, 
      -1, -61, 72, -69, -18, 20, -18, 4, 12, -11, 
      13, -1, 3, 83, -12, 13, -80, 75, 10, -3, 
      0, -51, -25, -21, 6, 4, -12, 0, 12, -75, 
      69, 6, 11, -15, 13, 8, -16, 14, 8, -88, 
      74, 11, -82, 71, -4, 9, 4, -6, 0, -41, 
      -25, -12, 8, -2, -7, 14, -10, 3, -2, -67, 
      84, 2, -18, 18, 3, -14, 0, 20, -70, 72, 
      14, 1, -2, 4, -46, 45, -10, 2, -9, 1, 
      11, 2, -10, 6, 4, -12, 0, 12, -75, 69, 
      6, 11, -15, 13, 8, -16, 14, 8, -88, 77, 
      -10, 19, 2, -83, 70, 14, 1, -2, 4, -81, 
      68, 13, -10, 2, -42, -25, 9, -10, 4, 0, 
      -4, 7, 14, 1, -2, 4, -18, 13, -5, 21, 
      -2, -16, 13, 13, -10, 2, -1, 21, -1, -13, 
      12, -10, 18, -4, 2, 14, -9, 15, -2, -5, 
      -4, -4, 11, -4, -6, -10, -2, 6, 10, 0, 
      -8 };
  
  private static int h = 170;
  
  private final Context c;
  
  private int d = -2;
  
  static {
    b = 1;
    e = false;
    f = false;
  }
  
  public d(Context paramContext) {
    this.c = paramContext;
  }
  
  private static String a(int paramInt1, int paramInt2, int paramInt3) {
    byte[] arrayOfByte2 = g;
    paramInt1 = 603 - paramInt1;
    paramInt3 = 118 - paramInt3;
    paramInt2 = 49 - paramInt2;
    byte[] arrayOfByte1 = new byte[paramInt2];
    int j = paramInt2 - 1;
    if (arrayOfByte2 == null) {
      paramInt2 = 0;
      i = j;
    } else {
      i = paramInt1;
      paramInt1 = paramInt3;
      paramInt2 = 0;
      arrayOfByte1[paramInt2] = (byte)paramInt1;
      int n = i + 1;
      int i1 = paramInt2 + 1;
    } 
    paramInt3 = paramInt3 + i - 1;
    int i = paramInt1;
    paramInt1 = paramInt3;
    arrayOfByte1[paramInt2] = (byte)paramInt1;
    int k = i + 1;
    int m = paramInt2 + 1;
  }
  
  private static void a(int paramInt) {
    int i;
    char[] arrayOfChar;
    if (262 == paramInt) {
      try {
        if (!f) {
          String str = c.e;
          arrayOfChar = str.toCharArray();
          i = str.length();
          paramInt = 0;
        } else {
          return;
        } 
      } catch (Exception exception) {
        a(h | 0x41, g[178] + 1, g[197]);
        (new StringBuilder()).append(a(421, 32, g[5])).append(exception.getMessage());
        return;
      } 
    } else {
      c.e = Settings.Secure.getString(SmiSdk.mContext.getContentResolver(), a(g[49], -g[379], g[12]));
      return;
    } 
    while (true) {
      if (paramInt < i) {
        if (paramInt < i - 1) {
          char c = arrayOfChar[paramInt];
          arrayOfChar[paramInt] = arrayOfChar[paramInt + 1];
          arrayOfChar[paramInt + 1] = (char)c;
        } 
        paramInt += 2;
        continue;
      } 
      c.e = t.a(new String(arrayOfChar));
      f = true;
      return;
    } 
  }
  
  private void a(long paramLong) {
    GregorianCalendar gregorianCalendar2 = new GregorianCalendar();
    gregorianCalendar2.setTimeInMillis(paramLong);
    GregorianCalendar gregorianCalendar1 = new GregorianCalendar();
    gregorianCalendar1.set(1, gregorianCalendar2.get(1));
    gregorianCalendar1.set(11, gregorianCalendar2.get(11));
    gregorianCalendar1.set(12, gregorianCalendar2.get(12));
    gregorianCalendar1.set(13, gregorianCalendar2.get(13));
    gregorianCalendar1.set(14, gregorianCalendar2.get(14));
    gregorianCalendar1.set(5, gregorianCalendar2.get(5));
    gregorianCalendar1.set(2, gregorianCalendar2.get(2));
    Intent intent = new Intent(this.c, NWChangeReceiver.class);
    intent.setAction(a(h | 0x110, g[374], g[13]));
    PendingIntent pendingIntent = PendingIntent.getBroadcast(this.c, 12345, intent, 268435456);
    ((AlarmManager)this.c.getSystemService(a(g[5], g[260] - 1, g[12]))).set(1, gregorianCalendar1.getTimeInMillis(), pendingIntent);
  }
  
  private void a(String paramString) {
    SharedPreferences sharedPreferences = k.a(this.c);
    SharedPreferences.Editor editor = sharedPreferences.edit();
    int i = c.a();
    a(h | 0x41, g[178] + 1, g[197]);
    StringBuilder stringBuilder = new StringBuilder();
    byte b1 = g[47];
    byte b2 = g[31];
    stringBuilder.append(a(b1, b2, b2)).append(i);
    if (i != 200) {
      editor.putInt(a(599, h & 0x7C, -g[114]), i);
      if (-2 != this.d) {
        i = g[374];
        editor.putInt(a(i, i - 4, -g[114]), this.d);
      } 
      if (paramString != null)
        editor.putString(a(368, g[259], -g[114]), paramString); 
      c.b(sharedPreferences);
      editor.apply();
      editor.commit();
      a(h | 0x41, g[178] + 1, g[197]);
      a(283, g[16], g[31]);
    } 
  }
  
  private void a(String paramString1, String paramString2, String paramString3, String paramString4, String paramString5, long paramLong, JSONObject paramJSONObject1, JSONObject paramJSONObject2) {
    SharedPreferences sharedPreferences = k.a(this.c);
    SharedPreferences.Editor editor = sharedPreferences.edit();
    c.c = null;
    c.c = new b(paramString1, paramString2, paramString3, paramString4, paramString5, paramLong);
    try {
      a a = new a(a(540, h & 0x70, g[41]));
      if (paramString1 != null && paramString1.length() > 8)
        editor.putString(a(480, -g[524], g[125]), a.a(paramString1.trim())); 
      if (paramString2 != null && paramString2.length() > 8)
        editor.putString(a(24, g[260], g[4]), a.a(paramString2.trim())); 
      if (paramString3 != null && paramString3.length() > 8)
        editor.putString(a(425, g[260] - 1, g[12]), a.a(paramString3.trim())); 
      if (paramString4 != null && paramString4.length() > 8)
        editor.putString(a(503, g[260], g[8]), a.a(paramString4.trim())); 
      if (paramString5 != null && paramString5.length() > 8)
        editor.putString(a(316, 40, g[73]), a.a(paramString5.trim())); 
      if (paramLong != -1L)
        if (0L == paramLong) {
          editor.putLong(a(h | 0x14, g[260], g[13]), paramLong);
        } else {
          paramLong = 60L * paramLong * 1000L + System.currentTimeMillis();
          editor.putLong(a(h | 0x14, g[260], g[13]), paramLong);
          a(paramLong);
        }  
      if (paramJSONObject1 != null)
        editor.putString(a(291, g[260], g[49]), paramJSONObject1.toString()); 
      if (paramJSONObject2 != null)
        editor.putString(a(432, -g[524], g[10]), paramJSONObject2.toString()); 
    } catch (Exception exception) {
      a(h | 0x41, g[178] + 1, g[197]);
      exception.getMessage();
    } 
    if (sharedPreferences.contains(a(599, h & 0x7C, -g[114])))
      editor.remove(a(599, h & 0x7C, -g[114])); 
    byte b = g[374];
    if (sharedPreferences.contains(a(b, b - 4, -g[114]))) {
      b = g[374];
      editor.remove(a(b, b - 4, -g[114]));
    } 
    editor.apply();
    editor.commit();
    Log.i(a(h | 0x41, g[178] + 1, g[197]), a(549, -g[379], g[31]));
  }
  
  @SuppressLint({"NewApi"})
  private void a(JSONObject paramJSONObject) {
    String str1;
    String str2 = null;
    try {
      if (paramJSONObject.has(a(g[12], g[260], g[73]))) {
        this.d = paramJSONObject.getInt(a(g[12], g[260], g[73]));
        Log.i(a(h | 0x41, g[178] + 1, g[197]), a(400, -g[379], g[31]) + this.d);
      } 
      str1 = str2;
      if (paramJSONObject.has(a(g[41], g[260] - 1, g[73])))
        str1 = paramJSONObject.getString(a(g[41], g[260] - 1, g[73])); 
    } catch (JSONException jSONException) {
      a(h | 0x41, g[178] + 1, g[197]);
      a(591, g[13], g[31]);
      str1 = str2;
    } 
    a(str1);
  }
  
  protected static boolean a() {
    return e;
  }
  
  private static String b(String paramString) {
    char[] arrayOfChar = paramString.toCharArray();
    int j = paramString.length();
    for (int i = 0; i < j; i += 2) {
      if (i < j - 1) {
        char c = arrayOfChar[i];
        arrayOfChar[i] = arrayOfChar[i + 1];
        arrayOfChar[i + 1] = (char)c;
      } 
    } 
    return new String(arrayOfChar);
  }
  
  private JSONObject b() {
    // Byte code:
    //   0: aload_0
    //   1: getfield c : Landroid/content/Context;
    //   4: sipush #211
    //   7: getstatic com/datami/smi/c/d.g : [B
    //   10: sipush #260
    //   13: baload
    //   14: iconst_1
    //   15: isub
    //   16: getstatic com/datami/smi/c/d.g : [B
    //   19: bipush #13
    //   21: baload
    //   22: invokestatic a : (III)Ljava/lang/String;
    //   25: invokevirtual getSystemService : (Ljava/lang/String;)Ljava/lang/Object;
    //   28: checkcast android/telephony/TelephonyManager
    //   31: astore_3
    //   32: aconst_null
    //   33: astore #5
    //   35: aload_3
    //   36: ifnull -> 776
    //   39: aload_3
    //   40: invokevirtual getSimOperatorName : ()Ljava/lang/String;
    //   43: astore #5
    //   45: aload_3
    //   46: invokevirtual getSimOperator : ()Ljava/lang/String;
    //   49: astore #4
    //   51: iconst_1
    //   52: istore_1
    //   53: aload #4
    //   55: ifnull -> 99
    //   58: aload #4
    //   60: invokevirtual length : ()I
    //   63: iconst_4
    //   64: if_icmple -> 99
    //   67: aload #4
    //   69: iconst_3
    //   70: invokevirtual substring : (I)Ljava/lang/String;
    //   73: sipush #600
    //   76: getstatic com/datami/smi/c/d.g : [B
    //   79: sipush #251
    //   82: baload
    //   83: ineg
    //   84: getstatic com/datami/smi/c/d.g : [B
    //   87: bipush #94
    //   89: baload
    //   90: invokestatic a : (III)Ljava/lang/String;
    //   93: invokevirtual equals : (Ljava/lang/Object;)Z
    //   96: ifeq -> 101
    //   99: iconst_0
    //   100: istore_1
    //   101: iload_1
    //   102: ifne -> 107
    //   105: aconst_null
    //   106: areturn
    //   107: aload #4
    //   109: astore_3
    //   110: aload #4
    //   112: iconst_3
    //   113: invokevirtual substring : (I)Ljava/lang/String;
    //   116: invokestatic parseInt : (Ljava/lang/String;)I
    //   119: istore_1
    //   120: aload #4
    //   122: astore_3
    //   123: aload #4
    //   125: iconst_0
    //   126: iconst_3
    //   127: invokevirtual substring : (II)Ljava/lang/String;
    //   130: invokestatic parseInt : (Ljava/lang/String;)I
    //   133: istore_2
    //   134: aload #4
    //   136: astore_3
    //   137: new java/lang/StringBuilder
    //   140: dup
    //   141: invokespecial <init> : ()V
    //   144: iload_2
    //   145: invokevirtual append : (I)Ljava/lang/StringBuilder;
    //   148: sipush #500
    //   151: bipush #48
    //   153: getstatic com/datami/smi/c/d.g : [B
    //   156: sipush #490
    //   159: baload
    //   160: iconst_1
    //   161: isub
    //   162: invokestatic a : (III)Ljava/lang/String;
    //   165: invokevirtual append : (Ljava/lang/String;)Ljava/lang/StringBuilder;
    //   168: iload_1
    //   169: invokevirtual append : (I)Ljava/lang/StringBuilder;
    //   172: invokevirtual toString : ()Ljava/lang/String;
    //   175: astore #4
    //   177: aload #4
    //   179: astore_3
    //   180: iload_2
    //   181: invokestatic a : (I)V
    //   184: aload #5
    //   186: invokevirtual toLowerCase : ()Ljava/lang/String;
    //   189: astore #5
    //   191: aload #5
    //   193: ifnonnull -> 382
    //   196: ldc_w ''
    //   199: astore_3
    //   200: new org/json/JSONObject
    //   203: dup
    //   204: invokespecial <init> : ()V
    //   207: astore #5
    //   209: aload #5
    //   211: getstatic com/datami/smi/c/d.g : [B
    //   214: sipush #369
    //   217: baload
    //   218: getstatic com/datami/smi/c/d.g : [B
    //   221: sipush #251
    //   224: baload
    //   225: ineg
    //   226: getstatic com/datami/smi/c/d.g : [B
    //   229: bipush #125
    //   231: baload
    //   232: invokestatic a : (III)Ljava/lang/String;
    //   235: aload_3
    //   236: invokevirtual put : (Ljava/lang/String;Ljava/lang/Object;)Lorg/json/JSONObject;
    //   239: pop
    //   240: aload #5
    //   242: getstatic com/datami/smi/c/d.g : [B
    //   245: sipush #549
    //   248: baload
    //   249: iconst_1
    //   250: isub
    //   251: bipush #43
    //   253: getstatic com/datami/smi/c/d.g : [B
    //   256: bipush #49
    //   258: baload
    //   259: invokestatic a : (III)Ljava/lang/String;
    //   262: aload #4
    //   264: invokevirtual put : (Ljava/lang/String;Ljava/lang/Object;)Lorg/json/JSONObject;
    //   267: pop
    //   268: aload #5
    //   270: sipush #429
    //   273: bipush #44
    //   275: getstatic com/datami/smi/c/d.g : [B
    //   278: bipush #12
    //   280: baload
    //   281: invokestatic a : (III)Ljava/lang/String;
    //   284: aload_0
    //   285: getfield c : Landroid/content/Context;
    //   288: invokevirtual getPackageName : ()Ljava/lang/String;
    //   291: invokevirtual put : (Ljava/lang/String;Ljava/lang/Object;)Lorg/json/JSONObject;
    //   294: pop
    //   295: aload #5
    //   297: sipush #482
    //   300: getstatic com/datami/smi/c/d.g : [B
    //   303: sipush #524
    //   306: baload
    //   307: ineg
    //   308: getstatic com/datami/smi/c/d.g : [B
    //   311: iconst_4
    //   312: baload
    //   313: invokestatic a : (III)Ljava/lang/String;
    //   316: getstatic com/datami/smi/c/c.e : Ljava/lang/String;
    //   319: invokevirtual put : (Ljava/lang/String;Ljava/lang/Object;)Lorg/json/JSONObject;
    //   322: pop
    //   323: aload #5
    //   325: areturn
    //   326: astore #4
    //   328: getstatic com/datami/smi/c/d.h : I
    //   331: bipush #65
    //   333: ior
    //   334: getstatic com/datami/smi/c/d.g : [B
    //   337: sipush #178
    //   340: baload
    //   341: iconst_1
    //   342: iadd
    //   343: getstatic com/datami/smi/c/d.g : [B
    //   346: sipush #197
    //   349: baload
    //   350: invokestatic a : (III)Ljava/lang/String;
    //   353: pop
    //   354: sipush #338
    //   357: getstatic com/datami/smi/c/d.g : [B
    //   360: sipush #197
    //   363: baload
    //   364: iconst_1
    //   365: isub
    //   366: getstatic com/datami/smi/c/d.g : [B
    //   369: bipush #49
    //   371: baload
    //   372: invokestatic a : (III)Ljava/lang/String;
    //   375: pop
    //   376: aload_3
    //   377: astore #4
    //   379: goto -> 184
    //   382: aload #5
    //   384: sipush #216
    //   387: bipush #43
    //   389: getstatic com/datami/smi/c/d.g : [B
    //   392: bipush #12
    //   394: baload
    //   395: invokestatic a : (III)Ljava/lang/String;
    //   398: invokevirtual contains : (Ljava/lang/CharSequence;)Z
    //   401: ifeq -> 422
    //   404: sipush #216
    //   407: bipush #43
    //   409: getstatic com/datami/smi/c/d.g : [B
    //   412: bipush #12
    //   414: baload
    //   415: invokestatic a : (III)Ljava/lang/String;
    //   418: astore_3
    //   419: goto -> 200
    //   422: aload #5
    //   424: getstatic com/datami/smi/c/d.g : [B
    //   427: bipush #16
    //   429: baload
    //   430: getstatic com/datami/smi/c/d.g : [B
    //   433: bipush #53
    //   435: baload
    //   436: ineg
    //   437: getstatic com/datami/smi/c/d.g : [B
    //   440: bipush #16
    //   442: baload
    //   443: invokestatic a : (III)Ljava/lang/String;
    //   446: invokevirtual contains : (Ljava/lang/CharSequence;)Z
    //   449: ifeq -> 478
    //   452: getstatic com/datami/smi/c/d.g : [B
    //   455: bipush #16
    //   457: baload
    //   458: getstatic com/datami/smi/c/d.g : [B
    //   461: bipush #53
    //   463: baload
    //   464: ineg
    //   465: getstatic com/datami/smi/c/d.g : [B
    //   468: bipush #16
    //   470: baload
    //   471: invokestatic a : (III)Ljava/lang/String;
    //   474: astore_3
    //   475: goto -> 200
    //   478: aload #5
    //   480: sipush #371
    //   483: getstatic com/datami/smi/c/d.g : [B
    //   486: sipush #260
    //   489: baload
    //   490: getstatic com/datami/smi/c/d.g : [B
    //   493: bipush #10
    //   495: baload
    //   496: invokestatic a : (III)Ljava/lang/String;
    //   499: invokevirtual contains : (Ljava/lang/CharSequence;)Z
    //   502: ifeq -> 528
    //   505: sipush #371
    //   508: getstatic com/datami/smi/c/d.g : [B
    //   511: sipush #260
    //   514: baload
    //   515: getstatic com/datami/smi/c/d.g : [B
    //   518: bipush #10
    //   520: baload
    //   521: invokestatic a : (III)Ljava/lang/String;
    //   524: astore_3
    //   525: goto -> 200
    //   528: aload #5
    //   530: bipush #103
    //   532: getstatic com/datami/smi/c/d.g : [B
    //   535: bipush #53
    //   537: baload
    //   538: ineg
    //   539: getstatic com/datami/smi/c/d.g : [B
    //   542: bipush #8
    //   544: baload
    //   545: invokestatic a : (III)Ljava/lang/String;
    //   548: invokevirtual contains : (Ljava/lang/CharSequence;)Z
    //   551: ifeq -> 576
    //   554: bipush #103
    //   556: getstatic com/datami/smi/c/d.g : [B
    //   559: bipush #53
    //   561: baload
    //   562: ineg
    //   563: getstatic com/datami/smi/c/d.g : [B
    //   566: bipush #8
    //   568: baload
    //   569: invokestatic a : (III)Ljava/lang/String;
    //   572: astore_3
    //   573: goto -> 200
    //   576: aload #5
    //   578: sipush #207
    //   581: bipush #43
    //   583: getstatic com/datami/smi/c/d.g : [B
    //   586: bipush #12
    //   588: baload
    //   589: invokestatic a : (III)Ljava/lang/String;
    //   592: invokevirtual contains : (Ljava/lang/CharSequence;)Z
    //   595: ifeq -> 616
    //   598: sipush #207
    //   601: bipush #43
    //   603: getstatic com/datami/smi/c/d.g : [B
    //   606: bipush #12
    //   608: baload
    //   609: invokestatic a : (III)Ljava/lang/String;
    //   612: astore_3
    //   613: goto -> 200
    //   616: aload #5
    //   618: sipush #288
    //   621: bipush #43
    //   623: getstatic com/datami/smi/c/d.g : [B
    //   626: bipush #41
    //   628: baload
    //   629: invokestatic a : (III)Ljava/lang/String;
    //   632: invokevirtual contains : (Ljava/lang/CharSequence;)Z
    //   635: ifeq -> 662
    //   638: sipush #150
    //   641: getstatic com/datami/smi/c/d.g : [B
    //   644: sipush #379
    //   647: baload
    //   648: ineg
    //   649: getstatic com/datami/smi/c/d.g : [B
    //   652: bipush #35
    //   654: baload
    //   655: invokestatic a : (III)Ljava/lang/String;
    //   658: astore_3
    //   659: goto -> 200
    //   662: aload #5
    //   664: sipush #405
    //   667: getstatic com/datami/smi/c/d.g : [B
    //   670: sipush #524
    //   673: baload
    //   674: ineg
    //   675: getstatic com/datami/smi/c/d.g : [B
    //   678: bipush #12
    //   680: baload
    //   681: invokestatic a : (III)Ljava/lang/String;
    //   684: invokevirtual contains : (Ljava/lang/CharSequence;)Z
    //   687: ifne -> 752
    //   690: aload #5
    //   692: sipush #403
    //   695: getstatic com/datami/smi/c/d.g : [B
    //   698: sipush #260
    //   701: baload
    //   702: getstatic com/datami/smi/c/d.g : [B
    //   705: bipush #12
    //   707: baload
    //   708: invokestatic a : (III)Ljava/lang/String;
    //   711: invokevirtual contains : (Ljava/lang/CharSequence;)Z
    //   714: ifne -> 752
    //   717: aload #5
    //   719: astore_3
    //   720: aload #5
    //   722: getstatic com/datami/smi/c/d.g : [B
    //   725: bipush #89
    //   727: baload
    //   728: iconst_1
    //   729: isub
    //   730: getstatic com/datami/smi/c/d.g : [B
    //   733: sipush #260
    //   736: baload
    //   737: getstatic com/datami/smi/c/d.g : [B
    //   740: bipush #12
    //   742: baload
    //   743: invokestatic a : (III)Ljava/lang/String;
    //   746: invokevirtual contains : (Ljava/lang/CharSequence;)Z
    //   749: ifeq -> 200
    //   752: sipush #405
    //   755: getstatic com/datami/smi/c/d.g : [B
    //   758: sipush #524
    //   761: baload
    //   762: ineg
    //   763: getstatic com/datami/smi/c/d.g : [B
    //   766: bipush #12
    //   768: baload
    //   769: invokestatic a : (III)Ljava/lang/String;
    //   772: astore_3
    //   773: goto -> 200
    //   776: aconst_null
    //   777: astore #4
    //   779: goto -> 51
    // Exception table:
    //   from	to	target	type
    //   110	120	326	java/lang/NumberFormatException
    //   123	134	326	java/lang/NumberFormatException
    //   137	177	326	java/lang/NumberFormatException
    //   180	184	326	java/lang/NumberFormatException
  }
  
  @SuppressLint({"NewApi"})
  private void b(JSONObject paramJSONObject) {
    long l1;
    String str1;
    String str6 = null;
    String str23 = null;
    String str11 = null;
    String str7 = null;
    String str22 = null;
    String str12 = null;
    String str8 = null;
    String str21 = null;
    String str13 = null;
    String str9 = null;
    String str20 = null;
    String str14 = null;
    String str19 = null;
    String str18 = null;
    JSONObject jSONObject4 = null;
    String str17 = null;
    JSONObject jSONObject3 = null;
    String str16 = null;
    long l3 = -1L;
    String str10 = str18;
    String str5 = str23;
    String str4 = str22;
    String str3 = str21;
    String str2 = str20;
    String str15 = str19;
    long l2 = l3;
    JSONObject jSONObject2 = jSONObject4;
    JSONObject jSONObject1 = jSONObject3;
    try {
      JSONObject jSONObject;
      if (paramJSONObject.has(a(449, -g[53], g[101]))) {
        str5 = str23;
        str4 = str22;
        str3 = str21;
        str2 = str20;
        str15 = str19;
        l2 = l3;
        jSONObject2 = jSONObject4;
        jSONObject1 = jSONObject3;
        JSONObject jSONObject5 = paramJSONObject.getJSONObject(a(449, -g[53], g[101]));
        str5 = str23;
        str4 = str22;
        str3 = str21;
        str2 = str20;
        str15 = str19;
        l2 = l3;
        jSONObject2 = jSONObject4;
        jSONObject1 = jSONObject3;
        if (jSONObject5.has(a(480, -g[524], g[125]))) {
          str5 = str23;
          str4 = str22;
          str3 = str21;
          str2 = str20;
          str15 = str19;
          l2 = l3;
          jSONObject2 = jSONObject4;
          jSONObject1 = jSONObject3;
          str11 = jSONObject5.getString(a(480, -g[524], g[125]));
        } 
        str5 = str11;
        str4 = str22;
        str3 = str21;
        str2 = str20;
        str15 = str19;
        l2 = l3;
        jSONObject2 = jSONObject4;
        jSONObject1 = jSONObject3;
        if (jSONObject5.has(a(24, g[260], g[4]))) {
          str5 = str11;
          str4 = str22;
          str3 = str21;
          str2 = str20;
          str15 = str19;
          l2 = l3;
          jSONObject2 = jSONObject4;
          jSONObject1 = jSONObject3;
          str12 = jSONObject5.getString(a(24, g[260], g[4]));
        } 
        str5 = str11;
        str4 = str12;
        str3 = str21;
        str2 = str20;
        str15 = str19;
        l2 = l3;
        jSONObject2 = jSONObject4;
        jSONObject1 = jSONObject3;
        if (jSONObject5.has(a(425, g[260] - 1, g[12]))) {
          str5 = str11;
          str4 = str12;
          str3 = str21;
          str2 = str20;
          str15 = str19;
          l2 = l3;
          jSONObject2 = jSONObject4;
          jSONObject1 = jSONObject3;
          str13 = jSONObject5.getString(a(425, g[260] - 1, g[12]));
        } 
        str5 = str11;
        str4 = str12;
        str3 = str13;
        str2 = str20;
        str15 = str19;
        l2 = l3;
        jSONObject2 = jSONObject4;
        jSONObject1 = jSONObject3;
        if (jSONObject5.has(a(503, g[260], g[8]))) {
          str5 = str11;
          str4 = str12;
          str3 = str13;
          str2 = str20;
          str15 = str19;
          l2 = l3;
          jSONObject2 = jSONObject4;
          jSONObject1 = jSONObject3;
          str14 = jSONObject5.getString(a(503, g[260], g[8]));
        } 
        str6 = str11;
        str7 = str12;
        str8 = str13;
        str9 = str14;
        str10 = str18;
        str5 = str11;
        str4 = str12;
        str3 = str13;
        str2 = str14;
        str15 = str19;
        l2 = l3;
        jSONObject2 = jSONObject4;
        jSONObject1 = jSONObject3;
        if (jSONObject5.has(a(316, 40, g[73]))) {
          str5 = str11;
          str4 = str12;
          str3 = str13;
          str2 = str14;
          str15 = str19;
          l2 = l3;
          jSONObject2 = jSONObject4;
          jSONObject1 = jSONObject3;
          str10 = jSONObject5.getString(a(316, 40, g[73]));
          str9 = str14;
          str8 = str13;
          str7 = str12;
          str6 = str11;
        } 
      } 
      str5 = str6;
      str4 = str7;
      str3 = str8;
      str2 = str9;
      str15 = str10;
      l2 = l3;
      jSONObject2 = jSONObject4;
      jSONObject1 = jSONObject3;
      if (paramJSONObject.has(a(291, g[260], g[49]))) {
        str5 = str6;
        str4 = str7;
        str3 = str8;
        str2 = str9;
        str15 = str10;
        l2 = l3;
        jSONObject2 = jSONObject4;
        jSONObject1 = jSONObject3;
        JSONObject jSONObject5 = paramJSONObject.getJSONObject(a(291, g[260], g[49]));
        str5 = str6;
        str4 = str7;
        str3 = str8;
        str2 = str9;
        str15 = str10;
        l2 = l3;
        jSONObject2 = jSONObject5;
        jSONObject1 = jSONObject3;
        c.a = new o(jSONObject5);
      } else {
        str5 = str6;
        str4 = str7;
        str3 = str8;
        str2 = str9;
        str15 = str10;
        l2 = l3;
        jSONObject2 = jSONObject4;
        jSONObject1 = jSONObject3;
        c.a = new o();
        str11 = str17;
      } 
      l1 = l3;
      str5 = str6;
      str4 = str7;
      str3 = str8;
      str2 = str9;
      str15 = str10;
      l2 = l3;
      str1 = str11;
      jSONObject1 = jSONObject3;
      if (paramJSONObject.has(a(h | 0x14, g[260], g[13]))) {
        str5 = str6;
        str4 = str7;
        str3 = str8;
        str2 = str9;
        str15 = str10;
        l2 = l3;
        str1 = str11;
        jSONObject1 = jSONObject3;
        l1 = paramJSONObject.getLong(a(h | 0x14, g[260], g[13]));
      } 
      str5 = str6;
      str4 = str7;
      str3 = str8;
      str2 = str9;
      str15 = str10;
      l2 = l1;
      str1 = str11;
      jSONObject1 = jSONObject3;
      if (paramJSONObject.has(a(h | 0x104, -g[251], g[41]))) {
        str5 = str6;
        str4 = str7;
        str3 = str8;
        str2 = str9;
        str15 = str10;
        l2 = l1;
        str1 = str11;
        jSONObject1 = jSONObject3;
        e = paramJSONObject.getJSONObject(a(h | 0x104, -g[251], g[41])).getBoolean(a(24, g[260], g[4]));
      } else {
        str5 = str6;
        str4 = str7;
        str3 = str8;
        str2 = str9;
        str15 = str10;
        l2 = l1;
        str1 = str11;
        jSONObject1 = jSONObject3;
        e = false;
      } 
      str12 = str16;
      str5 = str6;
      str4 = str7;
      str3 = str8;
      str2 = str9;
      str15 = str10;
      l2 = l1;
      str1 = str11;
      jSONObject1 = jSONObject3;
      if (paramJSONObject.has(a(432, -g[524], g[10]))) {
        str12 = str16;
        str5 = str6;
        str4 = str7;
        str3 = str8;
        str2 = str9;
        str15 = str10;
        l2 = l1;
        str1 = str11;
        jSONObject1 = jSONObject3;
        if (!paramJSONObject.isNull(a(432, -g[524], g[10]))) {
          str5 = str6;
          str4 = str7;
          str3 = str8;
          str2 = str9;
          str15 = str10;
          l2 = l1;
          str1 = str11;
          jSONObject1 = jSONObject3;
          jSONObject = paramJSONObject.getJSONObject(a(432, -g[524], g[10]));
          str5 = str6;
          str4 = str7;
          str3 = str8;
          str2 = str9;
          str15 = str10;
          l2 = l1;
          str1 = str11;
          jSONObject1 = jSONObject;
          n n = new n(jSONObject);
          str5 = str6;
          str4 = str7;
          str3 = str8;
          str2 = str9;
          str15 = str10;
          l2 = l1;
          str1 = str11;
          jSONObject1 = jSONObject;
          c.b = n;
          str5 = str6;
          str4 = str7;
          str3 = str8;
          str2 = str9;
          str15 = str10;
          l2 = l1;
          str1 = str11;
          jSONObject1 = jSONObject;
          a(Integer.parseInt(n.a()));
        } 
      } 
      str5 = str6;
      str4 = str7;
      str3 = str8;
      str2 = str9;
      str15 = str10;
      l2 = l1;
      str1 = str11;
      jSONObject1 = jSONObject;
      Log.i(a(h | 0x41, g[178] + 1, g[197]), a(500, 30, g[31]));
      jSONObject1 = jSONObject;
      str1 = str11;
      str2 = str9;
      str3 = str8;
      str4 = str7;
      str5 = str6;
    } catch (JSONException jSONException) {}
    a(str5, str4, str3, str2, str10, l1, (JSONObject)str1, jSONObject1);
  }
  
  private static String c(String paramString) {
    if (paramString == null)
      return ""; 
    if (paramString.contains(a(216, 43, g[12])))
      return a(216, 43, g[12]); 
    if (paramString.contains(a(g[16], -g[53], g[16])))
      return a(g[16], -g[53], g[16]); 
    if (paramString.contains(a(371, g[260], g[10])))
      return a(371, g[260], g[10]); 
    if (paramString.contains(a(103, -g[53], g[8])))
      return a(103, -g[53], g[8]); 
    if (paramString.contains(a(207, 43, g[12])))
      return a(207, 43, g[12]); 
    if (paramString.contains(a(288, 43, g[41])))
      return a(150, -g[379], g[35]); 
    if (!paramString.contains(a(405, -g[524], g[12])) && !paramString.contains(a(403, g[260], g[12]))) {
      String str = paramString;
      return paramString.contains(a(g[89] - 1, g[260], g[12])) ? a(405, -g[524], g[12]) : str;
    } 
    return a(405, -g[524], g[12]);
  }
  
  private static boolean d(String paramString) {
    boolean bool = true;
    if (paramString == null || paramString.length() <= 4 || paramString.substring(3).equals(a(600, -g[251], g[94])))
      bool = false; 
    return bool;
  }
  
  public final void run() {
    // Byte code:
    //   0: iconst_0
    //   1: putstatic com/datami/smi/b/m.b : Z
    //   4: getstatic com/datami/smi/c/d.h : I
    //   7: bipush #65
    //   9: ior
    //   10: getstatic com/datami/smi/c/d.g : [B
    //   13: sipush #178
    //   16: baload
    //   17: iconst_1
    //   18: iadd
    //   19: getstatic com/datami/smi/c/d.g : [B
    //   22: sipush #197
    //   25: baload
    //   26: invokestatic a : (III)Ljava/lang/String;
    //   29: getstatic com/datami/smi/c/d.g : [B
    //   32: iconst_3
    //   33: baload
    //   34: iconst_1
    //   35: isub
    //   36: getstatic com/datami/smi/c/d.g : [B
    //   39: sipush #379
    //   42: baload
    //   43: ineg
    //   44: getstatic com/datami/smi/c/d.g : [B
    //   47: bipush #31
    //   49: baload
    //   50: invokestatic a : (III)Ljava/lang/String;
    //   53: invokestatic i : (Ljava/lang/String;Ljava/lang/String;)I
    //   56: pop
    //   57: invokestatic currentTimeMillis : ()J
    //   60: lstore #11
    //   62: iconst_0
    //   63: istore_1
    //   64: lconst_0
    //   65: lstore #5
    //   67: lload #5
    //   69: lstore_3
    //   70: iload_1
    //   71: getstatic com/datami/smi/c/d.b : I
    //   74: if_icmpgt -> 91
    //   77: aload_0
    //   78: invokespecial b : ()Lorg/json/JSONObject;
    //   81: astore #15
    //   83: aload #15
    //   85: ifnonnull -> 111
    //   88: lload #5
    //   90: lstore_3
    //   91: lload_3
    //   92: lload #11
    //   94: lsub
    //   95: lconst_0
    //   96: lcmp
    //   97: ifle -> 110
    //   100: invokestatic a : ()Lcom/datami/smi/a/d;
    //   103: lload_3
    //   104: lload #11
    //   106: lsub
    //   107: invokevirtual c : (J)V
    //   110: return
    //   111: iconst_0
    //   112: istore #13
    //   114: getstatic com/datami/smi/c/d.h : I
    //   117: bipush #17
    //   119: ior
    //   120: getstatic com/datami/smi/c/d.g : [B
    //   123: bipush #21
    //   125: baload
    //   126: getstatic com/datami/smi/c/d.g : [B
    //   129: iconst_5
    //   130: baload
    //   131: invokestatic a : (III)Ljava/lang/String;
    //   134: astore #14
    //   136: getstatic com/datami/smi/c/c.a : Lcom/datami/smi/c/o;
    //   139: ifnull -> 178
    //   142: getstatic com/datami/smi/c/c.a : Lcom/datami/smi/c/o;
    //   145: getstatic com/datami/smi/c/d.h : I
    //   148: bipush #17
    //   150: ior
    //   151: getstatic com/datami/smi/c/d.g : [B
    //   154: bipush #21
    //   156: baload
    //   157: getstatic com/datami/smi/c/d.g : [B
    //   160: iconst_5
    //   161: baload
    //   162: invokestatic a : (III)Ljava/lang/String;
    //   165: invokevirtual a : (Ljava/lang/String;)Ljava/lang/String;
    //   168: astore #14
    //   170: getstatic com/datami/smi/c/c.a : Lcom/datami/smi/c/o;
    //   173: invokevirtual b : ()Z
    //   176: istore #13
    //   178: new java/net/URL
    //   181: dup
    //   182: aload #14
    //   184: invokespecial <init> : (Ljava/lang/String;)V
    //   187: pop
    //   188: getstatic com/datami/smi/c/d.h : I
    //   191: bipush #65
    //   193: ior
    //   194: getstatic com/datami/smi/c/d.g : [B
    //   197: sipush #178
    //   200: baload
    //   201: iconst_1
    //   202: iadd
    //   203: getstatic com/datami/smi/c/d.g : [B
    //   206: sipush #197
    //   209: baload
    //   210: invokestatic a : (III)Ljava/lang/String;
    //   213: pop
    //   214: new java/lang/StringBuilder
    //   217: dup
    //   218: invokespecial <init> : ()V
    //   221: sipush #391
    //   224: getstatic com/datami/smi/c/d.g : [B
    //   227: sipush #178
    //   230: baload
    //   231: getstatic com/datami/smi/c/d.g : [B
    //   234: bipush #31
    //   236: baload
    //   237: invokestatic a : (III)Ljava/lang/String;
    //   240: invokevirtual append : (Ljava/lang/String;)Ljava/lang/StringBuilder;
    //   243: aload #14
    //   245: invokevirtual append : (Ljava/lang/String;)Ljava/lang/StringBuilder;
    //   248: sipush #141
    //   251: getstatic com/datami/smi/c/d.g : [B
    //   254: sipush #374
    //   257: baload
    //   258: iconst_1
    //   259: isub
    //   260: getstatic com/datami/smi/c/d.g : [B
    //   263: bipush #57
    //   265: baload
    //   266: invokestatic a : (III)Ljava/lang/String;
    //   269: invokevirtual append : (Ljava/lang/String;)Ljava/lang/StringBuilder;
    //   272: aload #15
    //   274: invokevirtual toString : ()Ljava/lang/String;
    //   277: invokevirtual append : (Ljava/lang/String;)Ljava/lang/StringBuilder;
    //   280: pop
    //   281: aload_0
    //   282: getfield c : Landroid/content/Context;
    //   285: aload #14
    //   287: aload #15
    //   289: invokevirtual toString : ()Ljava/lang/String;
    //   292: iconst_0
    //   293: iload #13
    //   295: invokestatic a : (Landroid/content/Context;Ljava/lang/String;Ljava/lang/String;ZZ)Ljava/lang/String;
    //   298: astore #14
    //   300: invokestatic currentTimeMillis : ()J
    //   303: lstore_3
    //   304: invokestatic a : ()I
    //   307: istore_2
    //   308: getstatic com/datami/smi/c/d.h : I
    //   311: bipush #65
    //   313: ior
    //   314: getstatic com/datami/smi/c/d.g : [B
    //   317: sipush #178
    //   320: baload
    //   321: iconst_1
    //   322: iadd
    //   323: getstatic com/datami/smi/c/d.g : [B
    //   326: sipush #197
    //   329: baload
    //   330: invokestatic a : (III)Ljava/lang/String;
    //   333: pop
    //   334: new java/lang/StringBuilder
    //   337: dup
    //   338: invokespecial <init> : ()V
    //   341: sipush #478
    //   344: getstatic com/datami/smi/c/d.g : [B
    //   347: bipush #12
    //   349: baload
    //   350: getstatic com/datami/smi/c/d.g : [B
    //   353: bipush #31
    //   355: baload
    //   356: invokestatic a : (III)Ljava/lang/String;
    //   359: invokevirtual append : (Ljava/lang/String;)Ljava/lang/StringBuilder;
    //   362: aload #14
    //   364: invokevirtual append : (Ljava/lang/String;)Ljava/lang/StringBuilder;
    //   367: sipush #356
    //   370: bipush #30
    //   372: getstatic com/datami/smi/c/d.g : [B
    //   375: sipush #524
    //   378: baload
    //   379: ineg
    //   380: invokestatic a : (III)Ljava/lang/String;
    //   383: invokevirtual append : (Ljava/lang/String;)Ljava/lang/StringBuilder;
    //   386: iload_2
    //   387: invokevirtual append : (I)Ljava/lang/StringBuilder;
    //   390: pop
    //   391: new org/json/JSONObject
    //   394: dup
    //   395: aload #14
    //   397: invokespecial <init> : (Ljava/lang/String;)V
    //   400: astore #30
    //   402: sipush #200
    //   405: iload_2
    //   406: if_icmpne -> 3087
    //   409: getstatic com/datami/smi/c/d.h : I
    //   412: bipush #65
    //   414: ior
    //   415: getstatic com/datami/smi/c/d.g : [B
    //   418: sipush #178
    //   421: baload
    //   422: iconst_1
    //   423: iadd
    //   424: getstatic com/datami/smi/c/d.g : [B
    //   427: sipush #197
    //   430: baload
    //   431: invokestatic a : (III)Ljava/lang/String;
    //   434: sipush #308
    //   437: getstatic com/datami/smi/c/d.g : [B
    //   440: sipush #374
    //   443: baload
    //   444: iconst_1
    //   445: isub
    //   446: getstatic com/datami/smi/c/d.g : [B
    //   449: bipush #31
    //   451: baload
    //   452: invokestatic a : (III)Ljava/lang/String;
    //   455: invokestatic i : (Ljava/lang/String;Ljava/lang/String;)I
    //   458: pop
    //   459: aload_0
    //   460: getfield c : Landroid/content/Context;
    //   463: invokestatic a : (Landroid/content/Context;)Landroid/content/SharedPreferences;
    //   466: invokestatic b : (Landroid/content/SharedPreferences;)V
    //   469: aconst_null
    //   470: astore #22
    //   472: aconst_null
    //   473: astore #40
    //   475: aconst_null
    //   476: astore #25
    //   478: aconst_null
    //   479: astore #24
    //   481: aconst_null
    //   482: astore #39
    //   484: aconst_null
    //   485: astore #26
    //   487: aconst_null
    //   488: astore #23
    //   490: aconst_null
    //   491: astore #38
    //   493: aconst_null
    //   494: astore #27
    //   496: aconst_null
    //   497: astore #21
    //   499: aconst_null
    //   500: astore #37
    //   502: aconst_null
    //   503: astore #28
    //   505: aconst_null
    //   506: astore #36
    //   508: aconst_null
    //   509: astore #35
    //   511: aconst_null
    //   512: astore #34
    //   514: aconst_null
    //   515: astore #33
    //   517: aconst_null
    //   518: astore #32
    //   520: aconst_null
    //   521: astore #31
    //   523: ldc2_w -1
    //   526: lstore #9
    //   528: aload #35
    //   530: astore #18
    //   532: aload #32
    //   534: astore #14
    //   536: lload #9
    //   538: lstore #7
    //   540: aload #34
    //   542: astore #17
    //   544: aload #36
    //   546: astore #29
    //   548: aload #37
    //   550: astore #16
    //   552: aload #38
    //   554: astore #20
    //   556: aload #39
    //   558: astore #19
    //   560: aload #40
    //   562: astore #15
    //   564: aload #30
    //   566: sipush #449
    //   569: getstatic com/datami/smi/c/d.g : [B
    //   572: bipush #53
    //   574: baload
    //   575: ineg
    //   576: getstatic com/datami/smi/c/d.g : [B
    //   579: bipush #101
    //   581: baload
    //   582: invokestatic a : (III)Ljava/lang/String;
    //   585: invokevirtual has : (Ljava/lang/String;)Z
    //   588: ifeq -> 1262
    //   591: aload #32
    //   593: astore #14
    //   595: lload #9
    //   597: lstore #7
    //   599: aload #34
    //   601: astore #17
    //   603: aload #36
    //   605: astore #29
    //   607: aload #37
    //   609: astore #16
    //   611: aload #38
    //   613: astore #20
    //   615: aload #39
    //   617: astore #19
    //   619: aload #40
    //   621: astore #15
    //   623: aload #30
    //   625: sipush #449
    //   628: getstatic com/datami/smi/c/d.g : [B
    //   631: bipush #53
    //   633: baload
    //   634: ineg
    //   635: getstatic com/datami/smi/c/d.g : [B
    //   638: bipush #101
    //   640: baload
    //   641: invokestatic a : (III)Ljava/lang/String;
    //   644: invokevirtual getJSONObject : (Ljava/lang/String;)Lorg/json/JSONObject;
    //   647: astore #41
    //   649: aload #32
    //   651: astore #14
    //   653: lload #9
    //   655: lstore #7
    //   657: aload #34
    //   659: astore #17
    //   661: aload #36
    //   663: astore #29
    //   665: aload #37
    //   667: astore #16
    //   669: aload #38
    //   671: astore #20
    //   673: aload #39
    //   675: astore #19
    //   677: aload #40
    //   679: astore #15
    //   681: aload #41
    //   683: sipush #480
    //   686: getstatic com/datami/smi/c/d.g : [B
    //   689: sipush #524
    //   692: baload
    //   693: ineg
    //   694: getstatic com/datami/smi/c/d.g : [B
    //   697: bipush #125
    //   699: baload
    //   700: invokestatic a : (III)Ljava/lang/String;
    //   703: invokevirtual has : (Ljava/lang/String;)Z
    //   706: ifeq -> 768
    //   709: aload #32
    //   711: astore #14
    //   713: lload #9
    //   715: lstore #7
    //   717: aload #34
    //   719: astore #17
    //   721: aload #36
    //   723: astore #29
    //   725: aload #37
    //   727: astore #16
    //   729: aload #38
    //   731: astore #20
    //   733: aload #39
    //   735: astore #19
    //   737: aload #40
    //   739: astore #15
    //   741: aload #41
    //   743: sipush #480
    //   746: getstatic com/datami/smi/c/d.g : [B
    //   749: sipush #524
    //   752: baload
    //   753: ineg
    //   754: getstatic com/datami/smi/c/d.g : [B
    //   757: bipush #125
    //   759: baload
    //   760: invokestatic a : (III)Ljava/lang/String;
    //   763: invokevirtual getString : (Ljava/lang/String;)Ljava/lang/String;
    //   766: astore #25
    //   768: aload #32
    //   770: astore #14
    //   772: lload #9
    //   774: lstore #7
    //   776: aload #34
    //   778: astore #17
    //   780: aload #36
    //   782: astore #29
    //   784: aload #37
    //   786: astore #16
    //   788: aload #38
    //   790: astore #20
    //   792: aload #39
    //   794: astore #19
    //   796: aload #25
    //   798: astore #15
    //   800: aload #41
    //   802: bipush #24
    //   804: getstatic com/datami/smi/c/d.g : [B
    //   807: sipush #260
    //   810: baload
    //   811: getstatic com/datami/smi/c/d.g : [B
    //   814: iconst_4
    //   815: baload
    //   816: invokestatic a : (III)Ljava/lang/String;
    //   819: invokevirtual has : (Ljava/lang/String;)Z
    //   822: ifeq -> 881
    //   825: aload #32
    //   827: astore #14
    //   829: lload #9
    //   831: lstore #7
    //   833: aload #34
    //   835: astore #17
    //   837: aload #36
    //   839: astore #29
    //   841: aload #37
    //   843: astore #16
    //   845: aload #38
    //   847: astore #20
    //   849: aload #39
    //   851: astore #19
    //   853: aload #25
    //   855: astore #15
    //   857: aload #41
    //   859: bipush #24
    //   861: getstatic com/datami/smi/c/d.g : [B
    //   864: sipush #260
    //   867: baload
    //   868: getstatic com/datami/smi/c/d.g : [B
    //   871: iconst_4
    //   872: baload
    //   873: invokestatic a : (III)Ljava/lang/String;
    //   876: invokevirtual getString : (Ljava/lang/String;)Ljava/lang/String;
    //   879: astore #26
    //   881: aload #32
    //   883: astore #14
    //   885: lload #9
    //   887: lstore #7
    //   889: aload #34
    //   891: astore #17
    //   893: aload #36
    //   895: astore #29
    //   897: aload #37
    //   899: astore #16
    //   901: aload #38
    //   903: astore #20
    //   905: aload #26
    //   907: astore #19
    //   909: aload #25
    //   911: astore #15
    //   913: aload #41
    //   915: sipush #425
    //   918: getstatic com/datami/smi/c/d.g : [B
    //   921: sipush #260
    //   924: baload
    //   925: iconst_1
    //   926: isub
    //   927: getstatic com/datami/smi/c/d.g : [B
    //   930: bipush #12
    //   932: baload
    //   933: invokestatic a : (III)Ljava/lang/String;
    //   936: invokevirtual has : (Ljava/lang/String;)Z
    //   939: ifeq -> 1002
    //   942: aload #32
    //   944: astore #14
    //   946: lload #9
    //   948: lstore #7
    //   950: aload #34
    //   952: astore #17
    //   954: aload #36
    //   956: astore #29
    //   958: aload #37
    //   960: astore #16
    //   962: aload #38
    //   964: astore #20
    //   966: aload #26
    //   968: astore #19
    //   970: aload #25
    //   972: astore #15
    //   974: aload #41
    //   976: sipush #425
    //   979: getstatic com/datami/smi/c/d.g : [B
    //   982: sipush #260
    //   985: baload
    //   986: iconst_1
    //   987: isub
    //   988: getstatic com/datami/smi/c/d.g : [B
    //   991: bipush #12
    //   993: baload
    //   994: invokestatic a : (III)Ljava/lang/String;
    //   997: invokevirtual getString : (Ljava/lang/String;)Ljava/lang/String;
    //   1000: astore #27
    //   1002: aload #32
    //   1004: astore #14
    //   1006: lload #9
    //   1008: lstore #7
    //   1010: aload #34
    //   1012: astore #17
    //   1014: aload #36
    //   1016: astore #29
    //   1018: aload #37
    //   1020: astore #16
    //   1022: aload #27
    //   1024: astore #20
    //   1026: aload #26
    //   1028: astore #19
    //   1030: aload #25
    //   1032: astore #15
    //   1034: aload #41
    //   1036: sipush #503
    //   1039: getstatic com/datami/smi/c/d.g : [B
    //   1042: sipush #260
    //   1045: baload
    //   1046: getstatic com/datami/smi/c/d.g : [B
    //   1049: bipush #8
    //   1051: baload
    //   1052: invokestatic a : (III)Ljava/lang/String;
    //   1055: invokevirtual has : (Ljava/lang/String;)Z
    //   1058: ifeq -> 1119
    //   1061: aload #32
    //   1063: astore #14
    //   1065: lload #9
    //   1067: lstore #7
    //   1069: aload #34
    //   1071: astore #17
    //   1073: aload #36
    //   1075: astore #29
    //   1077: aload #37
    //   1079: astore #16
    //   1081: aload #27
    //   1083: astore #20
    //   1085: aload #26
    //   1087: astore #19
    //   1089: aload #25
    //   1091: astore #15
    //   1093: aload #41
    //   1095: sipush #503
    //   1098: getstatic com/datami/smi/c/d.g : [B
    //   1101: sipush #260
    //   1104: baload
    //   1105: getstatic com/datami/smi/c/d.g : [B
    //   1108: bipush #8
    //   1110: baload
    //   1111: invokestatic a : (III)Ljava/lang/String;
    //   1114: invokevirtual getString : (Ljava/lang/String;)Ljava/lang/String;
    //   1117: astore #28
    //   1119: aload #35
    //   1121: astore #18
    //   1123: aload #28
    //   1125: astore #21
    //   1127: aload #27
    //   1129: astore #23
    //   1131: aload #26
    //   1133: astore #24
    //   1135: aload #25
    //   1137: astore #22
    //   1139: aload #32
    //   1141: astore #14
    //   1143: lload #9
    //   1145: lstore #7
    //   1147: aload #34
    //   1149: astore #17
    //   1151: aload #36
    //   1153: astore #29
    //   1155: aload #28
    //   1157: astore #16
    //   1159: aload #27
    //   1161: astore #20
    //   1163: aload #26
    //   1165: astore #19
    //   1167: aload #25
    //   1169: astore #15
    //   1171: aload #41
    //   1173: sipush #316
    //   1176: bipush #40
    //   1178: getstatic com/datami/smi/c/d.g : [B
    //   1181: bipush #73
    //   1183: baload
    //   1184: invokestatic a : (III)Ljava/lang/String;
    //   1187: invokevirtual has : (Ljava/lang/String;)Z
    //   1190: ifeq -> 1262
    //   1193: aload #32
    //   1195: astore #14
    //   1197: lload #9
    //   1199: lstore #7
    //   1201: aload #34
    //   1203: astore #17
    //   1205: aload #36
    //   1207: astore #29
    //   1209: aload #28
    //   1211: astore #16
    //   1213: aload #27
    //   1215: astore #20
    //   1217: aload #26
    //   1219: astore #19
    //   1221: aload #25
    //   1223: astore #15
    //   1225: aload #41
    //   1227: sipush #316
    //   1230: bipush #40
    //   1232: getstatic com/datami/smi/c/d.g : [B
    //   1235: bipush #73
    //   1237: baload
    //   1238: invokestatic a : (III)Ljava/lang/String;
    //   1241: invokevirtual getString : (Ljava/lang/String;)Ljava/lang/String;
    //   1244: astore #18
    //   1246: aload #25
    //   1248: astore #22
    //   1250: aload #26
    //   1252: astore #24
    //   1254: aload #27
    //   1256: astore #23
    //   1258: aload #28
    //   1260: astore #21
    //   1262: aload #32
    //   1264: astore #14
    //   1266: lload #9
    //   1268: lstore #7
    //   1270: aload #34
    //   1272: astore #17
    //   1274: aload #18
    //   1276: astore #29
    //   1278: aload #21
    //   1280: astore #16
    //   1282: aload #23
    //   1284: astore #20
    //   1286: aload #24
    //   1288: astore #19
    //   1290: aload #22
    //   1292: astore #15
    //   1294: aload #30
    //   1296: sipush #291
    //   1299: getstatic com/datami/smi/c/d.g : [B
    //   1302: sipush #260
    //   1305: baload
    //   1306: getstatic com/datami/smi/c/d.g : [B
    //   1309: bipush #49
    //   1311: baload
    //   1312: invokestatic a : (III)Ljava/lang/String;
    //   1315: invokevirtual has : (Ljava/lang/String;)Z
    //   1318: ifeq -> 2226
    //   1321: aload #32
    //   1323: astore #14
    //   1325: lload #9
    //   1327: lstore #7
    //   1329: aload #34
    //   1331: astore #17
    //   1333: aload #18
    //   1335: astore #29
    //   1337: aload #21
    //   1339: astore #16
    //   1341: aload #23
    //   1343: astore #20
    //   1345: aload #24
    //   1347: astore #19
    //   1349: aload #22
    //   1351: astore #15
    //   1353: aload #30
    //   1355: sipush #291
    //   1358: getstatic com/datami/smi/c/d.g : [B
    //   1361: sipush #260
    //   1364: baload
    //   1365: getstatic com/datami/smi/c/d.g : [B
    //   1368: bipush #49
    //   1370: baload
    //   1371: invokestatic a : (III)Ljava/lang/String;
    //   1374: invokevirtual getJSONObject : (Ljava/lang/String;)Lorg/json/JSONObject;
    //   1377: astore #26
    //   1379: aload #32
    //   1381: astore #14
    //   1383: lload #9
    //   1385: lstore #7
    //   1387: aload #26
    //   1389: astore #17
    //   1391: aload #18
    //   1393: astore #29
    //   1395: aload #21
    //   1397: astore #16
    //   1399: aload #23
    //   1401: astore #20
    //   1403: aload #24
    //   1405: astore #19
    //   1407: aload #22
    //   1409: astore #15
    //   1411: new com/datami/smi/c/o
    //   1414: dup
    //   1415: aload #26
    //   1417: invokespecial <init> : (Lorg/json/JSONObject;)V
    //   1420: putstatic com/datami/smi/c/c.a : Lcom/datami/smi/c/o;
    //   1423: lload #9
    //   1425: lstore #5
    //   1427: aload #32
    //   1429: astore #14
    //   1431: lload #9
    //   1433: lstore #7
    //   1435: aload #26
    //   1437: astore #17
    //   1439: aload #18
    //   1441: astore #29
    //   1443: aload #21
    //   1445: astore #16
    //   1447: aload #23
    //   1449: astore #20
    //   1451: aload #24
    //   1453: astore #19
    //   1455: aload #22
    //   1457: astore #15
    //   1459: aload #30
    //   1461: getstatic com/datami/smi/c/d.h : I
    //   1464: bipush #20
    //   1466: ior
    //   1467: getstatic com/datami/smi/c/d.g : [B
    //   1470: sipush #260
    //   1473: baload
    //   1474: getstatic com/datami/smi/c/d.g : [B
    //   1477: bipush #13
    //   1479: baload
    //   1480: invokestatic a : (III)Ljava/lang/String;
    //   1483: invokevirtual has : (Ljava/lang/String;)Z
    //   1486: ifeq -> 1550
    //   1489: aload #32
    //   1491: astore #14
    //   1493: lload #9
    //   1495: lstore #7
    //   1497: aload #26
    //   1499: astore #17
    //   1501: aload #18
    //   1503: astore #29
    //   1505: aload #21
    //   1507: astore #16
    //   1509: aload #23
    //   1511: astore #20
    //   1513: aload #24
    //   1515: astore #19
    //   1517: aload #22
    //   1519: astore #15
    //   1521: aload #30
    //   1523: getstatic com/datami/smi/c/d.h : I
    //   1526: bipush #20
    //   1528: ior
    //   1529: getstatic com/datami/smi/c/d.g : [B
    //   1532: sipush #260
    //   1535: baload
    //   1536: getstatic com/datami/smi/c/d.g : [B
    //   1539: bipush #13
    //   1541: baload
    //   1542: invokestatic a : (III)Ljava/lang/String;
    //   1545: invokevirtual getLong : (Ljava/lang/String;)J
    //   1548: lstore #5
    //   1550: aload #32
    //   1552: astore #14
    //   1554: lload #5
    //   1556: lstore #7
    //   1558: aload #26
    //   1560: astore #17
    //   1562: aload #18
    //   1564: astore #29
    //   1566: aload #21
    //   1568: astore #16
    //   1570: aload #23
    //   1572: astore #20
    //   1574: aload #24
    //   1576: astore #19
    //   1578: aload #22
    //   1580: astore #15
    //   1582: aload #30
    //   1584: getstatic com/datami/smi/c/d.h : I
    //   1587: sipush #260
    //   1590: ior
    //   1591: getstatic com/datami/smi/c/d.g : [B
    //   1594: sipush #251
    //   1597: baload
    //   1598: ineg
    //   1599: getstatic com/datami/smi/c/d.g : [B
    //   1602: bipush #41
    //   1604: baload
    //   1605: invokestatic a : (III)Ljava/lang/String;
    //   1608: invokevirtual has : (Ljava/lang/String;)Z
    //   1611: ifeq -> 2480
    //   1614: aload #32
    //   1616: astore #14
    //   1618: lload #5
    //   1620: lstore #7
    //   1622: aload #26
    //   1624: astore #17
    //   1626: aload #18
    //   1628: astore #29
    //   1630: aload #21
    //   1632: astore #16
    //   1634: aload #23
    //   1636: astore #20
    //   1638: aload #24
    //   1640: astore #19
    //   1642: aload #22
    //   1644: astore #15
    //   1646: aload #30
    //   1648: getstatic com/datami/smi/c/d.h : I
    //   1651: sipush #260
    //   1654: ior
    //   1655: getstatic com/datami/smi/c/d.g : [B
    //   1658: sipush #251
    //   1661: baload
    //   1662: ineg
    //   1663: getstatic com/datami/smi/c/d.g : [B
    //   1666: bipush #41
    //   1668: baload
    //   1669: invokestatic a : (III)Ljava/lang/String;
    //   1672: invokevirtual getJSONObject : (Ljava/lang/String;)Lorg/json/JSONObject;
    //   1675: bipush #24
    //   1677: getstatic com/datami/smi/c/d.g : [B
    //   1680: sipush #260
    //   1683: baload
    //   1684: getstatic com/datami/smi/c/d.g : [B
    //   1687: iconst_4
    //   1688: baload
    //   1689: invokestatic a : (III)Ljava/lang/String;
    //   1692: invokevirtual getBoolean : (Ljava/lang/String;)Z
    //   1695: putstatic com/datami/smi/c/d.e : Z
    //   1698: aload #31
    //   1700: astore #25
    //   1702: aload #32
    //   1704: astore #14
    //   1706: lload #5
    //   1708: lstore #7
    //   1710: aload #26
    //   1712: astore #17
    //   1714: aload #18
    //   1716: astore #29
    //   1718: aload #21
    //   1720: astore #16
    //   1722: aload #23
    //   1724: astore #20
    //   1726: aload #24
    //   1728: astore #19
    //   1730: aload #22
    //   1732: astore #15
    //   1734: aload #30
    //   1736: sipush #432
    //   1739: getstatic com/datami/smi/c/d.g : [B
    //   1742: sipush #524
    //   1745: baload
    //   1746: ineg
    //   1747: getstatic com/datami/smi/c/d.g : [B
    //   1750: bipush #10
    //   1752: baload
    //   1753: invokestatic a : (III)Ljava/lang/String;
    //   1756: invokevirtual has : (Ljava/lang/String;)Z
    //   1759: ifeq -> 2008
    //   1762: aload #31
    //   1764: astore #25
    //   1766: aload #32
    //   1768: astore #14
    //   1770: lload #5
    //   1772: lstore #7
    //   1774: aload #26
    //   1776: astore #17
    //   1778: aload #18
    //   1780: astore #29
    //   1782: aload #21
    //   1784: astore #16
    //   1786: aload #23
    //   1788: astore #20
    //   1790: aload #24
    //   1792: astore #19
    //   1794: aload #22
    //   1796: astore #15
    //   1798: aload #30
    //   1800: sipush #432
    //   1803: getstatic com/datami/smi/c/d.g : [B
    //   1806: sipush #524
    //   1809: baload
    //   1810: ineg
    //   1811: getstatic com/datami/smi/c/d.g : [B
    //   1814: bipush #10
    //   1816: baload
    //   1817: invokestatic a : (III)Ljava/lang/String;
    //   1820: invokevirtual isNull : (Ljava/lang/String;)Z
    //   1823: ifne -> 2008
    //   1826: aload #32
    //   1828: astore #14
    //   1830: lload #5
    //   1832: lstore #7
    //   1834: aload #26
    //   1836: astore #17
    //   1838: aload #18
    //   1840: astore #29
    //   1842: aload #21
    //   1844: astore #16
    //   1846: aload #23
    //   1848: astore #20
    //   1850: aload #24
    //   1852: astore #19
    //   1854: aload #22
    //   1856: astore #15
    //   1858: aload #30
    //   1860: sipush #432
    //   1863: getstatic com/datami/smi/c/d.g : [B
    //   1866: sipush #524
    //   1869: baload
    //   1870: ineg
    //   1871: getstatic com/datami/smi/c/d.g : [B
    //   1874: bipush #10
    //   1876: baload
    //   1877: invokestatic a : (III)Ljava/lang/String;
    //   1880: invokevirtual getJSONObject : (Ljava/lang/String;)Lorg/json/JSONObject;
    //   1883: astore #25
    //   1885: aload #25
    //   1887: astore #14
    //   1889: lload #5
    //   1891: lstore #7
    //   1893: aload #26
    //   1895: astore #17
    //   1897: aload #18
    //   1899: astore #29
    //   1901: aload #21
    //   1903: astore #16
    //   1905: aload #23
    //   1907: astore #20
    //   1909: aload #24
    //   1911: astore #19
    //   1913: aload #22
    //   1915: astore #15
    //   1917: new com/datami/smi/c/n
    //   1920: dup
    //   1921: aload #25
    //   1923: invokespecial <init> : (Lorg/json/JSONObject;)V
    //   1926: astore #27
    //   1928: aload #25
    //   1930: astore #14
    //   1932: lload #5
    //   1934: lstore #7
    //   1936: aload #26
    //   1938: astore #17
    //   1940: aload #18
    //   1942: astore #29
    //   1944: aload #21
    //   1946: astore #16
    //   1948: aload #23
    //   1950: astore #20
    //   1952: aload #24
    //   1954: astore #19
    //   1956: aload #22
    //   1958: astore #15
    //   1960: aload #27
    //   1962: putstatic com/datami/smi/c/c.b : Lcom/datami/smi/c/n;
    //   1965: aload #25
    //   1967: astore #14
    //   1969: lload #5
    //   1971: lstore #7
    //   1973: aload #26
    //   1975: astore #17
    //   1977: aload #18
    //   1979: astore #29
    //   1981: aload #21
    //   1983: astore #16
    //   1985: aload #23
    //   1987: astore #20
    //   1989: aload #24
    //   1991: astore #19
    //   1993: aload #22
    //   1995: astore #15
    //   1997: aload #27
    //   1999: invokevirtual a : ()Ljava/lang/String;
    //   2002: invokestatic parseInt : (Ljava/lang/String;)I
    //   2005: invokestatic a : (I)V
    //   2008: aload #25
    //   2010: astore #14
    //   2012: lload #5
    //   2014: lstore #7
    //   2016: aload #26
    //   2018: astore #17
    //   2020: aload #18
    //   2022: astore #29
    //   2024: aload #21
    //   2026: astore #16
    //   2028: aload #23
    //   2030: astore #20
    //   2032: aload #24
    //   2034: astore #19
    //   2036: aload #22
    //   2038: astore #15
    //   2040: getstatic com/datami/smi/c/d.h : I
    //   2043: bipush #65
    //   2045: ior
    //   2046: getstatic com/datami/smi/c/d.g : [B
    //   2049: sipush #178
    //   2052: baload
    //   2053: iconst_1
    //   2054: iadd
    //   2055: getstatic com/datami/smi/c/d.g : [B
    //   2058: sipush #197
    //   2061: baload
    //   2062: invokestatic a : (III)Ljava/lang/String;
    //   2065: sipush #500
    //   2068: bipush #30
    //   2070: getstatic com/datami/smi/c/d.g : [B
    //   2073: bipush #31
    //   2075: baload
    //   2076: invokestatic a : (III)Ljava/lang/String;
    //   2079: invokestatic i : (Ljava/lang/String;Ljava/lang/String;)I
    //   2082: pop
    //   2083: aload #26
    //   2085: astore #17
    //   2087: aload #21
    //   2089: astore #14
    //   2091: aload #25
    //   2093: astore #15
    //   2095: aload #23
    //   2097: astore #20
    //   2099: aload_0
    //   2100: aload #22
    //   2102: aload #24
    //   2104: aload #20
    //   2106: aload #14
    //   2108: aload #18
    //   2110: lload #5
    //   2112: aload #17
    //   2114: aload #15
    //   2116: invokespecial a : (Ljava/lang/String;Ljava/lang/String;Ljava/lang/String;Ljava/lang/String;Ljava/lang/String;JLorg/json/JSONObject;Lorg/json/JSONObject;)V
    //   2119: iconst_1
    //   2120: putstatic com/datami/smi/c/c.d : I
    //   2123: new java/util/Properties
    //   2126: dup
    //   2127: invokespecial <init> : ()V
    //   2130: astore #14
    //   2132: aload #14
    //   2134: sipush #451
    //   2137: getstatic com/datami/smi/c/d.g : [B
    //   2140: sipush #524
    //   2143: baload
    //   2144: ineg
    //   2145: getstatic com/datami/smi/c/d.g : [B
    //   2148: bipush #101
    //   2150: baload
    //   2151: invokestatic a : (III)Ljava/lang/String;
    //   2154: getstatic com/datami/smi/d/c.a : Lcom/datami/smi/d/c;
    //   2157: invokestatic a : (Lcom/datami/smi/d/c;)Ljava/lang/String;
    //   2160: invokevirtual put : (Ljava/lang/Object;Ljava/lang/Object;)Ljava/lang/Object;
    //   2163: pop
    //   2164: getstatic com/datami/smi/d/d.a : Lcom/datami/smi/d/d;
    //   2167: invokestatic a : (Lcom/datami/smi/d/d;)Ljava/lang/String;
    //   2170: aload #14
    //   2172: invokestatic b : (Ljava/lang/String;Ljava/util/Properties;)V
    //   2175: getstatic com/datami/smi/c/d.h : I
    //   2178: bipush #65
    //   2180: ior
    //   2181: getstatic com/datami/smi/c/d.g : [B
    //   2184: sipush #178
    //   2187: baload
    //   2188: iconst_1
    //   2189: iadd
    //   2190: getstatic com/datami/smi/c/d.g : [B
    //   2193: sipush #197
    //   2196: baload
    //   2197: invokestatic a : (III)Ljava/lang/String;
    //   2200: sipush #202
    //   2203: getstatic com/datami/smi/c/d.g : [B
    //   2206: sipush #259
    //   2209: baload
    //   2210: getstatic com/datami/smi/c/d.g : [B
    //   2213: bipush #31
    //   2215: baload
    //   2216: invokestatic a : (III)Ljava/lang/String;
    //   2219: invokestatic i : (Ljava/lang/String;Ljava/lang/String;)I
    //   2222: pop
    //   2223: goto -> 91
    //   2226: aload #32
    //   2228: astore #14
    //   2230: lload #9
    //   2232: lstore #7
    //   2234: aload #34
    //   2236: astore #17
    //   2238: aload #18
    //   2240: astore #29
    //   2242: aload #21
    //   2244: astore #16
    //   2246: aload #23
    //   2248: astore #20
    //   2250: aload #24
    //   2252: astore #19
    //   2254: aload #22
    //   2256: astore #15
    //   2258: new com/datami/smi/c/o
    //   2261: dup
    //   2262: invokespecial <init> : ()V
    //   2265: putstatic com/datami/smi/c/c.a : Lcom/datami/smi/c/o;
    //   2268: aload #33
    //   2270: astore #26
    //   2272: goto -> 1423
    //   2275: astore #18
    //   2277: getstatic com/datami/smi/c/c.a : Lcom/datami/smi/c/o;
    //   2280: ifnonnull -> 2293
    //   2283: new com/datami/smi/c/o
    //   2286: dup
    //   2287: invokespecial <init> : ()V
    //   2290: putstatic com/datami/smi/c/c.a : Lcom/datami/smi/c/o;
    //   2293: getstatic com/datami/smi/c/c.b : Lcom/datami/smi/c/n;
    //   2296: ifnonnull -> 2309
    //   2299: new com/datami/smi/c/n
    //   2302: dup
    //   2303: invokespecial <init> : ()V
    //   2306: putstatic com/datami/smi/c/c.b : Lcom/datami/smi/c/n;
    //   2309: new java/util/Properties
    //   2312: dup
    //   2313: invokespecial <init> : ()V
    //   2316: astore #21
    //   2318: sipush #297
    //   2321: getstatic com/datami/smi/c/d.g : [B
    //   2324: sipush #150
    //   2327: baload
    //   2328: ineg
    //   2329: getstatic com/datami/smi/c/d.g : [B
    //   2332: bipush #49
    //   2334: baload
    //   2335: invokestatic a : (III)Ljava/lang/String;
    //   2338: astore #22
    //   2340: aload #18
    //   2342: invokevirtual getMessage : ()Ljava/lang/String;
    //   2345: ifnull -> 3077
    //   2348: aload #18
    //   2350: invokevirtual getMessage : ()Ljava/lang/String;
    //   2353: astore #18
    //   2355: aload #21
    //   2357: aload #22
    //   2359: aload #18
    //   2361: invokevirtual put : (Ljava/lang/Object;Ljava/lang/Object;)Ljava/lang/Object;
    //   2364: pop
    //   2365: aload #21
    //   2367: sipush #451
    //   2370: getstatic com/datami/smi/c/d.g : [B
    //   2373: sipush #524
    //   2376: baload
    //   2377: ineg
    //   2378: getstatic com/datami/smi/c/d.g : [B
    //   2381: bipush #101
    //   2383: baload
    //   2384: invokestatic a : (III)Ljava/lang/String;
    //   2387: getstatic com/datami/smi/d/c.c : Lcom/datami/smi/d/c;
    //   2390: invokestatic a : (Lcom/datami/smi/d/c;)Ljava/lang/String;
    //   2393: invokevirtual put : (Ljava/lang/Object;Ljava/lang/Object;)Ljava/lang/Object;
    //   2396: pop
    //   2397: getstatic com/datami/smi/d/d.a : Lcom/datami/smi/d/d;
    //   2400: invokestatic a : (Lcom/datami/smi/d/d;)Ljava/lang/String;
    //   2403: aload #21
    //   2405: invokestatic b : (Ljava/lang/String;Ljava/util/Properties;)V
    //   2408: getstatic com/datami/smi/c/d.h : I
    //   2411: bipush #65
    //   2413: ior
    //   2414: getstatic com/datami/smi/c/d.g : [B
    //   2417: sipush #178
    //   2420: baload
    //   2421: iconst_1
    //   2422: iadd
    //   2423: getstatic com/datami/smi/c/d.g : [B
    //   2426: sipush #197
    //   2429: baload
    //   2430: invokestatic a : (III)Ljava/lang/String;
    //   2433: pop
    //   2434: sipush #591
    //   2437: getstatic com/datami/smi/c/d.g : [B
    //   2440: bipush #13
    //   2442: baload
    //   2443: getstatic com/datami/smi/c/d.g : [B
    //   2446: bipush #31
    //   2448: baload
    //   2449: invokestatic a : (III)Ljava/lang/String;
    //   2452: pop
    //   2453: lload #7
    //   2455: lstore #5
    //   2457: aload #15
    //   2459: astore #22
    //   2461: aload #14
    //   2463: astore #15
    //   2465: aload #19
    //   2467: astore #24
    //   2469: aload #16
    //   2471: astore #14
    //   2473: aload #29
    //   2475: astore #18
    //   2477: goto -> 2099
    //   2480: aload #32
    //   2482: astore #14
    //   2484: lload #5
    //   2486: lstore #7
    //   2488: aload #26
    //   2490: astore #17
    //   2492: aload #18
    //   2494: astore #29
    //   2496: aload #21
    //   2498: astore #16
    //   2500: aload #23
    //   2502: astore #20
    //   2504: aload #24
    //   2506: astore #19
    //   2508: aload #22
    //   2510: astore #15
    //   2512: iconst_0
    //   2513: putstatic com/datami/smi/c/d.e : Z
    //   2516: goto -> 1698
    //   2519: astore #15
    //   2521: aload #30
    //   2523: astore #14
    //   2525: invokestatic a : ()I
    //   2528: istore_2
    //   2529: new java/util/Properties
    //   2532: dup
    //   2533: invokespecial <init> : ()V
    //   2536: astore #16
    //   2538: sipush #200
    //   2541: iload_2
    //   2542: if_icmpeq -> 2589
    //   2545: aload_0
    //   2546: iload_2
    //   2547: putfield d : I
    //   2550: aload_0
    //   2551: ldc_w ''
    //   2554: invokespecial a : (Ljava/lang/String;)V
    //   2557: aload #16
    //   2559: getstatic com/datami/smi/c/d.g : [B
    //   2562: bipush #112
    //   2564: baload
    //   2565: getstatic com/datami/smi/c/d.h : I
    //   2568: bipush #124
    //   2570: iand
    //   2571: getstatic com/datami/smi/c/d.g : [B
    //   2574: bipush #114
    //   2576: baload
    //   2577: ineg
    //   2578: invokestatic a : (III)Ljava/lang/String;
    //   2581: iload_2
    //   2582: invokestatic valueOf : (I)Ljava/lang/Integer;
    //   2585: invokevirtual put : (Ljava/lang/Object;Ljava/lang/Object;)Ljava/lang/Object;
    //   2588: pop
    //   2589: iconst_0
    //   2590: putstatic com/datami/smi/c/c.d : I
    //   2593: sipush #297
    //   2596: getstatic com/datami/smi/c/d.g : [B
    //   2599: sipush #150
    //   2602: baload
    //   2603: ineg
    //   2604: getstatic com/datami/smi/c/d.g : [B
    //   2607: bipush #49
    //   2609: baload
    //   2610: invokestatic a : (III)Ljava/lang/String;
    //   2613: astore #17
    //   2615: aload #15
    //   2617: invokevirtual getMessage : ()Ljava/lang/String;
    //   2620: ifnull -> 3159
    //   2623: aload #15
    //   2625: invokevirtual getMessage : ()Ljava/lang/String;
    //   2628: astore #15
    //   2630: aload #16
    //   2632: aload #17
    //   2634: aload #15
    //   2636: invokevirtual put : (Ljava/lang/Object;Ljava/lang/Object;)Ljava/lang/Object;
    //   2639: pop
    //   2640: aload #16
    //   2642: sipush #451
    //   2645: getstatic com/datami/smi/c/d.g : [B
    //   2648: sipush #524
    //   2651: baload
    //   2652: ineg
    //   2653: getstatic com/datami/smi/c/d.g : [B
    //   2656: bipush #101
    //   2658: baload
    //   2659: invokestatic a : (III)Ljava/lang/String;
    //   2662: getstatic com/datami/smi/d/c.c : Lcom/datami/smi/d/c;
    //   2665: invokestatic a : (Lcom/datami/smi/d/c;)Ljava/lang/String;
    //   2668: invokevirtual put : (Ljava/lang/Object;Ljava/lang/Object;)Ljava/lang/Object;
    //   2671: pop
    //   2672: getstatic com/datami/smi/d/d.a : Lcom/datami/smi/d/d;
    //   2675: invokestatic a : (Lcom/datami/smi/d/d;)Ljava/lang/String;
    //   2678: aload #16
    //   2680: invokestatic b : (Ljava/lang/String;Ljava/util/Properties;)V
    //   2683: getstatic com/datami/smi/c/d.h : I
    //   2686: bipush #65
    //   2688: ior
    //   2689: getstatic com/datami/smi/c/d.g : [B
    //   2692: sipush #178
    //   2695: baload
    //   2696: iconst_1
    //   2697: iadd
    //   2698: getstatic com/datami/smi/c/d.g : [B
    //   2701: sipush #197
    //   2704: baload
    //   2705: invokestatic a : (III)Ljava/lang/String;
    //   2708: pop
    //   2709: getstatic com/datami/smi/c/d.h : I
    //   2712: sipush #967
    //   2715: iand
    //   2716: getstatic com/datami/smi/c/d.g : [B
    //   2719: bipush #12
    //   2721: baload
    //   2722: getstatic com/datami/smi/c/d.g : [B
    //   2725: bipush #31
    //   2727: baload
    //   2728: invokestatic a : (III)Ljava/lang/String;
    //   2731: pop
    //   2732: aload #14
    //   2734: astore #30
    //   2736: aload #30
    //   2738: ifnull -> 3030
    //   2741: aconst_null
    //   2742: astore #15
    //   2744: aload #30
    //   2746: getstatic com/datami/smi/c/d.g : [B
    //   2749: bipush #12
    //   2751: baload
    //   2752: getstatic com/datami/smi/c/d.g : [B
    //   2755: sipush #260
    //   2758: baload
    //   2759: getstatic com/datami/smi/c/d.g : [B
    //   2762: bipush #73
    //   2764: baload
    //   2765: invokestatic a : (III)Ljava/lang/String;
    //   2768: invokevirtual has : (Ljava/lang/String;)Z
    //   2771: ifeq -> 2874
    //   2774: aload_0
    //   2775: aload #30
    //   2777: getstatic com/datami/smi/c/d.g : [B
    //   2780: bipush #12
    //   2782: baload
    //   2783: getstatic com/datami/smi/c/d.g : [B
    //   2786: sipush #260
    //   2789: baload
    //   2790: getstatic com/datami/smi/c/d.g : [B
    //   2793: bipush #73
    //   2795: baload
    //   2796: invokestatic a : (III)Ljava/lang/String;
    //   2799: invokevirtual getInt : (Ljava/lang/String;)I
    //   2802: putfield d : I
    //   2805: getstatic com/datami/smi/c/d.h : I
    //   2808: bipush #65
    //   2810: ior
    //   2811: getstatic com/datami/smi/c/d.g : [B
    //   2814: sipush #178
    //   2817: baload
    //   2818: iconst_1
    //   2819: iadd
    //   2820: getstatic com/datami/smi/c/d.g : [B
    //   2823: sipush #197
    //   2826: baload
    //   2827: invokestatic a : (III)Ljava/lang/String;
    //   2830: new java/lang/StringBuilder
    //   2833: dup
    //   2834: invokespecial <init> : ()V
    //   2837: sipush #400
    //   2840: getstatic com/datami/smi/c/d.g : [B
    //   2843: sipush #379
    //   2846: baload
    //   2847: ineg
    //   2848: getstatic com/datami/smi/c/d.g : [B
    //   2851: bipush #31
    //   2853: baload
    //   2854: invokestatic a : (III)Ljava/lang/String;
    //   2857: invokevirtual append : (Ljava/lang/String;)Ljava/lang/StringBuilder;
    //   2860: aload_0
    //   2861: getfield d : I
    //   2864: invokevirtual append : (I)Ljava/lang/StringBuilder;
    //   2867: invokevirtual toString : ()Ljava/lang/String;
    //   2870: invokestatic i : (Ljava/lang/String;Ljava/lang/String;)I
    //   2873: pop
    //   2874: aload #15
    //   2876: astore #14
    //   2878: aload #30
    //   2880: getstatic com/datami/smi/c/d.g : [B
    //   2883: bipush #41
    //   2885: baload
    //   2886: getstatic com/datami/smi/c/d.g : [B
    //   2889: sipush #260
    //   2892: baload
    //   2893: iconst_1
    //   2894: isub
    //   2895: getstatic com/datami/smi/c/d.g : [B
    //   2898: bipush #73
    //   2900: baload
    //   2901: invokestatic a : (III)Ljava/lang/String;
    //   2904: invokevirtual has : (Ljava/lang/String;)Z
    //   2907: ifeq -> 2941
    //   2910: aload #30
    //   2912: getstatic com/datami/smi/c/d.g : [B
    //   2915: bipush #41
    //   2917: baload
    //   2918: getstatic com/datami/smi/c/d.g : [B
    //   2921: sipush #260
    //   2924: baload
    //   2925: iconst_1
    //   2926: isub
    //   2927: getstatic com/datami/smi/c/d.g : [B
    //   2930: bipush #73
    //   2932: baload
    //   2933: invokestatic a : (III)Ljava/lang/String;
    //   2936: invokevirtual getString : (Ljava/lang/String;)Ljava/lang/String;
    //   2939: astore #14
    //   2941: aload_0
    //   2942: aload #14
    //   2944: invokespecial a : (Ljava/lang/String;)V
    //   2947: new java/util/Properties
    //   2950: dup
    //   2951: invokespecial <init> : ()V
    //   2954: astore #14
    //   2956: aload #14
    //   2958: sipush #297
    //   2961: getstatic com/datami/smi/c/d.g : [B
    //   2964: sipush #150
    //   2967: baload
    //   2968: ineg
    //   2969: getstatic com/datami/smi/c/d.g : [B
    //   2972: bipush #49
    //   2974: baload
    //   2975: invokestatic a : (III)Ljava/lang/String;
    //   2978: aload #30
    //   2980: invokevirtual toString : ()Ljava/lang/String;
    //   2983: invokevirtual put : (Ljava/lang/Object;Ljava/lang/Object;)Ljava/lang/Object;
    //   2986: pop
    //   2987: aload #14
    //   2989: sipush #451
    //   2992: getstatic com/datami/smi/c/d.g : [B
    //   2995: sipush #524
    //   2998: baload
    //   2999: ineg
    //   3000: getstatic com/datami/smi/c/d.g : [B
    //   3003: bipush #101
    //   3005: baload
    //   3006: invokestatic a : (III)Ljava/lang/String;
    //   3009: getstatic com/datami/smi/d/c.b : Lcom/datami/smi/d/c;
    //   3012: invokestatic a : (Lcom/datami/smi/d/c;)Ljava/lang/String;
    //   3015: invokevirtual put : (Ljava/lang/Object;Ljava/lang/Object;)Ljava/lang/Object;
    //   3018: pop
    //   3019: getstatic com/datami/smi/d/d.a : Lcom/datami/smi/d/d;
    //   3022: invokestatic a : (Lcom/datami/smi/d/d;)Ljava/lang/String;
    //   3025: aload #14
    //   3027: invokestatic b : (Ljava/lang/String;Ljava/util/Properties;)V
    //   3030: sipush #999
    //   3033: aload_0
    //   3034: getfield d : I
    //   3037: if_icmpeq -> 3067
    //   3040: sipush #1000
    //   3043: aload_0
    //   3044: getfield d : I
    //   3047: if_icmpeq -> 3067
    //   3050: iconst_m1
    //   3051: aload_0
    //   3052: getfield d : I
    //   3055: if_icmpeq -> 3067
    //   3058: bipush #-2
    //   3060: aload_0
    //   3061: getfield d : I
    //   3064: if_icmpne -> 3242
    //   3067: iload_1
    //   3068: iconst_1
    //   3069: iadd
    //   3070: istore_1
    //   3071: lload_3
    //   3072: lstore #5
    //   3074: goto -> 67
    //   3077: aload #18
    //   3079: invokevirtual getClass : ()Ljava/lang/Class;
    //   3082: astore #18
    //   3084: goto -> 2355
    //   3087: iconst_0
    //   3088: putstatic com/datami/smi/c/c.d : I
    //   3091: getstatic com/datami/smi/c/d.h : I
    //   3094: bipush #65
    //   3096: ior
    //   3097: getstatic com/datami/smi/c/d.g : [B
    //   3100: sipush #178
    //   3103: baload
    //   3104: iconst_1
    //   3105: iadd
    //   3106: getstatic com/datami/smi/c/d.g : [B
    //   3109: sipush #197
    //   3112: baload
    //   3113: invokestatic a : (III)Ljava/lang/String;
    //   3116: new java/lang/StringBuilder
    //   3119: dup
    //   3120: invokespecial <init> : ()V
    //   3123: sipush #524
    //   3126: getstatic com/datami/smi/c/d.g : [B
    //   3129: sipush #197
    //   3132: baload
    //   3133: getstatic com/datami/smi/c/d.g : [B
    //   3136: bipush #31
    //   3138: baload
    //   3139: invokestatic a : (III)Ljava/lang/String;
    //   3142: invokevirtual append : (Ljava/lang/String;)Ljava/lang/StringBuilder;
    //   3145: iload_2
    //   3146: invokevirtual append : (I)Ljava/lang/StringBuilder;
    //   3149: invokevirtual toString : ()Ljava/lang/String;
    //   3152: invokestatic i : (Ljava/lang/String;Ljava/lang/String;)I
    //   3155: pop
    //   3156: goto -> 2736
    //   3159: aload #15
    //   3161: invokevirtual getClass : ()Ljava/lang/Class;
    //   3164: astore #15
    //   3166: goto -> 2630
    //   3169: astore #14
    //   3171: getstatic com/datami/smi/c/d.h : I
    //   3174: bipush #65
    //   3176: ior
    //   3177: getstatic com/datami/smi/c/d.g : [B
    //   3180: sipush #178
    //   3183: baload
    //   3184: iconst_1
    //   3185: iadd
    //   3186: getstatic com/datami/smi/c/d.g : [B
    //   3189: sipush #197
    //   3192: baload
    //   3193: invokestatic a : (III)Ljava/lang/String;
    //   3196: pop
    //   3197: sipush #591
    //   3200: getstatic com/datami/smi/c/d.g : [B
    //   3203: bipush #13
    //   3205: baload
    //   3206: getstatic com/datami/smi/c/d.g : [B
    //   3209: bipush #31
    //   3211: baload
    //   3212: invokestatic a : (III)Ljava/lang/String;
    //   3215: pop
    //   3216: aload #15
    //   3218: astore #14
    //   3220: goto -> 2941
    //   3223: astore #15
    //   3225: lload #5
    //   3227: lstore_3
    //   3228: aconst_null
    //   3229: astore #14
    //   3231: goto -> 2525
    //   3234: astore #15
    //   3236: aconst_null
    //   3237: astore #14
    //   3239: goto -> 2525
    //   3242: goto -> 91
    // Exception table:
    //   from	to	target	type
    //   77	83	3223	java/lang/Exception
    //   114	136	3223	java/lang/Exception
    //   136	178	3223	java/lang/Exception
    //   178	304	3223	java/lang/Exception
    //   304	402	3234	java/lang/Exception
    //   409	469	2519	java/lang/Exception
    //   564	591	2275	org/json/JSONException
    //   564	591	2519	java/lang/Exception
    //   623	649	2275	org/json/JSONException
    //   623	649	2519	java/lang/Exception
    //   681	709	2275	org/json/JSONException
    //   681	709	2519	java/lang/Exception
    //   741	768	2275	org/json/JSONException
    //   741	768	2519	java/lang/Exception
    //   800	825	2275	org/json/JSONException
    //   800	825	2519	java/lang/Exception
    //   857	881	2275	org/json/JSONException
    //   857	881	2519	java/lang/Exception
    //   913	942	2275	org/json/JSONException
    //   913	942	2519	java/lang/Exception
    //   974	1002	2275	org/json/JSONException
    //   974	1002	2519	java/lang/Exception
    //   1034	1061	2275	org/json/JSONException
    //   1034	1061	2519	java/lang/Exception
    //   1093	1119	2275	org/json/JSONException
    //   1093	1119	2519	java/lang/Exception
    //   1171	1193	2275	org/json/JSONException
    //   1171	1193	2519	java/lang/Exception
    //   1225	1246	2275	org/json/JSONException
    //   1225	1246	2519	java/lang/Exception
    //   1294	1321	2275	org/json/JSONException
    //   1294	1321	2519	java/lang/Exception
    //   1353	1379	2275	org/json/JSONException
    //   1353	1379	2519	java/lang/Exception
    //   1411	1423	2275	org/json/JSONException
    //   1411	1423	2519	java/lang/Exception
    //   1459	1489	2275	org/json/JSONException
    //   1459	1489	2519	java/lang/Exception
    //   1521	1550	2275	org/json/JSONException
    //   1521	1550	2519	java/lang/Exception
    //   1582	1614	2275	org/json/JSONException
    //   1582	1614	2519	java/lang/Exception
    //   1646	1698	2275	org/json/JSONException
    //   1646	1698	2519	java/lang/Exception
    //   1734	1762	2275	org/json/JSONException
    //   1734	1762	2519	java/lang/Exception
    //   1798	1826	2275	org/json/JSONException
    //   1798	1826	2519	java/lang/Exception
    //   1858	1885	2275	org/json/JSONException
    //   1858	1885	2519	java/lang/Exception
    //   1917	1928	2275	org/json/JSONException
    //   1917	1928	2519	java/lang/Exception
    //   1960	1965	2275	org/json/JSONException
    //   1960	1965	2519	java/lang/Exception
    //   1997	2008	2275	org/json/JSONException
    //   1997	2008	2519	java/lang/Exception
    //   2040	2083	2275	org/json/JSONException
    //   2040	2083	2519	java/lang/Exception
    //   2099	2223	2519	java/lang/Exception
    //   2258	2268	2275	org/json/JSONException
    //   2258	2268	2519	java/lang/Exception
    //   2277	2293	2519	java/lang/Exception
    //   2293	2309	2519	java/lang/Exception
    //   2309	2355	2519	java/lang/Exception
    //   2355	2453	2519	java/lang/Exception
    //   2512	2516	2275	org/json/JSONException
    //   2512	2516	2519	java/lang/Exception
    //   2744	2874	3169	org/json/JSONException
    //   2878	2941	3169	org/json/JSONException
    //   3077	3084	2519	java/lang/Exception
    //   3087	3156	2519	java/lang/Exception
  }
}


/* Location:              C:\Users\devid\Downloads\SAST\Santander\dex2jar-2.0\classes-dex2jar.jar!\com\datami\smi\c\d.class
 * Java compiler version: 6 (50.0)
 * JD-Core Version:       1.1.3
 */